F25_core/simple-core/params.vh
`ifndef PARAMS_VH
`define PARAMS_VH

// Opcode Decoding Type
`define R_Type          7'b0110011
`define I_Type_A        7'b0010011
`define I_Type_L        7'b0000011
`define S_Type          7'b0100011
`define B_Type          7'b1100011
`define J_Type_lk       7'b1101111
`define I_Type_JALR     7'b1100111
`define U_Type_lui      7'b0110111
`define U_Type_auipc    7'b0010111
`define I_Type_ECALL    7'b1110011
`define NOOP            32'h00000013

// Instruction Function Codes
`define ADD_FUN7        7'b0000000
`define SUB_FUN7        7'b0100000
`define SRA_FUN7        7'b0100000

`define ADD_FUN3        3'b000
`define SUB_FUN3        3'b000
`define SLL_FUN3        3'b001
`define SLT_FUN3        3'b010
`define SLTU_FUN3       3'b011
`define XOR_FUN3        3'b100
`define SRL_FUN3        3'b101
`define SRA_FUN3        3'b101
`define OR_FUN3         3'b110
`define AND_FUN3        3'b111

// Load/Store function codes
`define LB_FUN3         3'b000
`define LH_FUN3         3'b001
`define LW_FUN3         3'b010
`define LBU_FUN3        3'b100
`define LHU_FUN3        3'b101

`define SB_FUN3         3'b000
`define SH_FUN3         3'b001
`define SW_FUN3         3'b010

`endif // PARAMS_VH

F25_core/Simple_Core/dataMem.v
module dataMem (
    input wire clk,
    input wire reset, 
    input wire [31:0] address_i,
    input wire [31:0] storeData,
    input wire load_en,
    input wire store_en,
    output wire [31:0] loadData_w
);
    reg [31:0] DMEM [0:1023];
    
    // Wire for Combinational Read Access (Required for proper BRAM inference)
    wire [31:0] read_data_comb; 
    
    // Register for Pipelined Output (MEM/WB boundary)
    reg [31:0] loadData_reg;
    
    integer i;

    // 1. COMBINATIONAL READ ACCESS
    // Data is read combinatorially based on the address (which is the registered ALU result)
    assign read_data_comb = DMEM[address_i[11:2]];

    // 2. REGISTERED OUTPUT
    assign loadData_w = loadData_reg; 

    always @(posedge clk) begin
        if (reset) begin
            // Reset logic
            for (i=0; i<1024; i=i+1) begin
                DMEM[i] <= 32'b0;
            end
            loadData_reg <= 32'b0;
        end else begin
            
            // Synchronous Write (for Store instructions)
            if (store_en) begin
                DMEM[address_i[11:2]] <= storeData;
            end
            
            // Synchronous Register of Read Data (for Load instructions)
            if (load_en) begin
                // Register the data read *combinatorially* on the positive edge
                loadData_reg <= read_data_comb; 
            end
        end
    end
endmodule

F25_core/Simple_Core/execute.v
`include "params.vh"

module execute (
    input  wire i_clk,
    input  wire i_en,
    input  wire [31:0] operand1_pi,
    input  wire [31:0] operand2_pi,
    input  wire [31:0] imm_i,
    input  wire [31:0] pc_i,
    input  wire [6:0] opcode_i,
    input  wire [2:0] fun3_i,
    input  wire [6:0] fun7_i,
    input  wire [4:0] rd_i,
    
    // Pipelined outputs (Registered results for MEM/WB stage)
    output wire [31:0] alu_result_o,          // Registered ALU result
    output wire jump_inst_o,                 // Registered jump control
    output wire write_reg_file_o,            // Registered register write enable
    output wire [4:0] rd_addr_o,             // Registered destination register address
    
    // Immediate output (Combinational branch condition for PC unit)
    output wire branch_inst_o                // Branch condition (Combinational or Registered depending on hazard module)
);

    // Internal REGs for combinational calculation (must be declared as reg to be assigned inside always @(*))
    reg  [31:0] result_comb;
    reg  branch_cond_comb;
    reg  branch_inst_comb;
    reg  jump_inst_comb;
    reg  write_reg_file_comb;

    // Output registers for pipelining (Sequential logic for EX/MEM boundary)
    reg  [31:0] alu_result_reg;
    reg  jump_inst_reg;
    reg  write_reg_file_reg;
    reg  [4:0] rd_addr_reg;
    reg  branch_inst_reg; // Also register the branch instruction type

    // Sign extension wires
    wire signed [31:0] operand1_pi_signed = $signed(operand1_pi);
    wire signed [31:0] operand2_pi_signed = $signed(operand2_pi);
    wire signed [31:0] imm_i_signed = $signed(imm_i);

    // Final output assignments (Connecting registers to output ports)
    assign alu_result_o       = alu_result_reg;
    assign jump_inst_o        = jump_inst_reg;
    assign write_reg_file_o   = (~(rd_addr_reg == 5'b0)) & write_reg_file_reg; 
    assign rd_addr_o          = rd_addr_reg;
    
    // The Branch Instruction Output must assert both the control type AND the calculated condition
    // NOTE: This signal needs to be immediately available to the PC unit for branch resolution/prediction.
    assign branch_inst_o      = branch_inst_comb & branch_cond_comb;


    // ====================================================================
    // 1. Combinational Logic (ALU and Control Calculation - Uses Blocking assignments '=')
    // **This logic cone must complete within one clock period (the original critical path)**
    // ====================================================================
    
    always @(*) begin
        // Default assignments (Reset all combinational control signals)
        result_comb         = 32'b0;
        branch_inst_comb    = 1'b0;
        jump_inst_comb      = 1'b0;
        write_reg_file_comb = 1'b0;
        branch_cond_comb    = 1'b0; 

        case(opcode_i) 
        
            `R_Type: begin
                write_reg_file_comb = 1'b1;
                case (fun3_i)
                    3'b000: result_comb = (fun7_i == `ADD_FUN7) ? operand1_pi + operand2_pi : operand1_pi - operand2_pi; 
                    3'b001: result_comb = (operand1_pi << operand2_pi[4:0]); 
                    3'b010: result_comb = (operand1_pi_signed < operand2_pi_signed) ? 1 : 0; 
                    3'b011: result_comb = (operand1_pi < operand2_pi) ? 1 : 0; 
                    3'b100: result_comb = operand1_pi ^ operand2_pi;
                    3'b101: result_comb = (fun7_i == `ADD_FUN7) ? (operand1_pi >> operand2_pi[4:0]) : ($signed(operand1_pi) >>> operand2_pi[4:0]); 
                    3'b110: result_comb = operand1_pi | operand2_pi;
                    3'b111: result_comb = operand1_pi & operand2_pi; 
                endcase
            end
            
            `I_Type_A: begin
                write_reg_file_comb = 1'b1;
                case (fun3_i)
                    3'b000: result_comb = operand1_pi + imm_i;
                    3'b010: result_comb = (operand1_pi_signed < imm_i_signed) ? 1 : 0; 
                    3'b011: result_comb = (operand1_pi < imm_i) ? 1 : 0;
                    3'b100: result_comb = operand1_pi ^ imm_i; 
                    3'b110: result_comb = operand1_pi | imm_i;
                    3'b111: result_comb = operand1_pi & imm_i;
                    3'b001: result_comb = (operand1_pi << imm_i[4:0]);
                    3'b101: result_comb = (fun7_i == `ADD_FUN7) ? (operand1_pi >> imm_i[4:0]) : ($signed(operand1_pi) >>> imm_i[4:0]);
                endcase
            end
            
            // Load and Store Address Calculation
            `I_Type_L, `S_Type: begin
                write_reg_file_comb = (opcode_i == `I_Type_L) ? 1'b1 : 1'b0;
                result_comb = operand1_pi + imm_i;
            end
            
            `B_Type: begin
                branch_inst_comb    = 1'b1;
                result_comb         = pc_i + imm_i; // Branch Target Address (BTA)
                
                // branch_cond computes the condition flag
                case (fun3_i)
                    3'b000: branch_cond_comb = (operand1_pi == operand2_pi);        // BEQ
                    3'b001: branch_cond_comb = (operand1_pi != operand2_pi);        // BNE
                    3'b100: branch_cond_comb = (operand1_pi_signed < operand2_pi_signed); // BLT
                    3'b101: branch_cond_comb = (operand1_pi_signed >= operand2_pi_signed); // BGE
                    3'b110: branch_cond_comb = (operand1_pi < operand2_pi);         // BLTU
                    3'b111: branch_cond_comb = (operand1_pi >= operand2_pi);        // BGEU
                endcase
            end
            
            // JAL/JALR
            `J_Type_lk, `I_Type_JALR: begin
                jump_inst_comb      = 1'b1;
                write_reg_file_comb = 1'b1;
                // Target PC
                result_comb = (opcode_i == `J_Type_lk) ? (pc_i + imm_i) : ((operand1_pi + imm_i) & 32'hFFFFFFFE);
            end
            
            // U-Type
            `U_Type_lui, `U_Type_auipc: begin
                write_reg_file_comb = 1'b1;
                result_comb = (opcode_i == `U_Type_lui) ? imm_i : pc_i + imm_i;
            end
            
        endcase
    end
    

    // ====================================================================
    // 2. Sequential Logic (Pipelining the EX Stage - Uses Non-Blocking assignments '<=')
    // **This register break isolates the critical path**
    // ====================================================================
    
    always @(posedge i_clk) begin
        if (i_en) begin
            alu_result_reg     <= result_comb;
            jump_inst_reg      <= jump_inst_comb;
            write_reg_file_reg <= write_reg_file_comb;
            rd_addr_reg        <= rd_i; 
        end
    end

endmodule

F25_core/simple-core/regfile.v
module regfile(
    input  wire        clk,
    input  wire        reset,
    input  wire [4:0]  rs1_addr,
    input  wire [4:0]  rs2_addr,
    output wire [31:0] rs1_data,
    output wire [31:0] rs2_data,
    input  wire [4:0]  rd_addr,
    input  wire [31:0] rd_data,
    input  wire        we_i
);

    reg [31:0] register_file [0:31];

    // Read ports
    assign rs1_data = (rs1_addr != 0) ? register_file[rs1_addr] : 32'b0;
    assign rs2_data = (rs2_addr != 0) ? register_file[rs2_addr] : 32'b0;

    // Write port
    always @(posedge clk) begin
        if (reset) begin
            // On reset, clear register 1 to 31. Register 0 is hard-wired to zero.
            register_file[1] <= 32'b0;
            register_file[2] <= 32'b0;
            // ... and so on for all 31 registers. A full reset is handled by the testbench.
        end else if (we_i && (rd_addr != 0)) begin
            register_file[rd_addr] <= rd_data;
        end
    end
endmodule

F25_core/Simple_Core/decode.v
`include "params.vh"

module decode (
    input  wire [31:0]  instruction,
    output wire  [4:0]  rd_o,
    output wire  [4:0]  rs1_o,
    output wire  [4:0]  rs2_o,
    output wire  [2:0]  fun3_o,
    output wire  [6:0]  fun7_o,
    output wire  [31:0] imm_o,
    output wire  [6:0]  opcode_o
);
    wire [6:0] opcode;
    wire [4:0] rd, rs1, rs2;
    wire [2:0] fun3;
    wire [6:0] fun7;

    // Extracted fields
    assign opcode = instruction[6:0];
    assign rd     = instruction[11:7];
    assign fun3   = instruction[14:12];
    assign rs1    = instruction[19:15];
    assign rs2    = instruction[24:20];
    assign fun7   = instruction[31:25];

    // Output assignments
    assign rd_o     = rd;
    assign rs1_o    = rs1;
    assign rs2_o    = rs2;
    assign fun3_o   = fun3;
    assign fun7_o   = fun7;
    assign opcode_o = opcode;

    // Immediate value generation based on instruction type (FIXED)
    reg [31:0] imm_o_reg;
    assign imm_o = imm_o_reg;

    always @(*) begin
        // FIX: Use blocking assignment (=) in this combinational block
        case (opcode)
            // I-Type (ALU Imm, Load, JALR)
            `I_Type_A, `I_Type_L, `I_Type_JALR: 
                imm_o_reg = {{21{instruction[31]}}, instruction[30:20]};
            
            // S-Type (Store)
            `S_Type:
                imm_o_reg = {{21{instruction[31]}}, instruction[31:25], instruction[11:7]};

            // B-Type (Branch)
            `B_Type:
                // imm[12] = instruction[31], imm[10:5] = instruction[30:25], imm[4:1] = instruction[11:8], imm[0] is 0
                imm_o_reg = {{20{instruction[31]}}, instruction[7], instruction[30:25], instruction[11:8], 1'b0};

            // U-Type (LUI, AUIPC)
            `U_Type_lui, `U_Type_auipc:
                // imm[31:12] = instruction[31:12], imm[11:0] = 12'b0
                imm_o_reg = {instruction[31:12], 12'b0};

            // J-Type (JAL)
            `J_Type_lk:
                // imm[20] = instruction[31], imm[10:1] = instruction[30:21], imm[11] = instruction[20], imm[19:12] = instruction[19:12]
                imm_o_reg = {{12{instruction[31]}}, instruction[19:12], instruction[20], instruction[30:21], 1'b0};

            default:
                imm_o_reg = 32'b0;
        endcase
    end
endmodule

F25_core/simple-core/ins_mem.v
module ins_mem (
    input  wire         clk,
    input  wire         reset,
    input  wire [31:0]  pc_i,
    output wire [31:0]  instruction_o
);

    // Instruction memory array
    reg [31:0] instruction_memory [0:1023];
    
    // Output register
    reg [31:0] instruction_o_reg;
    
    // Assign output wire to output register
    assign instruction_o = instruction_o_reg;

    // Load instructions from a file on initialization
    initial begin
        $readmemh("program.hex", instruction_memory);
    end

    // Read logic
    always @(posedge clk) begin
        if (reset) begin
            instruction_o_reg <= 32'b0;
        end else begin
            // Read instruction from memory at the current PC address
            // The PC is byte-addressed, so we use bits [31:2] to get the word address
            instruction_o_reg <= instruction_memory[pc_i[31:2]];
        end
    end
endmodule

F25_core/simple-core/pc.v
module pc(
    input wire clk_i,
    input wire reset_i,
    input wire stage_IF_ready,
    input wire jump_inst_wire, 
    input wire branch_inst_wire,
    input wire enable_design, 
    input wire [31:0] targetPC_i,
    input wire [31:0] initial_pc_i,
    output wire[31:0] pc_o,
    output wire       pc_valid
);
    reg  [31:0] PC;
    wire [31:0] nextPC;
    reg pc_valid_r;
    wire change_PC_condition_for_jump_or_branch;
    assign change_PC_condition_for_jump_or_branch = (jump_inst_wire | branch_inst_wire);
    assign nextPC = change_PC_condition_for_jump_or_branch ? targetPC_i : PC + 4;
    assign pc_o = PC;
    assign pc_valid = enable_design;

    always @(posedge clk_i) begin
        if (reset_i) begin
            pc_valid_r <= 1'b1;
            PC <= initial_pc_i;
        end else if (enable_design) begin
            if (stage_IF_ready | change_PC_condition_for_jump_or_branch) begin
                PC <= nextPC;
                pc_valid_r <= 1'b1;
            end else begin
                pc_valid_r <= 1'b0;
            end
        end
    end
endmodule

F25_core/simple-core/riscv32i.v
`include "params.vh"

module riscv32i (
    // PYNQ-Z2 Core I/O
    input wire sysclk,
    input wire [1:0] sw, // sw[0] used as reset
    
    // Output connected to LED (Low 4 bits of ALU result)
    output wire [3:0] led
);

// ----------------------------------------------------------------------
// Internal Signal Declarations (IF/ID Boundary)
// ----------------------------------------------------------------------
    wire reset = sw[0];
    
    wire [31:0] if_pc; // Accessible as core.if_pc
    wire [31:0] if_instruction;
    
    // ID Stage Wires
    wire [4:0] id_rd, id_rs1, id_rs2;
    wire [2:0] id_fun3;
    wire [6:0] id_fun7;
    wire [31:0] id_imm;
    wire [6:0] id_opcode;
    
    wire [31:0] id_rs1_data, id_rs2_data; // Raw register file read data

// ----------------------------------------------------------------------
// ID/EX Pipeline Registers (Registered at clock edge)
// ----------------------------------------------------------------------
    reg [31:0] id_ex_op1_reg, id_ex_op2_reg;
    reg [31:0] id_ex_imm_reg;
    reg [31:0] id_ex_pc_reg;
    reg [4:0]  id_ex_rd_reg;
    reg [6:0]  id_ex_opcode_reg;
    reg [2:0]  id_ex_fun3_reg;
    reg [6:0]  id_ex_fun7_reg;

// ----------------------------------------------------------------------
// EX/MEM Boundary Wires (Registered outputs of execute.v)
// ----------------------------------------------------------------------
    wire [31:0] ex_mem_alu_result; // Accessible as core.ex_mem_alu_result
    wire ex_mem_jump_inst;
    wire ex_mem_branch_inst;
    wire ex_mem_write_reg;
    wire [4:0] ex_mem_rd_o;

// ----------------------------------------------------------------------
// MEM/WB Boundary Wires (Registered output of dataMem.v)
// ----------------------------------------------------------------------
    wire [31:0] mem_wb_load_data; 
    wire mem_load_en;
    wire mem_store_en;

    wire dummy_pc_valid;
    
    // LED Output
    assign led = ex_mem_alu_result[3:0]; 
    
// ----------------------------------------------------------------------
// ID/EX Pipeline Register Logic
// ----------------------------------------------------------------------
    always @(posedge sysclk) begin
        if (reset) begin
            id_ex_op1_reg    <= 32'b0;
            id_ex_op2_reg    <= 32'b0;
            id_ex_imm_reg    <= 32'b0;
            id_ex_pc_reg     <= 32'b0;
            id_ex_rd_reg     <= 5'b0;
            id_ex_opcode_reg <= 7'b0;
            id_ex_fun3_reg   <= 3'b0;
            id_ex_fun7_reg   <= 7'b0;
        end else begin
            id_ex_op1_reg    <= id_rs1_data; 
            id_ex_op2_reg    <= id_rs2_data;
            id_ex_imm_reg    <= id_imm;
            id_ex_pc_reg     <= if_pc;
            id_ex_rd_reg     <= id_rd;

            id_ex_opcode_reg <= id_opcode;
            id_ex_fun3_reg   <= id_fun3;
            id_ex_fun7_reg   <= id_fun7;
        end
    end
    
// ----------------------------------------------------------------------
// Modules Instantiation
// ----------------------------------------------------------------------

// Stage 1: Instruction Fetch (IF) and Program Counter (PC)
    pc PC_unit (
        .clk_i(sysclk),
        .reset_i(reset),
        .stage_IF_ready(1'b1),
        .jump_inst_wire(ex_mem_jump_inst),
        .branch_inst_wire(ex_mem_branch_inst),
        .enable_design(1'b1),
        .targetPC_i(ex_mem_alu_result),
        .initial_pc_i(32'h00000000),
        .pc_o(if_pc),
        .pc_valid(dummy_pc_valid)
    );

    // Instruction Memory
    ins_mem IMEM (
        .clk(sysclk),
        .reset(reset),
        .pc_i(if_pc),
        .instruction_o(if_instruction)
    );

// Stage 2: Decode (ID)
    decode DEC (
        .instruction(if_instruction),
        .rd_o(id_rd),
        .rs1_o(id_rs1),
        .rs2_o(id_rs2),
        .fun3_o(id_fun3),
        .fun7_o(id_fun7),
        .imm_o(id_imm),
        .opcode_o(id_opcode)
    );

    // Register File (Reads in ID stage, Writes in WB stage)
    regfile REG_FILE (
        .clk(sysclk),
        .reset(reset),
        .rs1_addr(id_rs1),
        .rs2_addr(id_rs2),
        .rs1_data(id_rs1_data), 
        .rs2_data(id_rs2_data), 
        
        .rd_addr(ex_mem_rd_o),
        .rd_data(ex_mem_alu_result), // Assuming Load data path is not fully implemented yet
        .we_i(ex_mem_write_reg)
    );

// Stage 3: Execute (EX)
    execute EXEC (
        .i_clk(sysclk),
        .i_en(1'b1),
        .operand1_pi(id_ex_op1_reg),
        .operand2_pi(id_ex_op2_reg),
        .imm_i(id_ex_imm_reg),
        .pc_i(id_ex_pc_reg),
        .opcode_i(id_ex_opcode_reg),
        .fun3_i(id_ex_fun3_reg),
        .fun7_i(id_ex_fun7_reg),
        .rd_i(id_ex_rd_reg), 
        
        .alu_result_o(ex_mem_alu_result),
        .branch_inst_o(ex_mem_branch_inst),
        .jump_inst_o(ex_mem_jump_inst),
        .write_reg_file_o(ex_mem_write_reg),
        .rd_addr_o(ex_mem_rd_o)
    );

// Stage 4: Data Memory (MEM)
    assign mem_load_en = (id_ex_opcode_reg == `I_Type_L);
    assign mem_store_en = (id_ex_opcode_reg == `S_Type);

    dataMem DMEM (
        .clk(sysclk),
        .reset(reset), 
        .address_i(ex_mem_alu_result),
        .storeData(id_ex_op2_reg),
        .load_en(mem_load_en),
        .store_en(mem_store_en),
        .loadData_w(mem_wb_load_data)
    );
    
endmodule

F25_core/Simple_Core/riscv_tb.v
`include "params.vh"

module riscv_tb;

    // Testbench ????
    reg clk;
    reg reset_sim;
    
    // ???? riscv32i ?????
    wire [1:0] sw_sim;
    wire [3:0] led_sim;
    
    // **FIX: ?? dbg_pc_sim ? dbg_alu_sim wires,???????????????**
    // wire [31:0] dbg_pc_sim; 
    // wire [31:0] dbg_alu_sim; 

    // 1. ???? (10ns ??,100 MHz)
    initial begin
        clk = 0;
        forever #5 clk = ~clk; 
    end

    // 2. ???? (??? riscv32i ? sw[0])
    assign sw_sim[0] = reset_sim;
    // sw[0] = reset
    assign sw_sim[1] = 1'b0;
    // sw[1] ??

    initial begin
        reset_sim = 1;
        #20;
        // ???? 20ns (2?????)
        reset_sim = 0;
    end

    // ?????????
    riscv32i core (
        .sysclk(clk),         // ?? testbench clk ? riscv32i ? sysclk
        .sw(sw_sim),          // ?? sw ??
        .led(led_sim)         // ?? LED ??
        // **FIX: ?? dbg_pc ? dbg_alu ?????**
        // .dbg_pc(dbg_pc_sim), 
        // .dbg_alu(dbg_alu_sim) 
    ); 

    // 3. ?????
    initial begin
        // ??????
        $dumpfile("riscv_core.vcd");
        $dumpvars(0, riscv_tb);
        
        // ??????? Console
        // **FIX: ???????????**
        $monitor("Time: %t | PC: %h | Inst: %h | ALU_Result: %h", 
                 $time, core.if_pc, core.IMEM.instruction_o, core.ex_mem_alu_result);
        #250; // ?? 250ns
        $finish;
    end

endmodule

F25_core/Simple_Core/riscv_core.vcd
$date
	Sat Nov  1 23:28:26 2025
$end
$version
	Icarus Verilog
$end
$timescale
	1s
$end
$scope module riscv_tb $end
$var wire 2 ! sw_sim [1:0] $end
$var wire 4 " led_sim [3:0] $end
$var reg 1 # clk $end
$var reg 1 $ reset_sim $end
$scope module core $end
$var wire 2 % sw [1:0] $end
$var wire 1 # sysclk $end
$var wire 1 & reset $end
$var wire 32 ' mem_wb_load_data [31:0] $end
$var wire 1 ( mem_store_en $end
$var wire 1 ) mem_load_en $end
$var wire 4 * led [3:0] $end
$var wire 32 + if_pc [31:0] $end
$var wire 32 , if_instruction [31:0] $end
$var wire 32 - id_rs2_data [31:0] $end
$var wire 5 . id_rs2 [4:0] $end
$var wire 32 / id_rs1_data [31:0] $end
$var wire 5 0 id_rs1 [4:0] $end
$var wire 5 1 id_rd [4:0] $end
$var wire 7 2 id_opcode [6:0] $end
$var wire 32 3 id_imm [31:0] $end
$var wire 7 4 id_fun7 [6:0] $end
$var wire 3 5 id_fun3 [2:0] $end
$var wire 1 6 ex_mem_write_reg $end
$var wire 5 7 ex_mem_rd_o [4:0] $end
$var wire 1 8 ex_mem_jump_inst $end
$var wire 1 9 ex_mem_branch_inst $end
$var wire 32 : ex_mem_alu_result [31:0] $end
$var wire 1 ; dummy_pc_valid $end
$var reg 3 < id_ex_fun3_reg [2:0] $end
$var reg 7 = id_ex_fun7_reg [6:0] $end
$var reg 32 > id_ex_imm_reg [31:0] $end
$var reg 32 ? id_ex_op1_reg [31:0] $end
$var reg 32 @ id_ex_op2_reg [31:0] $end
$var reg 7 A id_ex_opcode_reg [6:0] $end
$var reg 32 B id_ex_pc_reg [31:0] $end
$var reg 5 C id_ex_rd_reg [4:0] $end
$scope module DEC $end
$var wire 3 D fun3_o [2:0] $end
$var wire 7 E fun7_o [6:0] $end
$var wire 32 F imm_o [31:0] $end
$var wire 7 G opcode_o [6:0] $end
$var wire 5 H rd_o [4:0] $end
$var wire 5 I rs1_o [4:0] $end
$var wire 5 J rs2_o [4:0] $end
$var wire 5 K rs2 [4:0] $end
$var wire 5 L rs1 [4:0] $end
$var wire 5 M rd [4:0] $end
$var wire 7 N opcode [6:0] $end
$var wire 32 O instruction [31:0] $end
$var wire 7 P fun7 [6:0] $end
$var wire 3 Q fun3 [2:0] $end
$var reg 32 R imm_o_reg [31:0] $end
$upscope $end
$scope module DMEM $end
$var wire 1 # clk $end
$var wire 32 S loadData_w [31:0] $end
$var wire 1 ) load_en $end
$var wire 32 T read_data_comb [31:0] $end
$var wire 1 & reset $end
$var wire 32 U storeData [31:0] $end
$var wire 1 ( store_en $end
$var wire 32 V address_i [31:0] $end
$var reg 32 W loadData_reg [31:0] $end
$var integer 32 X i [31:0] $end
$upscope $end
$scope module EXEC $end
$var wire 1 9 branch_inst_o $end
$var wire 3 Y fun3_i [2:0] $end
$var wire 7 Z fun7_i [6:0] $end
$var wire 1 # i_clk $end
$var wire 1 [ i_en $end
$var wire 32 \ imm_i [31:0] $end
$var wire 32 ] imm_i_signed [31:0] $end
$var wire 7 ^ opcode_i [6:0] $end
$var wire 32 _ operand1_pi [31:0] $end
$var wire 32 ` operand1_pi_signed [31:0] $end
$var wire 32 a operand2_pi [31:0] $end
$var wire 32 b operand2_pi_signed [31:0] $end
$var wire 32 c pc_i [31:0] $end
$var wire 5 d rd_addr_o [4:0] $end
$var wire 5 e rd_i [4:0] $end
$var wire 1 6 write_reg_file_o $end
$var wire 1 8 jump_inst_o $end
$var wire 32 f alu_result_o [31:0] $end
$var reg 32 g alu_result_reg [31:0] $end
$var reg 1 h branch_cond_comb $end
$var reg 1 i branch_inst_comb $end
$var reg 1 j jump_inst_comb $end
$var reg 1 8 jump_inst_reg $end
$var reg 5 k rd_addr_reg [4:0] $end
$var reg 32 l result_comb [31:0] $end
$var reg 1 m write_reg_file_comb $end
$var reg 1 n write_reg_file_reg $end
$upscope $end
$scope module IMEM $end
$var wire 1 # clk $end
$var wire 1 & reset $end
$var wire 32 o pc_i [31:0] $end
$var wire 32 p instruction_o [31:0] $end
$var reg 32 q instruction_o_reg [31:0] $end
$upscope $end
$scope module PC_unit $end
$var wire 1 9 branch_inst_wire $end
$var wire 1 r change_PC_condition_for_jump_or_branch $end
$var wire 1 # clk_i $end
$var wire 1 s enable_design $end
$var wire 32 t initial_pc_i [31:0] $end
$var wire 1 8 jump_inst_wire $end
$var wire 32 u pc_o [31:0] $end
$var wire 1 ; pc_valid $end
$var wire 1 & reset_i $end
$var wire 1 v stage_IF_ready $end
$var wire 32 w targetPC_i [31:0] $end
$var wire 32 x nextPC [31:0] $end
$var reg 32 y PC [31:0] $end
$var reg 1 z pc_valid_r $end
$upscope $end
$scope module REG_FILE $end
$var wire 1 # clk $end
$var wire 5 { rd_addr [4:0] $end
$var wire 32 | rd_data [31:0] $end
$var wire 1 & reset $end
$var wire 5 } rs1_addr [4:0] $end
$var wire 5 ~ rs2_addr [4:0] $end
$var wire 1 6 we_i $end
$var wire 32 !" rs2_data [31:0] $end
$var wire 32 "" rs1_data [31:0] $end
$upscope $end
$upscope $end
$upscope $end
$enddefinitions $end
$comment Show the parameter values. $end
$dumpall
$end
#0
$dumpvars
bx ""
bx !"
bx ~
bx }
bx |
bx {
xz
bx y
bx x
bx w
1v
bx u
b0 t
1s
xr
bx q
bx p
bx o
xn
xm
bx l
bx k
xj
xi
xh
bx g
bx f
bx e
bx d
bx c
bx b
bx a
bx `
bx _
bx ^
bx ]
bx \
1[
bx Z
bx Y
bx X
bx W
bx V
bx U
bx T
bx S
bx R
bx Q
bx P
bx O
bx N
bx M
bx L
bx K
bx J
bx I
bx H
bx G
bx F
bx E
bx D
bx C
bx B
bx A
bx @
bx ?
bx >
bx =
bx <
1;
bx :
x9
x8
bx 7
x6
bx 5
bx 4
bx 3
bx 2
bx 1
bx 0
bx /
bx .
bx -
bx ,
bx +
bx *
x)
x(
bx '
1&
b1 %
1$
0#
bx "
b1 !
$end
#5
b0 -
b0 !"
b0 /
b0 ""
09
b0 4
b0 E
b0 P
b0 .
b0 J
b0 ~
b0 K
b0 0
b0 I
b0 }
b0 L
b0 5
b0 D
b0 Q
b0 1
b0 H
b0 M
b0 2
b0 G
b0 N
b0 3
b0 F
b0 R
0h
0m
0j
0i
b0 l
b0 +
b0 o
b0 u
b0 y
1z
b0 ,
b0 O
b0 p
b0 q
b0 '
b0 S
b0 W
b0 =
b0 Z
b0 <
b0 Y
0)
0(
b0 A
b0 ^
b0 C
b0 e
b0 B
b0 c
b0 ]
b0 >
b0 \
b0 b
b0 @
b0 U
b0 a
b0 `
b0 ?
b0 _
b10000000000 X
1#
#10
0#
#15
06
0r
b100 x
b0 T
b0 "
b0 *
b0 7
b0 d
b0 {
b0 k
0n
08
b0 :
b0 V
b0 f
b0 g
b0 w
b0 |
b10000000000 X
1#
#20
0&
0#
b0 !
b0 %
0$
#25
bx -
bx !"
b1010 3
b1010 F
b1010 R
b1000 x
b1010 .
b1010 J
b1010 ~
b1010 K
b1 1
b1 H
b1 M
b10011 2
b10011 G
b10011 N
b100 +
b100 o
b100 u
b100 y
b101000000000000010010011 ,
b101000000000000010010011 O
b101000000000000010010011 p
b101000000000000010010011 q
1#
#30
0#
#35
b1010 l
1m
b10100 .
b10100 J
b10100 ~
b10100 K
b10 1
b10 H
b10 M
b10100 3
b10100 F
b10100 R
b1100 x
b10011 A
b10011 ^
b1 C
b1 e
b100 B
b100 c
b1010 ]
b1010 >
b1010 \
bx b
bx @
bx U
bx a
b1010000000000000100010011 ,
b1010000000000000100010011 O
b1010000000000000100010011 p
b1010000000000000100010011 q
b1000 +
b1000 o
b1000 u
b1000 y
1#
#40
0#
#45
b0 -
b0 !"
16
b10000 x
b10 .
b10 J
b10 ~
b10 K
b1 0
b1 I
b1 }
b1 L
b11 1
b11 H
b11 M
b110011 2
b110011 G
b110011 N
b0 3
b0 F
b0 R
b1010 "
b1010 *
1m
b10100 l
b1100 +
b1100 o
b1100 u
b1100 y
b1000001000000110110011 ,
b1000001000000110110011 O
b1000001000000110110011 p
b1000001000000110110011 q
b1 7
b1 d
b1 {
b1 k
1n
b1010 :
b1010 V
b1010 f
b1010 g
b1010 w
b1010 |
b10 C
b10 e
b1000 B
b1000 c
b10100 ]
b10100 >
b10100 \
1#
#50
0#
#55
b1010 -
b1010 !"
1m
b0 l
b100 "
b100 *
b100000 4
b100000 E
b100000 P
b1 .
b1 J
b1 ~
b1 K
b10 0
b10 I
b10 }
b10 L
b100 1
b100 H
b100 M
b10100 x
b110011 A
b110011 ^
b11 C
b11 e
b1100 B
b1100 c
b0 ]
b0 >
b0 \
b0 b
b0 @
b0 U
b0 a
b10 7
b10 d
b10 {
b10 k
b10100 :
b10100 V
b10100 f
b10100 g
b10100 w
b10100 |
b1000000000100010000001000110011 ,
b1000000000100010000001000110011 O
b1000000000100010000001000110011 p
b1000000000100010000001000110011 q
b10000 +
b10000 o
b10000 u
b10000 y
1#
#60
0#
#65
bx -
bx !"
b1111 3
b1111 F
b1111 R
b11000 x
b0 4
b0 E
b0 P
b1111 .
b1111 J
b1111 ~
b1111 K
b0 0
b0 I
b0 }
b0 L
b101 1
b101 H
b101 M
b10011 2
b10011 G
b10011 N
b0 /
b0 ""
b0 "
b0 *
b11111111111111111111111111110110 l
1m
b10100 +
b10100 o
b10100 u
b10100 y
b111100000000001010010011 ,
b111100000000001010010011 O
b111100000000001010010011 p
b111100000000001010010011 q
b11 7
b11 d
b11 {
b11 k
b0 :
b0 V
b0 f
b0 g
b0 w
b0 |
b100000 =
b100000 Z
b100 C
b100 e
b10000 B
b10000 c
b1010 b
b1010 @
b1010 U
b1010 a
1#
#70
0#
#75
1m
b1111 l
b110 "
b110 *
b111 4
b111 E
b111 P
b10000 .
b10000 J
b10000 ~
b10000 K
b110 1
b110 H
b110 M
b11110000 3
b11110000 F
b11110000 R
b11100 x
b0 =
b0 Z
b10011 A
b10011 ^
b101 C
b101 e
b10100 B
b10100 c
b1111 ]
b1111 >
b1111 \
bx b
bx @
bx U
bx a
b100 7
b100 d
b100 {
b100 k
b11111111111111111111111111110110 :
b11111111111111111111111111110110 V
b11111111111111111111111111110110 f
b11111111111111111111111111110110 g
b11111111111111111111111111110110 w
b11111111111111111111111111110110 |
b1111000000000000001100010011 ,
b1111000000000000001100010011 O
b1111000000000000001100010011 p
b1111000000000000001100010011 q
b11000 +
b11000 o
b11000 u
b11000 y
1#
#80
0#
