coco_tb/DUT_top/exu_imm_swc.v
module ex_imm_en (
    hclk                                        ,
    hrstn                                       ,
    cycle_cnt                                   ,
    dec_branch_en                               ,
    dec_addi                                    ,
    dec_slti                                    ,
    dec_sltiu                                   ,
    dec_xori                                    ,
    dec_ori                                     ,
    dec_andi                                    ,
    dec_slli                                    ,
    dec_srli                                    ,
    dec_srai                                    ,
    dec_imm_type_i                              ,
    dec_rd                                      ,
    dec_rs1                                     ,
    pc                                          ,
    reg_waddr                                   ,
    reg_wen                                     ,
    reg_wdata                                   ,
    reg_raddr_1                                 ,
    reg_ren_1                                   ,
    reg_rdata_1                                 
);
/*
This module performs Integer-Register Immediate instructions, placing the result in the dec_rd register.
*/
// general signals
input                       hclk                ;
input                       hrstn               ;
// control signals
input           [3:0]       cycle_cnt           ;
// signals from deccoder
input                       dec_branch_en       ;
input                       dec_addi            ;
input                       dec_slti            ;
input                       dec_sltiu           ;
input                       dec_xori            ;
input                       dec_ori             ;
input                       dec_andi            ;
input                       dec_slli            ;
input                       dec_srli            ;
input                       dec_srai            ;
input           [11:0]      dec_imm_type_i      ;
input           [4:0]       dec_rd              ;
input           [4:0]       dec_rs1             ;
// PC signals
input           [31:0]      pc                  ;
// regfile signals
inout           [4:0]       reg_waddr           ;
inout                       reg_wen             ;
inout           [31:0]      reg_wdata           ;
inout           [4:0]       reg_raddr_1         ;
inout                       reg_ren_1           ;
input           [31:0]      reg_rdata_1         ;
// middle signals
reg             [4:0]       mid_reg_waddr       ;
reg                         mid_reg_wen         ;
reg             [31:0]      mid_reg_wdata       ;
reg             [4:0]       mid_reg_raddr_1     ;
reg                         mid_reg_ren_1       ;

assign reg_waddr   = mid_reg_wen   ? mid_reg_waddr    : 'z  ;
assign reg_wen     = mid_reg_wen   ? mid_reg_wen      : 'z  ;
assign reg_wdata   = mid_reg_wen   ? mid_reg_wdata    : 'z  ;
assign reg_raddr_1 = mid_reg_ren_1 ? mid_reg_raddr_1  : 'z  ;
assign reg_ren_1   = mid_reg_ren_1 ? mid_reg_ren_1    : 'z  ;

// the process
always@(posedge hclk or negedge hrstn) begin
    if(!hrstn) begin
    	// on a reset, set all intermediate values to 0
        mid_reg_raddr_1 <= 0;
        mid_reg_ren_1   <= 0;
        
        mid_reg_waddr   <= 0;
        mid_reg_wen     <= 0;
        mid_reg_wdata   <= 0;
    end else if(dec_branch_en)begin
        if(cycle_cnt == 1) begin // on cycle 1 assign the temp read address to the decoded address, and enable writing to the read address
            mid_reg_raddr_1 <= dec_rs1;
            mid_reg_ren_1   <= 1;

            mid_reg_waddr   <= 0;
            mid_reg_wen     <= 0;
            mid_reg_wdata   <= 0;
        end else if(cycle_cnt == 2) begin // on cycle 2 clear the intermediate values.
            mid_reg_raddr_1 <= 0;
            mid_reg_ren_1   <= 0;

            mid_reg_waddr   <= 0;
            mid_reg_wen     <= 0;
            mid_reg_wdata   <= 0;
        end else if(cycle_cnt == 3)begin // on cycle 3 assign the write address to the destination register and enable writing to the register.
            mid_reg_raddr_1 <= 0;
            mid_reg_ren_1   <= 0;

            mid_reg_waddr   <= dec_rd;
            mid_reg_wen     <= 1;
            if(dec_addi) // for ADDI add the immediate to the data
                mid_reg_wdata <= {{20{dec_imm_type_i[11]}}, dec_imm_type_i} + reg_rdata_1;
            else if(dec_slti) // for SLTI check if the data is less than the immediate for signed values
                mid_reg_wdata <= {31'b0, $signed(reg_rdata_1) < $signed({{20{dec_imm_type_i[11]}}, dec_imm_type_i})};
            else if(dec_sltiu) // for SLTIU check if the data is less than the immediate for unsigned values
                mid_reg_wdata <= {31'b0, reg_rdata_1 < {{20{dec_imm_type_i[11]}}, dec_imm_type_i}};
            else if(dec_xori) // for XORI take the bitwise XOR of the data and immediate
                mid_reg_wdata <= reg_rdata_1 ^ {{20{dec_imm_type_i[11]}}, dec_imm_type_i};
            else if(dec_ori) // for ORI take the bitwise OR of the data and immediate
                mid_reg_wdata <= reg_rdata_1 | {{20{dec_imm_type_i[11]}}, dec_imm_type_i};
            else if(dec_andi) // for ANDI take the bitwise AND of the data and immediate
                mid_reg_wdata <= reg_rdata_1 & {{20{dec_imm_type_i[11]}}, dec_imm_type_i};
            else if(dec_slli) // for SLLI perform a logical left shift of the data by the immediate value
                mid_reg_wdata <= reg_rdata_1 << dec_imm_type_i[4:0];
            else if(dec_srli) // for SRLI perform a logical right shift of the data by the immediate value
                mid_reg_wdata <= reg_rdata_1 >> dec_imm_type_i[4:0];
            else if(dec_srai) // for SRAI perform an arithmetic right shift of the data by the immediate value
                mid_reg_wdata <= $signed(reg_rdata_1) >>> dec_imm_type_i[4:0];
            else
                mid_reg_wdata <= 0;
            end else begin // on cycle 4 set all the temp registers to 0
                mid_reg_raddr_1 <= 0;
                mid_reg_ren_1   <= 0;
    
                mid_reg_waddr   <= 0;
                mid_reg_wen     <= 0;
                mid_reg_wdata   <= 0;
            end
    end else begin // if dec_branch_en is not enabled, set all temp registers to 0
        mid_reg_raddr_1 <= 0;
        mid_reg_ren_1   <= 0;

        mid_reg_waddr   <= 0;
        mid_reg_wen     <= 0;
        mid_reg_wdata   <= 0;
    end
end
endmodule

archive/rtl/chip/core/exu_swc/exu_imm_swc/exu_imm_wrapper.v
module ex_imm_en_wrapper (
    input hclk,
    input hrstn,
    input [3:0] cycle_cnt,
    input dec_branch_en,
    input dec_addi,
    input dec_slti,
    input dec_sltiu,
    input dec_xori,
    input dec_ori,
    input dec_andi,
    input dec_slli,
    input dec_srli,
    input dec_srai,
    input [11:0] dec_imm_type_i,
    input [4:0] dec_rd,
    input [4:0] dec_rs1,
    input [31:0] pc,
    input [31:0] reg_rdata_1,
    inout [4:0] reg_waddr,
    inout reg_wen,
    inout [31:0] reg_wdata,
    inout [4:0] reg_raddr_1,
    inout reg_ren_1
);

    ex_imm_en dut (
        .hclk(hclk),
        .hrstn(hrstn),
        .cycle_cnt(cycle_cnt),
        .dec_branch_en(dec_branch_en),
        .dec_addi(dec_addi),
        .dec_slti(dec_slti),
        .dec_sltiu(dec_sltiu),
        .dec_xori(dec_xori),
        .dec_ori(dec_ori),
        .dec_andi(dec_andi),
        .dec_slli(dec_slli),
        .dec_srli(dec_srli),
        .dec_srai(dec_srai),
        .dec_imm_type_i(dec_imm_type_i),
        .dec_rd(dec_rd),
        .dec_rs1(dec_rs1),
        .pc(pc),
        .reg_rdata_1(reg_rdata_1),
        .reg_waddr(reg_waddr),
        .reg_wen(reg_wen),
        .reg_wdata(reg_wdata),
        .reg_raddr_1(reg_raddr_1),
        .reg_ren_1(reg_ren_1)
    );
    initial begin
        $dumpfile("ex_imm_cocotb.vcd");
        $dumpvars(0, ex_imm_en_wrapper);
    end
endmodule

archive/rtl/chip/core/exu_swc/exu_imm_swc/dump.vcd
$date
	Mon Nov 11 10:24:57 2024
$end
$version
	Icarus Verilog
$end
$timescale
	1ps
$end
$scope module ex_imm_en_wrapper $end
$var wire 4 ! cycle_cnt [3:0] $end
$var wire 1 " dec_addi $end
$var wire 1 # dec_andi $end
$var wire 1 $ dec_branch_en $end
$var wire 12 % dec_imm_type_i [11:0] $end
$var wire 1 & dec_ori $end
$var wire 5 ' dec_rd [4:0] $end
$var wire 5 ( dec_rs1 [4:0] $end
$var wire 1 ) dec_slli $end
$var wire 1 * dec_slti $end
$var wire 1 + dec_sltiu $end
$var wire 1 , dec_srai $end
$var wire 1 - dec_srli $end
$var wire 1 . dec_xori $end
$var wire 1 / hclk $end
$var wire 1 0 hrstn $end
$var wire 32 1 pc [31:0] $end
$var wire 32 2 reg_rdata_1 [31:0] $end
$var wire 1 3 reg_wen $end
$var wire 32 4 reg_wdata [31:0] $end
$var wire 5 5 reg_waddr [4:0] $end
$var wire 1 6 reg_ren_1 $end
$var wire 5 7 reg_raddr_1 [4:0] $end
$scope module dut $end
$var wire 4 8 cycle_cnt [3:0] $end
$var wire 1 " dec_addi $end
$var wire 1 # dec_andi $end
$var wire 1 $ dec_branch_en $end
$var wire 12 9 dec_imm_type_i [11:0] $end
$var wire 1 & dec_ori $end
$var wire 5 : dec_rd [4:0] $end
$var wire 5 ; dec_rs1 [4:0] $end
$var wire 1 ) dec_slli $end
$var wire 1 * dec_slti $end
$var wire 1 + dec_sltiu $end
$var wire 1 , dec_srai $end
$var wire 1 - dec_srli $end
$var wire 1 . dec_xori $end
$var wire 1 / hclk $end
$var wire 1 0 hrstn $end
$var wire 32 < pc [31:0] $end
$var wire 32 = reg_rdata_1 [31:0] $end
$var wire 1 3 reg_wen $end
$var wire 32 > reg_wdata [31:0] $end
$var wire 5 ? reg_waddr [4:0] $end
$var wire 1 6 reg_ren_1 $end
$var wire 5 @ reg_raddr_1 [4:0] $end
$var reg 5 A mid_reg_raddr_1 [4:0] $end
$var reg 1 B mid_reg_ren_1 $end
$var reg 5 C mid_reg_waddr [4:0] $end
$var reg 32 D mid_reg_wdata [31:0] $end
$var reg 1 E mid_reg_wen $end
$upscope $end
$upscope $end
$enddefinitions $end
$comment Show the parameter values. $end
$dumpall
$end
#0
$dumpvars
0E
b0 D
b0 C
0B
b0 A
bz @
bz ?
bz >
b1110 =
b0 <
bz ;
bz :
b1011101 9
b1 8
bz 7
z6
bz 5
bz 4
z3
b1110 2
b0 1
00
0/
0.
0-
0,
0+
0*
1)
bz (
bz '
0&
b1011101 %
1$
0#
0"
b1 !
$end
#1000
b10 !
b10 8
1/
#2000
0/
#3000
b11 !
b11 8
1/
#4000
0/
#5000
b100 !
b100 8
13
b11000000000000000000000000000000 4
b11000000000000000000000000000000 >
b11000000000000000000000000000000 D
1E
bz C
1/
10
#6000
0/
#7000
b1 !
b1 8
z3
bz 4
bz >
b0 D
0E
b0 C
1/
#8000
0/
#9000
b10 !
b10 8
16
1B
bz A
1/
#10000
0/
#11000
b11 !
b11 8
z6
0B
b0 A
1/
#12000
0/
#13000
b100 !
b100 8
13
b11000000000000000000000000000000 4
b11000000000000000000000000000000 >
b11000000000000000000000000000000 D
1E
bz C
1/
#14000
0/
#15000
z3
bz 4
bz >
b0 D
0E
b0 C
1/
#15001
b1 !
b1 8
0/
00
0)
1"
b1101000 %
b1101000 9
b110111 2
b110111 =
#16001
b10 !
b10 8
1/
#17001
0/
#18001
b11 !
b11 8
1/
#19001
0/
#20001
b100 !
b100 8
13
b10011111 4
b10011111 >
b10011111 D
1E
bz C
1/
10
#21001
0/
#22001
b1 !
b1 8
z3
bz 4
bz >
b0 D
0E
b0 C
1/
#23001
0/
#24001
b10 !
b10 8
16
1B
bz A
1/
#25001
0/
#26001
b11 !
b11 8
z6
0B
b0 A
1/
#27001
0/
#28001
b100 !
b100 8
13
b10011111 4
b10011111 >
b10011111 D
1E
bz C
1/
#29001
0/
#30001
b1 !
b1 8
00
1+
0"
b1011101 %
b1011101 9
b10100101 2
b10100101 =
z3
bz 4
bz >
b0 D
0E
b0 C
0/
#31001
b10 !
b10 8
1/
#32001
0/
#33001
b11 !
b11 8
1/
#34001
0/
#35001
b100 !
b100 8
13
b0 4
b0 >
1E
bz C
1/
10
#36001
0/
#37001
b1 !
b1 8
z3
bz 4
bz >
0E
b0 C
1/
#38001
0/
#39001
b10 !
b10 8
16
1B
bz A
1/
#40001
0/
#41001
b11 !
b11 8
z6
0B
b0 A
1/
#42001
0/
#43001
b100 !
b100 8
13
b0 4
b0 >
1E
bz C
1/
#44001
0/
#45001
b1 !
b1 8
00
b10011101 %
b10011101 9
b1110001 2
b1110001 =
z3
bz 4
bz >
0E
b0 C
0/
#46001
b10 !
b10 8
1/
#47001
0/
#48001
b11 !
b11 8
1/
#49001
0/
#50001
b100 !
b100 8
13
b1 4
b1 >
b1 D
1E
bz C
1/
10
#51001
0/
#52001
b1 !
b1 8
z3
bz 4
bz >
b0 D
0E
b0 C
1/
#53001
0/
#54001
b10 !
b10 8
16
1B
bz A
1/
#55001
0/
#56001
b11 !
b11 8
z6
0B
b0 A
1/
#57001
0/
#58001
b100 !
b100 8
13
b1 4
b1 >
b1 D
1E
bz C
1/
#59001
0/
#60001
b1 !
b1 8
00
1&
0+
b11010 %
b11010 9
b11000 2
b11000 =
z3
bz 4
bz >
b0 D
0E
b0 C
0/
#61001
b10 !
b10 8
1/
#62001
0/
#63001
b11 !
b11 8
1/
#64001
0/
#65001
b100 !
b100 8
13
b11010 4
b11010 >
b11010 D
1E
bz C
1/
10
#66001
0/
#67001
b1 !
b1 8
z3
bz 4
bz >
b0 D
0E
b0 C
1/
#68001
0/
#69001
b10 !
b10 8
16
1B
bz A
1/
#70001
0/
#71001
b11 !
b11 8
z6
0B
b0 A
1/
#72001
0/
#73001
b100 !
b100 8
13
b11010 4
b11010 >
b11010 D
1E
bz C
1/
#74001
0/
#75001
b1 !
b1 8
00
1,
0&
b100011 %
b100011 9
b100000 2
b100000 =
z3
bz 4
bz >
b0 D
0E
b0 C
0/
#76001
b10 !
b10 8
1/
#77001
0/
#78001
b11 !
b11 8
1/
#79001
0/
#80001
b100 !
b100 8
13
b100 4
b100 >
b100 D
1E
bz C
1/
10
#81001
0/
#82001
b1 !
b1 8
z3
bz 4
bz >
b0 D
0E
b0 C
1/
#83001
0/
#84001
b10 !
b10 8
16
1B
bz A
1/
#85001
0/
#86001
b11 !
b11 8
z6
0B
b0 A
1/
#87001
0/
#88001
b100 !
b100 8
13
b100 4
b100 >
b100 D
1E
bz C
1/
#89001
0/
#90001
b1 !
b1 8
00
0,
1*
b10111000 %
b10111000 9
b10101000 2
b10101000 =
z3
bz 4
bz >
b0 D
0E
b0 C
0/
#91001
b10 !
b10 8
1/
#92001
0/
#93001
b11 !
b11 8
1/
#94001
0/
#95001
b100 !
b100 8
13
b1 4
b1 >
b1 D
1E
bz C
1/
10
#96001
0/
#97001
b1 !
b1 8
z3
bz 4
bz >
b0 D
0E
b0 C
1/
#98001
0/
#99001
b10 !
b10 8
16
1B
bz A
1/
#100001
0/
#101001
b11 !
b11 8
z6
0B
b0 A
1/
#102001
0/
#103001
b100 !
b100 8
13
b1 4
b1 >
b1 D
1E
bz C
1/
#104001
0/
#105001
b1 !
b1 8
00
1.
0*
b1000111 %
b1000111 9
b111010 2
b111010 =
z3
bz 4
bz >
b0 D
0E
b0 C
0/
#106001
b10 !
b10 8
1/
#107001
0/
#108001
b11 !
b11 8
1/
#109001
0/
#110001
b100 !
b100 8
13
b1111101 4
b1111101 >
b1111101 D
1E
bz C
1/
10
#111001
0/
#112001
b1 !
b1 8
z3
bz 4
bz >
b0 D
0E
b0 C
1/
#113001
0/
#114001
b10 !
b10 8
16
1B
bz A
1/
#115001
0/
#116001
b11 !
b11 8
z6
0B
b0 A
1/
#117001
0/
#118001
b100 !
b100 8
13
b1111101 4
b1111101 >
b1111101 D
1E
bz C
1/
#119001
0/
#120001
b1 !
b1 8
00
1)
0.
b1010011 %
b1010011 9
b10111101 2
b10111101 =
z3
bz 4
bz >
b0 D
0E
b0 C
0/
#121001
b10 !
b10 8
1/
#122001
0/
#123001
b11 !
b11 8
1/
#124001
0/
#125001
b100 !
b100 8
13
b101111010000000000000000000 4
b101111010000000000000000000 >
b101111010000000000000000000 D
1E
bz C
1/
10
#126001
0/
#127001
b1 !
b1 8
z3
bz 4
bz >
b0 D
0E
b0 C
1/
#128001
0/
#129001
b10 !
b10 8
16
1B
bz A
1/
#130001
0/
#131001
b11 !
b11 8
z6
0B
b0 A
1/
#132001
0/
#133001
b100 !
b100 8
13
b101111010000000000000000000 4
b101111010000000000000000000 >
b101111010000000000000000000 D
1E
bz C
1/
#134001
0/
#135001
b1 !
b1 8
00
1,
0)
b11001 %
b11001 9
b11000011 2
b11000011 =
z3
bz 4
bz >
b0 D
0E
b0 C
0/
#136001
b10 !
b10 8
1/
#137001
0/
#138001
b11 !
b11 8
1/
#139001
0/
#140001
b100 !
b100 8
13
b0 4
b0 >
1E
bz C
1/
10
#141001
0/
#142001
b1 !
b1 8
z3
bz 4
bz >
0E
b0 C
1/
#143001
0/
#144001
b10 !
b10 8
16
1B
bz A
1/
#145001
0/
#146001
b11 !
b11 8
z6
0B
b0 A
1/
#147001
0/
#148001
b100 !
b100 8
13
b0 4
b0 >
1E
bz C
1/
#149001
0/
#150001
b1 !
b1 8
00
0,
1.
b1101 %
b1101 9
b11001000 2
b11001000 =
z3
bz 4
bz >
0E
b0 C
0/
#151001
b10 !
b10 8
1/
#152001
0/
#153001
b11 !
b11 8
1/
#154001
0/
#155001
b100 !
b100 8
13
b11000101 4
b11000101 >
b11000101 D
1E
bz C
1/
10
#156001
0/
#157001
b1 !
b1 8
z3
bz 4
bz >
b0 D
0E
b0 C
1/
#158001
0/
#159001
b10 !
b10 8
16
1B
bz A
1/
#160001
0/
#161001
b11 !
b11 8
z6
0B
b0 A
1/
#162001
0/
#163001
b100 !
b100 8
13
b11000101 4
b11000101 >
b11000101 D
1E
bz C
1/
#164001
0/
#165001
b1 !
b1 8
00
0.
1"
b1110001 %
b1110001 9
b1001000 2
b1001000 =
z3
bz 4
bz >
b0 D
0E
b0 C
0/
#166001
b10 !
b10 8
1/
#167001
0/
#168001
b11 !
b11 8
1/
#169001
0/
#170001
b100 !
b100 8
13
b10111001 4
b10111001 >
b10111001 D
1E
bz C
1/
10
#171001
0/
#172001
b1 !
b1 8
z3
bz 4
bz >
b0 D
0E
b0 C
1/
#173001
0/
#174001
b10 !
b10 8
16
1B
bz A
1/
#175001
0/
#176001
b11 !
b11 8
z6
0B
b0 A
1/
#177001
0/
#178001
b100 !
b100 8
13
b10111001 4
b10111001 >
b10111001 D
1E
bz C
1/
#179001
0/
#180001
b1 !
b1 8
00
b10110001 %
b10110001 9
b1111110 2
b1111110 =
z3
bz 4
bz >
b0 D
0E
b0 C
0/
#181001
b10 !
b10 8
1/
#182001
0/
#183001
b11 !
b11 8
1/
#184001
0/
#185001
b100 !
b100 8
13
b100101111 4
b100101111 >
b100101111 D
1E
bz C
1/
10
#186001
0/
#187001
b1 !
b1 8
z3
bz 4
bz >
b0 D
0E
b0 C
1/
#188001
0/
#189001
b10 !
b10 8
16
1B
bz A
1/
#190001
0/
#191001
b11 !
b11 8
z6
0B
b0 A
1/
#192001
0/
#193001
b100 !
b100 8
13
b100101111 4
b100101111 >
b100101111 D
1E
bz C
1/
#194001
0/
#195001
b1 !
b1 8
00
1.
0"
b11000011 %
b11000011 9
b1000101 2
b1000101 =
z3
bz 4
bz >
b0 D
0E
b0 C
0/
#196001
b10 !
b10 8
1/
#197001
0/
#198001
b11 !
b11 8
1/
#199001
0/
#200001
b100 !
b100 8
13
b10000110 4
b10000110 >
b10000110 D
1E
bz C
1/
10
#201001
0/
#202001
b1 !
b1 8
z3
bz 4
bz >
b0 D
0E
b0 C
1/
#203001
0/
#204001
b10 !
b10 8
16
1B
bz A
1/
#205001
0/
#206001
b11 !
b11 8
z6
0B
b0 A
1/
#207001
0/
#208001
b100 !
b100 8
13
b10000110 4
b10000110 >
b10000110 D
1E
bz C
1/
#209001
0/
#210001
b1 !
b1 8
00
0.
1"
b10010100 %
b10010100 9
b1001001 2
b1001001 =
z3
bz 4
bz >
b0 D
0E
b0 C
0/
#211001
b10 !
b10 8
1/
#212001
0/
#213001
b11 !
b11 8
1/
#214001
0/
#215001
b100 !
b100 8
13
b11011101 4
b11011101 >
b11011101 D
1E
bz C
1/
10
#216001
0/
#217001
b1 !
b1 8
z3
bz 4
bz >
b0 D
0E
b0 C
1/
#218001
0/
#219001
b10 !
b10 8
16
1B
bz A
1/
#220001
0/
#221001
b11 !
b11 8
z6
0B
b0 A
1/
#222001
0/
#223001
b100 !
b100 8
13
b11011101 4
b11011101 >
b11011101 D
1E
bz C
1/
#224001
0/
#225001
b1 !
b1 8
00
1*
0"
b11111 %
b11111 9
b11000 2
b11000 =
z3
bz 4
bz >
b0 D
0E
b0 C
0/
#226001
b10 !
b10 8
1/
#227001
0/
#228001
b11 !
b11 8
1/
#229001
0/
#230001
b100 !
b100 8
13
b1 4
b1 >
b1 D
1E
bz C
1/
10
#231001
0/
#232001
b1 !
b1 8
z3
bz 4
bz >
b0 D
0E
b0 C
1/
#233001
0/
#234001
b10 !
b10 8
16
1B
bz A
1/
#235001
0/
#236001
b11 !
b11 8
z6
0B
b0 A
1/
#237001
0/
#238001
b100 !
b100 8
13
b1 4
b1 >
b1 D
1E
bz C
1/
#239001
0/
#240001
b1 !
b1 8
00
1+
0*
b110000 %
b110000 9
b10100 2
b10100 =
z3
bz 4
bz >
b0 D
0E
b0 C
0/
#241001
b10 !
b10 8
1/
#242001
0/
#243001
b11 !
b11 8
1/
#244001
0/
#245001
b100 !
b100 8
13
b1 4
b1 >
b1 D
1E
bz C
1/
10
#246001
0/
#247001
b1 !
b1 8
z3
bz 4
bz >
b0 D
0E
b0 C
1/
#248001
0/
#249001
b10 !
b10 8
16
1B
bz A
1/
#250001
0/
#251001
b11 !
b11 8
z6
0B
b0 A
1/
#252001
0/
#253001
b100 !
b100 8
13
b1 4
b1 >
b1 D
1E
bz C
1/
#254001
0/
#255001
b1 !
b1 8
00
1#
0+
b110111 %
b110111 9
b10010010 2
b10010010 =
z3
bz 4
bz >
b0 D
0E
b0 C
0/
#256001
b10 !
b10 8
1/
#257001
0/
#258001
b11 !
b11 8
1/
#259001
0/
#260001
b100 !
b100 8
13
b10010 4
b10010 >
b10010 D
1E
bz C
1/
10
#261001
0/
#262001
b1 !
b1 8
z3
bz 4
bz >
b0 D
0E
b0 C
1/
#263001
0/
#264001
b10 !
b10 8
16
1B
bz A
1/
#265001
0/
#266001
b11 !
b11 8
z6
0B
b0 A
1/
#267001
0/
#268001
b100 !
b100 8
13
b10010 4
b10010 >
b10010 D
1E
bz C
1/
#269001
0/
#270001
b1 !
b1 8
00
0#
1.
b10101101 %
b10101101 9
b1010100 2
b1010100 =
z3
bz 4
bz >
b0 D
0E
b0 C
0/
#271001
b10 !
b10 8
1/
#272001
0/
#273001
b11 !
b11 8
1/
#274001
0/
#275001
b100 !
b100 8
13
b11111001 4
b11111001 >
b11111001 D
1E
bz C
1/
10
#276001
0/
#277001
b1 !
b1 8
z3
bz 4
bz >
b0 D
0E
b0 C
1/
#278001
0/
#279001
b10 !
b10 8
16
1B
bz A
1/
#280001
0/
#281001
b11 !
b11 8
z6
0B
b0 A
1/
#282001
0/
#283001
b100 !
b100 8
13
b11111001 4
b11111001 >
b11111001 D
1E
bz C
1/
#284001
0/
#285001
b1 !
b1 8
00
0.
1"
b10000010 %
b10000010 9
b10000 2
b10000 =
z3
bz 4
bz >
b0 D
0E
b0 C
0/
#286001
b10 !
b10 8
1/
#287001
0/
#288001
b11 !
b11 8
1/
#289001
0/
#290001
b100 !
b100 8
13
b10010010 4
b10010010 >
b10010010 D
1E
bz C
1/
10
#291001
0/
#292001
b1 !
b1 8
z3
bz 4
bz >
b0 D
0E
b0 C
1/
#293001
0/
#294001
b10 !
b10 8
16
1B
bz A
1/
#295001
0/
#296001
b11 !
b11 8
z6
0B
b0 A
1/
#297001
0/
#298001
b100 !
b100 8
13
b10010010 4
b10010010 >
b10010010 D
1E
bz C
1/
#299001
0/
#300001
b1 !
b1 8
00
1.
0"
b1000100 %
b1000100 9
b10101011 2
b10101011 =
z3
bz 4
bz >
b0 D
0E
b0 C
0/
#301001
b10 !
b10 8
1/
#302001
0/
#303001
b11 !
b11 8
1/
#304001
0/
#305001
b100 !
b100 8
13
b11101111 4
b11101111 >
b11101111 D
1E
bz C
1/
10
#306001
0/
#307001
b1 !
b1 8
z3
bz 4
bz >
b0 D
0E
b0 C
1/
#308001
0/
#309001
b10 !
b10 8
16
1B
bz A
1/
#310001
0/
#311001
b11 !
b11 8
z6
0B
b0 A
1/
#312001
0/
#313001
b100 !
b100 8
13
b11101111 4
b11101111 >
b11101111 D
1E
bz C
1/
#314001
0/
#315001
b1 !
b1 8
00
1&
0.
b10010110 %
b10010110 9
b1000010 2
b1000010 =
z3
bz 4
bz >
b0 D
0E
b0 C
0/
#316001
b10 !
b10 8
1/
#317001
0/
#318001
b11 !
b11 8
1/
#319001
0/
#320001
b100 !
b100 8
13
b11010110 4
b11010110 >
b11010110 D
1E
bz C
1/
10
#321001
0/
#322001
b1 !
b1 8
z3
bz 4
bz >
b0 D
0E
b0 C
1/
#323001
0/
#324001
b10 !
b10 8
16
1B
bz A
1/
#325001
0/
#326001
b11 !
b11 8
z6
0B
b0 A
1/
#327001
0/
#328001
b100 !
b100 8
13
b11010110 4
b11010110 >
b11010110 D
1E
bz C
1/
#329001
0/
#330001
b1 !
b1 8
00
0&
1+
b110110 %
b110110 9
b10010001 2
b10010001 =
z3
bz 4
bz >
b0 D
0E
b0 C
0/
#331001
b10 !
b10 8
1/
#332001
0/
#333001
b11 !
b11 8
1/
#334001
0/
#335001
b100 !
b100 8
13
b0 4
b0 >
1E
bz C
1/
10
#336001
0/
#337001
b1 !
b1 8
z3
bz 4
bz >
0E
b0 C
1/
#338001
0/
#339001
b10 !
b10 8
16
1B
bz A
1/
#340001
0/
#341001
b11 !
b11 8
z6
0B
b0 A
1/
#342001
0/
#343001
b100 !
b100 8
13
b0 4
b0 >
1E
bz C
1/
#344001
0/
#345001
b1 !
b1 8
00
1)
0+
b11000100 %
b11000100 9
b11100 2
b11100 =
z3
bz 4
bz >
0E
b0 C
0/
#346001
b10 !
b10 8
1/
#347001
0/
#348001
b11 !
b11 8
1/
#349001
0/
#350001
b100 !
b100 8
13
b111000000 4
b111000000 >
b111000000 D
1E
bz C
1/
10
#351001
0/
#352001
b1 !
b1 8
z3
bz 4
bz >
b0 D
0E
b0 C
1/
#353001
0/
#354001
b10 !
b10 8
16
1B
bz A
1/
#355001
0/
#356001
b11 !
b11 8
z6
0B
b0 A
1/
#357001
0/
#358001
b100 !
b100 8
13
b111000000 4
b111000000 >
b111000000 D
1E
bz C
1/
#359001
0/
#360001
b1 !
b1 8
00
0)
1&
b1001101 %
b1001101 9
b10000100 2
b10000100 =
z3
bz 4
bz >
b0 D
0E
b0 C
0/
#361001
b10 !
b10 8
1/
#362001
0/
#363001
b11 !
b11 8
1/
#364001
0/
#365001
b100 !
b100 8
13
b11001101 4
b11001101 >
b11001101 D
1E
bz C
1/
10
#366001
0/
#367001
b1 !
b1 8
z3
bz 4
bz >
b0 D
0E
b0 C
1/
#368001
0/
#369001
b10 !
b10 8
16
1B
bz A
1/
#370001
0/
#371001
b11 !
b11 8
z6
0B
b0 A
1/
#372001
0/
#373001
b100 !
b100 8
13
b11001101 4
b11001101 >
b11001101 D
1E
bz C
1/
#374001
0/
#375001
b1 !
b1 8
00
1)
0&
b1000100 %
b1000100 9
b10110111 2
b10110111 =
z3
bz 4
bz >
b0 D
0E
b0 C
0/
#376001
b10 !
b10 8
1/
#377001
0/
#378001
b11 !
b11 8
1/
#379001
0/
#380001
b100 !
b100 8
13
b101101110000 4
b101101110000 >
b101101110000 D
1E
bz C
1/
10
#381001
0/
#382001
b1 !
b1 8
z3
bz 4
bz >
b0 D
0E
b0 C
1/
#383001
0/
#384001
b10 !
b10 8
16
1B
bz A
1/
#385001
0/
#386001
b11 !
b11 8
z6
0B
b0 A
1/
#387001
0/
#388001
b100 !
b100 8
13
b101101110000 4
b101101110000 >
b101101110000 D
1E
bz C
1/
#389001
0/
#390001
b1 !
b1 8
00
0)
1*
b1010111 %
b1010111 9
b1011100 2
b1011100 =
z3
bz 4
bz >
b0 D
0E
b0 C
0/
#391001
b10 !
b10 8
1/
#392001
0/
#393001
b11 !
b11 8
1/
#394001
0/
#395001
b100 !
b100 8
13
b0 4
b0 >
1E
bz C
1/
10
#396001
0/
#397001
b1 !
b1 8
z3
bz 4
bz >
0E
b0 C
1/
#398001
0/
#399001
b10 !
b10 8
16
1B
bz A
1/
#400001
0/
#401001
b11 !
b11 8
z6
0B
b0 A
1/
#402001
0/
#403001
b100 !
b100 8
13
b0 4
b0 >
1E
bz C
1/
#404001
0/
#405001
b1 !
b1 8
00
1#
0*
b101100 %
b101100 9
b1101111 2
b1101111 =
z3
bz 4
bz >
0E
b0 C
0/
#406001
b10 !
b10 8
1/
#407001
0/
#408001
b11 !
b11 8
1/
#409001
0/
#410001
b100 !
b100 8
13
b101100 4
b101100 >
b101100 D
1E
bz C
1/
10
#411001
0/
#412001
b1 !
b1 8
z3
bz 4
bz >
b0 D
0E
b0 C
1/
#413001
0/
#414001
b10 !
b10 8
16
1B
bz A
1/
#415001
0/
#416001
b11 !
b11 8
z6
0B
b0 A
1/
#417001
0/
#418001
b100 !
b100 8
13
b101100 4
b101100 >
b101100 D
1E
bz C
1/
#419001
0/
#420001
b1 !
b1 8
00
1,
0#
b10001011 %
b10001011 9
b1001101 2
b1001101 =
z3
bz 4
bz >
b0 D
0E
b0 C
0/
#421001
b10 !
b10 8
1/
#422001
0/
#423001
b11 !
b11 8
1/
#424001
0/
#425001
b100 !
b100 8
13
b0 4
b0 >
1E
bz C
1/
10
#426001
0/
#427001
b1 !
b1 8
z3
bz 4
bz >
0E
b0 C
1/
#428001
0/
#429001
b10 !
b10 8
16
1B
bz A
1/
#430001
0/
#431001
b11 !
b11 8
z6
0B
b0 A
1/
#432001
0/
#433001
b100 !
b100 8
13
b0 4
b0 >
1E
bz C
1/
#434001
0/
#435001
b1 !
b1 8
00
0,
1-
b0 %
b0 9
b1101011 2
b1101011 =
z3
bz 4
bz >
0E
b0 C
0/
#436001
b10 !
b10 8
1/
#437001
0/
#438001
b11 !
b11 8
1/
#439001
0/
#440001
b100 !
b100 8
13
b1101011 4
b1101011 >
b1101011 D
1E
bz C
1/
10
#441001
0/
#442001
b1 !
b1 8
z3
bz 4
bz >
b0 D
0E
b0 C
1/
#443001
0/
#444001
b10 !
b10 8
16
1B
bz A
1/
#445001
0/
#446001
b11 !
b11 8
z6
0B
b0 A
1/
#447001
0/
