verification/coco_tb/DUT_2025/params.vh
`ifndef PARAMS_VH
`define PARAMS_VH


`define PC_reg              31:00   //[31:00]
`define instruct            63:32   //[31:00]
`define alu_res1            95:64   //[31:00]
`define load_reg           101
`define jump_en            102     //[ 4:0]
`define branch_en          103     //[ 4:0]
`define reg_write_en       104     //[ 4:0]
`define LD_ready           105     //[ 4:0]
`define SD_ready           106     //[ 4:0]
`define rd                 111:107 //[ 4:0]
`define operand_amt        115:112 //[ 3:0]
`define opRs1_reg          120:116 //[4:0]
`define opRs2_reg          127:121 //[4:0]
`define op1_reg            159:128 //[31:00]
`define op2_reg            191:160 //[31:00]
`define immediate          223:192 //[31:0]
`define alu_res2           255:224 //[31:0]
`define rd_data            287:256 //[31:0]
`define Single_Instruction 351:288 //[63:00]   
`define data_mem_loaded    383:352  

// Opcode Decoding Type
`define R_Type            7'b0110011 //0110011
`define I_Type_A          7'b0010011 // 0010011
`define I_Type_L          7'b0000011
`define S_Type            7'b0100011
`define B_Type            7'b1100011
`define J_Type_lk         7'b1101111
`define I_Type_JALR       7'b1100111
`define U_Type_lui        7'b0110111
`define U_Type_auipc      7'b0010111
`define I_Type_ECALL      7'b1110011
`define F_TYPE_FENCE      7'b0001111
`define NOOP             32'h00000013


`define ONE_OP      4'b0001
`define TWO_OP      4'b0010


// Encoding Type
`define INST_typ_R             7'b0000001
`define INST_typ_I             7'b0000010
`define INST_typ_I_ECALL       7'b1000010
`define INST_typ_S             7'b0000100
`define INST_typ_B             7'b0001000
`define INST_typ_U             7'b0010000
`define INST_typ_J             7'b0100000
`define INST_typ_F             7'b1000000
`define UNRECGONIZED           7'b0000000

// Instructions
`define inst_UNKNOWN    64'h0000_0000_0000_0000
`define inst_ADD    64'h0000_0000_0000_0001
`define inst_SUB    64'h0000_0000_0000_0002
`define inst_XOR    64'h0000_0000_0000_0004
`define inst_OR     64'h0000_0000_0000_0008

`define inst_AND    64'h0000_0000_0000_0010
`define inst_SLL    64'h0000_0000_0000_0020
`define inst_SRL    64'h0000_0000_0000_0040
`define inst_SRA    64'h0000_0000_0000_0080

`define inst_SLT    64'h0000_0000_0000_0100
`define inst_SLTU   64'h0000_0000_0000_0200
`define inst_ADDI   64'h0000_0000_0000_0400
`define inst_XORI   64'h0000_0000_0000_0800

`define inst_ORI    64'h0000_0000_0000_1000
`define inst_ANDI   64'h0000_0000_0000_2000
`define inst_SLLI   64'h0000_0000_0000_4000
`define inst_SRLI   64'h0000_0000_0000_8000

`define inst_SRAI   64'h0000_0000_0001_0000
`define inst_SLTI   64'h0000_0000_0002_0000
`define inst_SLTIU  64'h0000_0000_0004_0000
`define inst_LB     64'h0000_0000_0008_0000

`define inst_LH     64'h0000_0000_0010_0000
`define inst_LW     64'h0000_0000_0020_0000
`define inst_LBU    64'h0000_0000_0040_0000
`define inst_LHU    64'h0000_0000_0080_0000

`define inst_SB     64'h0000_0000_0100_0000
`define inst_SH     64'h0000_0000_0200_0000
`define inst_SW     64'h0000_0000_0400_0000
`define inst_BEQ    64'h0000_0000_0800_0000

`define inst_BNE    64'h0000_0000_1000_0000
`define inst_BLT    64'h0000_0000_2000_0000
`define inst_BGE    64'h0000_0000_4000_0000
`define inst_BLTU   64'h0000_0000_8000_0000

`define inst_BGEU   64'h0000_0001_0000_0000
`define inst_JAL    64'h0000_0002_0000_0000
`define inst_JALR   64'h0000_0004_0000_0000
`define inst_LUI    64'h0000_0008_0000_0000

`define inst_AUIPC  64'h0000_0010_0000_0000
`define inst_ECALL  64'h0000_0020_0000_0000
`define inst_EBREAK 64'h0000_0040_0000_0000
`define inst_FENCE  64'h0000_0080_0000_0000

`define inst_FENCEI 64'h0000_0100_0000_0000
`define inst_CSRRW  64'h0000_0200_0000_0000
`define inst_CSRRS  64'h0000_0400_0000_0000
`define inst_CSRRC  64'h0000_0800_0000_0000
`define inst_CSRRWI 64'h0000_1000_0000_0000
`define inst_CSRRSI 64'h0000_2000_0000_0000
`define inst_CSRRCI 64'h0000_4000_0000_0000

`endif

verification/coco_tb/DUT_2025/decode.v
`include "./DUT_2025/params.vh"

module decode 
   # (
    parameter   N_param = 32   ) (
    input  wire i_clk,
    input  wire i_en,
    input  wire [N_param-1:0]  instruction,
    // outputs to register file
    output wire  [4:0] rd_o,
    output wire  [4:0] rs1_o,
    output wire  [4:0] rs2_o,
    output wire  [2:0] fun3_o,
    output wire  [6:0] fun7_o,
    output wire  [31:0] imm_o,
    output wire  [63:0] Single_Instruction_o,
    output wire  [6:0] INST_typ_o,
    output wire  [6:0] opcode_o,
    output wire   [3:0] operand_amt_o
    // outputs to ALU
);

    // param_module params ()
wire [6:0] opcode;
reg  [31:0] imm;
reg  [6:0] INST_typ;
reg  [2:0] fun3;
reg  [6:0] fun7;
reg  [4:0] rd,rs1,rs2;
reg [63:0] Single_Instruction; 
reg  [3:0] operand_amt;
//FPGA 
initial begin 
    imm         <=0;
    INST_typ    <=0;
    fun3        <=0;
    fun7        <=0;
    rd          <=0;
    rs1         <=0;
    rs2         <=0;
    operand_amt <=0;
end

assign operand_amt_o        = operand_amt;
assign opcode               = instruction[6:0];
assign opcode_o             = instruction[6:0];
assign Single_Instruction_o = Single_Instruction;


always @(*) begin
    case (opcode)
        `R_Type: begin
            INST_typ <= `INST_typ_R;
            rd     <= instruction[11:7];
            fun3   <= instruction[14:12];
            rs1    <= instruction[19:15];
            rs2    <= instruction[24:20];
            fun7   <= instruction[31:25];
            imm    <= 32'b0;
        end

        `I_Type_A,`I_Type_L, `I_Type_JALR: begin  
            INST_typ <= `INST_typ_I;
            rd     <= instruction[11:7];
            fun3   <= instruction[14:12];
            rs1    <= instruction[19:15];
            rs2    <= 0;
            fun7   <= instruction[31:25];
            imm    <= {{20{instruction[31]}},instruction[31:20]};
        end

        `I_Type_ECALL: begin
            INST_typ <= `INST_typ_I_ECALL;
            rd     <= instruction[11:7];
            fun3   <= instruction[14:12];
            rs1    <= instruction[19:15];
            rs2    <= instruction[24:20];
            fun7   <= instruction[31:25];
            imm    <= {{20{instruction[31]}},instruction[31:20]};

        end 

        `S_Type: begin  
            INST_typ <= `INST_typ_S;
            rd     <= 0;
            fun3   <= instruction[14:12];
            rs1    <= instruction[19:15];
            rs2    <= instruction[24:20];
            fun7   <= 0;
            imm    <= {{20{instruction[31]}},instruction[31:25],instruction[11:7]};
        end

        `B_Type: begin  
            INST_typ <= `INST_typ_B;
            rd     <= 0;
            fun3   <= instruction[14:12];
            rs1    <= instruction[19:15];
            rs2    <= instruction[24:20];
            fun7   <= 0;
            imm    <= { {20{instruction[31]}}, instruction[7], instruction[30:25], instruction[11:8], 1'b0 }; // {{19{i_inst[31]}},i_inst[31],i_inst[7],i_inst[30:25],i_inst[11:8],1'b0} 
        end

        `U_Type_auipc, `U_Type_lui: begin  
            INST_typ <= `INST_typ_U;
            rd       <= instruction[11:7];
            fun3     <= 0;
            rs1      <= 0;
            rs2      <= 0;
            fun7     <= 0;
            imm      <= { instruction[31:12], 12'b0};     
        end

       `J_Type_lk: begin  
            INST_typ <= `INST_typ_J;
            rd     <= instruction[11:7];
            fun3   <= 0; 
            rs1    <= 0; 
            rs2    <= 0; 
            fun7   <= 0; 
            imm    <= { {12{instruction[31]}}, instruction[19:12], instruction[20], instruction[30:25], instruction[24:21], 1'b0 };
        end

        `F_TYPE_FENCE: begin  
            INST_typ <= `INST_typ_F;
            rd     <= instruction[11:7];
            fun3   <= instruction[14:12];
            rs1    <= instruction[19:15];
            rs2    <= instruction[24:20];
            fun7   <= instruction[31:25];
            imm    <= 32'b0;
        end

        default: begin
            INST_typ <= `UNRECGONIZED;
            rd     <= 0;
            fun3   <= 0;
            rs1    <= 0; 
            rs2    <= 0; 
            fun7   <= 0; 
            imm    <= 0;
        end
    endcase

    case (INST_typ)
        `INST_typ_R: begin
            case ({fun7,fun3})
            {7'b0000000,3'b000}: begin  // ADD
            Single_Instruction <= `inst_ADD;
            end 
            {7'b0100000,3'b000}: begin  // SUB
            Single_Instruction <= `inst_SUB;
            end 
            {7'b0000000,3'b001}: begin  // SLL
            Single_Instruction <= `inst_SLL;
            end 
            {7'b0000000,3'b010}: begin  // SLT
            Single_Instruction <= `inst_SLT;
            end 
            {7'b0000000,3'b011}: begin  //SLTU 
            Single_Instruction <= `inst_SLTU;
            end 
            {7'b0000000,3'b100}: begin  // XOR
            Single_Instruction <= `inst_XOR;
            end 
            {7'b0000000,3'b101}: begin  //SRL 
            Single_Instruction <= `inst_SRL;
            end 
            {7'b0100000,3'b101}: begin  // SRA
            Single_Instruction <= `inst_SRA;
            end 
            {7'b0000000,3'b110}: begin  // OR 
            Single_Instruction <= `inst_OR;
            end 
            {7'b0000000,3'b111}: begin  //AND 
            Single_Instruction <= `inst_AND;
            end 
            default: begin  //UNKNOWN 
            Single_Instruction <= `inst_UNKNOWN;
            end 
            endcase
        end
        `INST_typ_U:  begin 
            case(opcode)
            `U_Type_auipc:begin 
            Single_Instruction <= `inst_AUIPC;   
            end
            `U_Type_lui:begin 
            Single_Instruction <= `inst_LUI;
            end
            default: begin 
            Single_Instruction <= `inst_UNKNOWN;
            end
            endcase
        


        end
        `INST_typ_I: begin
            case(opcode)
            `I_Type_A: begin 
                case ({fun3})
                {3'b000}: begin  // ADDI
                Single_Instruction <= `inst_ADDI;
                end 
                {3'b010}: begin  // SLTI
                Single_Instruction <= `inst_SLTI;
                end 
                {3'b011}: begin  //SLTIU 
                Single_Instruction <= `inst_SLTIU;
                end 
                {3'b100}: begin  // XORI
                Single_Instruction <= `inst_XORI;
                end 
                {3'b110}: begin  // ORI 
                Single_Instruction <= `inst_ORI;
                end 
                {3'b111}: begin  //ANDI 
                Single_Instruction <= `inst_ANDI;
                end 
                {3'b001}: begin  //SLLI 
                    case(fun7)
                        {7'b0000000}:begin 
                Single_Instruction <= `inst_SLLI;
                        end 
                        default: begin 
                Single_Instruction <= `inst_UNKNOWN;
                        end
                    endcase
                end 
                {3'b101}: begin  
                    case(fun7)
                        {7'b0000000}:begin  //SRLI
                Single_Instruction <= `inst_SRLI;
                        end 
                        {7'b0100000}:begin //SRAI
                Single_Instruction <= `inst_SRAI;
                        end 
                        default: begin 
                Single_Instruction <= `inst_UNKNOWN;
                        end
                    endcase
                end 
                default: begin  // 
                Single_Instruction <= `inst_UNKNOWN;
                end 
            endcase
            end
            `I_Type_L: begin 
                case ({fun3})
                {3'b000}: begin  // LB
                Single_Instruction <= `inst_LB;
                end 
                {3'b001}: begin  // LH
                Single_Instruction <= `inst_LH;
                end 
                {3'b010}: begin  // LW
                Single_Instruction <= `inst_LW;
                end 
                {3'b100}: begin  // LBU
                Single_Instruction <= `inst_LBU;
                end 
                {3'b101}: begin  // LHU
                Single_Instruction <= `inst_LHU;
                end 
                default:begin 
                Single_Instruction <= `inst_UNKNOWN;
                end
                endcase
            end
            `I_Type_JALR: begin 
                case ({fun3})
                {3'b000}: begin  // JALR
                Single_Instruction <= `inst_JALR;
                end 
                default: begin 
                Single_Instruction <= `inst_UNKNOWN;
                end
                endcase
            end

            endcase
        end

        `INST_typ_I_ECALL: begin 
                case ({fun3})
                {3'b000}: begin  //
                if (instruction[20]==1'b1) begin 
                Single_Instruction <= `inst_EBREAK ;

                end else begin
                Single_Instruction <= `inst_ECALL;

                 end
                end 
                {3'b001}: begin  //
                Single_Instruction <= `inst_CSRRW;
                end 
                {3'b010}: begin  //CSRRS
                Single_Instruction <= `inst_CSRRS;
                end 
                {3'b011}: begin  //CSRRC
                Single_Instruction <= `inst_CSRRC;
                end 
                {3'b101}: begin  //CSRRWI
                Single_Instruction <= `inst_CSRRWI;
                end 
                {3'b110}: begin  //CSRRSI
                Single_Instruction <= `inst_CSRRSI;
                end 
                {3'b111}: begin  //CSRRCI
                Single_Instruction <= `inst_CSRRCI;
                end 
                default: begin 
                Single_Instruction <= `inst_UNKNOWN;
                end
        endcase

        end
        
        `INST_typ_S: begin  
            case ({fun3})
                {3'b000}: begin  // SB
                Single_Instruction <= `inst_SB;
                end 
                {3'b001}: begin  // SH
                Single_Instruction <= `inst_SH;
                end 
                {3'b010}: begin  // SW
                Single_Instruction <= `inst_SW;
                end 
                default: begin 
                Single_Instruction <= `inst_UNKNOWN;
                end
            endcase
        end

        `INST_typ_B: begin  
            case ({fun3})
                {3'b000}: begin  // SEQ
                Single_Instruction <= `inst_BEQ;
                end 
                {3'b001}: begin  // BNE
                Single_Instruction <= `inst_BNE;
                end 
                {3'b100}: begin  // BLT
                Single_Instruction <= `inst_BLT;
                end 
                {3'b101}: begin  // BGE
                Single_Instruction <= `inst_BGE;
                end 
                {3'b110}: begin  // BLTU
                Single_Instruction <= `inst_BLTU;
                end 
                {3'b111}: begin  // BGEU
                Single_Instruction <= `inst_BGEU;
                end 
                default: begin 
                Single_Instruction <= `inst_UNKNOWN;
                end
            endcase  
        end

        `INST_typ_J: begin  
                Single_Instruction <= `inst_JAL;
        end

        `INST_typ_F: begin         
                case ({fun3})
                {3'b000}: begin  // FENCE
                Single_Instruction <= `inst_FENCE;
                end 
                {3'b001}: begin  // FENCE
                Single_Instruction <= `inst_FENCEI;
                end 
                default: begin 
                Single_Instruction <= `inst_UNKNOWN;
                end
            endcase
        end


        `UNRECGONIZED: begin  
                Single_Instruction <= `inst_UNKNOWN;
        end
        default: begin
                Single_Instruction <= `inst_UNKNOWN;
        end
    
    endcase

    
end


assign rd_o   = rd;
assign fun3_o = fun3;
assign fun7_o = fun7;
assign rs1_o  = rs1;
assign rs2_o  = rs2;
assign imm_o  = imm;
assign INST_typ_o = INST_typ;
// assign opcode_o = opcode;


endmodule

verification/coco_tb/DUT_2025_Wrapper/decode_wrapper.v
module decode_wrapper # (
    parameter N_param = 32   ) (
    input wire i_clk,
    input wire i_en,
    input wire [N_param-1:0] instruction,
    output wire [4:0] rd_o,
    output wire [4:0] rs1_o,
    output wire [4:0] rs2_o,
    output wire [2:0] fun3_o,
    output wire [6:0] fun7_o,
    output wire [31:0] imm_o,
    output wire [63:0] Single_Instruction_o,
    output wire [6:0] INST_typ_o,
    output wire [6:0] opcode_o,
    output wire [3:0] operand_amt_o
);

    decode dut (
        .i_clk(i_clk),
        .i_en(i_en),
        .instruction(instruction),
        .rd_o(rd_o),
        .rs1_o(rs1_o),
        .rs2_o(rs2_o),
        .fun3_o(fun3_o),
        .fun7_o(fun7_o),
        .imm_o(imm_o),
        .Single_Instruction_o(Single_Instruction_o),
        .INST_typ_o(INST_typ_o),
        .opcode_o(opcode_o),
        .operand_amt_o(operand_amt_o)
    );
    initial begin
        $dumpfile("./vcds/decode.vcd");
        $dumpvars(0, decode_wrapper);
    end
endmodule

verification/coco_tb/vcds/decode.vcd
$date
	Sat Feb  8 12:50:41 2025
$end
$version
	Icarus Verilog
$end
$timescale
	1ps
$end
$scope module decode_wrapper $end
$var wire 1 ! i_clk $end
$var wire 1 " i_en $end
$var wire 32 # instruction [31:0] $end
$var wire 5 $ rs2_o [4:0] $end
$var wire 5 % rs1_o [4:0] $end
$var wire 5 & rd_o [4:0] $end
$var wire 4 ' operand_amt_o [3:0] $end
$var wire 7 ( opcode_o [6:0] $end
$var wire 32 ) imm_o [31:0] $end
$var wire 7 * fun7_o [6:0] $end
$var wire 3 + fun3_o [2:0] $end
$var wire 64 , Single_Instruction_o [63:0] $end
$var wire 7 - INST_typ_o [6:0] $end
$var parameter 32 . N_param $end
$scope module dut $end
$var wire 7 / INST_typ_o [6:0] $end
$var wire 64 0 Single_Instruction_o [63:0] $end
$var wire 3 1 fun3_o [2:0] $end
$var wire 7 2 fun7_o [6:0] $end
$var wire 1 ! i_clk $end
$var wire 1 " i_en $end
$var wire 32 3 imm_o [31:0] $end
$var wire 32 4 instruction [31:0] $end
$var wire 4 5 operand_amt_o [3:0] $end
$var wire 5 6 rd_o [4:0] $end
$var wire 5 7 rs1_o [4:0] $end
$var wire 5 8 rs2_o [4:0] $end
$var wire 7 9 opcode_o [6:0] $end
$var wire 7 : opcode [6:0] $end
$var parameter 32 ; N_param $end
$var reg 7 < INST_typ [6:0] $end
$var reg 64 = Single_Instruction [63:0] $end
$var reg 3 > fun3 [2:0] $end
$var reg 7 ? fun7 [6:0] $end
$var reg 32 @ imm [31:0] $end
$var reg 4 A operand_amt [3:0] $end
$var reg 5 B rd [4:0] $end
$var reg 5 C rs1 [4:0] $end
$var reg 5 D rs2 [4:0] $end
$upscope $end
$upscope $end
$enddefinitions $end
$comment Show the parameter values. $end
$dumpall
b100000 ;
b100000 .
$end
#0
$dumpvars
b0 D
b0 C
b0 B
b0 A
b0 @
b0 ?
b0 >
b0 =
b0 <
bz :
bz 9
b0 8
b0 7
b0 6
b0 5
bz 4
b0 3
b0 2
b0 1
b0 0
b0 /
b0 -
b0 ,
b0 +
b0 *
b0 )
bz (
b0 '
b0 &
b0 %
b0 $
bz #
0"
1!
$end
#5000
0!
#10000
b1000 ,
b1000 0
b1000 =
b10010 $
b10010 8
b10010 D
b10110 %
b10110 7
b10110 C
b110 +
b110 1
b110 >
b1111 &
b1111 6
b1111 B
b1 -
b1 /
b1 <
b110011 :
b110011 (
b110011 9
1!
b1001010110110011110110011 #
b1001010110110011110110011 4
1"
#15000
0!
#20000
1!
#25000
0!
#30000
1!
#35000
0!
#40000
1!
#45000
0!
#50000
1!
#55000
0!
#60000
1!
#65000
0!
#70001
1!
0"
#75001
0!
#80001
b100000000000000000000000 ,
b100000000000000000000000 0
b100000000000000000000000 =
b11111111111111111111110111011001 )
b11111111111111111111110111011001 3
b11111111111111111111110111011001 @
b1101110 *
b1101110 2
b1101110 ?
b0 $
b0 8
b0 D
b11111 %
b11111 7
b11111 C
b101 +
b101 1
b101 >
b1100 &
b1100 6
b1100 B
b10 -
b10 /
b10 <
b11 :
b11 (
b11 9
1!
b11011101100111111101011000000011 #
b11011101100111111101011000000011 4
1"
#85001
0!
#90001
1!
#95001
0!
#100001
1!
#105001
0!
#110001
1!
#115001
0!
#120001
1!
#125001
0!
#130001
1!
#135001
0!
#140002
1!
0"
#145002
0!
#150002
b100000000000000000000000000 ,
b100000000000000000000000000 0
b100000000000000000000000000 =
b11111111111111111111101000110001 )
b11111111111111111111101000110001 3
b11111111111111111111101000110001 @
b0 *
b0 2
b0 ?
b1111 %
b1111 7
b1111 C
b10 +
b10 1
b10 >
b0 &
b0 6
b0 B
b100 -
b100 /
b100 <
b100011 :
b100011 (
b100011 9
1!
b10100010000001111010100010100011 #
b10100010000001111010100010100011 4
1"
#155002
0!
#160002
1!
#165002
0!
#170002
1!
#175002
0!
#180002
1!
#185002
0!
#190002
1!
#195002
0!
#200002
1!
#205002
0!
#210003
1!
0"
#215003
0!
#220003
b100000000000000000000000000000 ,
b100000000000000000000000000000 0
b100000000000000000000000000000 =
b11111111111111111111111010001000 )
b11111111111111111111111010001000 3
b11111111111111111111111010001000 @
b101 $
b101 8
b101 D
b10100 %
b10100 7
b10100 C
b100 +
b100 1
b100 >
b1000 -
b1000 /
b1000 <
b1100011 :
b1100011 (
b1100011 9
1!
b11101000010110100100010011100011 #
b11101000010110100100010011100011 4
1"
#225003
0!
#230003
1!
#235003
0!
#240003
1!
#245003
0!
#250003
1!
#255003
0!
#260003
1!
#265003
0!
#270003
1!
#275003
0!
#280004
1!
0"
#285004
0!
#290004
b100000000000000000000000000000000000 ,
b100000000000000000000000000000000000 0
b100000000000000000000000000000000000 =
b11101011010111011001000000000000 )
b11101011010111011001000000000000 3
b11101011010111011001000000000000 @
b0 $
b0 8
b0 D
b0 %
b0 7
b0 C
b0 +
b0 1
b0 >
b1001 &
b1001 6
b1001 B
b10000 -
b10000 /
b10000 <
b110111 :
b110111 (
b110111 9
1!
b11101011010111011001010010110111 #
b11101011010111011001010010110111 4
1"
#295004
0!
#300004
1!
#305004
0!
#310004
1!
#315004
0!
#320004
1!
#325004
0!
#330004
1!
#335004
0!
#340004
1!
#345004
0!
#350005
1!
0"
#355005
0!
#360005
b1000000000000000000000000000000000 ,
b1000000000000000000000000000000000 0
b1000000000000000000000000000000000 =
b10001001100000001010 )
b10001001100000001010 3
b10001001100000001010 @
b1 &
b1 6
b1 B
b100000 -
b100000 /
b100000 <
b1101111 :
b1101111 (
b1101111 9
1!
b101110001001000011101111 #
b101110001001000011101111 4
1"
