verification/coco_tb/DUT_top/exu_jump_swc.v
module exu_jump_swc  (
    hclk                                        ,
    hrstn                                       ,
    cycle_cnt                                   ,
    dec_jump_en                                 ,
    dec_jal                                     ,
    dec_jalr                                    ,
    dec_imm_type_i                              ,
    dec_imm_type_j                              ,
    dec_rd                                      ,
    dec_rs1                                     ,
    pc                                          ,
    pc_write                                    ,
    pc_wdata                                    ,
    flush                                       ,
    reg_waddr                                   ,
    reg_wen                                     ,
    reg_wdata                                   ,
    reg_raddr_1                                 ,
    reg_ren_1                                   ,
    reg_rdata_1                                 
);
/*
Performs Direct or Indirect jump.

Jump and Link (JAL): 
Add a sign-extended J-immediate to the address of the jump instruction to form the jump target address. Store the address of the instruction following the jump into register rd. 

Jump and Link register (JALR) / indirect jump instruction: 
Add a sign extended 12-bit I-immediate to the register rs1, and set the least-significant bit of the result to 0. Store the address of the instruction following the jump into register rd. 
*/
input                       hclk                ;
input                       hrstn               ;
input           [3:0]       cycle_cnt           ;
// signals from dec 
input                       dec_jump_en         ;
input                       dec_jal             ;
input                       dec_jalr            ;
input           [11:0]      dec_imm_type_i      ;
input           [20:0]      dec_imm_type_j      ;
input           [4:0]       dec_rd              ;
input           [4:0]       dec_rs1             ;
// PC
input           [31:0]      pc                  ;
inout                       pc_write            ;
inout           [31:0]      pc_wdata            ;
// pipeline flushing
inout           [1:0]       flush               ;
// regfile write port   
inout           [4:0]       reg_waddr           ;
inout                       reg_wen             ;
inout           [31:0]      reg_wdata           ;
inout           [4:0]       reg_raddr_1         ;
inout                       reg_ren_1           ;
input           [31:0]      reg_rdata_1         ;
// middle signals
reg             [4:0]       mid_reg_waddr       ;
reg                         mid_reg_wen         ;
reg             [31:0]      mid_reg_wdata       ;
reg             [4:0]       mid_reg_raddr_1     ;
reg                         mid_reg_ren_1       ;
reg                         mid_pc_write        ;
reg             [31:0]      mid_pc_wdata        ;
// SEXT values
wire            [31:0]      sext_imm_type_j     ;
wire            [31:0]      sext_imm_type_i     ;

assign reg_waddr   = mid_reg_wen   ? mid_reg_waddr    : 'z  ;
assign reg_wen     = mid_reg_wen   ? mid_reg_wen      : 'z  ;
assign reg_wdata   = mid_reg_wen   ? mid_reg_wdata    : 'z  ;
assign reg_raddr_1 = mid_reg_ren_1 ? mid_reg_raddr_1  : 'z  ;
assign reg_ren_1   = mid_reg_ren_1 ? mid_reg_ren_1    : 'z  ;

assign sext_imm_type_j = {{11{dec_imm_type_j[19]}}, dec_imm_type_j};
assign sext_imm_type_i = {{20{dec_imm_type_i[11]}}, dec_imm_type_i};

wire [31:0] pc_real = pc - 8;
wire [31:0] pc_next = dec_jal ? (pc_real + sext_imm_type_j) : ((reg_rdata_1 + sext_imm_type_i) & ~1); // assigns the pc to jump to based on if dec_jal was called, to do the direct jump, otherwise do the indirect jump

// Read and write the register values during cycles 1 and 2
always@(posedge hclk or negedge hrstn) begin
    if(!hrstn) begin
        mid_reg_raddr_1 <= 0;
        mid_reg_ren_1   <= 0;

        mid_reg_waddr   <= 0;
        mid_reg_wen     <= 0;
        mid_reg_wdata   <= 0;
    end else if(dec_jump_en) begin
        if(cycle_cnt == 1)begin// on cycle 1, if performing an indirect jump, assign the temp register read address to the decoded register and enable reading
            if(dec_jalr) begin
                mid_reg_raddr_1 <= dec_rs1;
                mid_reg_ren_1   <= 1;
            end else begin
                mid_reg_raddr_1 <= 0;
                mid_reg_ren_1   <= 0;
            end

            mid_reg_waddr   <= 0;
            mid_reg_wen     <= 0;
            mid_reg_wdata   <= 0;
        end else if(cycle_cnt == 2)begin // on cycle 2, assign the temp register write address to the decoded rd value and enable writing, with the write data being the address following the jump instruction.
            mid_reg_raddr_1 <= 0;
            mid_reg_ren_1   <= 0;

            mid_reg_waddr <= dec_rd;
            mid_reg_wen   <= 1;
            mid_reg_wdata <= pc_real + 4;
        end else begin
            mid_reg_raddr_1 <= 0;
            mid_reg_ren_1   <= 0;

            mid_reg_waddr <= 0;
            mid_reg_wen   <= 0;
            mid_reg_wdata <= 0;
        end
    end else begin
        mid_reg_raddr_1 <= 0;
        mid_reg_ren_1   <= 0;

        mid_reg_waddr <= 0;
        mid_reg_wen   <= 0;
        mid_reg_wdata <= 0;
    end
end

// Change the PC value during cycles 3 and 4 based on the pc_next value from earlier.
always@(posedge hclk or negedge hrstn) begin
    if(!hrstn) begin
        mid_pc_write <= 0;
        mid_pc_wdata <= 0;
    end else if(dec_jump_en) begin
        if(cycle_cnt == 3) begin // on cycle 3, if we are jumping to a value other than 4 or 8 ahead, we assign the temp pc write value to 1 and the temp pc write data value to the pc_next value previously assigned.
            if(pc_next != pc_real + 4 && pc_next != pc_real + 8) begin
                mid_pc_write <= 1;
                mid_pc_wdata <= pc_next;
            end else begin
                mid_pc_write <= 0;
                mid_pc_wdata <= 0;
            end
        end else if(cycle_cnt == 4) begin // on cycle 4, hold the temp pc values.
            mid_pc_write <= mid_pc_write;
            mid_pc_wdata <= mid_pc_wdata;
        end else begin
            mid_pc_write <= 0;
            mid_pc_wdata <= 0;
        end
    end else begin
        mid_pc_write <= 0;
        mid_pc_wdata <= 0;
    end
end

assign pc_write = dec_jump_en ? mid_pc_write : 'z;
assign pc_wdata = dec_jump_en ? mid_pc_wdata : 'z;

localparam FLUSH_DISABLE = 0, FLUSH_CYCLE_1 = 1, FLUSH_CYCLE_2 = 2;
reg [1:0] mid_flush;


// Set the flush state during cycles 3 and 4 based on how many values we are jumping by.
always@(posedge hclk or negedge hrstn) begin
    if(!hrstn) begin
        mid_flush <= FLUSH_DISABLE;
    end else if(dec_jump_en) begin
        if(cycle_cnt == 3)begin // on cycle 3, set the temporary flush state
            if(pc_next == pc_real + 4) begin // if we are jumping by 4, do not flush
                mid_flush <= FLUSH_DISABLE;
            end else if(pc_next == pc_real + 8) begin // if we are jumping by 8, go to flush cycle 1
                mid_flush <= FLUSH_CYCLE_1;
            end else begin // otherwise, go to flush cycle 2
                mid_flush <= FLUSH_CYCLE_2;
            end
        end else if(cycle_cnt == 4) begin // on cycle 4, hold the temporary flush state
            mid_flush <= mid_flush;
        end else begin // on cycles 1 and 2, disable flushing.
            mid_flush <= FLUSH_DISABLE;
        end
    end else begin
        mid_flush <= FLUSH_DISABLE;
    end
end

assign flush = dec_jump_en ? mid_flush : 'z;

endmodule

verification/coco_tb/DUT_Wrapper/exu_jump_swc_wrapper.v
module exu_jump_swc_wrapper (
    input hclk,
    input hrstn,
    input [3:0] cycle_cnt,
    input dec_jump_en,
    input dec_jal,
    input dec_jalr,
    input [11:0] dec_imm_type_i,
    input [20:0] dec_imm_type_j,
    input [4:0] dec_rd,
    input [4:0] dec_rs1,
    input [31:0] pc,
    input [31:0] reg_rdata_1,
    inout pc_write,
    inout [31:0] pc_wdata,
    inout [1:0] flush,
    inout [4:0] reg_waddr,
    inout reg_wen,
    inout [31:0] reg_wdata,
    inout [4:0] reg_raddr_1,
    inout reg_ren_1
);

    exu_jump_swc dut (
        .hclk(hclk),
        .hrstn(hrstn),
        .cycle_cnt(cycle_cnt),
        .dec_jump_en(dec_jump_en),
        .dec_jal(dec_jal),
        .dec_jalr(dec_jalr),
        .dec_imm_type_i(dec_imm_type_i),
        .dec_imm_type_j(dec_imm_type_j),
        .dec_rd(dec_rd),
        .dec_rs1(dec_rs1),
        .pc(pc),
        .reg_rdata_1(reg_rdata_1),
        .pc_write(pc_write),
        .pc_wdata(pc_wdata),
        .flush(flush),
        .reg_waddr(reg_waddr),
        .reg_wen(reg_wen),
        .reg_wdata(reg_wdata),
        .reg_raddr_1(reg_raddr_1),
        .reg_ren_1(reg_ren_1)
    );
    initial begin
        $dumpfile("./vcds/exu_jump_swc.vcd");
        $dumpvars(0, exu_jump_swc_wrapper);
    end
endmodule

verification/coco_tb/vcds/exu_jump_swc.vcd
$date
	Wed Jan 29 08:55:18 2025
$end
$version
	Icarus Verilog
$end
$timescale
	1ps
$end
$scope module exu_jump_swc_wrapper $end
$var wire 4 ! cycle_cnt [3:0] $end
$var wire 12 " dec_imm_type_i [11:0] $end
$var wire 21 # dec_imm_type_j [20:0] $end
$var wire 1 $ dec_jal $end
$var wire 1 % dec_jalr $end
$var wire 1 & dec_jump_en $end
$var wire 5 ' dec_rd [4:0] $end
$var wire 5 ( dec_rs1 [4:0] $end
$var wire 1 ) hclk $end
$var wire 1 * hrstn $end
$var wire 32 + pc [31:0] $end
$var wire 32 , reg_rdata_1 [31:0] $end
$var wire 1 - reg_wen $end
$var wire 32 . reg_wdata [31:0] $end
$var wire 5 / reg_waddr [4:0] $end
$var wire 1 0 reg_ren_1 $end
$var wire 5 1 reg_raddr_1 [4:0] $end
$var wire 1 2 pc_write $end
$var wire 32 3 pc_wdata [31:0] $end
$var wire 2 4 flush [1:0] $end
$scope module dut $end
$var wire 4 5 cycle_cnt [3:0] $end
$var wire 12 6 dec_imm_type_i [11:0] $end
$var wire 21 7 dec_imm_type_j [20:0] $end
$var wire 1 $ dec_jal $end
$var wire 1 % dec_jalr $end
$var wire 1 & dec_jump_en $end
$var wire 5 8 dec_rd [4:0] $end
$var wire 5 9 dec_rs1 [4:0] $end
$var wire 1 ) hclk $end
$var wire 1 * hrstn $end
$var wire 32 : pc [31:0] $end
$var wire 32 ; reg_rdata_1 [31:0] $end
$var wire 32 < sext_imm_type_j [31:0] $end
$var wire 32 = sext_imm_type_i [31:0] $end
$var wire 1 - reg_wen $end
$var wire 32 > reg_wdata [31:0] $end
$var wire 5 ? reg_waddr [4:0] $end
$var wire 1 0 reg_ren_1 $end
$var wire 5 @ reg_raddr_1 [4:0] $end
$var wire 1 2 pc_write $end
$var wire 32 A pc_wdata [31:0] $end
$var wire 32 B pc_real [31:0] $end
$var wire 32 C pc_next [31:0] $end
$var wire 2 D flush [1:0] $end
$var parameter 32 E FLUSH_CYCLE_1 $end
$var parameter 32 F FLUSH_CYCLE_2 $end
$var parameter 32 G FLUSH_DISABLE $end
$var reg 2 H mid_flush [1:0] $end
$var reg 32 I mid_pc_wdata [31:0] $end
$var reg 1 J mid_pc_write $end
$var reg 5 K mid_reg_raddr_1 [4:0] $end
$var reg 1 L mid_reg_ren_1 $end
$var reg 5 M mid_reg_waddr [4:0] $end
$var reg 32 N mid_reg_wdata [31:0] $end
$var reg 1 O mid_reg_wen $end
$upscope $end
$upscope $end
$enddefinitions $end
$comment Show the parameter values. $end
$dumpall
b0 G
b10 F
b1 E
$end
#0
$dumpvars
0O
b0 N
b0 M
0L
b0 K
0J
b0 I
b0 H
b0 D
b1000 C
b10 B
b0 A
bz @
bz ?
bz >
b101 =
bz <
b11 ;
b1010 :
bz 9
bz 8
bz 7
b101 6
bz 5
b0 4
b0 3
02
bz 1
z0
bz /
bz .
z-
b11 ,
b1010 +
0*
1)
bz (
bz '
1&
1%
0$
bz #
b101 "
bz !
$end
#1000
0)
#2000
1)
#3000
0)
#4000
1)
#5000
0)
#6000
1)
#7000
0)
#8000
1)
#9000
0)
#10000
1)
b1 !
b1 5
1*
#11000
0)
#12000
b10 !
b10 5
10
1L
bz K
1)
#13000
0)
#14000
b11 !
b11 5
1-
b110 .
b110 >
z0
b110 N
1O
bz M
0L
b0 K
1)
#15000
0)
#16000
b100 !
b100 5
z-
bz .
bz >
b1000 3
b1000 A
12
b10 4
b10 D
b0 N
0O
b0 M
b1000 I
1J
b10 H
1)
#17000
0)
#18000
1)
#18001
b0 3
b0 A
02
b0 4
b0 D
b0 I
0J
b0 H
b10110000000 C
0*
b10001000001111100 <
b10001000001111100 #
b10001000001111100 7
b1100100010 =
b1100100010 "
b1100100010 6
b1001011111 ,
b1001011111 ;
b11111111111111111111111111111000 B
b0 +
b0 :
#19001
0)
#20001
1)
#21001
0)
#22001
1)
#23001
0)
#24001
1)
#25001
0)
#26001
1)
#27001
0)
#28001
1)
b1 !
b1 5
1*
#29001
0)
#30001
b10 !
b10 5
10
1L
bz K
1)
#31001
0)
#32001
b11 !
b11 5
1-
b11111111111111111111111111111100 .
b11111111111111111111111111111100 >
z0
b11111111111111111111111111111100 N
1O
bz M
0L
b0 K
1)
#33001
0)
#34001
b100 !
b100 5
z-
bz .
bz >
b10110000000 3
b10110000000 A
12
b10 4
b10 D
b0 N
0O
b0 M
b10110000000 I
1J
b10 H
1)
#35001
0)
#36001
b0 3
b0 A
02
b0 4
b0 D
b0 I
0J
b0 H
b1011110000010100101 C
0*
0%
1$
b1011110000010101101 <
b1011110000010101101 #
b1011110000010101101 7
b11111111111111111111101111001001 =
b101111001001 "
b101111001001 6
b111111110000 ,
b111111110000 ;
b1 !
b1 5
1)
#37001
0)
#38001
b10 !
b10 5
1)
#39001
0)
#40001
b11 !
b11 5
1)
#41001
0)
#42001
b100 !
b100 5
1)
#43001
0)
#44001
b1 !
b1 5
1)
#45001
0)
#46001
1)
b1 !
b1 5
1*
#47001
0)
#48001
b10 !
b10 5
1)
#49001
0)
#50001
b11 !
b11 5
1-
b11111111111111111111111111111100 .
b11111111111111111111111111111100 >
b11111111111111111111111111111100 N
1O
bz M
1)
#51001
0)
#52001
b100 !
b100 5
z-
bz .
bz >
b1011110000010100101 3
b1011110000010100101 A
12
b10 4
b10 D
b0 N
0O
b0 M
b1011110000010100101 I
1J
b10 H
1)
#53001
0)
#54001
b0 3
b0 A
02
b0 4
b0 D
b0 I
0J
b0 H
b101011011000 C
0*
1%
0$
b1111011000011111001 <
b1111011000011111001 #
b1111011000011111001 7
b110111011 =
b110111011 "
b110111011 6
b100100011101 ,
b100100011101 ;
b1 !
b1 5
1)
#55001
0)
#56001
b10 !
b10 5
1)
#57001
0)
#58001
b11 !
b11 5
1)
#59001
0)
#60001
b100 !
b100 5
1)
#61001
0)
#62001
b1 !
b1 5
1)
#63001
0)
#64001
1)
b1 !
b1 5
1*
#65001
0)
#66001
b10 !
b10 5
10
1L
bz K
1)
#67001
0)
#68001
b11 !
b11 5
1-
b11111111111111111111111111111100 .
b11111111111111111111111111111100 >
z0
b11111111111111111111111111111100 N
1O
bz M
0L
b0 K
1)
#69001
0)
#70001
b100 !
b100 5
z-
bz .
bz >
b101011011000 3
b101011011000 A
12
b10 4
b10 D
b0 N
0O
b0 M
b101011011000 I
1J
b10 H
1)
#71001
0)
#72001
b0 3
b0 A
02
b0 4
b0 D
b0 I
0J
b0 H
b100100100010 C
0*
b1011100111001100 <
b1011100111001100 #
b1011100111001100 7
b10010111100 =
b10010111100 "
b10010111100 6
b10001100110 ,
b10001100110 ;
b1 !
b1 5
1)
#73001
0)
#74001
b10 !
b10 5
1)
#75001
0)
#76001
b11 !
b11 5
1)
#77001
0)
#78001
b100 !
b100 5
1)
#79001
0)
#80001
b1 !
b1 5
1)
#81001
0)
#82001
1)
b1 !
b1 5
1*
#83001
0)
#84001
b10 !
b10 5
10
1L
bz K
1)
#85001
0)
#86001
b11 !
b11 5
1-
b11111111111111111111111111111100 .
b11111111111111111111111111111100 >
z0
b11111111111111111111111111111100 N
1O
bz M
0L
b0 K
1)
#87001
0)
#88001
b100 !
b100 5
z-
bz .
bz >
b100100100010 3
b100100100010 A
12
b10 4
b10 D
b0 N
0O
b0 M
b100100100010 I
1J
b10 H
1)
#89001
0)
#90001
b0 3
b0 A
02
b0 4
b0 D
b0 I
0J
b0 H
b110110001101011001 C
0*
0%
1$
b110110001101100001 <
b110110001101100001 #
b110110001101100001 7
b10101111111 =
b10101111111 "
b10101111111 6
b1111100101 ,
b1111100101 ;
b1 !
b1 5
1)
#91001
0)
#92001
b10 !
b10 5
1)
#93001
0)
#94001
b11 !
b11 5
1)
#95001
0)
#96001
b100 !
b100 5
1)
#97001
0)
#98001
b1 !
b1 5
1)
#99001
0)
#100001
1)
b1 !
b1 5
1*
#101001
0)
#102001
b10 !
b10 5
1)
#103001
0)
#104001
b11 !
b11 5
1-
b11111111111111111111111111111100 .
b11111111111111111111111111111100 >
b11111111111111111111111111111100 N
1O
bz M
1)
#105001
0)
#106001
b100 !
b100 5
z-
bz .
bz >
b110110001101011001 3
b110110001101011001 A
12
b10 4
b10 D
b0 N
0O
b0 M
b110110001101011001 I
1J
b10 H
1)
#107001
0)
#108001
b0 3
b0 A
02
b0 4
b0 D
b0 I
0J
b0 H
b100100011111100011 C
0*
b100100011111101011 <
b100100011111101011 #
b100100011111101011 7
b1011000001 =
b1011000001 "
b1011000001 6
b111011011000 ,
b111011011000 ;
b1 !
b1 5
1)
#109001
0)
#110001
b10 !
b10 5
1)
#111001
0)
#112001
b11 !
b11 5
1)
#113001
0)
#114001
b100 !
b100 5
1)
#115001
0)
#116001
b1 !
b1 5
1)
#117001
0)
#118001
1)
b1 !
b1 5
1*
#119001
0)
#120001
b10 !
b10 5
1)
#121001
0)
#122001
b11 !
b11 5
1-
b11111111111111111111111111111100 .
b11111111111111111111111111111100 >
b11111111111111111111111111111100 N
1O
bz M
1)
#123001
0)
#124001
b100 !
b100 5
z-
bz .
bz >
b100100011111100011 3
b100100011111100011 A
12
b10 4
b10 D
b0 N
0O
b0 M
b100100011111100011 I
1J
b10 H
1)
#125001
0)
#126001
b0 3
b0 A
02
b0 4
b0 D
b0 I
0J
b0 H
b1000101011101101101 C
0*
b1000101011101110101 <
b1000101011101110101 #
b1000101011101110101 7
b11111111111111111111101100001001 =
b101100001001 "
b101100001001 6
b10101111110 ,
b10101111110 ;
b1 !
b1 5
1)
#127001
0)
#128001
b10 !
b10 5
1)
#129001
0)
#130001
b11 !
b11 5
1)
#131001
0)
#132001
b100 !
b100 5
1)
#133001
0)
#134001
b1 !
b1 5
1)
#135001
0)
#136001
1)
b1 !
b1 5
1*
#137001
0)
#138001
b10 !
b10 5
1)
#139001
0)
#140001
b11 !
b11 5
1-
b11111111111111111111111111111100 .
b11111111111111111111111111111100 >
b11111111111111111111111111111100 N
1O
bz M
1)
#141001
0)
#142001
b100 !
b100 5
z-
bz .
bz >
b1000101011101101101 3
b1000101011101101101 A
12
b10 4
b10 D
b0 N
0O
b0 M
b1000101011101101101 I
1J
b10 H
1)
#143001
0)
#144001
b0 3
b0 A
02
b0 4
b0 D
b0 I
0J
b0 H
b10101001010 C
0*
1%
0$
b111011000010101101 <
b111011000010101101 #
b111011000010101101 7
b11111111111111111111100000111111 =
b100000111111 "
b100000111111 6
b110100001011 ,
b110100001011 ;
b1 !
b1 5
1)
#145001
0)
#146001
b10 !
b10 5
1)
#147001
0)
#148001
b11 !
b11 5
1)
#149001
0)
#150001
b100 !
b100 5
1)
#151001
0)
#152001
b1 !
b1 5
1)
#153001
0)
#154001
1)
b1 !
b1 5
1*
#155001
0)
#156001
b10 !
b10 5
10
1L
bz K
1)
#157001
0)
#158001
b11 !
b11 5
1-
b11111111111111111111111111111100 .
b11111111111111111111111111111100 >
z0
b11111111111111111111111111111100 N
1O
bz M
0L
b0 K
1)
#159001
0)
#160001
b100 !
b100 5
z-
bz .
bz >
b10101001010 3
b10101001010 A
12
b10 4
b10 D
b0 N
0O
b0 M
b10101001010 I
1J
b10 H
1)
#161001
0)
#162001
b0 3
b0 A
02
b0 4
b0 D
b0 I
0J
b0 H
b1101101001101010111 C
0*
0%
1$
b1101101001101011111 <
b1101101001101011111 #
b1101101001101011111 7
b11110111011 =
b11110111011 "
b11110111011 6
b11110101100 ,
b11110101100 ;
b1 !
b1 5
1)
#163001
0)
#164001
b10 !
b10 5
1)
#165001
0)
#166001
b11 !
b11 5
1)
#167001
0)
#168001
b100 !
b100 5
1)
#169001
0)
#170001
b1 !
b1 5
1)
#171001
0)
#172001
1)
b1 !
b1 5
1*
#173001
0)
#174001
b10 !
b10 5
1)
#175001
0)
#176001
b11 !
b11 5
1-
b11111111111111111111111111111100 .
b11111111111111111111111111111100 >
b11111111111111111111111111111100 N
1O
bz M
1)
#177001
0)
#178001
b100 !
b100 5
z-
bz .
bz >
b1101101001101010111 3
b1101101001101010111 A
12
b10 4
b10 D
b0 N
0O
b0 M
b1101101001101010111 I
1J
b10 H
1)
#179001
0)
#180001
b0 3
b0 A
02
b0 4
b0 D
b0 I
0J
b0 H
b11111111111111111111111111011000 C
0*
1%
0$
b1001100001110011101 <
b1001100001110011101 #
b1001100001110011101 7
b11111111111111111111100101110110 =
b100101110110 "
b100101110110 6
b11001100010 ,
b11001100010 ;
b1 !
b1 5
1)
#181001
0)
#182001
b10 !
b10 5
1)
#183001
0)
#184001
b11 !
b11 5
1)
#185001
0)
#186001
b100 !
b100 5
1)
#187001
0)
#188001
b1 !
b1 5
1)
#189001
0)
#190001
1)
b1 !
b1 5
1*
#191001
0)
#192001
b10 !
b10 5
10
1L
bz K
1)
#193001
0)
#194001
b11 !
b11 5
1-
b11111111111111111111111111111100 .
b11111111111111111111111111111100 >
z0
b11111111111111111111111111111100 N
1O
bz M
0L
b0 K
1)
#195001
0)
#196001
b100 !
b100 5
z-
bz .
bz >
b11111111111111111111111111011000 3
b11111111111111111111111111011000 A
12
b10 4
b10 D
b0 N
0O
b0 M
b11111111111111111111111111011000 I
1J
b10 H
1)
#197001
0)
#198001
b0 3
b0 A
02
b0 4
b0 D
b0 I
0J
b0 H
b100001000110 C
0*
b1000010011010001110 <
b1000010011010001110 #
b1000010011010001110 7
b11111111111111111111100010110011 =
b100010110011 "
b100010110011 6
b111110010011 ,
b111110010011 ;
b1 !
b1 5
1)
#199001
0)
#200001
b10 !
b10 5
1)
#201001
0)
#202001
b11 !
b11 5
1)
#203001
0)
#204001
b100 !
b100 5
1)
#205001
0)
#206001
b1 !
b1 5
1)
#207001
0)
#208001
1)
b1 !
b1 5
1*
#209001
0)
#210001
b10 !
b10 5
10
1L
bz K
1)
#211001
0)
#212001
b11 !
b11 5
1-
b11111111111111111111111111111100 .
b11111111111111111111111111111100 >
z0
b11111111111111111111111111111100 N
1O
bz M
0L
b0 K
1)
#213001
0)
#214001
b100 !
b100 5
z-
bz .
bz >
b100001000110 3
b100001000110 A
12
b10 4
b10 D
b0 N
0O
b0 M
b100001000110 I
1J
b10 H
1)
#215001
0)
#216001
b0 3
b0 A
02
b0 4
b0 D
b0 I
0J
b0 H
b11110100 C
0*
b1110100011100001101 <
b1110100011100001101 #
b1110100011100001101 7
b11111111111111111111100001101101 =
b100001101101 "
b100001101101 6
b100010001000 ,
b100010001000 ;
b1 !
b1 5
1)
#217001
0)
#218001
b10 !
b10 5
1)
#219001
0)
#220001
b11 !
b11 5
1)
#221001
0)
#222001
b100 !
b100 5
1)
#223001
0)
#224001
b1 !
b1 5
1)
#225001
0)
#226001
1)
b1 !
b1 5
1*
#227001
0)
#228001
b10 !
b10 5
10
1L
bz K
1)
#229001
0)
#230001
b11 !
b11 5
1-
b11111111111111111111111111111100 .
b11111111111111111111111111111100 >
z0
b11111111111111111111111111111100 N
1O
bz M
0L
b0 K
1)
#231001
0)
#232001
b100 !
b100 5
z-
bz .
bz >
b11110100 3
b11110100 A
12
b10 4
b10 D
b0 N
0O
b0 M
b11110100 I
1J
b10 H
1)
#233001
0)
#234001
b0 3
b0 A
02
b0 4
b0 D
b0 I
0J
b0 H
b100100000010 C
0*
b1111000110001010101 <
b1111000110001010101 #
b1111000110001010101 7
b11111111111111111111111100000100 =
b111100000100 "
b111100000100 6
b100111111110 ,
b100111111110 ;
b1 !
b1 5
1)
#235001
0)
#236001
b10 !
b10 5
1)
#237001
0)
#238001
b11 !
b11 5
1)
#239001
0)
#240001
b100 !
b100 5
1)
#241001
0)
#242001
b1 !
b1 5
1)
#243001
0)
#244001
1)
b1 !
b1 5
1*
#245001
0)
#246001
b10 !
b10 5
10
1L
bz K
1)
#247001
0)
#248001
b11 !
b11 5
1-
b11111111111111111111111111111100 .
b11111111111111111111111111111100 >
z0
b11111111111111111111111111111100 N
1O
bz M
0L
b0 K
1)
#249001
0)
#250001
b100 !
b100 5
z-
bz .
bz >
b100100000010 3
b100100000010 A
12
b10 4
b10 D
b0 N
0O
b0 M
b100100000010 I
1J
b10 H
1)
#251001
0)
#252001
b0 3
b0 A
02
b0 4
b0 D
b0 I
0J
b0 H
b11011010110 C
0*
b1001011111100100 <
b1001011111100100 #
b1001011111100100 7
b10100 =
b10100 "
b10100 6
b11011000011 ,
b11011000011 ;
b1 !
b1 5
1)
#253001
0)
#254001
b10 !
b10 5
1)
#255001
0)
#256001
b11 !
b11 5
1)
#257001
0)
#258001
b100 !
b100 5
1)
#259001
0)
#260001
b1 !
b1 5
1)
#261001
0)
#262001
1)
b1 !
b1 5
1*
#263001
0)
#264001
b10 !
b10 5
10
1L
bz K
1)
#265001
0)
#266001
b11 !
b11 5
1-
b11111111111111111111111111111100 .
b11111111111111111111111111111100 >
z0
b11111111111111111111111111111100 N
1O
bz M
0L
b0 K
1)
#267001
0)
#268001
b100 !
b100 5
z-
bz .
bz >
b11011010110 3
b11011010110 A
12
b10 4
b10 D
b0 N
0O
b0 M
b11011010110 I
1J
b10 H
1)
#269001
0)
#270001
b0 3
b0 A
02
b0 4
b0 D
b0 I
0J
b0 H
b11111111111111111111110111110010 C
0*
b1010111001110101111 <
b1010111001110101111 #
b1010111001110101111 7
b11111111111111111111100101001101 =
b100101001101 "
b100101001101 6
b10010100101 ,
b10010100101 ;
b1 !
b1 5
1)
#271001
0)
#272001
b10 !
b10 5
1)
#273001
0)
#274001
b11 !
b11 5
1)
#275001
0)
#276001
b100 !
b100 5
1)
#277001
0)
#278001
b1 !
b1 5
1)
#279001
0)
#280001
1)
b1 !
b1 5
1*
#281001
0)
#282001
b10 !
b10 5
10
1L
bz K
1)
#283001
0)
#284001
b11 !
b11 5
1-
b11111111111111111111111111111100 .
b11111111111111111111111111111100 >
z0
b11111111111111111111111111111100 N
1O
bz M
0L
b0 K
1)
#285001
0)
#286001
b100 !
b100 5
z-
bz .
bz >
b11111111111111111111110111110010 3
b11111111111111111111110111110010 A
12
b10 4
b10 D
b0 N
0O
b0 M
b11111111111111111111110111110010 I
1J
b10 H
1)
#287001
0)
#288001
b0 3
b0 A
02
b0 4
b0 D
b0 I
0J
b0 H
b111100101001100100 C
0*
0%
1$
b111100101001101100 <
b111100101001101100 #
b111100101001101100 7
b11111111111111111111110100110110 =
b110100110110 "
b110100110110 6
b110000101010 ,
b110000101010 ;
b1 !
b1 5
1)
#289001
0)
#290001
b10 !
b10 5
1)
#291001
0)
#292001
b11 !
b11 5
1)
#293001
0)
#294001
b100 !
b100 5
1)
#295001
0)
#296001
b1 !
b1 5
1)
#297001
0)
#298001
1)
b1 !
b1 5
1*
#299001
0)
#300001
b10 !
b10 5
1)
#301001
0)
#302001
b11 !
b11 5
1-
b11111111111111111111111111111100 .
b11111111111111111111111111111100 >
b11111111111111111111111111111100 N
1O
bz M
1)
#303001
0)
#304001
b100 !
b100 5
z-
bz .
bz >
b111100101001100100 3
b111100101001100100 A
12
b10 4
b10 D
b0 N
0O
b0 M
b111100101001100100 I
1J
b10 H
1)
#305001
0)
#306001
b0 3
b0 A
02
b0 4
b0 D
b0 I
0J
b0 H
b110001010000 C
0*
1%
0$
b1011110101111101110 <
b1011110101111101110 #
b1011110101111101110 7
b10010101000 =
b10010101000 "
b10010101000 6
b11110101000 ,
b11110101000 ;
b1 !
b1 5
1)
#307001
0)
#308001
b10 !
b10 5
1)
#309001
0)
#310001
b11 !
b11 5
1)
#311001
0)
#312001
b100 !
b100 5
1)
#313001
0)
#314001
b1 !
b1 5
1)
#315001
0)
#316001
1)
b1 !
b1 5
1*
#317001
0)
#318001
b10 !
b10 5
10
1L
bz K
1)
#319001
0)
#320001
b11 !
b11 5
1-
b11111111111111111111111111111100 .
b11111111111111111111111111111100 >
z0
b11111111111111111111111111111100 N
1O
bz M
0L
b0 K
1)
#321001
0)
#322001
b100 !
b100 5
z-
bz .
bz >
b110001010000 3
b110001010000 A
12
b10 4
b10 D
b0 N
0O
b0 M
b110001010000 I
1J
b10 H
1)
#323001
0)
#324001
b0 3
b0 A
02
b0 4
b0 D
b0 I
0J
b0 H
b11110011110 C
0*
b1110111001110111001 <
b1110111001110111001 #
b1110111001110111001 7
b11111111111111111111100111000110 =
b100111000110 "
b100111000110 6
b110111011001 ,
b110111011001 ;
b1 !
b1 5
1)
#325001
0)
#326001
b10 !
b10 5
1)
#327001
0)
#328001
b11 !
b11 5
1)
#329001
0)
#330001
b100 !
b100 5
1)
#331001
0)
#332001
b1 !
b1 5
1)
#333001
0)
#334001
1)
b1 !
b1 5
1*
#335001
0)
#336001
b10 !
b10 5
10
1L
bz K
1)
#337001
0)
#338001
b11 !
b11 5
1-
b11111111111111111111111111111100 .
b11111111111111111111111111111100 >
z0
b11111111111111111111111111111100 N
1O
bz M
0L
b0 K
1)
#339001
0)
#340001
b100 !
b100 5
z-
bz .
bz >
b11110011110 3
b11110011110 A
12
b10 4
b10 D
b0 N
0O
b0 M
b11110011110 I
1J
b10 H
1)
#341001
0)
#342001
b0 3
b0 A
02
b0 4
b0 D
b0 I
0J
b0 H
b111111110 C
0*
b1001011000100100000 <
b1001011000100100000 #
b1001011000100100000 7
b11101 =
b11101 "
b11101 6
b111100001 ,
b111100001 ;
b1 !
b1 5
1)
#343001
0)
#344001
b10 !
b10 5
1)
#345001
0)
#346001
b11 !
b11 5
1)
#347001
0)
#348001
b100 !
b100 5
1)
#349001
0)
#350001
b1 !
b1 5
1)
#351001
0)
#352001
1)
b1 !
b1 5
1*
#353001
0)
#354001
b10 !
b10 5
10
1L
bz K
1)
#355001
0)
#356001
b11 !
b11 5
1-
b11111111111111111111111111111100 .
b11111111111111111111111111111100 >
z0
b11111111111111111111111111111100 N
1O
bz M
0L
b0 K
1)
#357001
0)
#358001
b100 !
b100 5
z-
bz .
bz >
b111111110 3
b111111110 A
12
b10 4
b10 D
b0 N
0O
b0 M
b111111110 I
1J
b10 H
1)
#359001
0)
