verification/coco_tb/DUT/exu_imm_swc.v
module exu_imm_swc (
    hclk                                        ,
    hrstn                                       ,
    cycle_cnt                                   ,
    dec_branch_en                               ,
    dec_addi                                    ,
    dec_slti                                    ,
    dec_sltiu                                   ,
    dec_xori                                    ,
    dec_ori                                     ,
    dec_andi                                    ,
    dec_slli                                    ,
    dec_srli                                    ,
    dec_srai                                    ,
    dec_imm_type_i                              ,
    dec_rd                                      ,
    dec_rs1                                     ,
    pc                                          ,
    reg_waddr                                   ,
    reg_wen                                     ,
    reg_wdata                                   ,
    reg_raddr_1                                 ,
    reg_ren_1                                   ,
    reg_rdata_1                                 
);
/*
This module performs Integer-Register Immediate instructions, placing the result in the dec_rd register.
*/
// general signals
input                       hclk                ;
input                       hrstn               ;
// control signals
input           [3:0]       cycle_cnt           ;
// signals from deccoder
input                       dec_branch_en       ;
input                       dec_addi            ;
input                       dec_slti            ;
input                       dec_sltiu           ;
input                       dec_xori            ;
input                       dec_ori             ;
input                       dec_andi            ;
input                       dec_slli            ;
input                       dec_srli            ;
input                       dec_srai            ;
input           [11:0]      dec_imm_type_i      ;
input           [4:0]       dec_rd              ;
input           [4:0]       dec_rs1             ;
// PC signals
input           [31:0]      pc                  ;
// regfile signals
inout           [4:0]       reg_waddr           ;
inout                       reg_wen             ;
inout           [31:0]      reg_wdata           ;
inout           [4:0]       reg_raddr_1         ;
inout                       reg_ren_1           ;
input           [31:0]      reg_rdata_1         ;
// middle signals
reg             [4:0]       mid_reg_waddr       ;
reg                         mid_reg_wen         ;
reg             [31:0]      mid_reg_wdata       ;
reg             [4:0]       mid_reg_raddr_1     ;
reg                         mid_reg_ren_1       ;

assign reg_waddr   = mid_reg_wen   ? mid_reg_waddr    : 'z  ;
assign reg_wen     = mid_reg_wen   ? mid_reg_wen      : 'z  ;
assign reg_wdata   = mid_reg_wen   ? mid_reg_wdata    : 'z  ;
assign reg_raddr_1 = mid_reg_ren_1 ? mid_reg_raddr_1  : 'z  ;
assign reg_ren_1   = mid_reg_ren_1 ? mid_reg_ren_1    : 'z  ;

// the process
always@(posedge hclk or negedge hrstn) begin
    if(!hrstn) begin
    	// on a reset, set all intermediate values to 0
        mid_reg_raddr_1 <= 0;
        mid_reg_ren_1   <= 0;
        
        mid_reg_waddr   <= 0;
        mid_reg_wen     <= 0;
        mid_reg_wdata   <= 0;
    end else if(dec_branch_en)begin
        if(cycle_cnt == 1) begin // on cycle 1 assign the temp read address to the decoded address, and enable writing to the read address
            mid_reg_raddr_1 <= dec_rs1;
            mid_reg_ren_1   <= 1;

            mid_reg_waddr   <= 0;
            mid_reg_wen     <= 0;
            mid_reg_wdata   <= 0;
        end else if(cycle_cnt == 2) begin // on cycle 2 clear the intermediate values.
            mid_reg_raddr_1 <= 0;
            mid_reg_ren_1   <= 0;

            mid_reg_waddr   <= 0;
            mid_reg_wen     <= 0;
            mid_reg_wdata   <= 0;
        end else if(cycle_cnt == 3)begin // on cycle 3 assign the write address to the destination register and enable writing to the register.
            mid_reg_raddr_1 <= 0;
            mid_reg_ren_1   <= 0;

            mid_reg_waddr   <= dec_rd;
            mid_reg_wen     <= 1;
            if(dec_addi) // for ADDI add the immediate to the data
                mid_reg_wdata <= {{20{dec_imm_type_i[11]}}, dec_imm_type_i} + reg_rdata_1;
            else if(dec_slti) // for SLTI check if the data is less than the immediate for signed values
                mid_reg_wdata <= {31'b0, $signed(reg_rdata_1) < $signed({{20{dec_imm_type_i[11]}}, dec_imm_type_i})};
            else if(dec_sltiu) // for SLTIU check if the data is less than the immediate for unsigned values
                mid_reg_wdata <= {31'b0, reg_rdata_1 < {{20{dec_imm_type_i[11]}}, dec_imm_type_i}};
            else if(dec_xori) // for XORI take the bitwise XOR of the data and immediate
                mid_reg_wdata <= reg_rdata_1 ^ {{20{dec_imm_type_i[11]}}, dec_imm_type_i};
            else if(dec_ori) // for ORI take the bitwise OR of the data and immediate
                mid_reg_wdata <= reg_rdata_1 | {{20{dec_imm_type_i[11]}}, dec_imm_type_i};
            else if(dec_andi) // for ANDI take the bitwise AND of the data and immediate
                mid_reg_wdata <= reg_rdata_1 & {{20{dec_imm_type_i[11]}}, dec_imm_type_i};
            else if(dec_slli) // for SLLI perform a logical left shift of the data by the immediate value
                mid_reg_wdata <= reg_rdata_1 << dec_imm_type_i[4:0];
            else if(dec_srli) // for SRLI perform a logical right shift of the data by the immediate value
                mid_reg_wdata <= reg_rdata_1 >> dec_imm_type_i[4:0];
            else if(dec_srai) // for SRAI perform an arithmetic right shift of the data by the immediate value
                mid_reg_wdata <= $signed(reg_rdata_1) >>> dec_imm_type_i[4:0];
            else
                mid_reg_wdata <= 0;
            end else begin // on cycle 4 set all the temp registers to 0
                mid_reg_raddr_1 <= 0;
                mid_reg_ren_1   <= 0;
    
                mid_reg_waddr   <= 0;
                mid_reg_wen     <= 0;
                mid_reg_wdata   <= 0;
            end
    end else begin // if dec_branch_en is not enabled, set all temp registers to 0
        mid_reg_raddr_1 <= 0;
        mid_reg_ren_1   <= 0;

        mid_reg_waddr   <= 0;
        mid_reg_wen     <= 0;
        mid_reg_wdata   <= 0;
    end
end
endmodule

verification/coco_tb/DUT_Wrapper/exu_imm_swc_wrapper.v
module exu_imm_swc_wrapper (
    input hclk,
    input hrstn,
    input [3:0] cycle_cnt,
    input dec_branch_en,
    input dec_addi,
    input dec_slti,
    input dec_sltiu,
    input dec_xori,
    input dec_ori,
    input dec_andi,
    input dec_slli,
    input dec_srli,
    input dec_srai,
    input [11:0] dec_imm_type_i,
    input [4:0] dec_rd,
    input [4:0] dec_rs1,
    input [31:0] pc,
    input [31:0] reg_rdata_1,
    inout [4:0] reg_waddr,
    inout reg_wen,
    inout [31:0] reg_wdata,
    inout [4:0] reg_raddr_1,
    inout reg_ren_1
);

    exu_imm_swc dut (
        .hclk(hclk),
        .hrstn(hrstn),
        .cycle_cnt(cycle_cnt),
        .dec_branch_en(dec_branch_en),
        .dec_addi(dec_addi),
        .dec_slti(dec_slti),
        .dec_sltiu(dec_sltiu),
        .dec_xori(dec_xori),
        .dec_ori(dec_ori),
        .dec_andi(dec_andi),
        .dec_slli(dec_slli),
        .dec_srli(dec_srli),
        .dec_srai(dec_srai),
        .dec_imm_type_i(dec_imm_type_i),
        .dec_rd(dec_rd),
        .dec_rs1(dec_rs1),
        .pc(pc),
        .reg_rdata_1(reg_rdata_1),
        .reg_waddr(reg_waddr),
        .reg_wen(reg_wen),
        .reg_wdata(reg_wdata),
        .reg_raddr_1(reg_raddr_1),
        .reg_ren_1(reg_ren_1)
    );
    initial begin
        $dumpfile("./vcds/exu_imm_swc.vcd");
        $dumpvars(0, exu_imm_swc_wrapper);
    end
endmodule

verification/coco_tb/vcds/exu_imm_swc.vcd
$date
	Tue Jan 28 19:37:27 2025
$end
$version
	Icarus Verilog
$end
$timescale
	1ps
$end
$scope module exu_imm_swc_wrapper $end
$var wire 4 ! cycle_cnt [3:0] $end
$var wire 1 " dec_addi $end
$var wire 1 # dec_andi $end
$var wire 1 $ dec_branch_en $end
$var wire 12 % dec_imm_type_i [11:0] $end
$var wire 1 & dec_ori $end
$var wire 5 ' dec_rd [4:0] $end
$var wire 5 ( dec_rs1 [4:0] $end
$var wire 1 ) dec_slli $end
$var wire 1 * dec_slti $end
$var wire 1 + dec_sltiu $end
$var wire 1 , dec_srai $end
$var wire 1 - dec_srli $end
$var wire 1 . dec_xori $end
$var wire 1 / hclk $end
$var wire 1 0 hrstn $end
$var wire 32 1 pc [31:0] $end
$var wire 32 2 reg_rdata_1 [31:0] $end
$var wire 1 3 reg_wen $end
$var wire 32 4 reg_wdata [31:0] $end
$var wire 5 5 reg_waddr [4:0] $end
$var wire 1 6 reg_ren_1 $end
$var wire 5 7 reg_raddr_1 [4:0] $end
$scope module dut $end
$var wire 4 8 cycle_cnt [3:0] $end
$var wire 1 " dec_addi $end
$var wire 1 # dec_andi $end
$var wire 1 $ dec_branch_en $end
$var wire 12 9 dec_imm_type_i [11:0] $end
$var wire 1 & dec_ori $end
$var wire 5 : dec_rd [4:0] $end
$var wire 5 ; dec_rs1 [4:0] $end
$var wire 1 ) dec_slli $end
$var wire 1 * dec_slti $end
$var wire 1 + dec_sltiu $end
$var wire 1 , dec_srai $end
$var wire 1 - dec_srli $end
$var wire 1 . dec_xori $end
$var wire 1 / hclk $end
$var wire 1 0 hrstn $end
$var wire 32 < pc [31:0] $end
$var wire 32 = reg_rdata_1 [31:0] $end
$var wire 1 3 reg_wen $end
$var wire 32 > reg_wdata [31:0] $end
$var wire 5 ? reg_waddr [4:0] $end
$var wire 1 6 reg_ren_1 $end
$var wire 5 @ reg_raddr_1 [4:0] $end
$var reg 5 A mid_reg_raddr_1 [4:0] $end
$var reg 1 B mid_reg_ren_1 $end
$var reg 5 C mid_reg_waddr [4:0] $end
$var reg 32 D mid_reg_wdata [31:0] $end
$var reg 1 E mid_reg_wen $end
$upscope $end
$upscope $end
$enddefinitions $end
$comment Show the parameter values. $end
$dumpall
$end
#0
$dumpvars
0E
b0 D
b0 C
0B
b0 A
bz @
bz ?
bz >
b101 =
b0 <
bz ;
bz :
b11 9
bz 8
bz 7
z6
bz 5
bz 4
z3
b101 2
b0 1
00
1/
0.
0-
0,
0+
0*
0)
bz (
bz '
0&
b11 %
1$
0#
1"
bz !
$end
#1000
0/
#2000
1/
#3000
0/
#4000
1/
#5000
0/
#6000
1/
#7000
0/
#8000
1/
#9000
0/
#10000
1/
b1 !
b1 8
10
#11000
0/
#12000
b10 !
b10 8
16
1B
bz A
1/
#13000
0/
#14000
b11 !
b11 8
z6
0B
b0 A
1/
#15000
0/
#16000
b100 !
b100 8
13
b1000 4
b1000 >
b1000 D
1E
bz C
1/
#17000
0/
#18000
z3
bz 4
bz >
b0 D
0E
b0 C
1/
#18001
00
1*
0"
b11010111111 %
b11010111111 9
b110111011010101101011011000001 2
b110111011010101101011011000001 =
#19001
0/
#20001
1/
#21001
0/
#22001
1/
#23001
0/
#24001
1/
#25001
0/
#26001
1/
#27001
0/
#28001
1/
b1 !
b1 8
10
#29001
0/
#30001
b10 !
b10 8
16
1B
bz A
1/
#31001
0/
#32001
b11 !
b11 8
z6
0B
b0 A
1/
#33001
0/
#34001
b100 !
b100 8
13
b0 4
b0 >
1E
bz C
1/
#35001
0/
#36001
00
0*
1"
b100101110000 %
b100101110000 9
b10000001111011100101000111000110 2
b10000001111011100101000111000110 =
b1 !
b1 8
z3
bz 4
bz >
0E
b0 C
1/
#37001
0/
#38001
b10 !
b10 8
1/
#39001
0/
#40001
b11 !
b11 8
1/
#41001
0/
#42001
b100 !
b100 8
1/
#43001
0/
#44001
b1 !
b1 8
1/
#45001
0/
#46001
1/
b1 !
b1 8
10
#47001
0/
#48001
b10 !
b10 8
16
1B
bz A
1/
#49001
0/
#50001
b11 !
b11 8
z6
0B
b0 A
1/
#51001
0/
#52001
b100 !
b100 8
13
b10000001111011100100101100110110 4
b10000001111011100100101100110110 >
b10000001111011100100101100110110 D
1E
bz C
1/
#53001
0/
#54001
00
1)
0"
b1010100 %
b1010100 9
b1011101010000001111100011000101 2
b1011101010000001111100011000101 =
b1 !
b1 8
z3
bz 4
bz >
b0 D
0E
b0 C
1/
#55001
0/
#56001
b10 !
b10 8
1/
#57001
0/
#58001
b11 !
b11 8
1/
#59001
0/
#60001
b100 !
b100 8
1/
#61001
0/
#62001
b1 !
b1 8
1/
#63001
0/
#64001
1/
b1 !
b1 8
10
#65001
0/
#66001
b10 !
b10 8
16
1B
bz A
1/
#67001
0/
#68001
b11 !
b11 8
z6
0B
b0 A
1/
#69001
0/
#70001
b100 !
b100 8
13
b10001100010100000000000000000000 4
b10001100010100000000000000000000 >
b10001100010100000000000000000000 D
1E
bz C
1/
#71001
0/
#72001
00
0)
1#
b1111011000 %
b1111011000 9
b11000100010110000100011011100010 2
b11000100010110000100011011100010 =
b1 !
b1 8
z3
bz 4
bz >
b0 D
0E
b0 C
1/
#73001
0/
#74001
b10 !
b10 8
1/
#75001
0/
#76001
b11 !
b11 8
1/
#77001
0/
#78001
b100 !
b100 8
1/
#79001
0/
#80001
b1 !
b1 8
1/
#81001
0/
#82001
1/
b1 !
b1 8
10
#83001
0/
#84001
b10 !
b10 8
16
1B
bz A
1/
#85001
0/
#86001
b11 !
b11 8
z6
0B
b0 A
1/
#87001
0/
#88001
b100 !
b100 8
13
b1011000000 4
b1011000000 >
b1011000000 D
1E
bz C
1/
#89001
0/
#90001
00
0#
1.
b111011000011 %
b111011000011 9
b1101011111111011000100110001010 2
b1101011111111011000100110001010 =
b1 !
b1 8
z3
bz 4
bz >
b0 D
0E
b0 C
1/
#91001
0/
#92001
b10 !
b10 8
1/
#93001
0/
#94001
b11 !
b11 8
1/
#95001
0/
#96001
b100 !
b100 8
1/
#97001
0/
#98001
b1 !
b1 8
1/
#99001
0/
#100001
1/
b1 !
b1 8
10
#101001
0/
#102001
b10 !
b10 8
16
1B
bz A
1/
#103001
0/
#104001
b11 !
b11 8
z6
0B
b0 A
1/
#105001
0/
#106001
b100 !
b100 8
13
b10010100000000100111011101001001 4
b10010100000000100111011101001001 >
b10010100000000100111011101001001 D
1E
bz C
1/
#107001
0/
#108001
00
1)
0.
b101011010110 %
b101011010110 9
b11011111001010010000001001110011 2
b11011111001010010000001001110011 =
b1 !
b1 8
z3
bz 4
bz >
b0 D
0E
b0 C
1/
#109001
0/
#110001
b10 !
b10 8
1/
#111001
0/
#112001
b11 !
b11 8
1/
#113001
0/
#114001
b100 !
b100 8
1/
#115001
0/
#116001
b1 !
b1 8
1/
#117001
0/
#118001
1/
b1 !
b1 8
10
#119001
0/
#120001
b10 !
b10 8
16
1B
bz A
1/
#121001
0/
#122001
b11 !
b11 8
z6
0B
b0 A
1/
#123001
0/
#124001
b100 !
b100 8
13
b10011100110000000000000000000000 4
b10011100110000000000000000000000 >
b10011100110000000000000000000000 D
1E
bz C
1/
#125001
0/
#126001
00
0)
1+
b101110111110 %
b101110111110 9
b10010101011010010111000011001101 2
b10010101011010010111000011001101 =
b1 !
b1 8
z3
bz 4
bz >
b0 D
0E
b0 C
1/
#127001
0/
#128001
b10 !
b10 8
1/
#129001
0/
#130001
b11 !
b11 8
1/
#131001
0/
#132001
b100 !
b100 8
1/
#133001
0/
#134001
b1 !
b1 8
1/
#135001
0/
#136001
1/
b1 !
b1 8
10
#137001
0/
#138001
b10 !
b10 8
16
1B
bz A
1/
#139001
0/
#140001
b11 !
b11 8
z6
0B
b0 A
1/
#141001
0/
#142001
b100 !
b100 8
13
b1 4
b1 >
b1 D
1E
bz C
1/
#143001
0/
#144001
00
1.
0+
b110111101101 %
b110111101101 9
b111111111001001001101011110110 2
b111111111001001001101011110110 =
b1 !
b1 8
z3
bz 4
bz >
b0 D
0E
b0 C
1/
#145001
0/
#146001
b10 !
b10 8
1/
#147001
0/
#148001
b11 !
b11 8
1/
#149001
0/
#150001
b100 !
b100 8
1/
#151001
0/
#152001
b1 !
b1 8
1/
#153001
0/
#154001
1/
b1 !
b1 8
10
#155001
0/
#156001
b10 !
b10 8
16
1B
bz A
1/
#157001
0/
#158001
b11 !
b11 8
z6
0B
b0 A
1/
#159001
0/
#160001
b100 !
b100 8
13
b11000000000110110110011100011011 4
b11000000000110110110011100011011 >
b11000000000110110110011100011011 D
1E
bz C
1/
#161001
0/
#162001
00
0.
1"
b11001100001 %
b11001100001 9
b11000111011110010100011110100000 2
b11000111011110010100011110100000 =
b1 !
b1 8
z3
bz 4
bz >
b0 D
0E
b0 C
1/
#163001
0/
#164001
b10 !
b10 8
1/
#165001
0/
#166001
b11 !
b11 8
1/
#167001
0/
#168001
b100 !
b100 8
1/
#169001
0/
#170001
b1 !
b1 8
1/
#171001
0/
#172001
1/
b1 !
b1 8
10
#173001
0/
#174001
b10 !
b10 8
16
1B
bz A
1/
#175001
0/
#176001
b11 !
b11 8
z6
0B
b0 A
1/
#177001
0/
#178001
b100 !
b100 8
13
b11000111011110010100111000000001 4
b11000111011110010100111000000001 >
b11000111011110010100111000000001 D
1E
bz C
1/
#179001
0/
#180001
00
1,
0"
b1111101011 %
b1111101011 9
b10010100111011110001001011111100 2
b10010100111011110001001011111100 =
b1 !
b1 8
z3
bz 4
bz >
b0 D
0E
b0 C
1/
#181001
0/
#182001
b10 !
b10 8
1/
#183001
0/
#184001
b11 !
b11 8
1/
#185001
0/
#186001
b100 !
b100 8
1/
#187001
0/
#188001
b1 !
b1 8
1/
#189001
0/
#190001
1/
b1 !
b1 8
10
#191001
0/
#192001
b10 !
b10 8
16
1B
bz A
1/
#193001
0/
#194001
b11 !
b11 8
z6
0B
b0 A
1/
#195001
0/
#196001
b100 !
b100 8
13
b11111111111100101001110111100010 4
b11111111111100101001110111100010 >
b11111111111100101001110111100010 D
1E
bz C
1/
#197001
0/
#198001
00
0,
1+
b1110111011 %
b1110111011 9
b1100001011000110001101100010010 2
b1100001011000110001101100010010 =
b1 !
b1 8
z3
bz 4
bz >
b0 D
0E
b0 C
1/
#199001
0/
#200001
b10 !
b10 8
1/
#201001
0/
#202001
b11 !
b11 8
1/
#203001
0/
#204001
b100 !
b100 8
1/
#205001
0/
#206001
b1 !
b1 8
1/
#207001
0/
#208001
1/
b1 !
b1 8
10
#209001
0/
#210001
b10 !
b10 8
16
1B
bz A
1/
#211001
0/
#212001
b11 !
b11 8
z6
0B
b0 A
1/
#213001
0/
#214001
b100 !
b100 8
13
b0 4
b0 >
1E
bz C
1/
#215001
0/
#216001
00
1#
0+
b110001101111 %
b110001101111 9
b111011111100000011111000010000 2
b111011111100000011111000010000 =
b1 !
b1 8
z3
bz 4
bz >
0E
b0 C
1/
#217001
0/
#218001
b10 !
b10 8
1/
#219001
0/
#220001
b11 !
b11 8
1/
#221001
0/
#222001
b100 !
b100 8
1/
#223001
0/
#224001
b1 !
b1 8
1/
#225001
0/
#226001
1/
b1 !
b1 8
10
#227001
0/
#228001
b10 !
b10 8
16
1B
bz A
1/
#229001
0/
#230001
b11 !
b11 8
z6
0B
b0 A
1/
#231001
0/
#232001
b100 !
b100 8
13
b111011111100000011110000000000 4
b111011111100000011110000000000 >
b111011111100000011110000000000 D
1E
bz C
1/
#233001
0/
#234001
00
0#
1+
b11010000110 %
b11010000110 9
b1010101011011111100101010011110 2
b1010101011011111100101010011110 =
b1 !
b1 8
z3
bz 4
bz >
b0 D
0E
b0 C
1/
#235001
0/
#236001
b10 !
b10 8
1/
#237001
0/
#238001
b11 !
b11 8
1/
#239001
0/
#240001
b100 !
b100 8
1/
#241001
0/
#242001
b1 !
b1 8
1/
#243001
0/
#244001
1/
b1 !
b1 8
10
#245001
0/
#246001
b10 !
b10 8
16
1B
bz A
1/
#247001
0/
#248001
b11 !
b11 8
z6
0B
b0 A
1/
#249001
0/
#250001
b100 !
b100 8
13
b0 4
b0 >
1E
bz C
1/
#251001
0/
#252001
00
1.
0+
b11001001101 %
b11001001101 9
b1010001110001000000110110101110 2
b1010001110001000000110110101110 =
b1 !
b1 8
z3
bz 4
bz >
0E
b0 C
1/
#253001
0/
#254001
b10 !
b10 8
1/
#255001
0/
#256001
b11 !
b11 8
1/
#257001
0/
#258001
b100 !
b100 8
1/
#259001
0/
#260001
b1 !
b1 8
1/
#261001
0/
#262001
1/
b1 !
b1 8
10
#263001
0/
#264001
b10 !
b10 8
16
1B
bz A
1/
#265001
0/
#266001
b11 !
b11 8
z6
0B
b0 A
1/
#267001
0/
#268001
b100 !
b100 8
13
b1010001110001000000101111100011 4
b1010001110001000000101111100011 >
b1010001110001000000101111100011 D
1E
bz C
1/
#269001
0/
#270001
00
0.
1*
b110000010110 %
b110000010110 9
b1000100000010011001100001001 2
b1000100000010011001100001001 =
b1 !
b1 8
z3
bz 4
bz >
b0 D
0E
b0 C
1/
#271001
0/
#272001
b10 !
b10 8
1/
#273001
0/
#274001
b11 !
b11 8
1/
#275001
0/
#276001
b100 !
b100 8
1/
#277001
0/
#278001
b1 !
b1 8
1/
#279001
0/
#280001
1/
b1 !
b1 8
10
#281001
0/
#282001
b10 !
b10 8
16
1B
bz A
1/
#283001
0/
#284001
b11 !
b11 8
z6
0B
b0 A
1/
#285001
0/
#286001
b100 !
b100 8
13
b0 4
b0 >
1E
bz C
1/
#287001
0/
#288001
00
1)
0*
b11010110100 %
b11010110100 9
b11110111110001111011001000010000 2
b11110111110001111011001000010000 =
b1 !
b1 8
z3
bz 4
bz >
0E
b0 C
1/
#289001
0/
#290001
b10 !
b10 8
1/
#291001
0/
#292001
b11 !
b11 8
1/
#293001
0/
#294001
b100 !
b100 8
1/
#295001
0/
#296001
b1 !
b1 8
1/
#297001
0/
#298001
1/
b1 !
b1 8
10
#299001
0/
#300001
b10 !
b10 8
16
1B
bz A
1/
#301001
0/
#302001
b11 !
b11 8
z6
0B
b0 A
1/
#303001
0/
#304001
b100 !
b100 8
13
b100001000000000000000000000000 4
b100001000000000000000000000000 >
b100001000000000000000000000000 D
1E
bz C
1/
#305001
0/
#306001
00
0)
1#
b110010111 %
b110010111 9
b11101110101000001101111011010011 2
b11101110101000001101111011010011 =
b1 !
b1 8
z3
bz 4
bz >
b0 D
0E
b0 C
1/
#307001
0/
#308001
b10 !
b10 8
1/
#309001
0/
#310001
b11 !
b11 8
1/
#311001
0/
#312001
b100 !
b100 8
1/
#313001
0/
#314001
b1 !
b1 8
1/
#315001
0/
#316001
1/
b1 !
b1 8
10
#317001
0/
#318001
b10 !
b10 8
16
1B
bz A
1/
#319001
0/
#320001
b11 !
b11 8
z6
0B
b0 A
1/
#321001
0/
#322001
b100 !
b100 8
13
b10010011 4
b10010011 >
b10010011 D
1E
bz C
1/
#323001
0/
#324001
00
0#
1*
b100111110 %
b100111110 9
b11111001100001100001101110011001 2
b11111001100001100001101110011001 =
b1 !
b1 8
z3
bz 4
bz >
b0 D
0E
b0 C
1/
#325001
0/
#326001
b10 !
b10 8
1/
#327001
0/
#328001
b11 !
b11 8
1/
#329001
0/
#330001
b100 !
b100 8
1/
#331001
0/
#332001
b1 !
b1 8
1/
#333001
0/
#334001
1/
b1 !
b1 8
10
#335001
0/
#336001
b10 !
b10 8
16
1B
bz A
1/
#337001
0/
#338001
b11 !
b11 8
z6
0B
b0 A
1/
#339001
0/
#340001
b100 !
b100 8
13
b1 4
b1 >
b1 D
1E
bz C
1/
#341001
0/
#342001
00
1.
0*
b101000101 %
b101000101 9
b101011011010010010000000100100 2
b101011011010010010000000100100 =
b1 !
b1 8
z3
bz 4
bz >
b0 D
0E
b0 C
1/
#343001
0/
#344001
b10 !
b10 8
1/
#345001
0/
#346001
b11 !
b11 8
1/
#347001
0/
#348001
b100 !
b100 8
1/
#349001
0/
#350001
b1 !
b1 8
1/
#351001
0/
#352001
1/
b1 !
b1 8
10
#353001
0/
#354001
b10 !
b10 8
16
1B
bz A
1/
#355001
0/
#356001
b11 !
b11 8
z6
0B
b0 A
1/
#357001
0/
#358001
b100 !
b100 8
13
b101011011010010010000101100001 4
b101011011010010010000101100001 >
b101011011010010010000101100001 D
1E
bz C
1/
#359001
0/
#360001
00
1,
0.
b100001000001 %
b100001000001 9
b1111111111001011000111010111000 2
b1111111111001011000111010111000 =
b1 !
b1 8
z3
bz 4
bz >
b0 D
0E
b0 C
1/
#361001
0/
#362001
b10 !
b10 8
1/
#363001
0/
#364001
b11 !
b11 8
1/
#365001
0/
#366001
b100 !
b100 8
1/
#367001
0/
#368001
b1 !
b1 8
1/
#369001
0/
#370001
1/
b1 !
b1 8
10
#371001
0/
#372001
b10 !
b10 8
16
1B
bz A
1/
#373001
0/
#374001
b11 !
b11 8
z6
0B
b0 A
1/
#375001
0/
#376001
b100 !
b100 8
13
b111111111100101100011101011100 4
b111111111100101100011101011100 >
b111111111100101100011101011100 D
1E
bz C
1/
#377001
0/
#378001
00
0,
1#
b110110111000 %
b110110111000 9
b1000101100101111010101110000101 2
b1000101100101111010101110000101 =
b1 !
b1 8
z3
bz 4
bz >
b0 D
0E
b0 C
1/
#379001
0/
#380001
b10 !
b10 8
1/
#381001
0/
#382001
b11 !
b11 8
1/
#383001
0/
#384001
b100 !
b100 8
1/
#385001
0/
#386001
b1 !
b1 8
1/
#387001
0/
#388001
1/
b1 !
b1 8
10
#389001
0/
#390001
b10 !
b10 8
16
1B
bz A
1/
#391001
0/
#392001
b11 !
b11 8
z6
0B
b0 A
1/
#393001
0/
#394001
b100 !
b100 8
13
b1000101100101111010100110000000 4
b1000101100101111010100110000000 >
b1000101100101111010100110000000 D
1E
bz C
1/
#395001
0/
#396001
00
0#
1.
b11010111011 %
b11010111011 9
b11000010011110000001001000010100 2
b11000010011110000001001000010100 =
b1 !
b1 8
z3
bz 4
bz >
b0 D
0E
b0 C
1/
#397001
0/
#398001
b10 !
b10 8
1/
#399001
0/
#400001
b11 !
b11 8
1/
#401001
0/
#402001
b100 !
b100 8
1/
#403001
0/
#404001
b1 !
b1 8
1/
#405001
0/
#406001
1/
b1 !
b1 8
10
#407001
0/
#408001
b10 !
b10 8
16
1B
bz A
1/
#409001
0/
#410001
b11 !
b11 8
z6
0B
b0 A
1/
#411001
0/
#412001
b100 !
b100 8
13
b11000010011110000001010010101111 4
b11000010011110000001010010101111 >
b11000010011110000001010010101111 D
1E
bz C
1/
#413001
0/
#414001
00
b1101010000 %
b1101010000 9
b1011110010011111111010001011 2
b1011110010011111111010001011 =
b1 !
b1 8
z3
bz 4
bz >
b0 D
0E
b0 C
1/
#415001
0/
#416001
b10 !
b10 8
1/
#417001
0/
#418001
b11 !
b11 8
1/
#419001
0/
#420001
b100 !
b100 8
1/
#421001
0/
#422001
b1 !
b1 8
1/
#423001
0/
#424001
1/
b1 !
b1 8
10
#425001
0/
#426001
b10 !
b10 8
16
1B
bz A
1/
#427001
0/
#428001
b11 !
b11 8
z6
0B
b0 A
1/
#429001
0/
#430001
b100 !
b100 8
13
b1011110010011111110111011011 4
b1011110010011111110111011011 >
b1011110010011111110111011011 D
1E
bz C
1/
#431001
0/
#432001
00
0.
1+
b101111110100 %
b101111110100 9
b11011100000011100111100001010 2
b11011100000011100111100001010 =
b1 !
b1 8
z3
bz 4
bz >
b0 D
0E
b0 C
1/
#433001
0/
#434001
b10 !
b10 8
1/
#435001
0/
#436001
b11 !
b11 8
1/
#437001
0/
#438001
b100 !
b100 8
1/
#439001
0/
#440001
b1 !
b1 8
1/
#441001
0/
#442001
1/
b1 !
b1 8
10
#443001
0/
#444001
b10 !
b10 8
16
1B
bz A
1/
#445001
0/
#446001
b11 !
b11 8
z6
0B
b0 A
1/
#447001
0/
#448001
b100 !
b100 8
13
b1 4
b1 >
b1 D
1E
bz C
1/
#449001
0/
#450001
00
1)
0+
b110101001001 %
b110101001001 9
b11100001011001011010101101001000 2
b11100001011001011010101101001000 =
b1 !
b1 8
z3
bz 4
bz >
b0 D
0E
b0 C
1/
#451001
0/
#452001
b10 !
b10 8
1/
#453001
0/
#454001
b11 !
b11 8
1/
#455001
0/
#456001
b100 !
b100 8
1/
#457001
0/
#458001
b1 !
b1 8
1/
#459001
0/
#460001
1/
b1 !
b1 8
10
#461001
0/
#462001
b10 !
b10 8
16
1B
bz A
1/
#463001
0/
#464001
b11 !
b11 8
z6
0B
b0 A
1/
#465001
0/
#466001
b100 !
b100 8
13
b11001011010101101001000000000000 4
b11001011010101101001000000000000 >
b11001011010101101001000000000000 D
1E
bz C
1/
#467001
0/
#468001
00
0)
1.
b110011010100 %
b110011010100 9
b11011001111000111011001101010000 2
b11011001111000111011001101010000 =
b1 !
b1 8
z3
bz 4
bz >
b0 D
0E
b0 C
1/
#469001
0/
#470001
b10 !
b10 8
1/
#471001
0/
#472001
b11 !
b11 8
1/
#473001
0/
#474001
b100 !
b100 8
1/
#475001
0/
#476001
b1 !
b1 8
1/
#477001
0/
#478001
1/
b1 !
b1 8
10
#479001
0/
#480001
b10 !
b10 8
16
1B
bz A
1/
#481001
0/
#482001
b11 !
b11 8
z6
0B
b0 A
1/
#483001
0/
#484001
b100 !
b100 8
13
b100110000111000100111110000100 4
b100110000111000100111110000100 >
b100110000111000100111110000100 D
1E
bz C
1/
#485001
0/
#486001
00
b100110010001 %
b100110010001 9
b1100110101110100000011000111 2
b1100110101110100000011000111 =
b1 !
b1 8
z3
bz 4
bz >
b0 D
0E
b0 C
1/
#487001
0/
#488001
b10 !
b10 8
1/
#489001
0/
#490001
b11 !
b11 8
1/
#491001
0/
#492001
b100 !
b100 8
1/
#493001
0/
#494001
b1 !
b1 8
1/
#495001
0/
#496001
1/
b1 !
b1 8
10
#497001
0/
#498001
b10 !
b10 8
16
1B
bz A
1/
#499001
0/
#500001
b11 !
b11 8
z6
0B
b0 A
1/
#501001
0/
#502001
b100 !
b100 8
13
b11110011001010001011100101010110 4
b11110011001010001011100101010110 >
b11110011001010001011100101010110 D
1E
bz C
1/
#503001
0/
#504001
00
b11111001 %
b11111001 9
b10100100100001110101000110100010 2
b10100100100001110101000110100010 =
b1 !
b1 8
z3
bz 4
bz >
b0 D
0E
b0 C
1/
#505001
0/
#506001
b10 !
b10 8
1/
#507001
0/
#508001
b11 !
b11 8
1/
#509001
0/
#510001
b100 !
b100 8
1/
#511001
0/
#512001
b1 !
b1 8
1/
#513001
0/
#514001
1/
b1 !
b1 8
10
#515001
0/
#516001
b10 !
b10 8
16
1B
bz A
1/
#517001
0/
#518001
b11 !
b11 8
z6
0B
b0 A
1/
#519001
0/
#520001
b100 !
b100 8
13
b10100100100001110101000101011011 4
b10100100100001110101000101011011 >
b10100100100001110101000101011011 D
1E
bz C
1/
#521001
0/
#522001
00
1#
0.
b10111111101 %
b10111111101 9
b10011001110000110011100000100110 2
b10011001110000110011100000100110 =
b1 !
b1 8
z3
bz 4
bz >
b0 D
0E
b0 C
1/
#523001
0/
