verification/coco_tb/DUT/mau_swc.v
module mau_swc (
    hclk                                                        ,
    hrstn                                                       ,
    haddr                                                       ,
    hwrite                                                      ,
    hwdata                                                      ,
    hsize                                                       ,
    hburst                                                      ,
    hprot                                                       ,
    htrans                                                      ,
    hmastlock                                                   ,
    hready                                                      ,
    hresp                                                       ,
    hrdata                                                      ,
    cycle_cnt                                                   ,
    exu_load_rd                                                 ,
    exu_load_base_addr                                          ,
    exu_load_offset                                             ,
    exu_load_sext                                               ,
    exu_load_size                                               ,
    exu_load_en                                                 ,
    exu_store_addr                                              ,
    exu_store_data                                              ,
    exu_store_en                                                ,
    exu_store_size                                              ,
    mau_load_rd                                                 ,
    mau_load_data                                               ,
    mau_load_en                                                 
);

// general signals
input                                       hclk                ;
input                                       hrstn               ;
// control signals
input                   [3:0]               cycle_cnt           ;
// AHB bus signals
localparam  HTRANS_IDLE     = 0                                 ,
            HTRANS_BUSY     = 1                                 ,
            HTRANS_NONSEQ   = 2                                 ,
            HTRANS_SEQ      = 3                                 ;
output      reg         [31:0]              haddr               ;
output      reg                             hwrite              ;
output      reg         [31:0]              hwdata              ;
output      reg         [2:0]               hsize               ;
output      reg         [2:0]               hburst              ;
output      reg         [6:0]               hprot               ;
output      reg         [1:0]               htrans              ;
output      reg                             hmastlock           ;
input                                       hready              ;
input                                       hresp               ;
input                   [31:0]              hrdata              ;
// signals from exu
input                   [4:0]               exu_load_rd         ;
input                   [31:0]              exu_load_base_addr  ;
input                   [31:0]              exu_load_offset     ;
input                                       exu_load_sext       ;
input                   [1:0]               exu_load_size       ;
input                                       exu_load_en         ;
input                   [31:0]              exu_store_addr      ;
input                   [31:0]              exu_store_data      ;
input                                       exu_store_en        ;
input                   [1:0]               exu_store_size      ;
// signals to wbu
output reg              [4:0]               mau_load_rd         ;
output reg              [31:0]              mau_load_data       ;
output reg                                  mau_load_en         ;

// state machine
localparam  IDLE          = 0   ,
            READ_START    = 1   ,
            READ_WAIT1    = 2   ,
            READ_WAIT2    = 3   ,
            WRITE_START   = 4   ,
            WRITE_WAIT    = 5   ;
reg [2:0] state                 ;
reg [2:0] nextstate             ;
parameter CNT_MAX = 4;

always@(posedge hclk) begin
    if(!hrstn) begin
        state <= IDLE;
        //also updates htrans to idle
    end else begin
        state <= nextstate;
    end
end

always @(*) begin
    case(state)
    IDLE: begin
        // on any nextstate == START updates htrans to NONSEQUENTIAL (NONSEQ)
        if(cycle_cnt == 1 && exu_load_en) begin
            nextstate = READ_START;
        end else if(cycle_cnt == 1 && exu_store_en) begin
            nextstate = WRITE_START;
        end else begin
            nextstate = IDLE;
        end
    end
    READ_START: begin
        // htrans == NONSEQ
        if(hready) begin
            nextstate = READ_WAIT2;
        end else begin
            nextstate = READ_WAIT1;
        end
    end
    READ_WAIT1: begin
        if(hready) begin
            nextstate = READ_WAIT2;
        end else begin
            nextstate = READ_WAIT1;
        end
    end
    READ_WAIT2: begin
        if(hready) begin
            nextstate = IDLE;
        end else begin
            nextstate = READ_WAIT2;
        end
    end
    WRITE_START: begin
        // htrans == NONSEQ
        if(hready) begin
            nextstate = WRITE_WAIT;
        end else begin
            nextstate = WRITE_START;
        end
    end
    WRITE_WAIT: begin
        if(hready) begin
            nextstate = IDLE;
        end else begin
            nextstate = WRITE_WAIT;
        end
    end
    default: begin
        nextstate = IDLE;
    end
    endcase
end

// htrans
// only upload one word at a time (no need for sequential/busy)
always@(posedge hclk) begin
    if(!hrstn) begin
        htrans <= HTRANS_IDLE;
    end else if(nextstate == READ_START || nextstate == WRITE_START) begin
        // NONSEQ: transfer of single signal/burst and address/control signals are unrelated to previous transfer
        htrans <= HTRANS_NONSEQ;
    end else begin
        // 
        htrans <= HTRANS_IDLE;
    end
end

// hmastlock
// How is this driven by an assign statement??????
assign hmastlock = 0;

// hwrite
always@(posedge hclk) begin
    if(!hrstn) begin
        hwrite <= 0;
    end else if(nextstate == WRITE_START) begin
        hwrite <= 1;
    end else begin
        hwrite <= 0;
    end
end

// hsize
assign hsize = hrstn ? 2 : 0;

// hburst
assign hburst = 0;

// haddr
always@(posedge hclk) begin
    if(!hrstn) begin
        haddr <= 0;
    end else if(nextstate == READ_START) begin
        haddr <= exu_load_base_addr + exu_load_offset;
    end else if(nextstate == WRITE_START) begin
        haddr <= 0;
    end
end

// hwdata
always@(posedge hclk) begin
    if(!hrstn) begin
        hwdata <= 0;
    end else if(nextstate == WRITE_START) begin
        hwdata <= exu_store_data;
    end else begin
        hwdata <= 0;
    end
end

// mau_load_data_buff
reg [31:0]  mau_load_data_buff;
reg [4:0]   mau_load_rd_buff;
localparam LOAD_IDLE = 0, LOAD_BTYE = 1, LOAD_HALFWORD = 2, LOAD_WORD = 3;
always@(posedge hclk) begin
    if(!hrstn) begin
        mau_load_data_buff <= 0;
        mau_load_rd_buff   <= 0;
    end else if(state == READ_WAIT2 && nextstate == IDLE) begin
        // Largest value to load in is 32 bits AKA one word
        // Data seems signed?
        // Need some info from lindsey about EXU outputs to figure out exactly what the last two are used for
        mau_load_data_buff <=   (exu_load_size  == LOAD_BTYE      &&  exu_load_sext) ? {{24{hrdata[ 7]}}, hrdata[ 7:0] }    :
                                (exu_load_size  == LOAD_HALFWORD  &&  exu_load_sext) ? {{16{hrdata[15]}}, hrdata[15:0] }    :
                                (exu_load_size  == LOAD_WORD      &&  exu_load_sext) ? hrdata                               :
                                (exu_load_size  == LOAD_BTYE      && !exu_load_sext) ? {{24{      1'b0}}, hrdata[ 7:0] }    :
                                (exu_load_size  == LOAD_HALFWORD  && !exu_load_sext) ? {{16{      1'b0}}, hrdata[15:0] }    :
                                0                                                                                           ;
        mau_load_rd_buff   <= exu_load_rd;
    // This could mess with data being transferred correctly in next posedge hclk block
    end else if(cycle_cnt == CNT_MAX) begin
        mau_load_data_buff <= 0;
        mau_load_rd_buff   <= 0;
    end else begin
        mau_load_data_buff <= mau_load_data_buff;
        mau_load_rd_buff   <= mau_load_rd_buff;
    end
end

// mau_load_data
// Time limited by Cycle Count (seesm to also be present in other modules)
always@(posedge hclk) begin
    if(!hrstn) begin
        mau_load_data <= 0;
        mau_load_rd   <= 0;
        mau_load_en   <= 0;
    // Need to check if data is being properly transferred on this condition bc of previous block (timing might be an issue)
    // Also this entirely takes away the point of having a five stage system (you can't pipeline with this)
    end else if(cycle_cnt == CNT_MAX) begin
        mau_load_data <= mau_load_data_buff;
        mau_load_rd   <= mau_load_rd_buff;
        mau_load_en   <= exu_load_en;
    // Unsure what the point of this is?
    // Seems to literally just hold the value but it should already do that (just seems like unecessary code)
    end else begin
        mau_load_data <= mau_load_data;
        mau_load_rd   <= mau_load_rd;
        mau_load_en   <= mau_load_en;
    end
end

endmodule

verification/coco_tb/DUT_Wrapper/mau_swc_wrapper.v
module mau_swc_wrapper (
    input hclk,
    input hrstn,
    input [3:0] cycle_cnt,
    input hready,
    input hresp,
    input [31:0] hrdata,
    input [4:0] exu_load_rd,
    input [31:0] exu_load_base_addr,
    input [31:0] exu_load_offset,
    input exu_load_sext,
    input [1:0] exu_load_size,
    input exu_load_en,
    input [31:0] exu_store_addr,
    input [31:0] exu_store_data,
    input exu_store_en,
    input [1:0] exu_store_size,
    output reg [31:0] haddr,
    output reg hwrite,
    output reg [31:0] hwdata,
    output reg [2:0] hsize,
    output reg [2:0] hburst,
    output reg [6:0] hprot,
    output reg [1:0] htrans,
    output reg hmastlock,
    output reg [4:0] mau_load_rd,
    output reg [31:0] mau_load_data,
    output reg mau_load_en
);

    mau_swc dut (
        .hclk(hclk),
        .hrstn(hrstn),
        .cycle_cnt(cycle_cnt),
        .hready(hready),
        .hresp(hresp),
        .hrdata(hrdata),
        .exu_load_rd(exu_load_rd),
        .exu_load_base_addr(exu_load_base_addr),
        .exu_load_offset(exu_load_offset),
        .exu_load_sext(exu_load_sext),
        .exu_load_size(exu_load_size),
        .exu_load_en(exu_load_en),
        .exu_store_addr(exu_store_addr),
        .exu_store_data(exu_store_data),
        .exu_store_en(exu_store_en),
        .exu_store_size(exu_store_size),
        .haddr(haddr),
        .hwrite(hwrite),
        .hwdata(hwdata),
        .hsize(hsize),
        .hburst(hburst),
        .hprot(hprot),
        .htrans(htrans),
        .hmastlock(hmastlock),
        .mau_load_rd(mau_load_rd),
        .mau_load_data(mau_load_data),
        .mau_load_en(mau_load_en)
    );
    initial begin
        $dumpfile("./vcds/mau_swc.vcd");
        $dumpvars(0, mau_swc_wrapper);
    end
endmodule

verification/coco_tb/vcds/mau_swc.vcd
$date
	Tue Jan 28 19:31:39 2025
$end
$version
	Icarus Verilog
$end
$timescale
	1ps
$end
$scope module mau_swc_wrapper $end
$var wire 4 ! cycle_cnt [3:0] $end
$var wire 32 " exu_load_base_addr [31:0] $end
$var wire 1 # exu_load_en $end
$var wire 32 $ exu_load_offset [31:0] $end
$var wire 5 % exu_load_rd [4:0] $end
$var wire 1 & exu_load_sext $end
$var wire 2 ' exu_load_size [1:0] $end
$var wire 32 ( exu_store_addr [31:0] $end
$var wire 32 ) exu_store_data [31:0] $end
$var wire 1 * exu_store_en $end
$var wire 2 + exu_store_size [1:0] $end
$var wire 3 , hburst [2:0] $end
$var wire 1 - hclk $end
$var wire 1 . hmastlock $end
$var wire 32 / hrdata [31:0] $end
$var wire 1 0 hready $end
$var wire 1 1 hresp $end
$var wire 1 2 hrstn $end
$var wire 5 3 mau_load_rd [4:0] $end
$var wire 1 4 mau_load_en $end
$var wire 32 5 mau_load_data [31:0] $end
$var wire 1 6 hwrite $end
$var wire 32 7 hwdata [31:0] $end
$var wire 2 8 htrans [1:0] $end
$var wire 3 9 hsize [2:0] $end
$var wire 7 : hprot [6:0] $end
$var wire 32 ; haddr [31:0] $end
$scope module dut $end
$var wire 4 < cycle_cnt [3:0] $end
$var wire 32 = exu_load_base_addr [31:0] $end
$var wire 1 # exu_load_en $end
$var wire 32 > exu_load_offset [31:0] $end
$var wire 5 ? exu_load_rd [4:0] $end
$var wire 1 & exu_load_sext $end
$var wire 2 @ exu_load_size [1:0] $end
$var wire 32 A exu_store_addr [31:0] $end
$var wire 32 B exu_store_data [31:0] $end
$var wire 1 * exu_store_en $end
$var wire 2 C exu_store_size [1:0] $end
$var wire 3 D hburst [2:0] $end
$var wire 1 - hclk $end
$var wire 1 . hmastlock $end
$var wire 32 E hrdata [31:0] $end
$var wire 1 0 hready $end
$var wire 1 1 hresp $end
$var wire 1 2 hrstn $end
$var wire 3 F hsize [2:0] $end
$var parameter 32 G CNT_MAX $end
$var parameter 32 H HTRANS_BUSY $end
$var parameter 32 I HTRANS_IDLE $end
$var parameter 32 J HTRANS_NONSEQ $end
$var parameter 32 K HTRANS_SEQ $end
$var parameter 32 L IDLE $end
$var parameter 32 M LOAD_BTYE $end
$var parameter 32 N LOAD_HALFWORD $end
$var parameter 32 O LOAD_IDLE $end
$var parameter 32 P LOAD_WORD $end
$var parameter 32 Q READ_START $end
$var parameter 32 R READ_WAIT1 $end
$var parameter 32 S READ_WAIT2 $end
$var parameter 32 T WRITE_START $end
$var parameter 32 U WRITE_WAIT $end
$var reg 32 V haddr [31:0] $end
$var reg 7 W hprot [6:0] $end
$var reg 2 X htrans [1:0] $end
$var reg 32 Y hwdata [31:0] $end
$var reg 1 6 hwrite $end
$var reg 32 Z mau_load_data [31:0] $end
$var reg 32 [ mau_load_data_buff [31:0] $end
$var reg 1 4 mau_load_en $end
$var reg 5 \ mau_load_rd [4:0] $end
$var reg 5 ] mau_load_rd_buff [4:0] $end
$var reg 3 ^ nextstate [2:0] $end
$var reg 3 _ state [2:0] $end
$upscope $end
$upscope $end
$enddefinitions $end
$comment Show the parameter values. $end
$dumpall
b101 U
b100 T
b11 S
b10 R
b1 Q
b11 P
b0 O
b10 N
b1 M
b0 L
b11 K
b10 J
b0 I
b1 H
b100 G
$end
#0
$dumpvars
b0 _
b0 ^
b0 ]
b0 \
b0 [
b0 Z
b0 Y
b0 X
bx W
b0 V
b0 F
bz E
b0 D
bz C
bz B
bz A
bz @
bz ?
bz >
bz =
bz <
b0 ;
bx :
b0 9
b0 8
b0 7
06
b0 5
04
b0 3
02
z1
z0
bz /
0.
1-
b0 ,
bz +
z*
bz )
bz (
bz '
z&
bz %
bz $
z#
bz "
bz !
$end
#5000
0-
#10000
b1 ^
b10 9
b10 F
1-
1#
1&
b11 '
b11 @
b100 $
b100 >
b1000000000000 "
b1000000000000 =
10
b1 !
b1 <
12
#15000
0-
#20000
b10 !
b10 <
b11011110101011011011111011101111 /
b11011110101011011011111011101111 E
0#
b11 ^
b1 _
b10 8
b10 X
b1000000000100 ;
b1000000000100 V
1-
#25000
0-
#30000
b11 !
b11 <
b0 ^
b0 8
b0 X
b11 _
1-
#35000
0-
#40000
b100 !
b100 <
b0 _
bz ]
b11011110101011011011111011101111 [
1-
#45000
0-
#50000
b1 !
b1 <
bz 3
bz \
b11011110101011011011111011101111 5
b11011110101011011011111011101111 Z
b0 ]
b0 [
1-
#55000
0-
#60000
1-
#60001
b0 9
b0 F
b0 !
b0 <
02
#65001
0-
#70001
b1 ^
b1 !
b1 <
b10 9
b10 F
1-
1#
0&
b1 '
b1 @
b1 $
b1 >
12
#75001
0-
#80001
b10 !
b10 <
b10101011 /
b10101011 E
0#
b11 ^
b1 _
b10 8
b10 X
b1000000000001 ;
b1000000000001 V
1-
#85001
0-
#90001
b11 !
b11 <
b0 ^
b0 8
b0 X
b11 _
1-
#95001
0-
#100001
b100 !
b100 <
b0 _
bz ]
b10101011 [
1-
#105001
0-
#110001
b1 !
b1 <
b10101011 5
b10101011 Z
b0 ]
b0 [
1-
#115001
0-
#120001
1-
#120002
b0 9
b0 F
b0 !
b0 <
02
#125002
0-
#130002
b1 ^
b1 !
b1 <
b10 9
b10 F
1-
1#
1&
12
#135002
0-
#140002
b10 !
b10 <
0#
b11 ^
b1 _
b10 8
b10 X
1-
#145002
0-
#150002
b11 !
b11 <
b0 ^
b0 8
b0 X
b11 _
1-
#155002
0-
#160002
b100 !
b100 <
b0 _
bz ]
b11111111111111111111111110101011 [
1-
#165002
0-
#170002
b1 !
b1 <
b11111111111111111111111110101011 5
b11111111111111111111111110101011 Z
b0 ]
b0 [
1-
#175002
0-
#180002
1-
#180003
b0 9
b0 F
b0 !
b0 <
02
#185003
0-
#190003
b1 ^
b1 !
b1 <
b10 9
b10 F
1-
1#
0&
b10 '
b10 @
12
#195003
0-
#200003
b10 !
b10 <
b11011110101011011011111011101111 /
b11011110101011011011111011101111 E
0#
b11 ^
b1 _
b10 8
b10 X
1-
#205003
0-
#210003
b11 !
b11 <
b0 ^
b0 8
b0 X
b11 _
1-
#215003
0-
#220003
b100 !
b100 <
b0 _
bz ]
b1011111011101111 [
1-
#225003
0-
#230003
b1 !
b1 <
b1011111011101111 5
b1011111011101111 Z
b0 ]
b0 [
1-
#235003
0-
#240003
1-
#240004
b0 9
b0 F
b0 !
b0 <
02
#245004
0-
#250004
b1 ^
b1 !
b1 <
b10 9
b10 F
1-
1#
1&
12
#255004
0-
#260004
b10 !
b10 <
0#
b11 ^
b1 _
b10 8
b10 X
1-
#265004
0-
#270004
b11 !
b11 <
b0 ^
b0 8
b0 X
b11 _
1-
#275004
0-
#280004
b100 !
b100 <
b0 _
bz ]
b11111111111111111011111011101111 [
1-
#285004
0-
#290004
b1 !
b1 <
b11111111111111111011111011101111 5
b11111111111111111011111011101111 Z
b0 ]
b0 [
1-
#295004
0-
#300004
1-
#300005
b0 9
b0 F
b0 !
b0 <
02
#305005
0-
#310005
b100 ^
b1 !
b1 <
00
b10 9
b10 F
1-
b11011110101011011011111011101111 )
b11011110101011011011111011101111 B
1*
b11 '
b11 @
b100 $
b100 >
12
#315005
0-
#320005
b10 !
b10 <
b100 _
b10 8
b10 X
16
b0 ;
b0 V
b11011110101011011011111011101111 7
b11011110101011011011111011101111 Y
1-
