S25_core/rtl/lsu_arbiter/lsu_arbiter.v
module arbiter (
    input clk,
    input rst_n,
    // SDRAM Controller Interface
    output       L_sdrc_wr_n,
    output       L_sdrc_rd_n,
    output [31:0] L_sdrc_addr,
    output [3:0]  L_sdrc_dqm,
    output [7:0]  L_sdrc_data_len,
    output [31:0] L_sdrc_data,
    input        O_sdrc_busy_n,
    input [31:0] O_sdrc_data,
    input        O_sdrc_rd_valid,
    
    // I-cache LSU Interface
    input        icache_data_req,
    input [31:0] icache_data_addr,
    input        icache_data_we,
    input [3:0]  icache_data_be,
    input [31:0] icache_data_wdata,
    output       icache_data_gnt,
    output       icache_data_rvalid,
    output [31:0] icache_data_rdata,
    
    // D-cache LSU Interface
    input        dcache_data_req,
    input [31:0] dcache_data_addr,
    input        dcache_data_we,
    input [3:0]  dcache_data_be,
    input [31:0] dcache_data_wdata,
    output       dcache_data_gnt,
    output       dcache_data_rvalid,
    output [31:0] dcache_data_rdata
);

// FSM States
parameter IDLE = 1'b0;
parameter BUSY = 1'b1;
reg state, next_state;
reg current_icache; // 1: I-cache, 0: D-cache

// Latch addresses and control signals when request is granted
reg [31:0] selected_addr;
reg selected_we;
reg [3:0] selected_be;
reg [31:0] selected_wdata;

// FSM Transition Logic
always @(*) begin
    next_state = state;
    
    case (state)
        IDLE: begin
            // Check if we have requests and SDRAM is ready
            if (O_sdrc_busy_n) begin // When SDRAM is ready (not busy)
                if (icache_data_req)
                    next_state = BUSY;
                else if (dcache_data_req)
                    next_state = BUSY;
            end
        end
        BUSY: begin
            // For read operations, wait for read valid
            // For write operations, complete immediately
            if (O_sdrc_rd_valid || selected_we) 
                next_state = IDLE;
        end
    endcase
end

// FSM State Update and Current Request Latching
always @(posedge clk or negedge rst_n) begin
    if (!rst_n) begin
        state <= IDLE;
        current_icache <= 1'b0;
        selected_addr <= 32'h0;
        selected_we <= 1'b0;
        selected_be <= 4'h0;
        selected_wdata <= 32'h0;
    end else begin
        state <= next_state;
        
        // Latch cache and request details when granting
        if (state == IDLE && next_state == BUSY) begin
            if (icache_data_req) begin
                current_icache <= 1'b1;
                selected_addr <= icache_data_addr;
                selected_we <= icache_data_we;
                selected_be <= icache_data_be;
                selected_wdata <= icache_data_wdata;
            end else if (dcache_data_req) begin
                current_icache <= 1'b0;
                selected_addr <= dcache_data_addr;
                selected_we <= dcache_data_we;
                selected_be <= dcache_data_be;
                selected_wdata <= dcache_data_wdata;
            end
        end
    end
end

// Grant Signals - when SDRAM is ready (O_sdrc_busy_n = 1) and in IDLE state
assign icache_data_gnt = (state == IDLE) && O_sdrc_busy_n && icache_data_req;
assign dcache_data_gnt = (state == IDLE) && O_sdrc_busy_n && !icache_data_req && dcache_data_req;

// SDRAM Controller Interface Signals - Use latched values once in BUSY state
// Write enable signal (active low)
assign L_sdrc_wr_n = (state == IDLE && next_state == BUSY) ? 
                     (icache_data_req ? (icache_data_we ? 1'b0 : 1'b1) : (dcache_data_we ? 1'b0 : 1'b1)) : 
                     ((state == BUSY) ? (selected_we ? 1'b0 : 1'b1) : 1'b1);

// Read enable signal (active low)
assign L_sdrc_rd_n = (state == IDLE && next_state == BUSY) ? 
                    (icache_data_req ? (icache_data_we ? 1'b1 : 1'b0) : (dcache_data_we ? 1'b1 : 1'b0)) : 
                    ((state == BUSY) ? (selected_we ? 1'b1 : 1'b0) : 1'b1);

// SDRAM Controller Interface Signals - Use latched values once in BUSY state
// Address, data, and data mask connections
assign L_sdrc_addr = (state == IDLE && next_state == BUSY) ? 
                     (icache_data_req ? icache_data_addr : dcache_data_addr) : 
                     ((state == BUSY) ? selected_addr : 32'h0);

assign L_sdrc_dqm = (state == IDLE && next_state == BUSY) ? 
                   ~(icache_data_req ? icache_data_be : dcache_data_be) : 
                   ((state == BUSY) ? ~selected_be : 4'hF); // DQM is active low, BE is active high

assign L_sdrc_data = (state == IDLE && next_state == BUSY) ? 
                    (icache_data_req ? icache_data_wdata : dcache_data_wdata) : 
                    ((state == BUSY) ? selected_wdata : 32'h0);

// Fixed data length for 32-bit (4 byte) transfers
assign L_sdrc_data_len = 8'd4;

// Read Data and Valid Forwarding
assign icache_data_rvalid = current_icache && O_sdrc_rd_valid;
assign dcache_data_rvalid = !current_icache && O_sdrc_rd_valid;
assign icache_data_rdata = O_sdrc_data;
assign dcache_data_rdata = O_sdrc_data;

endmodule

S25_core/rtl/lsu_arbiter/tb_lsu_arbiter.v
`timescale 1ns/1ps

module arbiter_tb;
    // Clock and reset
    reg clk;
    reg rst_n;
    
    // I-cache Interface
    reg        icache_data_req;
    reg [31:0] icache_data_addr;
    reg        icache_data_we;
    reg [3:0]  icache_data_be;
    reg [31:0] icache_data_wdata;
    wire       icache_data_gnt;
    wire       icache_data_rvalid;
    wire [31:0] icache_data_rdata;
    
    // D-cache Interface
    reg        dcache_data_req;
    reg [31:0] dcache_data_addr;
    reg        dcache_data_we;
    reg [3:0]  dcache_data_be;
    reg [31:0] dcache_data_wdata;
    wire       dcache_data_gnt;
    wire       dcache_data_rvalid;
    wire [31:0] dcache_data_rdata;
    
    // SDRAM Controller Interface
    wire       L_sdrc_wr_n;
    wire       L_sdrc_rd_n;
    wire [31:0] L_sdrc_addr;
    wire [3:0]  L_sdrc_dqm;
    wire [7:0]  L_sdrc_data_len;
    wire [31:0] L_sdrc_data;
    reg        O_sdrc_busy_n;
    reg [31:0] O_sdrc_data;
    reg        O_sdrc_rd_valid;

    // Test control
    integer error_count;
    integer test_case;
    
    // Variables for tasks
    integer wait_count;
    reg     signal_detected;
    
    // Debug signals
    wire is_icache_selected;
    assign is_icache_selected = dut.current_icache;

    // Instantiate DUT
    arbiter dut (
        .clk(clk),
        .rst_n(rst_n),
        // SDRAM Controller Interface
        .L_sdrc_wr_n(L_sdrc_wr_n),
        .L_sdrc_rd_n(L_sdrc_rd_n),
        .L_sdrc_addr(L_sdrc_addr),
        .L_sdrc_dqm(L_sdrc_dqm),
        .L_sdrc_data_len(L_sdrc_data_len),
        .L_sdrc_data(L_sdrc_data),
        .O_sdrc_busy_n(O_sdrc_busy_n),
        .O_sdrc_data(O_sdrc_data),
        .O_sdrc_rd_valid(O_sdrc_rd_valid),
        // I-cache Interface
        .icache_data_req(icache_data_req),
        .icache_data_addr(icache_data_addr),
        .icache_data_we(icache_data_we),
        .icache_data_be(icache_data_be),
        .icache_data_wdata(icache_data_wdata),
        .icache_data_gnt(icache_data_gnt),
        .icache_data_rvalid(icache_data_rvalid),
        .icache_data_rdata(icache_data_rdata),
        // D-cache Interface
        .dcache_data_req(dcache_data_req),
        .dcache_data_addr(dcache_data_addr),
        .dcache_data_we(dcache_data_we),
        .dcache_data_be(dcache_data_be),
        .dcache_data_wdata(dcache_data_wdata),
        .dcache_data_gnt(dcache_data_gnt),
        .dcache_data_rvalid(dcache_data_rvalid),
        .dcache_data_rdata(dcache_data_rdata)
    );

    // Clock generation
    initial clk = 0;
    always #5 clk = ~clk;

    // Reset task
    task reset;
        begin
            rst_n = 0;
            #20 rst_n = 1;
            #10;
        end
    endtask
    
    // Initialize signals task
    task init_signals;
        begin
            icache_data_req = 0;
            dcache_data_req = 0;
            icache_data_addr = 0;
            icache_data_we = 0;
            icache_data_be = 0;
            icache_data_wdata = 0;
            dcache_data_addr = 0;
            dcache_data_we = 0;
            dcache_data_be = 0;
            dcache_data_wdata = 0;
            O_sdrc_rd_valid = 0;
            O_sdrc_data = 0;
            O_sdrc_busy_n = 1; // Default to ready
            error_count = 0;
            test_case = 0;
            wait_count = 0;
            signal_detected = 0;
        end
    endtask
    
    // SDRAM response model
    // Note: O_sdrc_busy_n is 1 when SDRAM is ready, 0 when busy
    always @(posedge clk) begin
        if (!rst_n) begin
            O_sdrc_busy_n <= 1;  // Ready by default
            O_sdrc_rd_valid <= 0;
        end else begin
            // Default values for each cycle
            O_sdrc_rd_valid <= 0;
            
            // Process read requests - when L_sdrc_rd_n goes low (active)
            if (!L_sdrc_rd_n && O_sdrc_busy_n) begin
                // Become busy for at least one cycle
                O_sdrc_busy_n <= 0;
                
                // After one cycle, return data and valid
                O_sdrc_data <= 32'hDEADBEEF;
                O_sdrc_rd_valid <= 1;
                
                // Return to ready state in the next cycle (handled outside this if block)
            end else if (!L_sdrc_wr_n && O_sdrc_busy_n) begin
                // Process write requests - when L_sdrc_wr_n goes low (active)
                // Become busy for one cycle
                O_sdrc_busy_n <= 0;
            end else if (!O_sdrc_busy_n) begin
                // Return to ready state after being busy for one cycle
                O_sdrc_busy_n <= 1;
            end
        end
    end

    // Wait for grant helper task
    task wait_for_grant;
        input is_icache;
        output got_grant;
        begin
            wait_count = 0;
            signal_detected = 0;
            
            while (wait_count < 10 && !signal_detected) begin
                @(posedge clk);
                if (is_icache && icache_data_gnt) 
                    signal_detected = 1;
                else if (!is_icache && dcache_data_gnt)
                    signal_detected = 1;
                wait_count = wait_count + 1;
            end
            
            got_grant = signal_detected;
        end
    endtask
    
    // Wait for read valid helper task
    task wait_for_read_valid;
        input is_icache;
        output got_valid;
        begin
            wait_count = 0;
            signal_detected = 0;
            
            while (wait_count < 10 && !signal_detected) begin
                @(posedge clk);
                if (is_icache && icache_data_rvalid) 
                    signal_detected = 1;
                else if (!is_icache && dcache_data_rvalid)
                    signal_detected = 1;
                wait_count = wait_count + 1;
            end
            
            got_valid = signal_detected;
        end
    endtask
    
    // I-cache read request task
    task test_icache_read;
        input [31:0] addr;
        reg got_grant;
        reg got_valid;
        begin
            $display("Test Case %0d: I-cache read request at address %h", test_case, addr);
            
            // Set request active
            @(posedge clk);
            icache_data_req = 1;
            icache_data_addr = addr;
            icache_data_we = 0; // Read request
            icache_data_be = 4'hF; // All bytes enabled
            
            // Wait for grant or timeout after 10 cycles
            wait_for_grant(1, got_grant);
            
            if (got_grant)
                $display("I-cache grant received");
            else
                $display("Error: I-cache grant timeout");
            
            // Wait for data valid or timeout after 10 cycles
            wait_for_read_valid(1, got_valid);
            
            if (got_valid)
                $display("I-cache read valid received, data = %h", icache_data_rdata);
            else
                $display("Error: I-cache read valid timeout");
            
            // Check data
            if (got_valid && icache_data_rdata !== 32'hDEADBEEF) begin
                $display("Error: I-cache read data mismatch: got %h, expected %h", 
                         icache_data_rdata, 32'hDEADBEEF);
                error_count = error_count + 1;
            end
            
            // Clear request and wait a couple cycles
            @(posedge clk);
            icache_data_req = 0;
            repeat (2) @(posedge clk);
        end
    endtask
    
    // D-cache read request task
    task test_dcache_read;
        input [31:0] addr;
        reg got_grant;
        reg got_valid;
        begin
            $display("Test Case %0d: D-cache read request at address %h", test_case, addr);
            
            // Set request active
            @(posedge clk);
            dcache_data_req = 1;
            dcache_data_addr = addr;
            dcache_data_we = 0; // Read request
            dcache_data_be = 4'hF; // All bytes enabled
            
            // Wait for grant or timeout after 10 cycles
            wait_for_grant(0, got_grant);
            
            if (got_grant)
                $display("D-cache grant received");
            else
                $display("Error: D-cache grant timeout");
            
            // Wait for data valid or timeout after 10 cycles
            wait_for_read_valid(0, got_valid);
            
            if (got_valid)
                $display("D-cache read valid received, data = %h", dcache_data_rdata);
            else
                $display("Error: D-cache read valid timeout");
            
            // Check data
            if (got_valid && dcache_data_rdata !== 32'hDEADBEEF) begin
                $display("Error: D-cache read data mismatch: got %h, expected %h", 
                         dcache_data_rdata, 32'hDEADBEEF);
                error_count = error_count + 1;
            end
            
            // Clear request and wait a couple cycles
            @(posedge clk);
            dcache_data_req = 0;
            repeat (2) @(posedge clk);
        end
    endtask
    
    // Test both caches simultaneously
    task test_both_caches;
        input [31:0] icache_addr;
        input [31:0] dcache_addr;
        reg got_grant;
        reg got_valid;
        begin
            $display("Test Case %0d: Both read requests (I-cache priority)", test_case);
            
            // First set up I-cache request
            @(posedge clk);
            icache_data_req = 1;
            icache_data_addr = icache_addr;
            icache_data_we = 0; // Read request
            icache_data_be = 4'hF; // All bytes enabled
            
            // Then set up D-cache request on the same cycle
            dcache_data_req = 1;
            dcache_data_addr = dcache_addr;
            dcache_data_we = 0; // Read request
            dcache_data_be = 4'hF; // All bytes enabled
            
            // Wait for icache grant or timeout after 10 cycles
            wait_for_grant(1, got_grant);
            
            if (got_grant)
                $display("I-cache grant received");
            else
                $display("Error: I-cache grant timeout");
            
            // Check that dcache doesn't get grant
            if (dcache_data_gnt) begin
                $display("Error: D-cache got grant when both requests active");
                error_count = error_count + 1;
            end
            
            // Explicitly check that the I-cache address is being used, not D-cache address
            @(posedge clk); // Wait to observe the correct address
            if (L_sdrc_addr !== icache_addr) begin
                $display("Error: Incorrect address for I-cache. Expected %h, got %h", 
                        icache_addr, L_sdrc_addr);
                error_count = error_count + 1;
            end
            
            // Wait for data valid or timeout after 10 cycles
            wait_for_read_valid(1, got_valid);
            
            if (got_valid)
                $display("I-cache read valid received, data = %h", icache_data_rdata);
            else
                $display("Error: I-cache read valid timeout");
            
            // Check data
            if (got_valid && icache_data_rdata !== 32'hDEADBEEF) begin
                $display("Error: I-cache read data mismatch: got %h, expected %h", 
                         icache_data_rdata, 32'hDEADBEEF);
                error_count = error_count + 1;
            end
            
            // Clear icache request but keep dcache active
            @(posedge clk);
            icache_data_req = 0;
            
            // Since we're forcing the D-cache to send a new request after I-cache finishes,
            // we need to retry the D-cache request after I-cache is done
            // Verify first that D-cache didn't get a grant automatically
            if (dcache_data_gnt) begin
                $display("Error: D-cache got grant automatically after I-cache completed");
                error_count = error_count + 1;
            end
            
            // Reset and re-assert D-cache request to ensure we get a fresh request
            dcache_data_req = 0;
            @(posedge clk);
            dcache_data_req = 1;
            
            // Wait a couple of cycles before checking for dcache grant
            @(posedge clk);
            
            // Wait for dcache grant or timeout after 10 cycles
            wait_for_grant(0, got_grant);
            
            if (got_grant)
                $display("D-cache grant received after I-cache completed");
            else
                $display("Error: D-cache grant timeout after I-cache completed");
            
            // Check address
            @(posedge clk); // Wait to observe the correct address
            if (L_sdrc_addr !== dcache_addr) begin
                $display("Error: Incorrect address for D-cache. Expected %h, got %h", 
                        dcache_addr, L_sdrc_addr);
                error_count = error_count + 1;
            end
            
            // Wait for data valid or timeout after 10 cycles
            wait_for_read_valid(0, got_valid);
            
            if (got_valid)
                $display("D-cache read valid received, data = %h", dcache_data_rdata);
            else
                $display("Error: D-cache read valid timeout");
            
            // Check data
            if (got_valid && dcache_data_rdata !== 32'hDEADBEEF) begin
                $display("Error: D-cache read data mismatch: got %h, expected %h", 
                         dcache_data_rdata, 32'hDEADBEEF);
                error_count = error_count + 1;
            end
            
            // Clear request and wait a couple cycles
            @(posedge clk);
            dcache_data_req = 0;
            repeat (2) @(posedge clk);
        end
    endtask
    
    // I-cache write request task
    task test_icache_write;
        input [31:0] addr;
        input [31:0] data;
        reg got_grant;
        begin
            $display("Test Case %0d: I-cache write request at address %h", test_case, addr);
            
            // Set request active
            @(posedge clk);
            icache_data_req = 1;
            icache_data_addr = addr;
            icache_data_we = 1; // Write request
            icache_data_be = 4'hF; // All bytes enabled
            icache_data_wdata = data;
            
            // Wait for grant or timeout after 10 cycles
            wait_for_grant(1, got_grant);
            
            if (got_grant)
                $display("I-cache grant received for write");
            else
                $display("Error: I-cache grant timeout for write");
            
            // One cycle is needed to observe the address and data
            @(posedge clk);
            
            // Check address after grant
            if (L_sdrc_addr !== addr) begin
                $display("Error: Incorrect address for I-cache write. Expected %h, got %h", 
                        addr, L_sdrc_addr);
                error_count = error_count + 1;
            end
            
            // Check data
            if (L_sdrc_data !== data) begin
                $display("Error: Incorrect data for I-cache write. Expected %h, got %h", 
                        data, L_sdrc_data);
                error_count = error_count + 1;
            end
            
            // Wait for write to complete and check write enable
            if (L_sdrc_wr_n) begin
                $display("Error: Write enable not asserted. Expected 0, got %b", L_sdrc_wr_n);
                error_count = error_count + 1;
            end
            
            // Wait a few cycles for write to complete
            repeat (3) @(posedge clk);
            
            // Clear request and wait a couple cycles
            icache_data_req = 0;
            repeat (2) @(posedge clk);
        end
    endtask

    // Main test sequence
    initial begin
        // Initialize
        init_signals();
        
        // Create VCD file
        $dumpfile("arbiter.vcd");
        $dumpvars(0, arbiter_tb);
        
        // Reset
        reset();
        
        // Test Case 1: I-cache read request
        test_case = 1;
        test_icache_read(32'h1000);
        
        // Test Case 2: D-cache read request
        test_case = 2;
        test_dcache_read(32'h2000);
        
        // Test Case 3: Both read requests (I-cache priority)
        test_case = 3;
        test_both_caches(32'h3000, 32'h2000);
        
        // Test Case 4: I-cache write request
        test_case = 4;
        test_icache_write(32'h4000, 32'hCAFEBABE);
        
        // Final report
        if (error_count == 0)
            $display("All test cases PASSED");
        else
            $display("%0d test cases FAILED", error_count);
        
        $finish;
    end
endmodule

S25_core/rtl/lsu_arbiter/arbiter.vcd
$date
	Sat Apr 26 15:51:37 2025
$end
$version
	Icarus Verilog
$end
$timescale
	1ps
$end
$scope module arbiter_tb $end
$var wire 8 ! L_sdrc_data_len [7:0] $end
$var wire 1 " is_icache_selected $end
$var wire 1 # icache_data_rvalid $end
$var wire 32 $ icache_data_rdata [31:0] $end
$var wire 1 % icache_data_gnt $end
$var wire 1 & dcache_data_rvalid $end
$var wire 32 ' dcache_data_rdata [31:0] $end
$var wire 1 ( dcache_data_gnt $end
$var wire 1 ) L_sdrc_wr_n $end
$var wire 1 * L_sdrc_rd_n $end
$var wire 4 + L_sdrc_dqm [3:0] $end
$var wire 32 , L_sdrc_data [31:0] $end
$var wire 32 - L_sdrc_addr [31:0] $end
$var reg 1 . O_sdrc_busy_n $end
$var reg 32 / O_sdrc_data [31:0] $end
$var reg 1 0 O_sdrc_rd_valid $end
$var reg 1 1 clk $end
$var reg 32 2 dcache_data_addr [31:0] $end
$var reg 4 3 dcache_data_be [3:0] $end
$var reg 1 4 dcache_data_req $end
$var reg 32 5 dcache_data_wdata [31:0] $end
$var reg 1 6 dcache_data_we $end
$var reg 32 7 icache_data_addr [31:0] $end
$var reg 4 8 icache_data_be [3:0] $end
$var reg 1 9 icache_data_req $end
$var reg 32 : icache_data_wdata [31:0] $end
$var reg 1 ; icache_data_we $end
$var reg 1 < rst_n $end
$var reg 1 = signal_detected $end
$var integer 32 > error_count [31:0] $end
$var integer 32 ? test_case [31:0] $end
$var integer 32 @ wait_count [31:0] $end
$scope module dut $end
$var wire 8 A L_sdrc_data_len [7:0] $end
$var wire 1 . O_sdrc_busy_n $end
$var wire 32 B O_sdrc_data [31:0] $end
$var wire 1 0 O_sdrc_rd_valid $end
$var wire 1 1 clk $end
$var wire 32 C dcache_data_addr [31:0] $end
$var wire 4 D dcache_data_be [3:0] $end
$var wire 1 ( dcache_data_gnt $end
$var wire 32 E dcache_data_rdata [31:0] $end
$var wire 1 4 dcache_data_req $end
$var wire 1 & dcache_data_rvalid $end
$var wire 32 F dcache_data_wdata [31:0] $end
$var wire 1 6 dcache_data_we $end
$var wire 32 G icache_data_addr [31:0] $end
$var wire 4 H icache_data_be [3:0] $end
$var wire 1 % icache_data_gnt $end
$var wire 32 I icache_data_rdata [31:0] $end
$var wire 1 9 icache_data_req $end
$var wire 1 # icache_data_rvalid $end
$var wire 32 J icache_data_wdata [31:0] $end
$var wire 1 ; icache_data_we $end
$var wire 1 < rst_n $end
$var wire 1 ) L_sdrc_wr_n $end
$var wire 1 * L_sdrc_rd_n $end
$var wire 4 K L_sdrc_dqm [3:0] $end
$var wire 32 L L_sdrc_data [31:0] $end
$var wire 32 M L_sdrc_addr [31:0] $end
$var parameter 1 N BUSY $end
$var parameter 1 O IDLE $end
$var reg 1 P current_icache $end
$var reg 1 Q next_state $end
$var reg 32 R selected_addr [31:0] $end
$var reg 4 S selected_be [3:0] $end
$var reg 32 T selected_wdata [31:0] $end
$var reg 1 U selected_we $end
$var reg 1 V state $end
$upscope $end
$scope task init_signals $end
$upscope $end
$scope task reset $end
$upscope $end
$scope task test_both_caches $end
$var reg 32 W dcache_addr [31:0] $end
$var reg 1 X got_grant $end
$var reg 1 Y got_valid $end
$var reg 32 Z icache_addr [31:0] $end
$upscope $end
$scope task test_dcache_read $end
$var reg 32 [ addr [31:0] $end
$var reg 1 \ got_grant $end
$var reg 1 ] got_valid $end
$upscope $end
$scope task test_icache_read $end
$var reg 32 ^ addr [31:0] $end
$var reg 1 _ got_grant $end
$var reg 1 ` got_valid $end
$upscope $end
$scope task test_icache_write $end
$var reg 32 a addr [31:0] $end
$var reg 32 b data [31:0] $end
$var reg 1 c got_grant $end
$upscope $end
$scope task wait_for_grant $end
$var reg 1 d got_grant $end
$var reg 1 e is_icache $end
$upscope $end
$scope task wait_for_read_valid $end
$var reg 1 f got_valid $end
$var reg 1 g is_icache $end
$upscope $end
$upscope $end
$enddefinitions $end
$comment Show the parameter values. $end
$dumpall
0O
1N
$end
#0
$dumpvars
xg
xf
xe
xd
xc
bx b
bx a
x`
x_
bx ^
x]
x\
bx [
bx Z
xY
xX
bx W
0V
0U
b0 T
b0 S
b0 R
0Q
0P
b0 M
b0 L
b1111 K
b0 J
b0 I
b0 H
b0 G
b0 F
b0 E
b0 D
b0 C
b0 B
b100 A
b0 @
b0 ?
b0 >
0=
0<
0;
b0 :
09
b0 8
b0 7
06
b0 5
04
b0 3
b0 2
01
00
b0 /
1.
b0 -
b0 ,
b1111 +
1*
1)
0(
b0 '
0&
0%
b0 $
0#
0"
b100 !
$end
#5000
11
#10000
01
#15000
11
#20000
01
1<
#25000
11
#30000
01
b1000000000000 ^
b1 ?
#35000
b0 +
b0 K
b1000000000000 -
b1000000000000 M
0*
1%
1Q
1e
b1111 8
b1111 H
b1000000000000 7
b1000000000000 G
19
11
#40000
01
#45000
0%
1#
0Q
b1111 S
b1000000000000 R
1"
1P
1V
10
b11011110101011011011111011101111 $
b11011110101011011011111011101111 I
b11011110101011011011111011101111 '
b11011110101011011011111011101111 E
b11011110101011011011111011101111 /
b11011110101011011011111011101111 B
0.
1g
1_
1d
b0 @
0=
11
#50000
01
#55000
1%
0#
1Q
0V
1.
00
1`
1f
b1 @
1=
11
#60000
01
#65000
1#
1V
10
0.
0*
b0 +
b0 K
b1000000000000 -
b1000000000000 M
0%
0Q
09
11
#70000
01
#75000
b1111 +
b1111 K
b0 -
b0 M
1*
0#
0V
1.
00
11
#80000
01
#85000
b10000000000000 [
b10 ?
11
#90000
01
#95000
b0 +
b0 K
b10000000000000 -
b10000000000000 M
0*
1(
1Q
0=
b0 @
0e
b1111 3
b1111 D
b10000000000000 2
b10000000000000 C
14
11
#100000
01
#105000
0(
1&
0Q
b10000000000000 R
0"
0P
1V
10
0.
0g
1\
b0 @
0=
11
#110000
01
#115000
1(
0&
1Q
0V
1.
00
1]
b1 @
1=
11
#120000
01
#125000
1&
1V
10
0.
b0 +
b0 K
b10000000000000 -
b10000000000000 M
0*
0(
0Q
04
11
#130000
01
#135000
b1111 +
b1111 K
b0 -
b0 M
1*
0&
0V
1.
00
11
#140000
01
#145000
b10000000000000 W
b11000000000000 Z
b11 ?
11
#150000
01
#155000
b0 +
b0 K
b11000000000000 -
b11000000000000 M
0*
1%
1Q
0=
b0 @
1e
14
b11000000000000 7
b11000000000000 G
19
11
#160000
01
#165000
0%
1#
0Q
b11000000000000 R
1"
1P
1V
10
0.
1X
b1 @
1=
11
#170000
01
#175000
1%
0#
1Q
0V
1.
00
0=
b0 @
1g
11
#180000
01
#185000
0%
1#
0Q
1V
10
0.
b1 @
11
#190000
01
#195000
1%
0#
1Q
0V
1.
00
1Y
b10 @
1=
11
#200000
01
#205000
1#
1V
10
0.
b0 +
b0 K
0*
b11000000000000 -
b11000000000000 M
0%
0Q
04
09
11
#210000
01
#215000
1(
b10000000000000 -
b10000000000000 M
0#
0V
1.
00
1Q
14
11
#220000
01
#225000
0(
1&
0Q
b10000000000000 R
0"
0P
1V
10
0.
0=
b0 @
0e
11
#230000
01
#235000
1(
0&
1Q
0V
1.
00
b1 @
11
#240000
01
#245000
0(
1&
0Q
1V
10
0.
b10 @
1=
11
#250000
01
#255000
1(
0&
1Q
0V
1.
00
0=
b0 @
0g
11
#260000
01
#265000
0(
1&
0Q
1V
10
0.
b1 @
11
#270000
01
#275000
1(
0&
1Q
0V
1.
00
b10 @
1=
11
#280000
01
#285000
1&
1V
10
0.
b0 +
b0 K
b10000000000000 -
b10000000000000 M
0*
0(
0Q
04
11
#290000
01
#295000
b1111 +
b1111 K
b0 -
b0 M
1*
0&
0V
1.
00
11
#300000
01
#305000
b11001010111111101011101010111110 b
b100000000000000 a
b100 ?
11
#310000
01
#315000
b11001010111111101011101010111110 ,
b11001010111111101011101010111110 L
b0 +
b0 K
b100000000000000 -
b100000000000000 M
0)
1%
1Q
0=
b0 @
1e
b11001010111111101011101010111110 :
b11001010111111101011101010111110 J
1;
b100000000000000 7
b100000000000000 G
19
11
#320000
01
#325000
0%
0Q
b11001010111111101011101010111110 T
1U
b100000000000000 R
1"
1P
1V
0.
1c
b1 @
1=
11
#330000
01
#335000
1%
1Q
0V
1.
11
#340000
01
#345000
0%
0Q
1V
0.
11
#350000
01
#355000
1%
1Q
0V
1.
11
#360000
01
#365000
1V
0.
b0 +
b0 K
0)
1*
b100000000000000 -
b100000000000000 M
b11001010111111101011101010111110 ,
b11001010111111101011101010111110 L
0%
0Q
09
11
#370000
01
#375000
b0 ,
b0 L
b1111 +
b1111 K
b0 -
b0 M
1)
0V
1.
11
