rtl/chip/core/exu_swc/exu_store_swc/exu_store_swc.v
module exu_store_swc (
    hclk                                        , //clock signal
    hrstn                                       , // Active low reset signal
    cycle_cnt                                   , // Cycle counter, used for timing control
    dec_store_en                                , // Store enable signal from the decoder
    dec_sb                                      , // Store byte enable signal
    dec_sh                                      , // Store halfword enable signal
    dec_sw                                      , // Store word enable signal
    dec_imm_type_s                              , // Immediate value for store instruction
    dec_rs1                                     , // Source register 1 from the decoder
    dec_rs2                                     , // Source register 2 from the decoder
    exu_store_addr                              , // Store address to memory access unit (MAU)
    exu_store_data                              , // Data to be stored
    exu_store_en                                , // Enable signal to the memory access unit
    exu_store_size                              , // Size of data to store (byte, halfword, word)
    reg_raddr_1                                 ,
    reg_ren_1                                   ,
    reg_rdata_1                                 ,
    reg_raddr_2                                 ,
    reg_ren_2                                   ,
    reg_rdata_2                                 ,
    exu_stall                                   
);
// general signals
input                                       hclk                ;
input                                       hrstn               ;
input                   [3:0]               cycle_cnt           ;
// signals from decoder
input                                       dec_store_en        ;
input                                       dec_sb              ;
input                                       dec_sh              ;
input                                       dec_sw              ;
input                   [11:0]              dec_imm_type_s      ;
input                   [4:0]               dec_rs1             ;
input                   [4:0]               dec_rs2             ;
// siganls to MAU
output reg              [31:0]              exu_store_addr      ;
output reg              [31:0]              exu_store_data      ;
output reg                                  exu_store_en        ;
output reg              [1:0]               exu_store_size      ;
// register file signals
inout                   [4:0]               reg_raddr_1         ; //Register read address 1
inout                                       reg_ren_1           ; // Register read enable 1
input                   [31:0]              reg_rdata_1         ; // Register read data 1
inout                   [4:0]               reg_raddr_2         ; // Register read address 2
inout                                       reg_ren_2           ; // Register read enable 2
input                   [31:0]              reg_rdata_2         ; // Register read data 2
// exu_stall
input                                       exu_stall           ;
// Middle signals used internally to manage register file reads
reg                     [4:0]               mid_reg_raddr_1     ; 
reg                                         mid_reg_ren_1       ;
reg                     [4:0]               mid_reg_raddr_2     ;
reg                                         mid_reg_ren_2       ;
//assign reg_raddr_1   = mid_reg_ren_1 ? mid_reg_raddr_1 : 'z     ;
//assign reg_ren_1     = mid_reg_ren_1 ? mid_reg_ren_1   : 'z     ;
//assign reg_raddr_2   = mid_reg_ren_2 ? mid_reg_raddr_2 : 'z     ;
//assign reg_ren_2     = mid_reg_ren_2 ? mid_reg_ren_2   : 'z     ;
assign reg_raddr_1   = mid_reg_ren_1 ? mid_reg_raddr_1 : 5'b0; // Using 0 instead of 'z
assign reg_ren_1     = mid_reg_ren_1 ? mid_reg_ren_1   : 1'b0;
assign reg_raddr_2   = mid_reg_ren_2 ? mid_reg_raddr_2 : 5'b0; 
assign reg_ren_2     = mid_reg_ren_2 ? mid_reg_ren_2   : 1'b0; 
// load the base address
always@(posedge hclk or negedge hrstn) begin
    if(!hrstn) begin //If hrstn is not true
        mid_reg_raddr_1 <= 0;
        mid_reg_ren_1   <= 0;

        mid_reg_raddr_2 <= 0;
        mid_reg_ren_2   <= 0;
    end 
    else if(dec_store_en && !exu_stall)begin
        if(cycle_cnt == 1) begin
            mid_reg_raddr_1 <= dec_rs1; //  dec_rs1 is Source register 1 from the decoder
            mid_reg_ren_1   <= 1;
            mid_reg_raddr_2 <= dec_rs2;
            mid_reg_ren_2   <= 1;
        end else begin
            mid_reg_raddr_1 <= 0;
            mid_reg_ren_1   <= 0;
            mid_reg_raddr_2 <= 0;
            mid_reg_ren_2   <= 0;
        end
    end 
    else begin
        mid_reg_raddr_1 <= 0;
        mid_reg_ren_1   <= 0;

        mid_reg_raddr_2 <= 0;
        mid_reg_ren_2   <= 0;
    end
end
// generate the signals to the mau
reg      [31:0]      exu_store_addr_buff        ;
reg      [31:0]      exu_store_data_buff        ;
reg                  exu_store_en_buff          ;
reg      [1:0]       exu_store_size_buff        ;

localparam STORE_BTYE = 0, STORE_HALFWORD = 1, STORE_WORD = 2, STORE_IDLE = 3;

always@(posedge hclk or negedge hrstn) begin
    if(!hrstn) begin
        exu_store_addr_buff <= 0;
        exu_store_data_buff <= 0;
        exu_store_en_buff   <= 0;
        exu_store_size_buff <= STORE_IDLE;
    end else if(dec_store_en && !exu_stall)begin
        if(cycle_cnt == 3)begin
            exu_store_addr_buff <= reg_rdata_1 + {{20{dec_imm_type_s[11]}}, dec_imm_type_s};
            exu_store_data_buff <= dec_sb ? {{24{1'b0}}, reg_rdata_2[ 7:0]} :
                                   dec_sh ? {{16{1'b0}}, reg_rdata_2[15:0]} : // stores the least significant 16 bits
                                   dec_sw ? reg_rdata_2                     : 
                                   0;
            exu_store_en_buff   <= 1;
            exu_store_size_buff <= dec_sb ? STORE_BTYE      :
                                   dec_sh ? STORE_HALFWORD  :
                                   dec_sw ? STORE_WORD      :
                                   STORE_IDLE;
        end
    end
end

// Assign store size, address, data, and enable on cycle 4
always@(posedge hclk or negedge hrstn) begin
    if(!hrstn) begin
        exu_store_addr      <= 0;
        exu_store_data      <= 0;
        exu_store_en        <= 0;
        exu_store_size      <= STORE_IDLE;
    end 
    else if(cycle_cnt == 4) begin
        exu_store_addr      <= exu_store_addr_buff;
        exu_store_data      <= exu_store_data_buff;
        exu_store_en        <= exu_store_en_buff;
        exu_store_size      <= exu_store_size_buff; // Correct transfer of store size
    end
end

endmodule

rtl/chip/core/exu_swc/exu_store_swc/exu_store_wrapper.v
module exu_store_swc_wrapper (
    input hclk,
    input hrstn,
    input [3:0] cycle_cnt,
    input dec_store_en,
    input dec_sb,
    input dec_sh,
    input dec_sw,
    input [11:0] dec_imm_type_s,
    input [4:0] dec_rs1,
    input [4:0] dec_rs2,
    input [31:0] reg_rdata_1,
    input [31:0] reg_rdata_2,
    input exu_stall,
    inout [4:0] reg_raddr_1,
    inout reg_ren_1,
    inout [4:0] reg_raddr_2,
    inout reg_ren_2,
    output reg [31:0] exu_store_addr,
    output reg [31:0] exu_store_data,
    output reg exu_store_en,
    output reg [1:0] exu_store_size
);

    exu_store_swc dut (
        .hclk(hclk),
        .hrstn(hrstn),
        .cycle_cnt(cycle_cnt),
        .dec_store_en(dec_store_en),
        .dec_sb(dec_sb),
        .dec_sh(dec_sh),
        .dec_sw(dec_sw),
        .dec_imm_type_s(dec_imm_type_s),
        .dec_rs1(dec_rs1),
        .dec_rs2(dec_rs2),
        .reg_rdata_1(reg_rdata_1),
        .reg_rdata_2(reg_rdata_2),
        .exu_stall(exu_stall),
        .reg_raddr_1(reg_raddr_1),
        .reg_ren_1(reg_ren_1),
        .reg_raddr_2(reg_raddr_2),
        .reg_ren_2(reg_ren_2),
        .exu_store_addr(exu_store_addr),
        .exu_store_data(exu_store_data),
        .exu_store_en(exu_store_en),
        .exu_store_size(exu_store_size)
    );
    initial begin
        $dumpfile("exu_store_cocotb.vcd");
        $dumpvars(0, exu_store_swc_wrapper);
    end
endmodule

rtl/chip/core/exu_swc/exu_store_swc/exu_store_cocotb.vcd
$date
	Tue Nov 19 22:46:05 2024
$end
$version
	Icarus Verilog
$end
$timescale
	1ps
$end
$scope module exu_store_swc_wrapper $end
$var wire 4 ! cycle_cnt [3:0] $end
$var wire 12 " dec_imm_type_s [11:0] $end
$var wire 5 # dec_rs1 [4:0] $end
$var wire 5 $ dec_rs2 [4:0] $end
$var wire 1 % dec_sb $end
$var wire 1 & dec_sh $end
$var wire 1 ' dec_store_en $end
$var wire 1 ( dec_sw $end
$var wire 1 ) exu_stall $end
$var wire 1 * hclk $end
$var wire 1 + hrstn $end
$var wire 32 , reg_rdata_1 [31:0] $end
$var wire 32 - reg_rdata_2 [31:0] $end
$var wire 1 . reg_ren_2 $end
$var wire 1 / reg_ren_1 $end
$var wire 5 0 reg_raddr_2 [4:0] $end
$var wire 5 1 reg_raddr_1 [4:0] $end
$var wire 2 2 exu_store_size [1:0] $end
$var wire 1 3 exu_store_en $end
$var wire 32 4 exu_store_data [31:0] $end
$var wire 32 5 exu_store_addr [31:0] $end
$scope module dut $end
$var wire 4 6 cycle_cnt [3:0] $end
$var wire 12 7 dec_imm_type_s [11:0] $end
$var wire 5 8 dec_rs1 [4:0] $end
$var wire 5 9 dec_rs2 [4:0] $end
$var wire 1 % dec_sb $end
$var wire 1 & dec_sh $end
$var wire 1 ' dec_store_en $end
$var wire 1 ( dec_sw $end
$var wire 1 ) exu_stall $end
$var wire 1 * hclk $end
$var wire 1 + hrstn $end
$var wire 32 : reg_rdata_1 [31:0] $end
$var wire 32 ; reg_rdata_2 [31:0] $end
$var wire 1 . reg_ren_2 $end
$var wire 1 / reg_ren_1 $end
$var wire 5 < reg_raddr_2 [4:0] $end
$var wire 5 = reg_raddr_1 [4:0] $end
$var parameter 32 > STORE_BTYE $end
$var parameter 32 ? STORE_HALFWORD $end
$var parameter 32 @ STORE_IDLE $end
$var parameter 32 A STORE_WORD $end
$var reg 32 B exu_store_addr [31:0] $end
$var reg 32 C exu_store_addr_buff [31:0] $end
$var reg 32 D exu_store_data [31:0] $end
$var reg 32 E exu_store_data_buff [31:0] $end
$var reg 1 3 exu_store_en $end
$var reg 1 F exu_store_en_buff $end
$var reg 2 G exu_store_size [1:0] $end
$var reg 2 H exu_store_size_buff [1:0] $end
$var reg 5 I mid_reg_raddr_1 [4:0] $end
$var reg 5 J mid_reg_raddr_2 [4:0] $end
$var reg 1 K mid_reg_ren_1 $end
$var reg 1 L mid_reg_ren_2 $end
$upscope $end
$upscope $end
$enddefinitions $end
$comment Show the parameter values. $end
$dumpall
b10 A
b11 @
b1 ?
b0 >
$end
#0
$dumpvars
0L
0K
b0 J
b0 I
b11 H
b11 G
0F
b0 E
b0 D
b0 C
b0 B
b0 =
b0 <
b11 ;
b10 :
bz 9
bz 8
b101 7
b1 6
b0 5
b0 4
03
b11 2
b0 1
b0 0
0/
0.
b11 -
b10 ,
0+
0*
z)
0(
1'
1&
0%
bz $
bz #
b101 "
b1 !
$end
#1000
b10 !
b10 6
1*
#2000
0*
#3000
b11 !
b11 6
1*
#4000
0*
1+
#5000
b100 !
b100 6
1*
#6000
0*
#7000
b1 !
b1 6
1*
#8000
0*
#9000
b10 !
b10 6
1*
#10000
0*
#11000
b11 !
b11 6
1*
#12000
0*
#13000
1*
#13001
b1 !
b1 6
0*
0+
1(
0&
b100101100100 "
b100101100100 7
b1100111111110111010110011010000 -
b1100111111110111010110011010000 ;
b100100001000100000110111000011 ,
b100100001000100000110111000011 :
#14001
b10 !
b10 6
1*
#15001
0*
#16001
b11 !
b11 6
1*
#17001
0*
1+
#18001
b100 !
b100 6
1*
#19001
0*
#20001
b1 !
b1 6
1*
#21001
0*
#22001
b10 !
b10 6
1*
#23001
0*
#24001
b11 !
b11 6
1*
#25001
0*
#26001
b1 !
b1 6
0+
0(
1&
b10110110110 "
b10110110110 7
b11010101010111111100110001100100 -
b11010101010111111100110001100100 ;
b10100001110010011111010001011 ,
b10100001110010011111010001011 :
0*
#27001
b10 !
b10 6
1*
#28001
0*
#29001
b11 !
b11 6
1*
#30001
0*
1+
#31001
b100 !
b100 6
1*
#32001
0*
#33001
b1 !
b1 6
1*
#34001
0*
#35001
b10 !
b10 6
1*
#36001
0*
#37001
b11 !
b11 6
1*
#38001
0*
#39001
b1 !
b1 6
0+
b10011000100 "
b10011000100 7
b1111100101100111101001010110 -
b1111100101100111101001010110 ;
b10101100001111101111001110000010 ,
b10101100001111101111001110000010 :
0*
#40001
b10 !
b10 6
1*
#41001
0*
#42001
b11 !
b11 6
1*
#43001
0*
1+
#44001
b100 !
b100 6
1*
#45001
0*
#46001
b1 !
b1 6
1*
#47001
0*
#48001
b10 !
b10 6
1*
#49001
0*
#50001
b11 !
b11 6
1*
#51001
0*
#52001
b1 !
b1 6
0+
0&
1%
b100110100100 "
b100110100100 7
b11000101101001010000000010110 -
b11000101101001010000000010110 ;
b10110011100110100110100101011111 ,
b10110011100110100110100101011111 :
0*
#53001
b10 !
b10 6
1*
#54001
0*
#55001
b11 !
b11 6
1*
#56001
0*
1+
#57001
b100 !
b100 6
1*
#58001
0*
#59001
b1 !
b1 6
1*
#60001
0*
#61001
b10 !
b10 6
1*
#62001
0*
#63001
b11 !
b11 6
1*
#64001
0*
#65001
b1 !
b1 6
0+
1(
0%
b11010110001 "
b11010110001 7
b100101100110010100111110100 -
b100101100110010100111110100 ;
b100100100101101001000010101010 ,
b100100100101101001000010101010 :
0*
#66001
b10 !
b10 6
1*
#67001
0*
#68001
b11 !
b11 6
1*
#69001
0*
1+
#70001
b100 !
b100 6
1*
#71001
0*
#72001
b1 !
b1 6
1*
#73001
0*
#74001
b10 !
b10 6
1*
#75001
0*
#76001
b11 !
b11 6
1*
#77001
0*
#78001
b1 !
b1 6
0+
0(
1&
b10011100010 "
b10011100010 7
b110001110001110010001011100111 -
b110001110001110010001011100111 ;
b10000011111011011110001100110100 ,
b10000011111011011110001100110100 :
0*
#79001
b10 !
b10 6
1*
#80001
0*
#81001
b11 !
b11 6
1*
#82001
0*
1+
#83001
b100 !
b100 6
1*
#84001
0*
#85001
b1 !
b1 6
1*
#86001
0*
#87001
b10 !
b10 6
1*
#88001
0*
#89001
b11 !
b11 6
1*
#90001
0*
#91001
b1 !
b1 6
0+
b110000000111 "
b110000000111 7
b10010110101000011100001100001110 -
b10010110101000011100001100001110 ;
b11101101011000010010111100110001 ,
b11101101011000010010111100110001 :
0*
#92001
b10 !
b10 6
1*
#93001
0*
#94001
b11 !
b11 6
1*
#95001
0*
1+
#96001
b100 !
b100 6
1*
#97001
0*
#98001
b1 !
b1 6
1*
#99001
0*
#100001
b10 !
b10 6
1*
#101001
0*
#102001
b11 !
b11 6
1*
#103001
0*
#104001
b1 !
b1 6
0+
b100110011000 "
b100110011000 7
b11010111110001010000101100000000 -
b11010111110001010000101100000000 ;
b1010111101000111010110001011100 ,
b1010111101000111010110001011100 :
0*
#105001
b10 !
b10 6
1*
#106001
0*
#107001
b11 !
b11 6
1*
#108001
0*
1+
#109001
b100 !
b100 6
1*
#110001
0*
#111001
b1 !
b1 6
1*
#112001
0*
#113001
b10 !
b10 6
1*
#114001
0*
#115001
b11 !
b11 6
1*
#116001
0*
#117001
b1 !
b1 6
0+
0&
1%
b111000010011 "
b111000010011 7
b1011111100100011010101110001110 -
b1011111100100011010101110001110 ;
b100100101110011001110011010100 ,
b100100101110011001110011010100 :
0*
#118001
b10 !
b10 6
1*
#119001
0*
#120001
b11 !
b11 6
1*
#121001
0*
1+
#122001
b100 !
b100 6
1*
#123001
0*
#124001
b1 !
b1 6
1*
#125001
0*
#126001
b10 !
b10 6
1*
#127001
0*
#128001
b11 !
b11 6
1*
#129001
0*
#130001
b1 !
b1 6
0+
1&
0%
b11000000110 "
b11000000110 7
b11010110111101001000010111111 -
b11010110111101001000010111111 ;
b101001000110111011101111000101 ,
b101001000110111011101111000101 :
0*
#131001
b10 !
b10 6
1*
#132001
0*
#133001
b11 !
b11 6
1*
#134001
0*
1+
#135001
b100 !
b100 6
1*
#136001
0*
#137001
b1 !
b1 6
1*
#138001
0*
#139001
b10 !
b10 6
1*
#140001
0*
#141001
b11 !
b11 6
1*
#142001
0*
#143001
b1 !
b1 6
0+
1(
0&
b100111000011 "
b100111000011 7
b1100010110100111001000101001000 -
b1100010110100111001000101001000 ;
b1100000011011100101100010011 ,
b1100000011011100101100010011 :
0*
#144001
b10 !
b10 6
1*
#145001
0*
#146001
b11 !
b11 6
1*
#147001
0*
1+
#148001
b100 !
b100 6
1*
#149001
0*
#150001
b1 !
b1 6
1*
#151001
0*
#152001
b10 !
b10 6
1*
#153001
0*
#154001
b11 !
b11 6
1*
#155001
0*
#156001
b1 !
b1 6
0+
b10111001010 "
b10111001010 7
b11111100111010100001010100010010 -
b11111100111010100001010100010010 ;
b11110100011100111011101011011010 ,
b11110100011100111011101011011010 :
0*
#157001
b10 !
b10 6
1*
#158001
0*
#159001
b11 !
b11 6
1*
#160001
0*
1+
#161001
b100 !
b100 6
1*
#162001
0*
#163001
b1 !
b1 6
1*
#164001
0*
#165001
b10 !
b10 6
1*
#166001
0*
#167001
b11 !
b11 6
1*
#168001
0*
#169001
b1 !
b1 6
0+
b100000110110 "
b100000110110 7
b10010101101100011000110100111010 -
b10010101101100011000110100111010 ;
b10100100010001000101011100111011 ,
b10100100010001000101011100111011 :
0*
#170001
b10 !
b10 6
1*
#171001
0*
#172001
b11 !
b11 6
1*
#173001
0*
1+
#174001
b100 !
b100 6
1*
#175001
0*
#176001
b1 !
b1 6
1*
#177001
0*
#178001
b10 !
b10 6
1*
#179001
0*
#180001
b11 !
b11 6
1*
#181001
0*
#182001
b1 !
b1 6
0+
0(
1%
b100100110 "
b100100110 7
b11001111011011010110010110110111 -
b11001111011011010110010110110111 ;
b10111011110001111111111001111011 ,
b10111011110001111111111001111011 :
0*
#183001
b10 !
b10 6
1*
#184001
0*
#185001
b11 !
b11 6
1*
#186001
0*
1+
#187001
b100 !
b100 6
1*
#188001
0*
#189001
b1 !
b1 6
1*
#190001
0*
#191001
b10 !
b10 6
1*
#192001
0*
#193001
b11 !
b11 6
1*
#194001
0*
#195001
b1 !
b1 6
0+
1&
0%
b101001110011 "
b101001110011 7
b11001111010100000000100011111101 -
b11001111010100000000100011111101 ;
b11011001111000101101001011011001 ,
b11011001111000101101001011011001 :
0*
#196001
b10 !
b10 6
1*
#197001
0*
#198001
b11 !
b11 6
1*
#199001
0*
1+
#200001
b100 !
b100 6
1*
#201001
0*
#202001
b1 !
b1 6
1*
#203001
0*
#204001
b10 !
b10 6
1*
#205001
0*
#206001
b11 !
b11 6
1*
#207001
0*
#208001
b1 !
b1 6
0+
1(
0&
b111010010101 "
b111010010101 7
b1010001100010110111110000000111 -
b1010001100010110111110000000111 ;
b10100001111110000001101111100111 ,
b10100001111110000001101111100111 :
0*
#209001
b10 !
b10 6
1*
#210001
0*
#211001
b11 !
b11 6
1*
#212001
0*
1+
#213001
b100 !
b100 6
1*
#214001
0*
#215001
b1 !
b1 6
1*
#216001
0*
#217001
b10 !
b10 6
1*
#218001
0*
#219001
b11 !
b11 6
1*
#220001
0*
#221001
b1 !
b1 6
0+
0(
1%
b1100010111 "
b1100010111 7
b11011001111101100111000011101101 -
b11011001111101100111000011101101 ;
b11011110101101101000110010110101 ,
b11011110101101101000110010110101 :
0*
#222001
b10 !
b10 6
1*
#223001
0*
#224001
b11 !
b11 6
1*
#225001
0*
1+
#226001
b100 !
b100 6
1*
#227001
0*
#228001
b1 !
b1 6
1*
#229001
0*
#230001
b10 !
b10 6
1*
#231001
0*
#232001
b11 !
b11 6
1*
#233001
0*
#234001
b1 !
b1 6
0+
1(
0%
b111010100100 "
b111010100100 7
b10001001100000000011100000111101 -
b10001001100000000011100000111101 ;
b10101011010111001111101000010110 ,
b10101011010111001111101000010110 :
0*
#235001
b10 !
b10 6
1*
#236001
0*
#237001
b11 !
b11 6
1*
#238001
0*
1+
#239001
b100 !
b100 6
1*
#240001
0*
#241001
b1 !
b1 6
1*
#242001
0*
#243001
b10 !
b10 6
1*
#244001
0*
#245001
b11 !
b11 6
1*
#246001
0*
#247001
b1 !
b1 6
0+
b10100100100 "
b10100100100 7
b11011000010111001111010101101 -
b11011000010111001111010101101 ;
b1110100010101110101101000101 ,
b1110100010101110101101000101 :
0*
#248001
b10 !
b10 6
1*
#249001
0*
#250001
b11 !
b11 6
1*
#251001
0*
1+
#252001
b100 !
b100 6
1*
#253001
0*
#254001
b1 !
b1 6
1*
#255001
0*
#256001
b10 !
b10 6
1*
#257001
0*
#258001
b11 !
b11 6
1*
#259001
0*
#260001
b1 !
b1 6
0+
0(
1&
b110001001 "
b110001001 7
b11010011001010000001101101111010 -
b11010011001010000001101101111010 ;
b11000100001001111110100010011010 ,
b11000100001001111110100010011010 :
0*
#261001
b10 !
b10 6
1*
#262001
0*
#263001
b11 !
b11 6
1*
#264001
0*
1+
#265001
b100 !
b100 6
1*
#266001
0*
#267001
b1 !
b1 6
1*
#268001
0*
#269001
b10 !
b10 6
1*
#270001
0*
#271001
b11 !
b11 6
1*
#272001
0*
#273001
b1 !
b1 6
0+
0&
1%
b100000111010 "
b100000111010 7
b1100000001011001000000110000 -
b1100000001011001000000110000 ;
b10000110001100101000001111001100 ,
b10000110001100101000001111001100 :
0*
#274001
b10 !
b10 6
1*
#275001
0*
#276001
b11 !
b11 6
1*
#277001
0*
1+
#278001
b100 !
b100 6
1*
#279001
0*
#280001
b1 !
b1 6
1*
#281001
0*
#282001
b10 !
b10 6
1*
#283001
0*
#284001
b11 !
b11 6
1*
#285001
0*
#286001
b1 !
b1 6
0+
1&
0%
b111010000001 "
b111010000001 7
b10011011010011011110001000011011 -
b10011011010011011110001000011011 ;
b11100110110011100000100101110001 ,
b11100110110011100000100101110001 :
0*
#287001
b10 !
b10 6
1*
#288001
0*
#289001
b11 !
b11 6
1*
#290001
0*
1+
#291001
b100 !
b100 6
1*
#292001
0*
#293001
b1 !
b1 6
1*
#294001
0*
#295001
b10 !
b10 6
1*
#296001
0*
#297001
b11 !
b11 6
1*
#298001
0*
#299001
b1 !
b1 6
0+
b111110000001 "
b111110000001 7
b10001110000101101001111100110101 -
b10001110000101101001111100110101 ;
b10100011101111110101101100011111 ,
b10100011101111110101101100011111 :
0*
#300001
b10 !
b10 6
1*
#301001
0*
#302001
b11 !
b11 6
1*
#303001
0*
1+
#304001
b100 !
b100 6
1*
#305001
0*
#306001
b1 !
b1 6
1*
#307001
0*
#308001
b10 !
b10 6
1*
#309001
0*
#310001
b11 !
b11 6
1*
#311001
0*
#312001
b1 !
b1 6
0+
b10110101110 "
b10110101110 7
b11111110100101001111111101100110 -
b11111110100101001111111101100110 ;
b1001000100001101010010011100110 ,
b1001000100001101010010011100110 :
0*
#313001
b10 !
b10 6
1*
#314001
0*
#315001
b11 !
b11 6
1*
#316001
0*
1+
#317001
b100 !
b100 6
1*
#318001
0*
#319001
b1 !
b1 6
1*
#320001
0*
#321001
b10 !
b10 6
1*
#322001
0*
#323001
b11 !
b11 6
1*
#324001
0*
#325001
b1 !
b1 6
0+
1(
0&
b101100110100 "
b101100110100 7
b11111010100100000001101001111 -
b11111010100100000001101001111 ;
b10101010001011110010001011011111 ,
b10101010001011110010001011011111 :
0*
#326001
b10 !
b10 6
1*
#327001
0*
#328001
b11 !
b11 6
1*
#329001
0*
1+
#330001
b100 !
b100 6
1*
#331001
0*
#332001
b1 !
b1 6
1*
#333001
0*
#334001
b10 !
b10 6
1*
#335001
0*
#336001
b11 !
b11 6
1*
#337001
0*
#338001
b1 !
b1 6
0+
0(
1%
b110001110 "
b110001110 7
b11000011010101111100110001100010 -
b11000011010101111100110001100010 ;
b110010101110110000010111001101 ,
b110010101110110000010111001101 :
0*
#339001
b10 !
b10 6
1*
#340001
0*
#341001
b11 !
b11 6
1*
#342001
0*
1+
#343001
b100 !
b100 6
1*
#344001
0*
#345001
b1 !
b1 6
1*
#346001
0*
#347001
b10 !
b10 6
1*
#348001
0*
#349001
b11 !
b11 6
1*
#350001
0*
#351001
b1 !
b1 6
0+
1(
0%
b111111100110 "
b111111100110 7
b1000001000010110110011001011011 -
b1000001000010110110011001011011 ;
b101111000110100000001100000000 ,
b101111000110100000001100000000 :
0*
#352001
b10 !
b10 6
1*
#353001
0*
#354001
b11 !
b11 6
1*
#355001
0*
1+
#356001
b100 !
b100 6
1*
#357001
0*
#358001
b1 !
b1 6
1*
#359001
0*
#360001
b10 !
b10 6
1*
#361001
0*
#362001
b11 !
b11 6
1*
#363001
0*
#364001
b1 !
b1 6
0+
b111001 "
b111001 7
b11000011110101011110101011100011 -
b11000011110101011110101011100011 ;
b10011010111111000101111001110100 ,
b10011010111111000101111001110100 :
0*
#365001
b10 !
b10 6
1*
#366001
0*
#367001
b11 !
b11 6
1*
#368001
0*
1+
#369001
b100 !
b100 6
1*
#370001
0*
#371001
b1 !
b1 6
1*
#372001
0*
#373001
b10 !
b10 6
1*
#374001
0*
#375001
b11 !
b11 6
1*
#376001
0*
#377001
b1 !
b1 6
0+
0(
1%
b101011101011 "
b101011101011 7
b11100111101101000110000000000011 -
b11100111101101000110000000000011 ;
b11110100011110000100010111110000 ,
b11110100011110000100010111110000 :
0*
#378001
b10 !
b10 6
1*
#379001
0*
#380001
b11 !
b11 6
1*
#381001
0*
1+
#382001
b100 !
b100 6
1*
#383001
0*
#384001
b1 !
b1 6
1*
#385001
0*
#386001
b10 !
b10 6
1*
#387001
0*
#388001
b11 !
b11 6
1*
#389001
0*
#390001
b1 !
b1 6
0+
1(
0%
b111111100111 "
b111111100111 7
b10010011010011001101111000110111 -
b10010011010011001101111000110111 ;
b101110000011110111100010111011 ,
b101110000011110111100010111011 :
0*
#391001
b10 !
b10 6
1*
#392001
0*
#393001
b11 !
b11 6
1*
#394001
0*
1+
#395001
b100 !
b100 6
1*
#396001
0*
#397001
b1 !
b1 6
1*
#398001
0*
#399001
b10 !
b10 6
1*
#400001
0*
#401001
b11 !
b11 6
1*
#402001
0*
#403001
b1 !
b1 6
0+
b111110100010 "
b111110100010 7
b10110010100001011100000010101110 -
b10110010100001011100000010101110 ;
b10001101011101101010011001100100 ,
b10001101011101101010011001100100 :
0*
#404001
b10 !
b10 6
1*
#405001
0*
#406001
b11 !
b11 6
1*
#407001
0*
1+
#408001
b100 !
b100 6
1*
#409001
0*
#410001
b1 !
b1 6
1*
#411001
0*
#412001
b10 !
b10 6
1*
#413001
0*
#414001
b11 !
b11 6
1*
#415001
0*
#416001
b1 !
b1 6
0+
0(
1%
b110011110100 "
b110011110100 7
b10000101101101111101011100000111 -
b10000101101101111101011100000111 ;
b1101111001111100110010111011010 ,
b1101111001111100110010111011010 :
0*
#417001
b10 !
b10 6
1*
#418001
0*
#419001
b11 !
b11 6
1*
#420001
0*
1+
#421001
b100 !
b100 6
1*
#422001
0*
#423001
b1 !
b1 6
1*
#424001
0*
#425001
b10 !
b10 6
1*
#426001
0*
#427001
b11 !
b11 6
1*
#428001
0*
#429001
b1 !
b1 6
0+
1(
0%
b1100000101 "
b1100000101 7
b11001111011110111111001101001101 -
b11001111011110111111001101001101 ;
b10101000111101000100011101001110 ,
b10101000111101000100011101001110 :
0*
#430001
b10 !
b10 6
1*
#431001
0*
#432001
b11 !
b11 6
1*
#433001
0*
1+
#434001
b100 !
b100 6
1*
#435001
0*
#436001
b1 !
b1 6
1*
#437001
0*
#438001
b10 !
b10 6
1*
#439001
0*
#440001
b11 !
b11 6
1*
#441001
0*
#442001
b1 !
b1 6
0+
0(
1%
b101110111001 "
b101110111001 7
b1001100100101001110000100110101 -
b1001100100101001110000100110101 ;
b1100101011011011011000010011 ,
b1100101011011011011000010011 :
0*
#443001
b10 !
b10 6
1*
#444001
0*
#445001
b11 !
b11 6
1*
#446001
0*
1+
#447001
b100 !
b100 6
1*
#448001
0*
#449001
b1 !
b1 6
1*
#450001
0*
#451001
b10 !
b10 6
1*
#452001
0*
#453001
b11 !
b11 6
1*
#454001
0*
#455001
b1 !
b1 6
0+
1&
0%
b111001101010 "
b111001101010 7
b11001100000110110000001000000011 -
b11001100000110110000001000000011 ;
b11011110100110100000001100010000 ,
b11011110100110100000001100010000 :
0*
#456001
b10 !
b10 6
1*
#457001
0*
#458001
b11 !
b11 6
1*
#459001
0*
1+
#460001
b100 !
b100 6
1*
#461001
0*
#462001
b1 !
b1 6
1*
#463001
0*
#464001
b10 !
b10 6
1*
#465001
0*
#466001
b11 !
b11 6
1*
#467001
0*
#468001
b1 !
b1 6
0+
b111110100100 "
b111110100100 7
b11111000101100011011100111011100 -
b11111000101100011011100111011100 ;
b11000000000010100000001011001101 ,
b11000000000010100000001011001101 :
0*
#469001
b10 !
b10 6
1*
#470001
0*
#471001
b11 !
b11 6
1*
#472001
0*
1+
#473001
b100 !
b100 6
1*
#474001
0*
#475001
b1 !
b1 6
1*
#476001
0*
#477001
b10 !
b10 6
1*
#478001
0*
#479001
b11 !
b11 6
1*
#480001
0*
#481001
b1 !
b1 6
0+
1(
0&
b111010000111 "
b111010000111 7
b11111010101101001100001001011 -
b11111010101101001100001001011 ;
b1011110010111100001101100001110 ,
b1011110010111100001101100001110 :
0*
#482001
b10 !
b10 6
1*
#483001
0*
#484001
b11 !
b11 6
1*
#485001
0*
1+
#486001
b100 !
b100 6
1*
#487001
0*
#488001
b1 !
b1 6
1*
#489001
0*
#490001
b10 !
b10 6
1*
#491001
0*
#492001
b11 !
b11 6
1*
#493001
0*
#494001
b1 !
b1 6
0+
b11001001 "
b11001001 7
b10001001000110111101110010111100 -
b10001001000110111101110010111100 ;
b11000110001100010001111101011000 ,
b11000110001100010001111101011000 :
0*
#495001
b10 !
b10 6
1*
#496001
0*
#497001
b11 !
b11 6
1*
#498001
0*
1+
#499001
b100 !
b100 6
1*
#500001
0*
#501001
b1 !
b1 6
1*
#502001
0*
#503001
b10 !
b10 6
1*
#504001
0*
#505001
b11 !
b11 6
1*
#506001
0*
#507001
b1 !
b1 6
0+
0(
1%
b101011001000 "
b101011001000 7
b111011000101001010100111000000 -
b111011000101001010100111000000 ;
b10111110111001000101111101100110 ,
b10111110111001000101111101100110 :
0*
#508001
b10 !
b10 6
1*
#509001
0*
#510001
b11 !
b11 6
1*
#511001
0*
1+
#512001
b100 !
b100 6
1*
#513001
0*
#514001
b1 !
b1 6
1*
#515001
0*
#516001
b10 !
b10 6
1*
#517001
0*
#518001
b11 !
b11 6
1*
#519001
0*
#520001
b1 !
b1 6
0+
1&
0%
b111010001000 "
b111010001000 7
b10100011010001001001001011011110 -
b10100011010001001001001011011110 ;
b10000011000110100110001110100100 ,
b10000011000110100110001110100100 :
0*
#521001
b10 !
b10 6
1*
#522001
0*
#523001
b11 !
b11 6
1*
#524001
0*
1+
#525001
b100 !
b100 6
1*
#526001
0*
#527001
b1 !
b1 6
1*
#528001
0*
#529001
b10 !
b10 6
1*
#530001
0*
#531001
b11 !
b11 6
1*
