verification/coco_tb/DUT_top/exu_jump_swc.v
module exu_jump_swc  (
    hclk                                        ,
    hrstn                                       ,
    cycle_cnt                                   ,
    dec_jump_en                                 ,
    dec_jal                                     ,
    dec_jalr                                    ,
    dec_imm_type_i                              ,
    dec_imm_type_j                              ,
    dec_rd                                      ,
    dec_rs1                                     ,
    pc                                          ,
    pc_write                                    ,
    pc_wdata                                    ,
    flush                                       ,
    reg_waddr                                   ,
    reg_wen                                     ,
    reg_wdata                                   ,
    reg_raddr_1                                 ,
    reg_ren_1                                   ,
    reg_rdata_1                                 
);
/*
Performs Direct or Indirect jump.

Jump and Link (JAL): 
Add a sign-extended J-immediate to the address of the jump instruction to form the jump target address. Store the address of the instruction following the jump into register rd. 

Jump and Link register (JALR) / indirect jump instruction: 
Add a sign extended 12-bit I-immediate to the register rs1, and set the least-significant bit of the result to 0. Store the address of the instruction following the jump into register rd. 
*/
input                       hclk                ;
input                       hrstn               ;
input           [3:0]       cycle_cnt           ;
// signals from dec 
input                       dec_jump_en         ;
input                       dec_jal             ;
input                       dec_jalr            ;
input           [11:0]      dec_imm_type_i      ;
input           [20:0]      dec_imm_type_j      ;
input           [4:0]       dec_rd              ;
input           [4:0]       dec_rs1             ;
// PC
input           [31:0]      pc                  ;
inout                       pc_write            ;
inout           [31:0]      pc_wdata            ;
// pipeline flushing
inout           [1:0]       flush               ;
// regfile write port   
inout           [4:0]       reg_waddr           ;
inout                       reg_wen             ;
inout           [31:0]      reg_wdata           ;
inout           [4:0]       reg_raddr_1         ;
inout                       reg_ren_1           ;
input           [31:0]      reg_rdata_1         ;
// middle signals
reg             [4:0]       mid_reg_waddr       ;
reg                         mid_reg_wen         ;
reg             [31:0]      mid_reg_wdata       ;
reg             [4:0]       mid_reg_raddr_1     ;
reg                         mid_reg_ren_1       ;
reg                         mid_pc_write        ;
reg             [31:0]      mid_pc_wdata        ;
// SEXT values
wire            [31:0]      sext_imm_type_j     ;
wire            [31:0]      sext_imm_type_i     ;

assign reg_waddr   = mid_reg_wen   ? mid_reg_waddr    : 'z  ;
assign reg_wen     = mid_reg_wen   ? mid_reg_wen      : 'z  ;
assign reg_wdata   = mid_reg_wen   ? mid_reg_wdata    : 'z  ;
assign reg_raddr_1 = mid_reg_ren_1 ? mid_reg_raddr_1  : 'z  ;
assign reg_ren_1   = mid_reg_ren_1 ? mid_reg_ren_1    : 'z  ;

assign sext_imm_type_j = {{11{dec_imm_type_j[19]}}, dec_imm_type_j};
assign sext_imm_type_i = {{20{dec_imm_type_i[11]}}, dec_imm_type_i};

wire [31:0] pc_real = pc - 8;
wire [31:0] pc_next = dec_jal ? (pc_real + sext_imm_type_j) : ((reg_rdata_1 + sext_imm_type_i) & ~1); // assigns the pc to jump to based on if dec_jal was called, to do the direct jump, otherwise do the indirect jump

// Read and write the register values during cycles 1 and 2
always@(posedge hclk or negedge hrstn) begin
    if(!hrstn) begin
        mid_reg_raddr_1 <= 0;
        mid_reg_ren_1   <= 0;

        mid_reg_waddr   <= 0;
        mid_reg_wen     <= 0;
        mid_reg_wdata   <= 0;
    end else if(dec_jump_en) begin
        if(cycle_cnt == 1)begin// on cycle 1, if performing an indirect jump, assign the temp register read address to the decoded register and enable reading
            if(dec_jalr) begin
                mid_reg_raddr_1 <= dec_rs1;
                mid_reg_ren_1   <= 1;
            end else begin
                mid_reg_raddr_1 <= 0;
                mid_reg_ren_1   <= 0;
            end

            mid_reg_waddr   <= 0;
            mid_reg_wen     <= 0;
            mid_reg_wdata   <= 0;
        end else if(cycle_cnt == 2)begin // on cycle 2, assign the temp register write address to the decoded rd value and enable writing, with the write data being the address following the jump instruction.
            mid_reg_raddr_1 <= 0;
            mid_reg_ren_1   <= 0;

            mid_reg_waddr <= dec_rd;
            mid_reg_wen   <= 1;
            mid_reg_wdata <= pc_real + 4;
        end else begin
            mid_reg_raddr_1 <= 0;
            mid_reg_ren_1   <= 0;

            mid_reg_waddr <= 0;
            mid_reg_wen   <= 0;
            mid_reg_wdata <= 0;
        end
    end else begin
        mid_reg_raddr_1 <= 0;
        mid_reg_ren_1   <= 0;

        mid_reg_waddr <= 0;
        mid_reg_wen   <= 0;
        mid_reg_wdata <= 0;
    end
end

// Change the PC value during cycles 3 and 4 based on the pc_next value from earlier.
always@(posedge hclk or negedge hrstn) begin
    if(!hrstn) begin
        mid_pc_write <= 0;
        mid_pc_wdata <= 0;
    end else if(dec_jump_en) begin
        if(cycle_cnt == 3) begin // on cycle 3, if we are jumping to a value other than 4 or 8 ahead, we assign the temp pc write value to 1 and the temp pc write data value to the pc_next value previously assigned.
            if(pc_next != pc_real + 4 && pc_next != pc_real + 8) begin
                mid_pc_write <= 1;
                mid_pc_wdata <= pc_next;
            end else begin
                mid_pc_write <= 0;
                mid_pc_wdata <= 0;
            end
        end else if(cycle_cnt == 4) begin // on cycle 4, hold the temp pc values.
            mid_pc_write <= mid_pc_write;
            mid_pc_wdata <= mid_pc_wdata;
        end else begin
            mid_pc_write <= 0;
            mid_pc_wdata <= 0;
        end
    end else begin
        mid_pc_write <= 0;
        mid_pc_wdata <= 0;
    end
end

assign pc_write = dec_jump_en ? mid_pc_write : 'z;
assign pc_wdata = dec_jump_en ? mid_pc_wdata : 'z;

localparam FLUSH_DISABLE = 0, FLUSH_CYCLE_1 = 1, FLUSH_CYCLE_2 = 2;
reg [1:0] mid_flush;


// Set the flush state during cycles 3 and 4 based on how many values we are jumping by.
always@(posedge hclk or negedge hrstn) begin
    if(!hrstn) begin
        mid_flush <= FLUSH_DISABLE;
    end else if(dec_jump_en) begin
        if(cycle_cnt == 3)begin // on cycle 3, set the temporary flush state
            if(pc_next == pc_real + 4) begin // if we are jumping by 4, do not flush
                mid_flush <= FLUSH_DISABLE;
            end else if(pc_next == pc_real + 8) begin // if we are jumping by 8, go to flush cycle 1
                mid_flush <= FLUSH_CYCLE_1;
            end else begin // otherwise, go to flush cycle 2
                mid_flush <= FLUSH_CYCLE_2;
            end
        end else if(cycle_cnt == 4) begin // on cycle 4, hold the temporary flush state
            mid_flush <= mid_flush;
        end else begin // on cycles 1 and 2, disable flushing.
            mid_flush <= FLUSH_DISABLE;
        end
    end else begin
        mid_flush <= FLUSH_DISABLE;
    end
end

assign flush = dec_jump_en ? mid_flush : 'z;

endmodule

archive/rtl/chip/core/exu_swc/exu_jump_swc/exu_jump_wrapper.v
module exu_jump_swc_wrapper (
    input hclk,
    input hrstn,
    input [3:0] cycle_cnt,
    input dec_jump_en,
    input dec_jal,
    input dec_jalr,
    input [11:0] dec_imm_type_i,
    input [20:0] dec_imm_type_j,
    input [4:0] dec_rd,
    input [4:0] dec_rs1,
    input [31:0] pc,
    input [31:0] reg_rdata_1,
    inout pc_write,
    inout [31:0] pc_wdata,
    inout [1:0] flush,
    inout [4:0] reg_waddr,
    inout reg_wen,
    inout [31:0] reg_wdata,
    inout [4:0] reg_raddr_1,
    inout reg_ren_1
);

    exu_jump_swc dut (
        .hclk(hclk),
        .hrstn(hrstn),
        .cycle_cnt(cycle_cnt),
        .dec_jump_en(dec_jump_en),
        .dec_jal(dec_jal),
        .dec_jalr(dec_jalr),
        .dec_imm_type_i(dec_imm_type_i),
        .dec_imm_type_j(dec_imm_type_j),
        .dec_rd(dec_rd),
        .dec_rs1(dec_rs1),
        .pc(pc),
        .reg_rdata_1(reg_rdata_1),
        .pc_write(pc_write),
        .pc_wdata(pc_wdata),
        .flush(flush),
        .reg_waddr(reg_waddr),
        .reg_wen(reg_wen),
        .reg_wdata(reg_wdata),
        .reg_raddr_1(reg_raddr_1),
        .reg_ren_1(reg_ren_1)
    );
    initial begin
        $dumpfile("exu_jump_cocotb.vcd");
        $dumpvars(0, exu_jump_swc_wrapper);
    end
endmodule

archive/rtl/chip/core/exu_swc/exu_jump_swc/exu_jump_cocotb.vcd
$date
	Tue Nov 12 11:39:07 2024
$end
$version
	Icarus Verilog
$end
$timescale
	1ps
$end
$scope module exu_jump_swc_wrapper $end
$var wire 4 ! cycle_cnt [3:0] $end
$var wire 12 " dec_imm_type_i [11:0] $end
$var wire 21 # dec_imm_type_j [20:0] $end
$var wire 1 $ dec_jal $end
$var wire 1 % dec_jalr $end
$var wire 1 & dec_jump_en $end
$var wire 5 ' dec_rd [4:0] $end
$var wire 5 ( dec_rs1 [4:0] $end
$var wire 1 ) hclk $end
$var wire 1 * hrstn $end
$var wire 32 + pc [31:0] $end
$var wire 32 , reg_rdata_1 [31:0] $end
$var wire 1 - reg_wen $end
$var wire 32 . reg_wdata [31:0] $end
$var wire 5 / reg_waddr [4:0] $end
$var wire 1 0 reg_ren_1 $end
$var wire 5 1 reg_raddr_1 [4:0] $end
$var wire 1 2 pc_write $end
$var wire 32 3 pc_wdata [31:0] $end
$var wire 2 4 flush [1:0] $end
$scope module dut $end
$var wire 4 5 cycle_cnt [3:0] $end
$var wire 12 6 dec_imm_type_i [11:0] $end
$var wire 21 7 dec_imm_type_j [20:0] $end
$var wire 1 $ dec_jal $end
$var wire 1 % dec_jalr $end
$var wire 1 & dec_jump_en $end
$var wire 5 8 dec_rd [4:0] $end
$var wire 5 9 dec_rs1 [4:0] $end
$var wire 1 ) hclk $end
$var wire 1 * hrstn $end
$var wire 32 : pc [31:0] $end
$var wire 32 ; reg_rdata_1 [31:0] $end
$var wire 32 < sext_imm_type_j [31:0] $end
$var wire 32 = sext_imm_type_i [31:0] $end
$var wire 1 - reg_wen $end
$var wire 32 > reg_wdata [31:0] $end
$var wire 5 ? reg_waddr [4:0] $end
$var wire 1 0 reg_ren_1 $end
$var wire 5 @ reg_raddr_1 [4:0] $end
$var wire 1 2 pc_write $end
$var wire 32 A pc_wdata [31:0] $end
$var wire 32 B pc_real [31:0] $end
$var wire 32 C pc_next [31:0] $end
$var wire 2 D flush [1:0] $end
$var parameter 32 E FLUSH_CYCLE_1 $end
$var parameter 32 F FLUSH_CYCLE_2 $end
$var parameter 32 G FLUSH_DISABLE $end
$var reg 2 H mid_flush [1:0] $end
$var reg 32 I mid_pc_wdata [31:0] $end
$var reg 1 J mid_pc_write $end
$var reg 5 K mid_reg_raddr_1 [4:0] $end
$var reg 1 L mid_reg_ren_1 $end
$var reg 5 M mid_reg_waddr [4:0] $end
$var reg 32 N mid_reg_wdata [31:0] $end
$var reg 1 O mid_reg_wen $end
$upscope $end
$upscope $end
$enddefinitions $end
$comment Show the parameter values. $end
$dumpall
b0 G
b10 F
b1 E
$end
#0
$dumpvars
0O
b0 N
b0 M
0L
b0 K
0J
b0 I
b0 H
b0 D
b1000 C
b10 B
b0 A
bz @
bz ?
bz >
b101 =
bz <
b11 ;
b1010 :
bz 9
bz 8
bz 7
b101 6
b1 5
b0 4
b0 3
02
bz 1
z0
bz /
bz .
z-
b11 ,
b1010 +
0*
0)
bz (
bz '
1&
1%
0$
bz #
b101 "
b1 !
$end
#1000
b10 !
b10 5
1)
#2000
0)
#3000
b11 !
b11 5
1)
#4000
0)
#5000
b100 !
b100 5
b10 4
b10 D
b1000 3
b1000 A
12
b10 H
b1000 I
1J
1)
1*
#6000
0)
#7000
b1 !
b1 5
1)
#8000
0)
#9000
b10 !
b10 5
b0 4
b0 D
b0 3
b0 A
02
10
b0 H
b0 I
0J
1L
bz K
1)
#10000
0)
#11000
b11 !
b11 5
1-
b110 .
b110 >
z0
b110 N
1O
bz M
0L
b0 K
1)
#12000
0)
#13000
b100 !
b100 5
b10 4
b10 D
b1000 3
b1000 A
12
z-
bz .
bz >
b10 H
b1000 I
1J
b0 N
0O
b0 M
1)
#14000
0)
#15000
1)
#15001
b0 4
b0 D
b0 3
b0 A
02
b0 H
b0 I
0J
b11111111111111111011111000110011 C
b1 !
b1 5
0)
0*
0%
1$
b11111111111111111011111000111011 <
b111111011111000111011 #
b111111011111000111011 7
b11111111111111111111110110001100 =
b110110001100 "
b110110001100 6
b110011110011 ,
b110011110011 ;
b11111111111111111111111111111000 B
b0 +
b0 :
#16001
b10 !
b10 5
1)
#17001
0)
#18001
b11 !
b11 5
1)
#19001
0)
#20001
b100 !
b100 5
b11111111111111111011111000110011 3
b11111111111111111011111000110011 A
12
b10 4
b10 D
b11111111111111111011111000110011 I
1J
b10 H
1)
1*
#21001
0)
#22001
b1 !
b1 5
1)
#23001
0)
#24001
b10 !
b10 5
b0 3
b0 A
02
b0 4
b0 D
b0 I
0J
b0 H
1)
#25001
0)
#26001
b11 !
b11 5
1-
b11111111111111111111111111111100 .
b11111111111111111111111111111100 >
b11111111111111111111111111111100 N
1O
bz M
1)
#27001
0)
#28001
b100 !
b100 5
z-
bz .
bz >
b11111111111111111011111000110011 3
b11111111111111111011111000110011 A
12
b10 4
b10 D
b0 N
0O
b0 M
b11111111111111111011111000110011 I
1J
b10 H
1)
#29001
0)
#30001
b0 3
b0 A
02
b0 4
b0 D
b0 I
0J
b0 H
b1001110110000 C
b1 !
b1 5
0*
1%
0$
b11111111111101011111101011010111 <
b101011111101011010111 #
b101011111101011010111 7
b10110000000 =
b10110000000 "
b10110000000 6
b111000110001 ,
b111000110001 ;
0)
#31001
b10 !
b10 5
1)
#32001
0)
#33001
b11 !
b11 5
1)
#34001
0)
#35001
b100 !
b100 5
b10 4
b10 D
b1001110110000 3
b1001110110000 A
12
b10 H
b1001110110000 I
1J
1)
1*
#36001
0)
#37001
b1 !
b1 5
1)
#38001
0)
#39001
b10 !
b10 5
b0 4
b0 D
b0 3
b0 A
02
10
b0 H
b0 I
0J
1L
bz K
1)
#40001
0)
#41001
b11 !
b11 5
1-
b11111111111111111111111111111100 .
b11111111111111111111111111111100 >
z0
b11111111111111111111111111111100 N
1O
bz M
0L
b0 K
1)
#42001
0)
#43001
b100 !
b100 5
b10 4
b10 D
b1001110110000 3
b1001110110000 A
12
z-
bz .
bz >
b10 H
b1001110110000 I
1J
b0 N
0O
b0 M
1)
#44001
0)
#45001
b0 4
b0 D
b0 3
b0 A
02
b0 H
b0 I
0J
b10100000010001010 C
b1 !
b1 5
0*
0%
1$
b10100000010010010 <
b10100000010010010 #
b10100000010010010 7
b11111111111111111111111101011110 =
b111101011110 "
b111101011110 6
b11101010000 ,
b11101010000 ;
0)
#46001
b10 !
b10 5
1)
#47001
0)
#48001
b11 !
b11 5
1)
#49001
0)
#50001
b100 !
b100 5
b10100000010001010 3
b10100000010001010 A
12
b10 4
b10 D
b10100000010001010 I
1J
b10 H
1)
1*
#51001
0)
#52001
b1 !
b1 5
1)
#53001
0)
#54001
b10 !
b10 5
b0 3
b0 A
02
b0 4
b0 D
b0 I
0J
b0 H
1)
#55001
0)
#56001
b11 !
b11 5
1-
b11111111111111111111111111111100 .
b11111111111111111111111111111100 >
b11111111111111111111111111111100 N
1O
bz M
1)
#57001
0)
#58001
b100 !
b100 5
z-
bz .
bz >
b10100000010001010 3
b10100000010001010 A
12
b10 4
b10 D
b0 N
0O
b0 M
b10100000010001010 I
1J
b10 H
1)
#59001
0)
#60001
b0 3
b0 A
02
b0 4
b0 D
b0 I
0J
b0 H
b1011000001010 C
b1 !
b1 5
0*
1%
0$
b11111111111101110010110100100111 <
b101110010110100100111 #
b101110010110100100111 7
b11100101000 =
b11100101000 "
b11100101000 6
b111011100010 ,
b111011100010 ;
0)
#61001
b10 !
b10 5
1)
#62001
0)
#63001
b11 !
b11 5
1)
#64001
0)
#65001
b100 !
b100 5
b10 4
b10 D
b1011000001010 3
b1011000001010 A
12
b10 H
b1011000001010 I
1J
1)
1*
#66001
0)
#67001
b1 !
b1 5
1)
#68001
0)
#69001
b10 !
b10 5
b0 4
b0 D
b0 3
b0 A
02
10
b0 H
b0 I
0J
1L
bz K
1)
#70001
0)
#71001
b11 !
b11 5
1-
b11111111111111111111111111111100 .
b11111111111111111111111111111100 >
z0
b11111111111111111111111111111100 N
1O
bz M
0L
b0 K
1)
#72001
0)
#73001
b100 !
b100 5
b10 4
b10 D
b1011000001010 3
b1011000001010 A
12
z-
bz .
bz >
b10 H
b1011000001010 I
1J
b0 N
0O
b0 M
1)
#74001
0)
#75001
b0 4
b0 D
b0 3
b0 A
02
b0 H
b0 I
0J
b1010011100 C
b1 !
b1 5
0*
b11111111111101010001000011010100 <
b101010001000011010100 #
b101010001000011010100 7
b11111111111111111111100010101110 =
b100010101110 "
b100010101110 6
b100111101110 ,
b100111101110 ;
0)
#76001
b10 !
b10 5
1)
#77001
0)
#78001
b11 !
b11 5
1)
#79001
0)
#80001
b100 !
b100 5
b1010011100 3
b1010011100 A
12
b10 4
b10 D
b1010011100 I
1J
b10 H
1)
1*
#81001
0)
#82001
b1 !
b1 5
1)
#83001
0)
#84001
b10 !
b10 5
10
b0 3
b0 A
02
b0 4
b0 D
1L
bz K
b0 I
0J
b0 H
1)
#85001
0)
#86001
b11 !
b11 5
1-
b11111111111111111111111111111100 .
b11111111111111111111111111111100 >
z0
b11111111111111111111111111111100 N
1O
bz M
0L
b0 K
1)
#87001
0)
#88001
b100 !
b100 5
z-
bz .
bz >
b1010011100 3
b1010011100 A
12
b10 4
b10 D
b0 N
0O
b0 M
b1010011100 I
1J
b10 H
1)
#89001
0)
#90001
b0 3
b0 A
02
b0 4
b0 D
b0 I
0J
b0 H
b11111111111110010011010110100111 C
b1 !
b1 5
0*
0%
1$
b11111111111110010011010110101111 <
b110010011010110101111 #
b110010011010110101111 7
b11110001110 =
b11110001110 "
b11110001110 6
b111010001111 ,
b111010001111 ;
0)
#91001
b10 !
b10 5
1)
#92001
0)
#93001
b11 !
b11 5
1)
#94001
0)
#95001
b100 !
b100 5
b10 4
b10 D
b11111111111110010011010110100111 3
b11111111111110010011010110100111 A
12
b10 H
b11111111111110010011010110100111 I
1J
1)
1*
#96001
0)
#97001
b1 !
b1 5
1)
#98001
0)
#99001
b10 !
b10 5
b0 4
b0 D
b0 3
b0 A
02
b0 H
b0 I
0J
1)
#100001
0)
#101001
b11 !
b11 5
1-
b11111111111111111111111111111100 .
b11111111111111111111111111111100 >
b11111111111111111111111111111100 N
1O
bz M
1)
#102001
0)
#103001
b100 !
b100 5
b10 4
b10 D
b11111111111110010011010110100111 3
b11111111111110010011010110100111 A
12
z-
bz .
bz >
b10 H
b11111111111110010011010110100111 I
1J
b0 N
0O
b0 M
1)
#104001
0)
#105001
b0 4
b0 D
b0 3
b0 A
02
b0 H
b0 I
0J
b10010001100 C
b1 !
b1 5
0*
1%
0$
b11111111111100101100100001110101 <
b100101100100001110101 #
b100101100100001110101 7
b110110000 =
b110110000 "
b110110000 6
b1011011101 ,
b1011011101 ;
0)
#106001
b10 !
b10 5
1)
#107001
0)
#108001
b11 !
b11 5
1)
#109001
0)
#110001
b100 !
b100 5
b10010001100 3
b10010001100 A
12
b10 4
b10 D
b10010001100 I
1J
b10 H
1)
1*
#111001
0)
#112001
b1 !
b1 5
1)
#113001
0)
#114001
b10 !
b10 5
10
b0 3
b0 A
02
b0 4
b0 D
1L
bz K
b0 I
0J
b0 H
1)
#115001
0)
#116001
b11 !
b11 5
1-
b11111111111111111111111111111100 .
b11111111111111111111111111111100 >
z0
b11111111111111111111111111111100 N
1O
bz M
0L
b0 K
1)
#117001
0)
#118001
b100 !
b100 5
z-
bz .
bz >
b10010001100 3
b10010001100 A
12
b10 4
b10 D
b0 N
0O
b0 M
b10010001100 I
1J
b10 H
1)
#119001
0)
#120001
b0 3
b0 A
02
b0 4
b0 D
b0 I
0J
b0 H
b100001110110 C
b1 !
b1 5
0*
b11111101101011101000 <
b11111101101011101000 #
b11111101101011101000 7
b11100100111 =
b11100100111 "
b11100100111 6
b101010000 ,
b101010000 ;
0)
#121001
b10 !
b10 5
1)
#122001
0)
#123001
b11 !
b11 5
1)
#124001
0)
#125001
b100 !
b100 5
b10 4
b10 D
b100001110110 3
b100001110110 A
12
b10 H
b100001110110 I
1J
1)
1*
#126001
0)
#127001
b1 !
b1 5
1)
#128001
0)
#129001
b10 !
b10 5
b0 4
b0 D
b0 3
b0 A
02
10
b0 H
b0 I
0J
1L
bz K
1)
#130001
0)
#131001
b11 !
b11 5
1-
b11111111111111111111111111111100 .
b11111111111111111111111111111100 >
z0
b11111111111111111111111111111100 N
1O
bz M
0L
b0 K
1)
#132001
0)
#133001
b100 !
b100 5
b10 4
b10 D
b100001110110 3
b100001110110 A
12
z-
bz .
bz >
b10 H
b100001110110 I
1J
b0 N
0O
b0 M
1)
#134001
0)
#135001
b0 4
b0 D
b0 3
b0 A
02
b0 H
b0 I
0J
b11001110110 C
b1 !
b1 5
0*
b1011010010011000011 <
b1011010010011000011 #
b1011010010011000011 7
b11111111111111111111100000001101 =
b100000001101 "
b100000001101 6
b111001101001 ,
b111001101001 ;
0)
#136001
b10 !
b10 5
1)
#137001
0)
#138001
b11 !
b11 5
1)
#139001
0)
#140001
b100 !
b100 5
b11001110110 3
b11001110110 A
12
b10 4
b10 D
b11001110110 I
1J
b10 H
1)
1*
#141001
0)
#142001
b1 !
b1 5
1)
#143001
0)
#144001
b10 !
b10 5
10
b0 3
b0 A
02
b0 4
b0 D
1L
bz K
b0 I
0J
b0 H
1)
#145001
0)
#146001
b11 !
b11 5
1-
b11111111111111111111111111111100 .
b11111111111111111111111111111100 >
z0
b11111111111111111111111111111100 N
1O
bz M
0L
b0 K
1)
#147001
0)
#148001
b100 !
b100 5
z-
bz .
bz >
b11001110110 3
b11001110110 A
12
b10 4
b10 D
b0 N
0O
b0 M
b11001110110 I
1J
b10 H
1)
#149001
0)
#150001
b0 3
b0 A
02
b0 4
b0 D
b0 I
0J
b0 H
b11111100001011101011 C
b1 !
b1 5
0*
0%
1$
b11111100001011110011 <
b11111100001011110011 #
b11111100001011110011 7
b11111111111111111111111000000001 =
b111000000001 "
b111000000001 6
b1110011010 ,
b1110011010 ;
0)
#151001
b10 !
b10 5
1)
#152001
0)
#153001
b11 !
b11 5
1)
#154001
0)
#155001
b100 !
b100 5
b10 4
b10 D
b11111100001011101011 3
b11111100001011101011 A
12
b10 H
b11111100001011101011 I
1J
1)
1*
#156001
0)
#157001
b1 !
b1 5
1)
#158001
0)
#159001
b10 !
b10 5
b0 4
b0 D
b0 3
b0 A
02
b0 H
b0 I
0J
1)
#160001
0)
#161001
b11 !
b11 5
1-
b11111111111111111111111111111100 .
b11111111111111111111111111111100 >
b11111111111111111111111111111100 N
1O
bz M
1)
#162001
0)
#163001
b100 !
b100 5
b10 4
b10 D
b11111100001011101011 3
b11111100001011101011 A
12
z-
bz .
bz >
b10 H
b11111100001011101011 I
1J
b0 N
0O
b0 M
1)
#164001
0)
#165001
b0 4
b0 D
b0 3
b0 A
02
b0 H
b0 I
0J
b100000011100101101 C
b1 !
b1 5
0*
b100000011100110101 <
b100000011100110101 #
b100000011100110101 7
b111100111 =
b111100111 "
b111100111 6
b110101101001 ,
b110101101001 ;
0)
#166001
b10 !
b10 5
1)
#167001
0)
#168001
b11 !
b11 5
1)
#169001
0)
#170001
b100 !
b100 5
b100000011100101101 3
b100000011100101101 A
12
b10 4
b10 D
b100000011100101101 I
1J
b10 H
1)
1*
#171001
0)
#172001
b1 !
b1 5
1)
#173001
0)
#174001
b10 !
b10 5
b0 3
b0 A
02
b0 4
b0 D
b0 I
0J
b0 H
1)
#175001
0)
#176001
b11 !
b11 5
1-
b11111111111111111111111111111100 .
b11111111111111111111111111111100 >
b11111111111111111111111111111100 N
1O
bz M
1)
#177001
0)
#178001
b100 !
b100 5
z-
bz .
bz >
b100000011100101101 3
b100000011100101101 A
12
b10 4
b10 D
b0 N
0O
b0 M
b100000011100101101 I
1J
b10 H
1)
#179001
0)
#180001
b0 3
b0 A
02
b0 4
b0 D
b0 I
0J
b0 H
b101010100010 C
b1 !
b1 5
0*
1%
0$
b10101001011011000010 <
b10101001011011000010 #
b10101001011011000010 7
b11111111111111111111101110101010 =
b101110101010 "
b101110101010 6
b111011111000 ,
b111011111000 ;
0)
#181001
b10 !
b10 5
1)
#182001
0)
#183001
b11 !
b11 5
1)
#184001
0)
#185001
b100 !
b100 5
b10 4
b10 D
b101010100010 3
b101010100010 A
12
b10 H
b101010100010 I
1J
1)
1*
#186001
0)
#187001
b1 !
b1 5
1)
#188001
0)
#189001
b10 !
b10 5
b0 4
b0 D
b0 3
b0 A
02
10
b0 H
b0 I
0J
1L
bz K
1)
#190001
0)
#191001
b11 !
b11 5
1-
b11111111111111111111111111111100 .
b11111111111111111111111111111100 >
z0
b11111111111111111111111111111100 N
1O
bz M
0L
b0 K
1)
#192001
0)
#193001
b100 !
b100 5
b10 4
b10 D
b101010100010 3
b101010100010 A
12
z-
bz .
bz >
b10 H
b101010100010 I
1J
b0 N
0O
b0 M
1)
#194001
0)
#195001
b0 4
b0 D
b0 3
b0 A
02
b0 H
b0 I
0J
b100011000100111101 C
b1 !
b1 5
0*
0%
1$
b100011000101000101 <
b100011000101000101 #
b100011000101000101 7
b11111111111111111111110111100100 =
b110111100100 "
b110111100100 6
b110100110100 ,
b110100110100 ;
0)
#196001
b10 !
b10 5
1)
#197001
0)
#198001
b11 !
b11 5
1)
#199001
0)
#200001
b100 !
b100 5
b100011000100111101 3
b100011000100111101 A
12
b10 4
b10 D
b100011000100111101 I
1J
b10 H
1)
1*
#201001
0)
#202001
b1 !
b1 5
1)
#203001
0)
#204001
b10 !
b10 5
b0 3
b0 A
02
b0 4
b0 D
b0 I
0J
b0 H
1)
#205001
0)
#206001
b11 !
b11 5
1-
b11111111111111111111111111111100 .
b11111111111111111111111111111100 >
b11111111111111111111111111111100 N
1O
bz M
1)
#207001
0)
#208001
b100 !
b100 5
z-
bz .
bz >
b100011000100111101 3
b100011000100111101 A
12
b10 4
b10 D
b0 N
0O
b0 M
b100011000100111101 I
1J
b10 H
1)
#209001
0)
#210001
b0 3
b0 A
02
b0 4
b0 D
b0 I
0J
b0 H
b11111111111110011010111111111111 C
b1 !
b1 5
0*
b11111111111110011011000000000111 <
b110011011000000000111 #
b110011011000000000111 7
b11010000001 =
b11010000001 "
b11010000001 6
b101101000110 ,
b101101000110 ;
0)
#211001
b10 !
b10 5
1)
#212001
0)
#213001
b11 !
b11 5
1)
#214001
0)
#215001
b100 !
b100 5
b10 4
b10 D
b11111111111110011010111111111111 3
b11111111111110011010111111111111 A
12
b10 H
b11111111111110011010111111111111 I
1J
1)
1*
#216001
0)
#217001
b1 !
b1 5
1)
#218001
0)
#219001
b10 !
b10 5
b0 4
b0 D
b0 3
b0 A
02
b0 H
b0 I
0J
1)
#220001
0)
#221001
b11 !
b11 5
1-
b11111111111111111111111111111100 .
b11111111111111111111111111111100 >
b11111111111111111111111111111100 N
1O
bz M
1)
#222001
0)
#223001
b100 !
b100 5
b10 4
b10 D
b11111111111110011010111111111111 3
b11111111111110011010111111111111 A
12
z-
bz .
bz >
b10 H
b11111111111110011010111111111111 I
1J
b0 N
0O
b0 M
1)
#224001
0)
#225001
b0 4
b0 D
b0 3
b0 A
02
b0 H
b0 I
0J
b11111111111111111111111011000000 C
b1 !
b1 5
0*
1%
0$
b101100000000010010 <
b101100000000010010 #
b101100000000010010 7
b11111111111111111111100100111110 =
b100100111110 "
b100100111110 6
b10110000011 ,
b10110000011 ;
0)
#226001
b10 !
b10 5
1)
#227001
0)
#228001
b11 !
b11 5
1)
#229001
0)
#230001
b100 !
b100 5
b11111111111111111111111011000000 3
b11111111111111111111111011000000 A
12
b10 4
b10 D
b11111111111111111111111011000000 I
1J
b10 H
1)
1*
#231001
0)
#232001
b1 !
b1 5
1)
#233001
0)
#234001
b10 !
b10 5
10
b0 3
b0 A
02
b0 4
b0 D
1L
bz K
b0 I
0J
b0 H
1)
#235001
0)
#236001
b11 !
b11 5
1-
b11111111111111111111111111111100 .
b11111111111111111111111111111100 >
z0
b11111111111111111111111111111100 N
1O
bz M
0L
b0 K
1)
#237001
0)
#238001
b100 !
b100 5
z-
bz .
bz >
b11111111111111111111111011000000 3
b11111111111111111111111011000000 A
12
b10 4
b10 D
b0 N
0O
b0 M
b11111111111111111111111011000000 I
1J
b10 H
1)
#239001
0)
#240001
b0 3
b0 A
02
b0 4
b0 D
b0 I
0J
b0 H
b1000000101110 C
b1 !
b1 5
0*
b11101011010110101 <
b11101011010110101 #
b11101011010110101 7
b110100100 =
b110100100 "
b110100100 6
b111010001011 ,
b111010001011 ;
0)
#241001
b10 !
b10 5
1)
#242001
0)
#243001
b11 !
b11 5
1)
#244001
0)
#245001
b100 !
b100 5
b10 4
b10 D
b1000000101110 3
b1000000101110 A
12
b10 H
b1000000101110 I
1J
1)
1*
#246001
0)
#247001
b1 !
b1 5
1)
#248001
0)
#249001
b10 !
b10 5
b0 4
b0 D
b0 3
b0 A
02
10
b0 H
b0 I
0J
1L
bz K
1)
#250001
0)
#251001
b11 !
b11 5
1-
b11111111111111111111111111111100 .
b11111111111111111111111111111100 >
z0
b11111111111111111111111111111100 N
1O
bz M
0L
b0 K
1)
#252001
0)
#253001
b100 !
b100 5
b10 4
b10 D
b1000000101110 3
b1000000101110 A
12
z-
bz .
bz >
b10 H
b1000000101110 I
1J
b0 N
0O
b0 M
1)
#254001
0)
#255001
b0 4
b0 D
b0 3
b0 A
02
b0 H
b0 I
0J
b110011101100100 C
b1 !
b1 5
0*
0%
1$
b110011101101100 <
b110011101101100 #
b110011101101100 7
b1100000100 =
b1100000100 "
b1100000100 6
b11110000101 ,
b11110000101 ;
0)
#256001
b10 !
b10 5
1)
#257001
0)
#258001
b11 !
b11 5
1)
#259001
0)
#260001
b100 !
b100 5
b110011101100100 3
b110011101100100 A
12
b10 4
b10 D
b110011101100100 I
1J
b10 H
1)
1*
#261001
0)
#262001
b1 !
b1 5
1)
#263001
0)
#264001
b10 !
b10 5
b0 3
b0 A
02
b0 4
b0 D
b0 I
0J
b0 H
1)
#265001
0)
