coco_tb/DUT_top/exu_reg_swc.v
module exu_reg_swc (
    hclk                                        ,
    hrstn                                       ,
    cycle_cnt                                   ,
    en                                          ,
    dec_add                                     ,
	dec_sub                                     ,
	dec_sll                                     ,
	dec_slt                                     ,
	dec_sltu                                    ,
	dec_xor                                     ,
	dec_srl                                     ,
	dec_sra                                     ,
	dec_or                                      ,
	dec_and                                     ,
    dec_rs1                                     ,
    dec_rs2                                     ,
    dec_rd                                      ,
    pc                                          ,
    reg_waddr                                   ,
    reg_wen                                     ,
    reg_wdata                                   ,
    reg_rdata_1                                 ,
    reg_raddr_1                                 ,
    reg_ren_1                                   ,
    reg_rdata_2                                 ,
    reg_raddr_2                                 ,
    reg_ren_2                                   ,
    exu_stall                                   
);
/*
Performs Integer Register-Register Operations.

Reads the values from the dec_rs1 and dec_rs2 registers as source operands.
Writes the result into dec_rd.
*/
input                       hclk                ;
input                       hrstn               ;
input           [3:0]       cycle_cnt           ;
// signals from dec 
input                       en                  ;
input                       dec_add             ;
input                       dec_sub             ;
input                       dec_sll             ;
input                       dec_slt             ;
input                       dec_sltu            ;
input                       dec_xor             ;
input                       dec_srl             ;
input                       dec_sra             ;
input                       dec_or              ;
input                       dec_and             ;
input           [4:0]       dec_rs1             ;
input           [4:0]       dec_rs2             ;
input           [4:0]       dec_rd              ; 
// PC
input           [31:0]      pc                  ;
// regfile write port
inout           [4:0]       reg_waddr           ;
inout                       reg_wen             ;
inout           [31:0]      reg_wdata           ;
input           [31:0]      reg_rdata_1         ;
inout           [4:0]       reg_raddr_1         ;
inout                       reg_ren_1           ;
input           [31:0]      reg_rdata_2         ;
inout           [4:0]       reg_raddr_2         ;
inout                       reg_ren_2           ;
// exu_stall
input                       exu_stall           ;
// middle signals
reg             [4:0]       mid_reg_waddr       ;
reg                         mid_reg_wen         ;
reg             [31:0]      mid_reg_wdata       ;
reg             [4:0]       mid_reg_raddr_1     ;
reg                         mid_reg_ren_1       ;
reg             [4:0]       mid_reg_raddr_2     ;
reg                         mid_reg_ren_2       ;

assign reg_waddr   = mid_reg_wen   ? mid_reg_waddr    : 'z  ;
assign reg_wen     = mid_reg_wen   ? mid_reg_wen      : 'z  ;
assign reg_wdata   = mid_reg_wen   ? mid_reg_wdata    : 'z  ;
assign reg_raddr_1 = mid_reg_ren_1 ? mid_reg_raddr_1  : 'z  ;
assign reg_ren_1   = mid_reg_ren_1 ? mid_reg_ren_1    : 'z  ;
assign reg_raddr_2 = mid_reg_ren_2 ? mid_reg_raddr_2  : 'z  ;
assign reg_ren_2   = mid_reg_ren_2 ? mid_reg_ren_2    : 'z  ;

always@(posedge hclk or negedge hrstn) begin
    if(!hrstn) begin // on a reset clear all the temp read and write values
        mid_reg_raddr_1 <= 0;
        mid_reg_ren_1   <= 0;

        mid_reg_raddr_2 <= 0;
        mid_reg_ren_2   <= 0;
        
        mid_reg_waddr   <= 0;
        mid_reg_wen     <= 0;
        mid_reg_wdata   <= 0;
    end else if(en && !exu_stall)begin // if enabled and we are not stalling, continue
        if(cycle_cnt == 1) begin // on cycle 1, assign the read registers and enable them
            mid_reg_raddr_1 <= dec_rs1;
            mid_reg_ren_1   <= 1;

            mid_reg_raddr_2 <= dec_rs2;
            mid_reg_ren_2   <= 1;

            mid_reg_waddr   <= 0;
            mid_reg_wen     <= 0;
            mid_reg_wdata   <= 0;
        end else if(cycle_cnt == 2) begin // on cycle 2 clear all
            mid_reg_raddr_1 <= 0;
            mid_reg_ren_1   <= 0;

            mid_reg_raddr_2 <= 0;
            mid_reg_ren_2   <= 0;

            mid_reg_waddr   <= 0;
            mid_reg_wen     <= 0;
            mid_reg_wdata   <= 0;
        end else if(cycle_cnt == 3)begin // on cycle 3 assign the write address and enable it
            mid_reg_raddr_1 <= 0;
            mid_reg_ren_1   <= 0;

            mid_reg_raddr_2 <= 0;
            mid_reg_ren_2   <= 0;

            mid_reg_waddr   <= dec_rd;
            mid_reg_wen     <= 1;
            // perform the operation and assign the temp write data to the result of the operation
            if(dec_add)
                mid_reg_wdata <= reg_rdata_1 + reg_rdata_2;
            else if(dec_sub)
                mid_reg_wdata <= reg_rdata_1 - reg_rdata_2;
            else if(dec_sll)
                mid_reg_wdata <= reg_rdata_1 << reg_rdata_2[4:0];
            else if(dec_slt)
                mid_reg_wdata <= {31'b0, $signed(reg_rdata_1) < $signed(reg_rdata_2)};
            else if(dec_sltu)
                mid_reg_wdata <= {31'b0, reg_rdata_1 < reg_rdata_2};
            else if(dec_xor)
                mid_reg_wdata <= reg_rdata_1 ^ reg_rdata_2;
            else if(dec_srl)
                mid_reg_wdata <= reg_rdata_1 >> reg_rdata_2[4:0];
            else if(dec_sra)
                mid_reg_wdata <= $signed(reg_rdata_1) >>> reg_rdata_2[4:0];
            else if(dec_or)
                mid_reg_wdata <= reg_rdata_1 | reg_rdata_2;
            else if(dec_and)
                mid_reg_wdata <= reg_rdata_1 & reg_rdata_2;
            else
                mid_reg_wdata <= 0;
        end else begin // on cycle 4 clear all
            mid_reg_raddr_1 <= 0;
            mid_reg_ren_1   <= 0;

            mid_reg_raddr_2 <= 0;
            mid_reg_ren_2   <= 0;

            mid_reg_waddr   <= 0;
            mid_reg_wen     <= 0;
            mid_reg_wdata   <= 0;    
        end 
    end else begin
    mid_reg_raddr_1 <= 0;
    mid_reg_ren_1   <= 0;

    mid_reg_raddr_2 <= 0;
    mid_reg_ren_2   <= 0;

    mid_reg_waddr <= 0;
    mid_reg_wen   <= 0;
    mid_reg_wdata <= 0;
    end
end

endmodule

archive/rtl/chip/core/exu_swc/exu_reg_swc/exu_reg_wrapper.v
module exu_reg_swc_wrapper (
    input hclk,
    input hrstn,
    input [3:0] cycle_cnt,
    input en,
    input dec_add,
    input dec_sub,
    input dec_sll,
    input dec_slt,
    input dec_sltu,
    input dec_xor,
    input dec_srl,
    input dec_sra,
    input dec_or,
    input dec_and,
    input [4:0] dec_rs1,
    input [4:0] dec_rs2,
    input [4:0] dec_rd,
    input [31:0] pc,
    input [31:0] reg_rdata_1,
    input [31:0] reg_rdata_2,
    input exu_stall,
    inout [4:0] reg_waddr,
    inout reg_wen,
    inout [31:0] reg_wdata,
    inout [4:0] reg_raddr_1,
    inout reg_ren_1,
    inout [4:0] reg_raddr_2,
    inout reg_ren_2
);

    exu_reg_swc dut (
        .hclk(hclk),
        .hrstn(hrstn),
        .cycle_cnt(cycle_cnt),
        .en(en),
        .dec_add(dec_add),
        .dec_sub(dec_sub),
        .dec_sll(dec_sll),
        .dec_slt(dec_slt),
        .dec_sltu(dec_sltu),
        .dec_xor(dec_xor),
        .dec_srl(dec_srl),
        .dec_sra(dec_sra),
        .dec_or(dec_or),
        .dec_and(dec_and),
        .dec_rs1(dec_rs1),
        .dec_rs2(dec_rs2),
        .dec_rd(dec_rd),
        .pc(pc),
        .reg_rdata_1(reg_rdata_1),
        .reg_rdata_2(reg_rdata_2),
        .exu_stall(exu_stall),
        .reg_waddr(reg_waddr),
        .reg_wen(reg_wen),
        .reg_wdata(reg_wdata),
        .reg_raddr_1(reg_raddr_1),
        .reg_ren_1(reg_ren_1),
        .reg_raddr_2(reg_raddr_2),
        .reg_ren_2(reg_ren_2)
    );
    initial begin
        $dumpfile("exu_reg_cocotb.vcd");
        $dumpvars(0, exu_reg_swc_wrapper);
    end
endmodule

archive/rtl/chip/core/exu_swc/exu_reg_swc/exu_reg_cocotb.vcd
$date
	Tue Nov 19 20:08:34 2024
$end
$version
	Icarus Verilog
$end
$timescale
	1ps
$end
$scope module exu_reg_swc_wrapper $end
$var wire 4 ! cycle_cnt [3:0] $end
$var wire 1 " dec_add $end
$var wire 1 # dec_and $end
$var wire 1 $ dec_or $end
$var wire 5 % dec_rd [4:0] $end
$var wire 5 & dec_rs1 [4:0] $end
$var wire 5 ' dec_rs2 [4:0] $end
$var wire 1 ( dec_sll $end
$var wire 1 ) dec_slt $end
$var wire 1 * dec_sltu $end
$var wire 1 + dec_sra $end
$var wire 1 , dec_srl $end
$var wire 1 - dec_sub $end
$var wire 1 . dec_xor $end
$var wire 1 / en $end
$var wire 1 0 exu_stall $end
$var wire 1 1 hclk $end
$var wire 1 2 hrstn $end
$var wire 32 3 pc [31:0] $end
$var wire 32 4 reg_rdata_1 [31:0] $end
$var wire 32 5 reg_rdata_2 [31:0] $end
$var wire 1 6 reg_wen $end
$var wire 32 7 reg_wdata [31:0] $end
$var wire 5 8 reg_waddr [4:0] $end
$var wire 1 9 reg_ren_2 $end
$var wire 1 : reg_ren_1 $end
$var wire 5 ; reg_raddr_2 [4:0] $end
$var wire 5 < reg_raddr_1 [4:0] $end
$scope module dut $end
$var wire 4 = cycle_cnt [3:0] $end
$var wire 1 " dec_add $end
$var wire 1 # dec_and $end
$var wire 1 $ dec_or $end
$var wire 5 > dec_rd [4:0] $end
$var wire 5 ? dec_rs1 [4:0] $end
$var wire 5 @ dec_rs2 [4:0] $end
$var wire 1 ( dec_sll $end
$var wire 1 ) dec_slt $end
$var wire 1 * dec_sltu $end
$var wire 1 + dec_sra $end
$var wire 1 , dec_srl $end
$var wire 1 - dec_sub $end
$var wire 1 . dec_xor $end
$var wire 1 / en $end
$var wire 1 0 exu_stall $end
$var wire 1 1 hclk $end
$var wire 1 2 hrstn $end
$var wire 32 A pc [31:0] $end
$var wire 32 B reg_rdata_1 [31:0] $end
$var wire 32 C reg_rdata_2 [31:0] $end
$var wire 1 6 reg_wen $end
$var wire 32 D reg_wdata [31:0] $end
$var wire 5 E reg_waddr [4:0] $end
$var wire 1 9 reg_ren_2 $end
$var wire 1 : reg_ren_1 $end
$var wire 5 F reg_raddr_2 [4:0] $end
$var wire 5 G reg_raddr_1 [4:0] $end
$var reg 5 H mid_reg_raddr_1 [4:0] $end
$var reg 5 I mid_reg_raddr_2 [4:0] $end
$var reg 1 J mid_reg_ren_1 $end
$var reg 1 K mid_reg_ren_2 $end
$var reg 5 L mid_reg_waddr [4:0] $end
$var reg 32 M mid_reg_wdata [31:0] $end
$var reg 1 N mid_reg_wen $end
$upscope $end
$upscope $end
$enddefinitions $end
$comment Show the parameter values. $end
$dumpall
$end
#0
$dumpvars
0N
b0 M
b0 L
0K
0J
b0 I
b0 H
bz G
bz F
bz E
bz D
b10001001010100111000001010110110 C
b1011101000101110001011100001 B
bz A
b10 @
b1 ?
b11 >
b1 =
bz <
bz ;
z:
z9
bz 8
bz 7
z6
b10001001010100111000001010110110 5
b1011101000101110001011100001 4
bz 3
02
01
00
1/
0.
0-
0,
0+
0*
0)
1(
b10 '
b1 &
b11 %
0$
0#
0"
b1 !
$end
#1000
b10 !
b10 =
11
#2000
01
#3000
b11 !
b11 =
11
#4000
01
#5000
b100 !
b100 =
b11 8
b11 E
16
b0 7
b0 D
1N
b11 L
11
12
#6000
01
#7000
1001010 M
1N
b11 L
11
12
#6000
01
#7000
z6
bz 7
bz D
bz 8
bz E
b0 M
0N
b0 L
11
#7001
b1 !
b1 =
01
02
0+
1-
b10100100101000101111001101111000 5
b10100100101000101111001101111000 C
b1001101110001000111100001101111 4
b1001101110001000111100001101111 B
#8001
b10 !
b10 =
11
#9001
01
#10001
b11 !
b11 =
11
#11001
01
#12001
b100 !
b100 =
b11 8
b11 E
16
b10101001001000011000010011110111 7
b10101001001000011000010011110111 D
b10101001001000011000010011110111 M
1N
b11 L
11
12
#13001
01
#14001
b1 !
b1 =
02
1*
0-
b101000001000010111010011101010 5
b101000001000010111010011101010 C
b1111100010011110000110100110001 4
b1111100010011110000110100110001 B
z6
bz 7
bz D
bz 8
bz E
b0 M
0N
b0 L
01
#15001
b10 !
b10 =
11
#16001
01
#17001
b11 !
b11 =
11
#18001
01
#19001
b100 !
b100 =
b11 8
b11 E
16
b0 7
b0 D
1N
b11 L
11
12
#20001
01
#21001
b1 !
b1 =
02
0*
1-
b1000001110000000110000101000 5
b1000001110000000110000101000 C
b10010110011110000001011100011101 4
b10010110011110000001011100011101 B
z6
bz 7
bz D
bz 8
bz E
0N
b0 L
01
#22001
b10 !
b10 =
11
#23001
01
#24001
b11 !
b11 =
11
#25001
01
#26001
b100 !
b100 =
b11 8
b11 E
16
b10001110010000000000101011110101 7
b10001110010000000000101011110101 D
b10001110010000000000101011110101 M
1N
b11 L
11
12
#27001
01
#28001
b1 !
b1 =
02
1.
0-
b1011111011000111010111001001100 5
b1011111011000111010111001001100 C
b110010100000111000101100100000 4
b110010100000111000101100100000 B
z6
bz 7
bz D
bz 8
bz E
b0 M
0N
b0 L
01
#29001
b10 !
b10 =
11
#30001
01
#31001
b11 !
b11 =
11
#32001
01
#33001
b100 !
b100 =
b11 8
b11 E
16
b1101101111000000010010101101100 7
b1101101111000000010010101101100 D
b1101101111000000010010101101100 M
1N
b11 L
11
12
#34001
01
#35001
b1 !
b1 =
02
0.
1(
b1010001000110000001011010000000 5
b1010001000110000001011010000000 C
b10101011011111101000101010110011 4
b10101011011111101000101010110011 B
z6
bz 7
bz D
bz 8
bz E
b0 M
0N
b0 L
01
#36001
b10 !
b10 =
11
#37001
01
#38001
b11 !
b11 =
11
#39001
01
#40001
b100 !
b100 =
b11 8
b11 E
16
b10101011011111101000101010110011 7
b10101011011111101000101010110011 D
b10101011011111101000101010110011 M
1N
b11 L
11
12
#41001
01
#42001
b1 !
b1 =
02
1*
0(
b101101001000000010001000001000 5
b101101001000000010001000001000 C
b10011011000111100001001111111110 4
b10011011000111100001001111111110 B
z6
bz 7
bz D
bz 8
bz E
b0 M
0N
b0 L
01
#43001
b10 !
b10 =
11
#44001
01
#45001
b11 !
b11 =
11
#46001
01
#47001
b100 !
b100 =
b11 8
b11 E
16
b0 7
b0 D
1N
b11 L
11
12
#48001
01
#49001
b1 !
b1 =
02
1#
0*
b11010101101101000010001001 5
b11010101101101000010001001 C
b10110011110110110000111011011111 4
b10110011110110110000111011011111 B
z6
bz 7
bz D
bz 8
bz E
0N
b0 L
01
#50001
b10 !
b10 =
11
#51001
01
#52001
b11 !
b11 =
11
#53001
01
#54001
b100 !
b100 =
b11 8
b11 E
16
b11010100100000000010001001 7
b11010100100000000010001001 D
b11010100100000000010001001 M
1N
b11 L
11
12
#55001
01
#56001
b1 !
b1 =
02
0#
1+
b1010001001101101111110111110011 5
b1010001001101101111110111110011 C
b1000010111100111000101101111101 4
b1000010111100111000101101111101 B
z6
bz 7
bz D
bz 8
bz E
b0 M
0N
b0 L
01
#57001
b10 !
b10 =
11
#58001
01
#59001
b11 !
b11 =
11
#60001
01
#61001
b100 !
b100 =
b11 8
b11 E
16
b100001011110 7
b100001011110 D
b100001011110 M
1N
b11 L
11
12
#62001
01
#63001
b1 !
b1 =
02
0+
1-
b10100010011101011001000101111011 5
b10100010011101011001000101111011 C
b10011111000110100000110100111010 4
b10011111000110100000110100111010 B
z6
bz 7
bz D
bz 8
bz E
b0 M
0N
b0 L
01
#64001
b10 !
b10 =
11
#65001
01
#66001
b11 !
b11 =
11
#67001
01
#68001
b100 !
b100 =
b11 8
b11 E
16
b11111100101001000111101110111111 7
b11111100101001000111101110111111 D
b11111100101001000111101110111111 M
1N
b11 L
11
12
#69001
01
#70001
b1 !
b1 =
02
1*
0-
b11000101100101110011101000101010 5
b11000101100101110011101000101010 C
b11010101010100111101010111100100 4
b11010101010100111101010111100100 B
z6
bz 7
bz D
bz 8
bz E
b0 M
0N
b0 L
01
#71001
b10 !
b10 =
11
#72001
01
#73001
b11 !
b11 =
11
#74001
01
#75001
b100 !
b100 =
b11 8
b11 E
16
b0 7
b0 D
1N
b11 L
11
12
#76001
01
#77001
b1 !
b1 =
02
1.
0*
b10101001000011001110011011110011 5
b10101001000011001110011011110011 C
b1101101100110000001111001000011 4
b1101101100110000001111001000011 B
z6
bz 7
bz D
bz 8
bz E
0N
b0 L
01
#78001
b10 !
b10 =
11
#79001
01
#80001
b11 !
b11 =
11
#81001
01
#82001
b100 !
b100 =
b11 8
b11 E
16
b11000100100101001111100010110000 7
b11000100100101001111100010110000 D
b11000100100101001111100010110000 M
1N
b11 L
11
12
#83001
01
#84001
b1 !
b1 =
02
1#
0.
b11010001110101101100001010000 5
b11010001110101101100001010000 C
b1011110111001111000011001100100 4
b1011110111001111000011001100100 B
z6
bz 7
bz D
bz 8
bz E
b0 M
0N
b0 L
01
#85001
b10 !
b10 =
11
#86001
01
#87001
b11 !
b11 =
11
#88001
01
#89001
b100 !
b100 =
b11 8
b11 E
16
b11010001000101000000001000000 7
b11010001000101000000001000000 D
b11010001000101000000001000000 M
1N
b11 L
11
12
#90001
01
#91001
b1 !
b1 =
02
0#
1,
b11001100100010010101101110111 5
b11001100100010010101101110111 C
b1000101010100000111010011101001 4
b1000101010100000111010011101001 B
z6
bz 7
bz D
bz 8
bz E
b0 M
0N
b0 L
01
#92001
b10 !
b10 =
11
#93001
01
#94001
b11 !
b11 =
11
#95001
01
#96001
b100 !
b100 =
b11 8
b11 E
16
b10001010 7
b10001010 D
b10001010 M
1N
b11 L
11
12
#97001
01
#98001
b1 !
b1 =
02
0,
1"
b10111101100110100111000110101010 5
b10111101100110100111000110101010 C
b10000001000100101100101110001001 4
b10000001000100101100101110001001 B
z6
bz 7
bz D
bz 8
bz E
b0 M
0N
b0 L
01
#99001
b10 !
b10 =
11
#100001
01
#101001
b11 !
b11 =
11
#102001
01
#103001
b100 !
b100 =
b11 8
b11 E
16
b111110101011010011110100110011 7
b111110101011010011110100110011 D
b111110101011010011110100110011 M
1N
b11 L
11
12
#104001
01
#105001
b1 !
b1 =
02
1.
0"
b10001011110011100000101101000000 5
b10001011110011100000101101000000 C
b10101111001110101001001001001100 4
b10101111001110101001001001001100 B
z6
bz 7
bz D
bz 8
bz E
b0 M
0N
b0 L
01
#106001
b10 !
b10 =
11
#107001
01
#108001
b11 !
b11 =
11
#109001
01
#110001
b100 !
b100 =
b11 8
b11 E
16
b100100111101001001100100001100 7
b100100111101001001100100001100 D
b100100111101001001100100001100 M
1N
b11 L
11
12
#111001
01
#112001
b1 !
b1 =
02
1,
0.
b1110100101010011101110000101111 5
b1110100101010011101110000101111 C
b1001000110010000001001011001100 4
b1001000110010000001001011001100 B
z6
bz 7
bz D
bz 8
bz E
b0 M
0N
b0 L
01
#113001
b10 !
b10 =
11
#114001
01
#115001
b11 !
b11 =
11
#116001
01
#117001
b100 !
b100 =
b11 8
b11 E
16
b1001000110010000 7
b1001000110010000 D
b1001000110010000 M
1N
b11 L
11
12
#118001
01
#119001
b1 !
b1 =
02
1+
0,
b11000100001010110000000110001001 5
b11000100001010110000000110001001 C
b1010001011100001110001000110 4
b1010001011100001110001000110 B
z6
bz 7
bz D
bz 8
bz E
b0 M
0N
b0 L
01
#120001
b10 !
b10 =
11
#121001
01
#122001
b11 !
b11 =
11
#123001
01
#124001
b100 !
b100 =
b11 8
b11 E
16
b1010001011100001110 7
b1010001011100001110 D
b1010001011100001110 M
1N
b11 L
11
12
#125001
01
#126001
b1 !
b1 =
02
0+
1"
b100111110001110000010011111010 5
b100111110001110000010011111010 C
b111100101100111010111111101111 4
b111100101100111010111111101111 B
z6
bz 7
bz D
bz 8
bz E
b0 M
0N
b0 L
01
#127001
b10 !
b10 =
11
#128001
01
#129001
b11 !
b11 =
11
#130001
01
#131001
b100 !
b100 =
b11 8
b11 E
16
b1100100011110101011010011101001 7
b1100100011110101011010011101001 D
b1100100011110101011010011101001 M
1N
b11 L
11
12
#132001
01
#133001
b1 !
b1 =
02
1,
0"
b10101111000111101010101010100001 5
b10101111000111101010101010100001 C
b1000111011100111100001011010000 4
b1000111011100111100001011010000 B
z6
bz 7
bz D
bz 8
bz E
b0 M
0N
b0 L
01
#134001
b10 !
b10 =
11
#135001
01
#136001
b11 !
b11 =
11
#137001
01
#138001
b100 !
b100 =
b11 8
b11 E
16
b100011101110011110000101101000 7
b100011101110011110000101101000 D
b100011101110011110000101101000 M
1N
b11 L
11
12
#139001
01
#140001
b1 !
b1 =
02
0,
1"
b1101111011010010011101010010011 5
b1101111011010010011101010010011 C
b11011000101101111110000000011001 4
b11011000101101111110000000011001 B
z6
bz 7
bz D
bz 8
bz E
b0 M
0N
b0 L
01
#141001
b10 !
b10 =
11
#142001
01
#143001
b11 !
b11 =
11
#144001
01
#145001
b100 !
b100 =
b11 8
b11 E
16
b1001000001000010001101010101100 7
b1001000001000010001101010101100 D
b1001000001000010001101010101100 M
1N
b11 L
11
12
#146001
01
#147001
b1 !
b1 =
02
1(
0"
b1100000010110111111110000011000 5
b1100000010110111111110000011000 C
b10100011010010111010011100100010 4
b10100011010010111010011100100010 B
z6
bz 7
bz D
bz 8
bz E
b0 M
0N
b0 L
01
#148001
b10 !
b10 =
11
#149001
01
#150001
b11 !
b11 =
11
#151001
01
#152001
b100 !
b100 =
b11 8
b11 E
16
b100010000000000000000000000000 7
b100010000000000000000000000000 D
b100010000000000000000000000000 M
1N
b11 L
11
12
#153001
01
#154001
b1 !
b1 =
02
1*
0(
b100111011001110111101010010011 5
b100111011001110111101010010011 C
b1001011111100111100101000101011 4
b1001011111100111100101000101011 B
z6
bz 7
bz D
bz 8
bz E
b0 M
0N
b0 L
01
#155001
b10 !
b10 =
11
#156001
01
#157001
b11 !
b11 =
11
#158001
01
#159001
b100 !
b100 =
b11 8
b11 E
16
b0 7
b0 D
1N
b11 L
11
12
#160001
01
#161001
b1 !
b1 =
02
1#
0*
b11111000001010100100000011000010 5
b11111000001010100100000011000010 C
b1111000010111010000100001010011 4
b1111000010111010000100001010011 B
z6
bz 7
bz D
bz 8
bz E
0N
b0 L
01
#162001
b10 !
b10 =
11
#163001
01
#164001
b11 !
b11 =
11
#165001
01
#166001
b100 !
b100 =
b11 8
b11 E
16
b1111000000010000000000001000010 7
b1111000000010000000000001000010 D
b1111000000010000000000001000010 M
1N
b11 L
11
12
#167001
01
#168001
b1 !
b1 =
02
0#
1+
b1000100011110100101001110001010 5
b1000100011110100101001110001010 C
b10110111001000100100100011010101 4
b10110111001000100100100011010101 B
z6
bz 7
bz D
bz 8
bz E
b0 M
0N
b0 L
01
#169001
b10 !
b10 =
11
#170001
01
#171001
b11 !
b11 =
11
#172001
01
#173001
b100 !
b100 =
b11 8
b11 E
16
b11111111111011011100100010010010 7
b11111111111011011100100010010010 D
b11111111111011011100100010010010 M
1N
b11 L
11
12
#174001
01
#175001
b1 !
b1 =
02
0+
1"
b100010111100001010101000110101 5
b100010111100001010101000110101 C
b1111111001110001010111001001 4
b1111111001110001010111001001 B
z6
bz 7
bz D
bz 8
bz E
b0 M
0N
b0 L
01
#176001
b10 !
b10 =
11
#177001
01
#178001
b11 !
b11 =
11
#179001
01
#180001
b100 !
b100 =
b11 8
b11 E
16
b110010110101111011111111111110 7
b110010110101111011111111111110 D
b110010110101111011111111111110 M
1N
b11 L
11
12
#181001
01
#182001
b1 !
b1 =
02
b10111111110110001110001001101101 5
b10111111110110001110001001101101 C
b100101011110010111001000111101 4
b100101011110010111001000111101 B
z6
bz 7
bz D
bz 8
bz E
b0 M
0N
b0 L
01
#183001
b10 !
b10 =
11
#184001
01
#185001
b11 !
b11 =
11
#186001
01
#187001
b100 !
b100 =
b11 8
b11 E
16
b11100101010100100101010010101010 7
b11100101010100100101010010101010 D
b11100101010100100101010010101010 M
1N
b11 L
11
12
#188001
01
#189001
b1 !
b1 =
02
1+
0"
b100100001010010110011000101001 5
b100100001010010110011000101001 C
b1111100001001001001101011110000 4
b1111100001001001001101011110000 B
z6
bz 7
bz D
bz 8
bz E
b0 M
0N
b0 L
01
#190001
b10 !
b10 =
11
#191001
01
#192001
b11 !
b11 =
11
#193001
01
#194001
b100 !
b100 =
b11 8
b11 E
16
b1111100001001001001101 7
b1111100001001001001101 D
b1111100001001001001101 M
1N
b11 L
11
12
#195001
01
#196001
b1 !
b1 =
02
0+
1-
b100001101100000110011110110100 5
b100001101100000110011110110100 C
b110111101100010001011111110011 4
b110111101100010001011111110011 B
z6
bz 7
bz D
bz 8
bz E
b0 M
0N
b0 L
01
#197001
b10 !
b10 =
11
#198001
01
#199001
b11 !
b11 =
11
#200001
01
#201001
b100 !
b100 =
b11 8
b11 E
16
b10110000000001011000000111111 7
b10110000000001011000000111111 D
b10110000000001011000000111111 M
1N
b11 L
11
12
#202001
01
#203001
b1 !
b1 =
02
1*
0-
b11000001100101110101111111110101 5
b11000001100101110101111111110101 C
b1000001101111101100111110110000 4
b1000001101111101100111110110000 B
z6
bz 7
bz D
bz 8
bz E
b0 M
0N
b0 L
01
#204001
b10 !
b10 =
11
#205001
01
#206001
b11 !
b11 =
11
#207001
01
#208001
b100 !
b100 =
b11 8
b11 E
16
b1 7
b1 D
b1 M
1N
b11 L
11
12
#209001
01
#210001
b1 !
b1 =
02
1$
0*
b1011010111110010110000101010110 5
b1011010111110010110000101010110 C
b10111111001001100111001001100111 4
b10111111001001100111001001100111 B
z6
bz 7
bz D
bz 8
bz E
b0 M
0N
b0 L
01
#211001
b10 !
b10 =
11
#212001
01
#213001
b11 !
b11 =
11
#214001
01
#215001
b100 !
b100 =
b11 8
b11 E
16
b11111111111111110111001101110111 7
b11111111111111110111001101110111 D
b11111111111111110111001101110111 M
1N
b11 L
11
12
#216001
01
#217001
b1 !
b1 =
02
0$
1)
b10101100100111100100111100010011 5
b10101100100111100100111100010011 C
b11100111010011001110100000001 4
b11100111010011001110100000001 B
z6
bz 7
bz D
bz 8
bz E
b0 M
0N
b0 L
01
#218001
b10 !
b10 =
11
#219001
01
#220001
b11 !
b11 =
11
#221001
01
#222001
b100 !
b100 =
b11 8
b11 E
16
b0 7
b0 D
1N
b11 L
11
12
#223001
01
#224001
b1 !
b1 =
02
b10100100001110101110100100110000 5
b10100100001110101110100100110000 C
b10101100011100010110101100111011 4
b10101100011100010110101100111011 B
z6
bz 7
bz D
bz 8
bz E
0N
b0 L
01
#225001
b10 !
b10 =
11
#226001
01
#227001
b11 !
b11 =
11
#228001
01
#229001
b100 !
b100 =
b11 8
b11 E
16
b0 7
b0 D
1N
b11 L
11
12
#230001
01
#231001
b1 !
b1 =
02
1,
0)
b11110110101010111101101011110110 5
b11110110101010111101101011110110 C
b11100011000110101110110100111001 4
b11100011000110101110110100111001 B
z6
bz 7
bz D
bz 8
bz E
0N
b0 L
01
#232001
b10 !
b10 =
11
#233001
01
#234001
b11 !
b11 =
11
#235001
01
#236001
b100 !
b100 =
b11 8
b11 E
16
b1110001100 7
b1110001100 D
b1110001100 M
1N
b11 L
11
12
#237001
01
#238001
b1 !
b1 =
02
0,
1-
b11001111110110111011011010001000 5
b11001111110110111011011010001000 C
b1101011100001011000101011111101 4
b1101011100001011000101011111101 B
z6
bz 7
bz D
bz 8
bz E
b0 M
0N
b0 L
01
#239001
b10 !
b10 =
11
#240001
01
#241001
b11 !
b11 =
11
#242001
01
#243001
b100 !
b100 =
b11 8
b11 E
16
b10011011101010011101010001110101 7
b10011011101010011101010001110101 D
b10011011101010011101010001110101 M
1N
b11 L
11
12
#244001
01
#245001
b1 !
b1 =
02
1,
0-
b11010001101101110011001000010111 5
b11010001101101110011001000010111 C
b11101000101010101000110000000111 4
b11101000101010101000110000000111 B
z6
bz 7
bz D
bz 8
bz E
b0 M
0N
b0 L
01
#246001
b10 !
b10 =
11
#247001
01
#248001
b11 !
b11 =
11
#249001
01
#250001
b100 !
b100 =
b11 8
b11 E
16
b111010001 7
b111010001 D
b111010001 M
1N
b11 L
11
12
#251001
01
#252001
b1 !
b1 =
02
1+
0,
b10000101101110010111101100100110 5
b10000101101110010111101100100110 C
b1011110110111010011001110011 4
b1011110110111010011001110011 B
z6
bz 7
bz D
bz 8
bz E
b0 M
0N
b0 L
01
#253001
b10 !
b10 =
11
#254001
01
#255001
b11 !
b11 =
11
#256001
01
#257001
b100 !
b100 =
b11 8
b11 E
16
b1011110110111010011001 7
b1011110110111010011001 D
b1011110110111010011001 M
1N
b11 L
11
12
#258001
01
#259001
b1 !
b1 =
02
1#
0+
b1011111110010100111010111111001 5
b1011111110010100111010111111001 C
b10111000101101111000111110011111 4
b10111000101101111000111110011111 B
z6
bz 7
bz D
bz 8
bz E
b0 M
0N
b0 L
01
#260001
b10 !
b10 =
11
#261001
01
#262001
b11 !
b11 =
11
#263001
01
#264001
b100 !
b100 =
b11 8
b11 E
16
b11000100000100000010110011001 7
b11000100000100000010110011001 D
b11000100000100000010110011001 M
1N
b11 L
11
12
#265001
01
#266001
b1 !
b1 =
02
0#
1,
b1011001000100110101001000100011 5
b1011001000100110101001000100011 C
b10011001111001100101111100010110 4
b10011001111001100101111100010110 B
z6
bz 7
bz D
bz 8
bz E
b0 M
0N
b0 L
01
#267001
b10 !
b10 =
11
#268001
01
#269001
b11 !
b11 =
11
#270001
01
#271001
b100 !
b100 =
b11 8
b11 E
16
b10011001111001100101111100010 7
b10011001111001100101111100010 D
b10011001111001100101111100010 M
1N
b11 L
11
12
#272001
01
#273001
b1 !
b1 =
02
0,
1-
b11100011101011001001000111011010 5
b11100011101011001001000111011010 C
b11011010101111100110110000001101 4
b11011010101111100110110000001101 B
z6
bz 7
bz D
bz 8
bz E
b0 M
0N
b0 L
01
#274001
b10 !
b10 =
11
#275001
01
#276001
b11 !
b11 =
11
#277001
01
#278001
b100 !
b100 =
b11 8
b11 E
16
b11110111000100011101101000110011 7
b11110111000100011101101000110011 D
b11110111000100011101101000110011 M
1N
b11 L
11
12
#279001
01
#280001
b1 !
b1 =
02
1)
0-
b11101100011010010100111111101011 5
b11101100011010010100111111101011 C
b1010111101111100001111000000110 4
b1010111101111100001111000000110 B
z6
bz 7
bz D
bz 8
bz E
b0 M
0N
b0 L
01
#281001
b10 !
b10 =
11
#282001
01
#283001
b11 !
b11 =
11
#284001
01
#285001
b100 !
b100 =
b11 8
b11 E
16
b0 7
b0 D
1N
b11 L
11
12
#286001
01
