rtl/chip/core/exu_swc/exu_branch_swc.v
module exu_branch_swc (
    hclk                                        ,
    hrstn                                       ,
    cycle_cnt                                   ,
    dec_branch_en                               ,
    dec_beq                                     ,
    dec_bne                                     ,
    dec_blt                                     ,
    dec_bge                                     ,
    dec_bltu                                    ,
    dec_bgeu                                    ,
    dec_imm_type_b                              ,
    dec_rs1                                     ,
    dec_rs2                                     ,
    pc                                          ,
    pc_write                                    ,
    pc_wdata                                    ,
    flush                                       ,
    reg_rdata_1                                 ,
    reg_raddr_1                                 ,
    reg_ren_1                                   ,
    reg_rdata_2                                 ,
    reg_raddr_2                                 ,
    reg_ren_2                                   
);

// general signals
input                       hclk                ;
input                       hrstn               ;
// control signals
input           [3:0]       cycle_cnt           ;
inout           [1:0]       flush               ;
// signals from dec
input                       dec_branch_en       ;
input                       dec_beq             ;
input                       dec_bne             ;
input                       dec_blt             ;
input                       dec_bge             ;
input                       dec_bltu            ;
input                       dec_bgeu            ;
input           [12:0]      dec_imm_type_b      ;
input           [4:0]       dec_rs1             ;
input           [4:0]       dec_rs2             ; 
// PC signals
input           [31:0]      pc                  ;
inout                       pc_write            ;
inout           [31:0]      pc_wdata            ;
// regfile signals
input           [31:0]      reg_rdata_1         ;
inout           [4:0]       reg_raddr_1         ;
inout                       reg_ren_1           ;
input           [31:0]      reg_rdata_2         ;
inout           [4:0]       reg_raddr_2         ;
inout                       reg_ren_2           ;
// middle signals
reg             [4:0]       mid_reg_raddr_1     ;
reg                         mid_reg_ren_1       ;
reg             [4:0]       mid_reg_raddr_2     ;
reg                         mid_reg_ren_2       ;
reg                         mid_pc_write        ;
reg             [31:0]      mid_pc_wdata        ;
// SEXT values
wire            [31:0]      sext_imm_type_b     ;

assign reg_raddr_1 = mid_reg_ren_1 ? mid_reg_raddr_1  : 'z  ;
assign reg_ren_1   = mid_reg_ren_1 ? mid_reg_ren_1    : 'z  ;
assign reg_raddr_2 = mid_reg_ren_2 ? mid_reg_raddr_2  : 'z  ;
assign reg_ren_2   = mid_reg_ren_2 ? mid_reg_ren_2    : 'z  ;

assign sext_imm_type_b = {{19{dec_imm_type_b[11]}}, dec_imm_type_b};

always@(posedge hclk or negedge hrstn) begin
    if(!hrstn) begin
        mid_reg_raddr_1 <= 0;
        mid_reg_ren_1   <= 0;

        mid_reg_raddr_2 <= 0;
        mid_reg_ren_2   <= 0;
    end else if(dec_branch_en)begin
        if(cycle_cnt == 1) begin
            mid_reg_raddr_1 <= dec_rs1;
            mid_reg_ren_1   <= 1;

            mid_reg_raddr_2 <= dec_rs2;
            mid_reg_ren_2   <= 1;
        end else begin
            mid_reg_raddr_1 <= 0;
            mid_reg_ren_1   <= 0;

            mid_reg_raddr_2 <= 0;
            mid_reg_ren_2   <= 0;   
        end 
    end else begin
        mid_reg_raddr_1 <= 0;
        mid_reg_ren_1   <= 0;

        mid_reg_raddr_2 <= 0;
        mid_reg_ren_2   <= 0;
    end
end

wire [31:0] pc_real = pc - 8;
wire [31:0] pc_next = pc_real  + sext_imm_type_b;
wire        branch  = dec_beq  ? (reg_rdata_1 == reg_rdata_2) :
                      dec_bne  ? (reg_rdata_1 != reg_rdata_2) :
                      dec_blt  ? ($signed(reg_rdata_1) <  $signed(reg_rdata_2)) :
                      dec_bge  ? ($signed(reg_rdata_1) >= $signed(reg_rdata_2)) :
                      dec_bltu ? (reg_rdata_1 <  reg_rdata_2) :
                      dec_bgeu ? (reg_rdata_1 >= reg_rdata_2) :
                      0;

always@(posedge hclk or negedge hrstn) begin
    if(!hrstn) begin
        mid_pc_write <= 0;
        mid_pc_wdata <= 0;
    end else if(dec_branch_en) begin
        if(cycle_cnt == 3) begin
            if(branch) begin
                if(pc_next != pc_real + 4 && pc_next != pc_real + 8) begin
                    mid_pc_write <= 1;
                    mid_pc_wdata <= pc_next;
                end else begin
                    mid_pc_write <= 0;
                    mid_pc_wdata <= 0;
                end
            end else begin
                mid_pc_write <= 0;
                mid_pc_wdata <= 0;
            end
        end else if(cycle_cnt == 4) begin
            mid_pc_write <= mid_pc_write;
            mid_pc_wdata <= mid_pc_wdata;
        end else begin
            mid_pc_write <= 0;
            mid_pc_wdata <= 0;
        end
    end else begin
        mid_pc_write <= 0;
        mid_pc_wdata <= 0;
    end
end

assign pc_write = dec_branch_en ? mid_pc_write : 'z;
assign pc_wdata = dec_branch_en ? mid_pc_wdata : 'z;

localparam FLUSH_DISABLE = 0, FLUSH_CYCLE_1 = 1, FLUSH_CYCLE_2 = 2;
reg [1:0] mid_flush;

always@(posedge hclk or negedge hrstn) begin
    if(!hrstn) begin
        mid_flush <= FLUSH_DISABLE;
    end else if(dec_branch_en) begin
        if(cycle_cnt == 3)begin
            if(branch) begin
                if(pc_next == pc_real + 4) begin
                    mid_flush <= FLUSH_DISABLE;
                end else if(pc_next == pc_real + 8) begin
                    mid_flush <= FLUSH_CYCLE_1;
                end else begin
                    mid_flush <= FLUSH_CYCLE_2;
                end
            end else begin
                mid_flush <= FLUSH_DISABLE;
            end
        end else if(cycle_cnt == 4) begin
            mid_flush <= mid_flush;
        end else begin
            mid_flush <= FLUSH_DISABLE;
        end
    end else begin
        mid_flush <= FLUSH_DISABLE;
    end
end

assign flush = dec_branch_en ? mid_flush : 'z;

endmodule

rtl/chip/core/exu_swc/exu_branch_swc/exu_branch_tb.v
module exu_branch_tb;

// general signals
reg           		  hclk                ;
reg           		  hrstn               ;
// control signals
reg           [3:0]       cycle_cnt           ;
reg           [1:0]       flush               ;
// signals from dec
reg                       dec_branch_en       ;
reg                       dec_beq             ;
reg                       dec_bne             ;
reg                       dec_blt             ;
reg                       dec_bge             ;
reg                       dec_bltu            ;
reg                       dec_bgeu            ;
reg           [12:0]      dec_imm_type_b      ;
reg           [4:0]       dec_rs1             ;
reg           [4:0]       dec_rs2             ; 
// PC signals
reg           [31:0]      pc                  ;
reg                       pc_write            ;
reg           [31:0]      pc_wdata            ;
// regfile signals
reg           [31:0]      reg_rdata_1         ;
reg           [4:0]       reg_raddr_1         ;
reg                       reg_ren_1           ;
reg           [31:0]      reg_rdata_2         ;
reg           [4:0]       reg_raddr_2         ;
reg                       reg_ren_2           ;

exu_branch_swc exu_branch_inst (
  .hclk               (hclk                             ),
  .hrstn              (hrstn                            ),
  .cycle_cnt	      (cycle_cnt			),
  .dec_branch_en      (dec_branch_en			),
  .dec_beq	      (dec_beq				),
  .dec_bne	      (dec_bne				),
  .dec_blt	      (dec_blt				),
  .dec_bge	      (dec_bge				),
  .dec_bltu	      (dec_bltu				),
  .dec_bgeu	      (dec_bgeu 			),
  .dec_imm_type_b     (dec_imm_type_b			),
  .dec_rs1	      (dec_rs1				),
  .dec_rs2	      (dec_rs2				),
  .pc	      	      (pc				),
  .pc_write	      (pc_write				),
  .pc_wdata	      (pc_wdata				),
  .flush	      (flush				),
  .reg_rdata_1	      (reg_rdata_1			),
  .reg_raddr_1	      (reg_raddr_1			),
  .reg_ren_1	      (reg_ren_1			),
  .reg_rdata_2	      (reg_rdata_2			),
  .reg_raddr_2	      (reg_raddr_2			),
  .reg_ren_2	      (reg_ren_2			)
);

always #5  hclk = !hclk ;


// copied from the core top
always@(posedge hclk) begin
  if(!hrstn)
      cycle_cnt <= 0;
  else if(cycle_cnt == 4)
      cycle_cnt <= 1;
  else
      cycle_cnt <= cycle_cnt + 1;
end

// copied from ifu_swc.v
always@(posedge hclk) begin
    if(!hrstn) begin
        pc <= 0;
    end else if(cycle_cnt == 4) begin
        if(pc_write) begin
            pc <= pc_wdata;
        end else begin
            pc <= pc + 4;
        end
    end else begin
        pc <= pc;
    end
end

initial begin
  dec_branch_en = 1;
  dec_bne = 0;
  dec_beq = 0;
  dec_blt = 1;
  dec_bltu = 0;
  dec_bgeu = 0;
  dec_bge = 0;
  dec_rs1 = 'h0;
  dec_rs2 = 'h0;
  reg_rdata_1 = 'h00000000;
  reg_rdata_2 = 'h00004444;
  reg_raddr_1 = 'h0;
  reg_raddr_2 = 'h0;
  reg_ren_1 = 1;
  reg_ren_2 = 1;
  pc = 'h00000020;
  hrstn = 0;
  dec_imm_type_b = 5;
  #20;
  hrstn = 1;
  #20;
  
  #10000;
  $finish;
end

initial begin
  $dumpfile("exu_branch_tb.vcd");
  $dumpvars(0, exu_branch_tb);
end

endmodule

rtl/chip/core/exu_swc/exu_branch_tb.vcd
$version Generated by VerilatedVcd $end
$timescale 1ps $end
 $scope module TOP $end
  $scope module exu_branch_tb $end
   $var wire 1 ? hclk $end
   $var wire 1 # hrstn $end
   $var wire 4 @ cycle_cnt [3:0] $end
   $var wire 2 1 flush [1:0] $end
   $var wire 1 $ dec_branch_en $end
   $var wire 1 % dec_beq $end
   $var wire 1 & dec_bne $end
   $var wire 1 ' dec_blt $end
   $var wire 1 ( dec_bge $end
   $var wire 1 ) dec_bltu $end
   $var wire 1 * dec_bgeu $end
   $var wire 13 + dec_imm_type_b [12:0] $end
   $var wire 5 , dec_rs1 [4:0] $end
   $var wire 5 - dec_rs2 [4:0] $end
   $var wire 32 A pc [31:0] $end
   $var wire 1 2 pc_write $end
   $var wire 32 3 pc_wdata [31:0] $end
   $var wire 32 . reg_rdata_1 [31:0] $end
   $var wire 5 4 reg_raddr_1 [4:0] $end
   $var wire 1 5 reg_ren_1 $end
   $var wire 32 / reg_rdata_2 [31:0] $end
   $var wire 5 6 reg_raddr_2 [4:0] $end
   $var wire 1 7 reg_ren_2 $end
   $scope module exu_branch_inst $end
    $var wire 1 ? hclk $end
    $var wire 1 # hrstn $end
    $var wire 4 @ cycle_cnt [3:0] $end
    $var wire 2 1 flush [1:0] $end
    $var wire 1 $ dec_branch_en $end
    $var wire 1 % dec_beq $end
    $var wire 1 & dec_bne $end
    $var wire 1 ' dec_blt $end
    $var wire 1 ( dec_bge $end
    $var wire 1 ) dec_bltu $end
    $var wire 1 * dec_bgeu $end
    $var wire 13 + dec_imm_type_b [12:0] $end
    $var wire 5 , dec_rs1 [4:0] $end
    $var wire 5 - dec_rs2 [4:0] $end
    $var wire 32 A pc [31:0] $end
    $var wire 1 2 pc_write $end
    $var wire 32 3 pc_wdata [31:0] $end
    $var wire 32 . reg_rdata_1 [31:0] $end
    $var wire 5 4 reg_raddr_1 [4:0] $end
    $var wire 1 5 reg_ren_1 $end
    $var wire 32 / reg_rdata_2 [31:0] $end
    $var wire 5 6 reg_raddr_2 [4:0] $end
    $var wire 1 7 reg_ren_2 $end
    $var wire 5 8 mid_reg_raddr_1 [4:0] $end
    $var wire 1 9 mid_reg_ren_1 $end
    $var wire 5 : mid_reg_raddr_2 [4:0] $end
    $var wire 1 ; mid_reg_ren_2 $end
    $var wire 1 < mid_pc_write $end
    $var wire 32 = mid_pc_wdata [31:0] $end
    $var wire 32 0 sext_imm_type_b [31:0] $end
    $var wire 32 B pc_real [31:0] $end
    $var wire 32 C pc_next [31:0] $end
    $var wire 1 D branch $end
    $var wire 32 E FLUSH_DISABLE [31:0] $end
    $var wire 32 F FLUSH_CYCLE_1 [31:0] $end
    $var wire 32 G FLUSH_CYCLE_2 [31:0] $end
    $var wire 2 > mid_flush [1:0] $end
   $upscope $end
  $upscope $end
 $upscope $end
$enddefinitions $end


#0
0#
1$
0%
0&
1'
0(
0)
0*
b0000000000101 +
b00000 ,
b00000 -
b00000000000000000000000000000000 .
b00000000000000000100010001000100 /
b00000000000000000000000000000101 0
b00 1
02
b00000000000000000000000000000000 3
b00000 4
15
b00000 6
17
b00000 8
09
b00000 :
0;
0<
b00000000000000000000000000000000 =
b00 >
0?
b0000 @
b00000000000000000000000000100000 A
b00000000000000000000000000011100 B
b00000000000000000000000000100001 C
1D
b00000000000000000000000000000000 E
b00000000000000000000000000000001 F
b00000000000000000000000000000010 G
#5
1?
b00000000000000000000000000000000 A
b11111111111111111111111111111100 B
b00000000000000000000000000000001 C
#10
0?
#15
1?
#20
1#
0?
#25
1?
b0001 @
#30
0?
#35
19
1;
1?
b0010 @
#40
0?
#45
09
0;
1?
b0011 @
#50
0?
#55
b10 1
12
b00000000000000000000000000000001 3
1<
b00000000000000000000000000000001 =
b10 >
1?
b0100 @
#60
0?
#65
1?
b0001 @
b00000000000000000000000000000001 A
b11111111111111111111111111111101 B
b00000000000000000000000000000010 C
#70
0?
#75
b00 1
02
b00000000000000000000000000000000 3
19
1;
0<
b00000000000000000000000000000000 =
b00 >
1?
b0010 @
#80
0?
#85
09
0;
1?
b0011 @
#90
0?
#95
b10 1
12
b00000000000000000000000000000010 3
1<
b00000000000000000000000000000010 =
b10 >
1?
b0100 @
#100
0?
#105
1?
b0001 @
b00000000000000000000000000000010 A
b11111111111111111111111111111110 B
b00000000000000000000000000000011 C
#110
0?
#115
b00 1
02
b00000000000000000000000000000000 3
19
1;
0<
b00000000000000000000000000000000 =
b00 >
1?
b0010 @
#120
0?
#125
09
0;
1?
b0011 @
#130
0?
#135
b10 1
12
b00000000000000000000000000000011 3
1<
b00000000000000000000000000000011 =
b10 >
1?
b0100 @
#140
0?
#145
1?
b0001 @
b00000000000000000000000000000011 A
b11111111111111111111111111111111 B
b00000000000000000000000000000100 C
#150
0?
#155
b00 1
02
b00000000000000000000000000000000 3
19
1;
0<
b00000000000000000000000000000000 =
b00 >
1?
b0010 @
#160
0?
#165
09
0;
1?
b0011 @
#170
0?
#175
b10 1
12
b00000000000000000000000000000100 3
1<
b00000000000000000000000000000100 =
b10 >
1?
b0100 @
#180
0?
#185
1?
b0001 @
b00000000000000000000000000000100 A
b00000000000000000000000000000000 B
b00000000000000000000000000000101 C
#190
0?
#195
b00 1
02
b00000000000000000000000000000000 3
19
1;
0<
b00000000000000000000000000000000 =
b00 >
1?
b0010 @
#200
0?
#205
09
0;
1?
b0011 @
#210
0?
#215
b10 1
12
b00000000000000000000000000000101 3
1<
b00000000000000000000000000000101 =
b10 >
1?
b0100 @
#220
0?
#225
1?
b0001 @
b00000000000000000000000000000101 A
b00000000000000000000000000000001 B
b00000000000000000000000000000110 C
#230
0?
#235
b00 1
02
b00000000000000000000000000000000 3
19
1;
0<
b00000000000000000000000000000000 =
b00 >
1?
b0010 @
#240
0?
#245
09
0;
1?
b0011 @
#250
0?
#255
b10 1
12
b00000000000000000000000000000110 3
1<
b00000000000000000000000000000110 =
b10 >
1?
b0100 @
#260
0?
#265
1?
b0001 @
b00000000000000000000000000000110 A
b00000000000000000000000000000010 B
b00000000000000000000000000000111 C
#270
0?
#275
b00 1
02
b00000000000000000000000000000000 3
19
1;
0<
b00000000000000000000000000000000 =
b00 >
1?
b0010 @
#280
0?
#285
09
0;
1?
b0011 @
#290
0?
#295
b10 1
12
b00000000000000000000000000000111 3
1<
b00000000000000000000000000000111 =
b10 >
1?
b0100 @
#300
0?
#305
1?
b0001 @
b00000000000000000000000000000111 A
b00000000000000000000000000000011 B
b00000000000000000000000000001000 C
#310
0?
#315
b00 1
02
b00000000000000000000000000000000 3
19
1;
0<
b00000000000000000000000000000000 =
b00 >
1?
b0010 @
#320
0?
#325
09
0;
1?
b0011 @
#330
0?
#335
b10 1
12
b00000000000000000000000000001000 3
1<
b00000000000000000000000000001000 =
b10 >
1?
b0100 @
#340
0?
#345
1?
b0001 @
b00000000000000000000000000001000 A
b00000000000000000000000000000100 B
b00000000000000000000000000001001 C
#350
0?
#355
b00 1
02
b00000000000000000000000000000000 3
19
1;
0<
b00000000000000000000000000000000 =
b00 >
1?
b0010 @
#360
0?
#365
09
0;
1?
b0011 @
#370
0?
#375
b10 1
12
b00000000000000000000000000001001 3
1<
b00000000000000000000000000001001 =
b10 >
1?
b0100 @
#380
0?
#385
1?
b0001 @
b00000000000000000000000000001001 A
b00000000000000000000000000000101 B
b00000000000000000000000000001010 C
#390
0?
#395
b00 1
02
b00000000000000000000000000000000 3
19
1;
0<
b00000000000000000000000000000000 =
b00 >
1?
b0010 @
#400
0?
#405
09
0;
1?
b0011 @
#410
0?
#415
b10 1
12
b00000000000000000000000000001010 3
1<
b00000000000000000000000000001010 =
b10 >
1?
b0100 @
#420
0?
#425
1?
b0001 @
b00000000000000000000000000001010 A
b00000000000000000000000000000110 B
b00000000000000000000000000001011 C
#430
0?
#435
b00 1
02
b00000000000000000000000000000000 3
19
1;
0<
b00000000000000000000000000000000 =
b00 >
1?
b0010 @
#440
0?
#445
09
0;
1?
b0011 @
#450
0?
#455
b10 1
12
b00000000000000000000000000001011 3
1<
b00000000000000000000000000001011 =
b10 >
1?
b0100 @
#460
0?
#465
1?
b0001 @
b00000000000000000000000000001011 A
b00000000000000000000000000000111 B
b00000000000000000000000000001100 C
#470
0?
#475
b00 1
02
b00000000000000000000000000000000 3
19
1;
0<
b00000000000000000000000000000000 =
b00 >
1?
b0010 @
#480
0?
#485
09
0;
1?
b0011 @
#490
0?
#495
b10 1
12
b00000000000000000000000000001100 3
1<
b00000000000000000000000000001100 =
b10 >
1?
b0100 @
#500
0?
#505
1?
b0001 @
b00000000000000000000000000001100 A
b00000000000000000000000000001000 B
b00000000000000000000000000001101 C
#510
0?
#515
b00 1
02
b00000000000000000000000000000000 3
19
1;
0<
b00000000000000000000000000000000 =
b00 >
1?
b0010 @
#520
0?
#525
09
0;
1?
b0011 @
#530
0?
#535
b10 1
12
b00000000000000000000000000001101 3
1<
b00000000000000000000000000001101 =
b10 >
1?
b0100 @
#540
0?
#545
1?
b0001 @
b00000000000000000000000000001101 A
b00000000000000000000000000001001 B
b00000000000000000000000000001110 C
#550
0?
#555
b00 1
02
b00000000000000000000000000000000 3
19
1;
0<
b00000000000000000000000000000000 =
b00 >
1?
b0010 @
#560
0?
#565
09
0;
1?
b0011 @
#570
0?
#575
b10 1
12
b00000000000000000000000000001110 3
1<
b00000000000000000000000000001110 =
b10 >
1?
b0100 @
#580
0?
#585
1?
b0001 @
b00000000000000000000000000001110 A
b00000000000000000000000000001010 B
b00000000000000000000000000001111 C
#590
0?
#595
b00 1
02
b00000000000000000000000000000000 3
19
1;
0<
b00000000000000000000000000000000 =
b00 >
1?
b0010 @
#600
0?
#605
09
0;
1?
b0011 @
#610
0?
#615
b10 1
12
b00000000000000000000000000001111 3
1<
b00000000000000000000000000001111 =
b10 >
1?
b0100 @
#620
0?
#625
1?
b0001 @
b00000000000000000000000000001111 A
b00000000000000000000000000001011 B
b00000000000000000000000000010000 C
#630
0?
#635
b00 1
02
b00000000000000000000000000000000 3
19
1;
0<
b00000000000000000000000000000000 =
b00 >
1?
b0010 @
#640
0?
#645
09
0;
1?
b0011 @
#650
0?
#655
b10 1
12
b00000000000000000000000000010000 3
1<
b00000000000000000000000000010000 =
b10 >
1?
b0100 @
#660
0?
#665
1?
b0001 @
b00000000000000000000000000010000 A
b00000000000000000000000000001100 B
b00000000000000000000000000010001 C
#670
0?
#675
b00 1
02
b00000000000000000000000000000000 3
19
1;
0<
b00000000000000000000000000000000 =
b00 >
1?
b0010 @
#680
0?
#685
09
0;
1?
b0011 @
#690
0?
#695
b10 1
12
b00000000000000000000000000010001 3
1<
b00000000000000000000000000010001 =
b10 >
1?
b0100 @
#700
0?
#705
1?
b0001 @
b00000000000000000000000000010001 A
b00000000000000000000000000001101 B
b00000000000000000000000000010010 C
#710
0?
#715
b00 1
02
b00000000000000000000000000000000 3
19
1;
0<
b00000000000000000000000000000000 =
b00 >
1?
b0010 @
#720
0?
#725
09
0;
1?
b0011 @
#730
0?
#735
b10 1
12
b00000000000000000000000000010010 3
1<
b00000000000000000000000000010010 =
b10 >
1?
b0100 @
#740
0?
#745
1?
b0001 @
b00000000000000000000000000010010 A
b00000000000000000000000000001110 B
b00000000000000000000000000010011 C
#750
0?
#755
b00 1
02
b00000000000000000000000000000000 3
19
1;
0<
b00000000000000000000000000000000 =
b00 >
1?
b0010 @
#760
0?
#765
09
0;
1?
b0011 @
#770
0?
#775
b10 1
12
b00000000000000000000000000010011 3
1<
b00000000000000000000000000010011 =
b10 >
1?
b0100 @
#780
0?
#785
1?
b0001 @
b00000000000000000000000000010011 A
b00000000000000000000000000001111 B
b00000000000000000000000000010100 C
#790
0?
#795
b00 1
02
b00000000000000000000000000000000 3
19
1;
0<
b00000000000000000000000000000000 =
b00 >
1?
b0010 @
#800
0?
#805
09
0;
1?
b0011 @
#810
0?
#815
b10 1
12
b00000000000000000000000000010100 3
1<
b00000000000000000000000000010100 =
b10 >
1?
b0100 @
#820
0?
#825
1?
b0001 @
b00000000000000000000000000010100 A
b00000000000000000000000000010000 B
b00000000000000000000000000010101 C
#830
0?
#835
b00 1
02
b00000000000000000000000000000000 3
19
1;
0<
b00000000000000000000000000000000 =
b00 >
1?
b0010 @
#840
0?
#845
09
0;
1?
b0011 @
#850
0?
#855
b10 1
12
b00000000000000000000000000010101 3
1<
b00000000000000000000000000010101 =
b10 >
1?
b0100 @
#860
0?
#865
1?
b0001 @
b00000000000000000000000000010101 A
b00000000000000000000000000010001 B
b00000000000000000000000000010110 C
#870
0?
#875
b00 1
02
b00000000000000000000000000000000 3
19
1;
0<
b00000000000000000000000000000000 =
b00 >
1?
b0010 @
#880
0?
#885
09
0;
1?
b0011 @
#890
0?
#895
b10 1
12
b00000000000000000000000000010110 3
1<
b00000000000000000000000000010110 =
b10 >
1?
b0100 @
#900
0?
#905
1?
b0001 @
b00000000000000000000000000010110 A
b00000000000000000000000000010010 B
b00000000000000000000000000010111 C
#910
0?
#915
b00 1
02
b00000000000000000000000000000000 3
19
1;
0<
b00000000000000000000000000000000 =
b00 >
1?
b0010 @
#920
0?
#925
09
0;
1?
b0011 @
#930
0?
#935
b10 1
12
b00000000000000000000000000010111 3
1<
b00000000000000000000000000010111 =
b10 >
1?
b0100 @
#940
0?
#945
1?
b0001 @
b00000000000000000000000000010111 A
b00000000000000000000000000010011 B
b00000000000000000000000000011000 C
#950
0?
#955
b00 1
02
b00000000000000000000000000000000 3
19
1;
0<
b00000000000000000000000000000000 =
b00 >
1?
b0010 @
#960
0?
#965
09
0;
1?
b0011 @
#970
0?
#975
b10 1
12
b00000000000000000000000000011000 3
1<
b00000000000000000000000000011000 =
b10 >
1?
b0100 @
#980
0?
#985
1?
b0001 @
b00000000000000000000000000011000 A
b00000000000000000000000000010100 B
b00000000000000000000000000011001 C
#990
0?
#995
b00 1
02
b00000000000000000000000000000000 3
19
1;
0<
b00000000000000000000000000000000 =
b00 >
1?
b0010 @
#1000
0?
#1005
09
0;
1?
b0011 @
#1010
0?
#1015
b10 1
12
b00000000000000000000000000011001 3
1<
b00000000000000000000000000011001 =
b10 >
1?
b0100 @
#1020
0?
#1025
1?
b0001 @
b00000000000000000000000000011001 A
b00000000000000000000000000010101 B
b00000000000000000000000000011010 C
#1030
0?
#1035
b00 1
02
b00000000000000000000000000000000 3
19
1;
0<
b00000000000000000000000000000000 =
b00 >
1?
b0010 @
#1040
0?
#1045
09
0;
1?
b0011 @
#1050
0?
#1055
b10 1
12
b00000000000000000000000000011010 3
1<
b00000000000000000000000000011010 =
b10 >
1?
b0100 @
#1060
0?
#1065
1?
b0001 @
b00000000000000000000000000011010 A
b00000000000000000000000000010110 B
b00000000000000000000000000011011 C
#1070
0?
#1075
b00 1
02
b00000000000000000000000000000000 3
19
1;
0<
b00000000000000000000000000000000 =
b00 >
1?
b0010 @
#1080
0?
#1085
09
0;
1?
b0011 @
#1090
0?
#1095
b10 1
12
b00000000000000000000000000011011 3
1<
b00000000000000000000000000011011 =
b10 >
1?
b0100 @
#1100
0?
#1105
1?
b0001 @
b00000000000000000000000000011011 A
b00000000000000000000000000010111 B
b00000000000000000000000000011100 C
#1110
0?
#1115
b00 1
02
b00000000000000000000000000000000 3
19
1;
0<
b00000000000000000000000000000000 =
b00 >
1?
b0010 @
#1120
0?
#1125
09
0;
1?
b0011 @
#1130
0?
#1135
b10 1
12
b00000000000000000000000000011100 3
1<
b00000000000000000000000000011100 =
b10 >
1?
b0100 @
#1140
0?
#1145
1?
b0001 @
b00000000000000000000000000011100 A
b00000000000000000000000000011000 B
b00000000000000000000000000011101 C
#1150
0?
#1155
b00 1
02
b00000000000000000000000000000000 3
19
1;
0<
b00000000000000000000000000000000 =
b00 >
1?
b0010 @
#1160
0?
#1165
09
0;
1?
b0011 @
#1170
0?
#1175
b10 1
12
b00000000000000000000000000011101 3
1<
b00000000000000000000000000011101 =
b10 >
1?
b0100 @
#1180
0?
#1185
1?
b0001 @
b00000000000000000000000000011101 A
b00000000000000000000000000011001 B
b00000000000000000000000000011110 C
#1190
0?
#1195
b00 1
02
b00000000000000000000000000000000 3
19
1;
0<
b00000000000000000000000000000000 =
b00 >
1?
b0010 @
#1200
0?
#1205
09
0;
1?
b0011 @
#1210
0?
#1215
b10 1
12
b00000000000000000000000000011110 3
1<
b00000000000000000000000000011110 =
b10 >
1?
b0100 @
#1220
0?
#1225
1?
b0001 @
b00000000000000000000000000011110 A
b00000000000000000000000000011010 B
b00000000000000000000000000011111 C
#1230
0?
#1235
b00 1
02
b00000000000000000000000000000000 3
19
1;
0<
b00000000000000000000000000000000 =
b00 >
1?
b0010 @
#1240
0?
#1245
09
0;
1?
b0011 @
#1250
0?
#1255
b10 1
12
b00000000000000000000000000011111 3
1<
b00000000000000000000000000011111 =
b10 >
1?
b0100 @
#1260
0?
#1265
1?
b0001 @
b00000000000000000000000000011111 A
b00000000000000000000000000011011 B
b00000000000000000000000000100000 C
#1270
0?
#1275
b00 1
02
b00000000000000000000000000000000 3
19
1;
0<
b00000000000000000000000000000000 =
b00 >
1?
b0010 @
#1280
0?
#1285
09
0;
1?
b0011 @
#1290
0?
#1295
b10 1
12
b00000000000000000000000000100000 3
1<
b00000000000000000000000000100000 =
b10 >
1?
b0100 @
#1300
0?
#1305
1?
b0001 @
b00000000000000000000000000100000 A
b00000000000000000000000000011100 B
b00000000000000000000000000100001 C
#1310
0?
#1315
b00 1
02
b00000000000000000000000000000000 3
19
1;
0<
b00000000000000000000000000000000 =
b00 >
1?
b0010 @
#1320
0?
#1325
09
0;
1?
b0011 @
#1330
0?
#1335
b10 1
12
b00000000000000000000000000100001 3
1<
b00000000000000000000000000100001 =
b10 >
1?
b0100 @
#1340
0?
#1345
1?
b0001 @
b00000000000000000000000000100001 A
b00000000000000000000000000011101 B
b00000000000000000000000000100010 C
#1350
0?
#1355
b00 1
02
b00000000000000000000000000000000 3
19
1;
0<
b00000000000000000000000000000000 =
b00 >
1?
b0010 @
#1360
0?
#1365
09
0;
1?
b0011 @
#1370
0?
#1375
b10 1
12
b00000000000000000000000000100010 3
1<
b00000000000000000000000000100010 =
b10 >
1?
b0100 @
#1380
0?
#1385
1?
b0001 @
b00000000000000000000000000100010 A
b00000000000000000000000000011110 B
b00000000000000000000000000100011 C
#1390
0?
#1395
b00 1
02
b00000000000000000000000000000000 3
19
1;
0<
b00000000000000000000000000000000 =
b00 >
1?
b0010 @
#1400
0?
#1405
09
0;
1?
b0011 @
#1410
0?
#1415
b10 1
12
b00000000000000000000000000100011 3
1<
b00000000000000000000000000100011 =
b10 >
1?
b0100 @
#1420
0?
#1425
1?
b0001 @
b00000000000000000000000000100011 A
b00000000000000000000000000011111 B
b00000000000000000000000000100100 C
#1430
0?
#1435
b00 1
02
b00000000000000000000000000000000 3
19
1;
0<
b00000000000000000000000000000000 =
b00 >
1?
b0010 @
#1440
0?
#1445
09
0;
1?
b0011 @
#1450
0?
#1455
b10 1
12
b00000000000000000000000000100100 3
1<
b00000000000000000000000000100100 =
b10 >
1?
b0100 @
#1460
0?
#1465
1?
b0001 @
b00000000000000000000000000100100 A
b00000000000000000000000000100000 B
b00000000000000000000000000100101 C
#1470
0?
#1475
b00 1
02
b00000000000000000000000000000000 3
19
1;
0<
b00000000000000000000000000000000 =
b00 >
1?
b0010 @
#1480
0?
#1485
09
0;
1?
b0011 @
#1490
0?
#1495
b10 1
12
b00000000000000000000000000100101 3
1<
b00000000000000000000000000100101 =
b10 >
1?
b0100 @
#1500
0?
#1505
1?
b0001 @
b00000000000000000000000000100101 A
b00000000000000000000000000100001 B
b00000000000000000000000000100110 C
#1510
0?
#1515
b00 1
02
b00000000000000000000000000000000 3
19
1;
0<
b00000000000000000000000000000000 =
b00 >
1?
b0010 @
#1520
0?
#1525
09
0;
1?
b0011 @
#1530
0?
#1535
b10 1
12
b00000000000000000000000000100110 3
1<
b00000000000000000000000000100110 =
b10 >
1?
b0100 @
#1540
0?
#1545
1?
b0001 @
b00000000000000000000000000100110 A
b00000000000000000000000000100010 B
b00000000000000000000000000100111 C
#1550
0?
#1555
b00 1
02
b00000000000000000000000000000000 3
19
1;
0<
b00000000000000000000000000000000 =
b00 >
1?
b0010 @
#1560
0?
#1565
09
0;
1?
b0011 @
#1570
0?
#1575
b10 1
12
b00000000000000000000000000100111 3
1<
b00000000000000000000000000100111 =
b10 >
1?
b0100 @
#1580
0?
#1585
1?
b0001 @
b00000000000000000000000000100111 A
b00000000000000000000000000100011 B
b00000000000000000000000000101000 C
#1590
0?
#1595
b00 1
02
b00000000000000000000000000000000 3
19
1;
0<
b00000000000000000000000000000000 =
b00 >
1?
b0010 @
#1600
0?
#1605
09
0;
1?
b0011 @
#1610
0?
#1615
b10 1
12
b00000000000000000000000000101000 3
1<
b00000000000000000000000000101000 =
b10 >
1?
b0100 @
#1620
0?
#1625
1?
b0001 @
b00000000000000000000000000101000 A
b00000000000000000000000000100100 B
b00000000000000000000000000101001 C
#1630
0?
#1635
b00 1
02
b00000000000000000000000000000000 3
19
1;
0<
b00000000000000000000000000000000 =
b00 >
1?
b0010 @
#1640
0?
#1645
09
0;
1?
b0011 @
#1650
0?
#1655
b10 1
12
b00000000000000000000000000101001 3
1<
b00000000000000000000000000101001 =
b10 >
1?
b0100 @
#1660
0?
#1665
1?
b0001 @
b00000000000000000000000000101001 A
b00000000000000000000000000100101 B
b00000000000000000000000000101010 C
#1670
0?
