rtl/chip/core/exu_swc/exu_load_swc.v
module exu_load_swc (
    hclk                                        ,
    hrstn                                       ,
    cycle_cnt                                   ,
    ifu_dec_stall                               ,
    dec_load_en                                 ,
    dec_lb                                      ,
    dec_lh                                      ,
    dec_lw                                      ,
    dec_lbu                                     ,
    dec_lhu                                     ,
    dec_imm_type_i                              ,
    dec_rd                                      ,
    dec_rs1                                     ,
    exu_load_rd                                 ,
    exu_load_base_addr                          ,
    exu_load_offset                             ,
    exu_load_sext                               ,
    exu_load_size                               ,
    exu_load_en                                 ,
    reg_raddr_1                                 ,
    reg_ren_1                                   ,
    reg_rdata_1                                 
);

// general signals
input                       hclk                ;
input                       hrstn               ;
// control signals
input           [3:0]       cycle_cnt           ;
output                      ifu_dec_stall       ;
// signals from dec 
input                       dec_load_en         ;
input                       dec_lb              ;
input                       dec_lh              ;
input                       dec_lw              ;
input                       dec_lbu             ;
input                       dec_lhu             ;
input           [11:0]      dec_imm_type_i      ;
input           [4:0]       dec_rd              ;
input           [4:0]       dec_rs1             ;
// signals to mau
output reg      [4:0]       exu_load_rd         ;
output reg      [31:0]      exu_load_base_addr  ;
output reg      [31:0]      exu_load_offset     ;
output reg                  exu_load_sext       ;
output reg      [1:0]       exu_load_size       ;
output reg                  exu_load_en         ;
// regfile signals
inout           [4:0]       reg_raddr_1         ;
inout                       reg_ren_1           ;
input           [31:0]      reg_rdata_1         ;
// middle signals
reg             [4:0]       mid_reg_raddr_1     ;
reg                         mid_reg_ren_1       ;

assign reg_raddr_1 = mid_reg_ren_1 ? mid_reg_raddr_1  : 'z  ;
assign reg_ren_1   = mid_reg_ren_1 ? mid_reg_ren_1    : 'z  ;

// load the base address
always@(posedge hclk or negedge hrstn) begin
    if(!hrstn) begin
        mid_reg_raddr_1 <= 0;
        mid_reg_ren_1   <= 0;
    end else if(dec_load_en)begin
        if(cycle_cnt == 1) begin
            mid_reg_raddr_1 <= dec_rs1;
            mid_reg_ren_1   <= 1;
        end else begin
            mid_reg_raddr_1 <= 0;
            mid_reg_ren_1   <= 0;
        end
    end else begin
        mid_reg_raddr_1 <= 0;
        mid_reg_ren_1   <= 0;
    end
end

// generate the signals to the mau
reg      [4:0]       exu_load_rd_buff           ;
reg      [31:0]      exu_load_base_addr_buff    ;
reg      [31:0]      exu_load_offset_buff       ;
reg                  exu_load_sext_buff         ;
reg      [1:0]       exu_load_size_buff         ;
reg                  exu_load_en_buff           ;
localparam LOAD_IDLE = 0, LOAD_BTYE = 1, LOAD_HALFWORD = 2, LOAD_WORD = 3;

always@(posedge hclk or negedge hrstn) begin
    if(!hrstn) begin
        exu_load_rd_buff        <= 0;
        exu_load_base_addr_buff <= 0;
        exu_load_offset_buff    <= 0;
        exu_load_sext_buff      <= 0;
        exu_load_size_buff      <= LOAD_IDLE;
        exu_load_en_buff        <= 0;
    end else if(dec_load_en)begin
        if(cycle_cnt == 3)begin
            exu_load_rd_buff        <=   dec_rd;
            exu_load_base_addr_buff <=   reg_rdata_1;
            exu_load_offset_buff    <=   {{20{dec_imm_type_i[11]}}, dec_imm_type_i};
            exu_load_sext_buff      <=   dec_lb | dec_lh | dec_lw;
            exu_load_size_buff      <=   (dec_lb | dec_lbu) ? LOAD_BTYE      :
                                         (dec_lh | dec_lhu) ? LOAD_HALFWORD  :
                                         (dec_lw)           ? LOAD_WORD      :
                                         LOAD_IDLE                           ;
            exu_load_en_buff        <=   1;
        end else if(cycle_cnt == 4)begin
            exu_load_rd_buff        <= exu_load_rd_buff       ;
            exu_load_base_addr_buff <= exu_load_base_addr_buff;
            exu_load_offset_buff    <= exu_load_offset_buff   ;
            exu_load_sext_buff      <= exu_load_sext_buff     ;
            exu_load_size_buff      <= exu_load_size_buff     ;
            exu_load_en_buff        <= exu_load_en_buff       ;
        end else begin
            exu_load_rd_buff        <= 0;
            exu_load_base_addr_buff <= 0;
            exu_load_offset_buff    <= 0;
            exu_load_sext_buff      <= 0;
            exu_load_size_buff      <= LOAD_IDLE;
            exu_load_en_buff        <= 0;
        end
    end else begin
        exu_load_rd_buff        <= 0;
        exu_load_base_addr_buff <= 0;
        exu_load_offset_buff    <= 0;
        exu_load_sext_buff      <= 0;
        exu_load_size_buff      <= LOAD_IDLE;
        exu_load_en_buff        <= 0;
    end
end

always@(posedge hclk or negedge hrstn) begin
    if(!hrstn) begin
        exu_load_rd        <= 0;
        exu_load_base_addr <= 0;
        exu_load_offset    <= 0;
        exu_load_sext      <= 0;
        exu_load_size      <= LOAD_IDLE;
        exu_load_en        <= 0;
    end else if(cycle_cnt == 4)begin
        exu_load_rd        <= exu_load_rd_buff          ;
        exu_load_base_addr <= exu_load_base_addr_buff   ;
        exu_load_offset    <= exu_load_offset_buff      ;
        exu_load_sext      <= exu_load_sext_buff        ;
        exu_load_size      <= exu_load_size_buff        ;
        exu_load_en        <= exu_load_en_buff          ;
    end else begin
        exu_load_rd        <= exu_load_rd               ;
        exu_load_base_addr <= exu_load_base_addr        ;
        exu_load_offset    <= exu_load_offset           ;
        exu_load_sext      <= exu_load_sext             ;
        exu_load_size      <= exu_load_size             ;
        exu_load_en        <= exu_load_en               ;
    end
end

assign ifu_dec_stall = exu_load_en;

endmodule

rtl/chip/core/exu_swc/exu_load_swc/exu_load_tb.v
module exu_load_tb;

// general signals
reg                       hclk                ;
reg                       hrstn               ;
// control signals
reg           [3:0]       cycle_cnt           ;
reg                      ifu_dec_stall       ;
// signals from dec 
reg                       dec_load_en         ;
reg                       dec_lb              ;
reg                       dec_lh              ;
reg                       dec_lw              ;
reg                       dec_lbu             ;
reg                       dec_lhu             ;
reg           [11:0]      dec_imm_type_i      ;
reg           [4:0]       dec_rd              ;
reg           [4:0]       dec_rs1             ;
// signals to mau
reg      [4:0]       exu_load_rd         ;
reg      [31:0]      exu_load_base_addr  ;
reg      [31:0]      exu_load_offset     ;
reg                  exu_load_sext       ;
reg      [1:0]       exu_load_size       ;
reg                  exu_load_en         ;
// regfile signals
reg           [4:0]       reg_raddr_1         ;
reg                       reg_ren_1           ;
reg           [31:0]      reg_rdata_1         ;

exu_load_swc exu_load_inst (
  .hclk			(hclk                           ),
  .hrstn		(hrstn                          ),
  .cycle_cnt		(cycle_cnt			),
  .ifu_dec_stall	(ifu_dec_stall			),
  .dec_load_en		(dec_load_en			),
  .dec_lb		(dec_lb				),
  .dec_lh		(dec_lh				),
  .dec_lw		(dec_lw				),
  .dec_lbu		(dec_lbu			),
  .dec_lhu		(dec_lhu 			),
  .dec_imm_type_i	(dec_imm_type_i			),
  .dec_rd		(dec_rd				),
  .dec_rs1		(dec_rs1			),
  .exu_load_rd		(exu_load_rd			),
  .exu_load_base_addr	(exu_load_base_addr		),
  .exu_load_offset	(exu_load_offset		),
  .exu_load_sext	(exu_load_sext			),
  .exu_load_size	(exu_load_size			),
  .exu_load_en		(exu_load_en			),
  .reg_raddr_1		(reg_raddr_1			),
  .reg_ren_1		(reg_ren_1			),
  .reg_rdata_1		(reg_rdata_1			)
);

always #5  hclk = !hclk ;


// copied from the core top
always@(posedge hclk) begin
  if(!hrstn)
      cycle_cnt <= 0;
  else if(cycle_cnt == 4)
      cycle_cnt <= 1;
  else
      cycle_cnt <= cycle_cnt + 1;
end


initial begin
  dec_load_en = 1;
  dec_lb = 1;
  dec_lh = 0;
  dec_lw = 0;
  dec_lbu = 0;
  dec_lhu = 0;
  dec_imm_type_i = 10;
  dec_rd = 5;
  dec_rs1 = 2;
  reg_rdata_1 = 2;
  #20;
  hrstn = 1;
  #100;
  dec_lb = 0;
  dec_lhu = 1;
  #10000;
  $finish;
end

initial begin
  $dumpfile("exu_load_tb.vcd");
  $dumpvars(0, exu_load_tb);
end

endmodule

rtl/chip/core/exu_swc/exu_load_tb.vcd
$version Generated by VerilatedVcd $end
$timescale 1ps $end
 $scope module TOP $end
  $scope module exu_load_tb $end
   $var wire 1 = hclk $end
   $var wire 1 # hrstn $end
   $var wire 4 > cycle_cnt [3:0] $end
   $var wire 1 . ifu_dec_stall $end
   $var wire 1 $ dec_load_en $end
   $var wire 1 % dec_lb $end
   $var wire 1 & dec_lh $end
   $var wire 1 ' dec_lw $end
   $var wire 1 ( dec_lbu $end
   $var wire 1 ) dec_lhu $end
   $var wire 12 * dec_imm_type_i [11:0] $end
   $var wire 5 + dec_rd [4:0] $end
   $var wire 5 , dec_rs1 [4:0] $end
   $var wire 5 / exu_load_rd [4:0] $end
   $var wire 32 0 exu_load_base_addr [31:0] $end
   $var wire 32 1 exu_load_offset [31:0] $end
   $var wire 1 2 exu_load_sext $end
   $var wire 2 3 exu_load_size [1:0] $end
   $var wire 1 . exu_load_en $end
   $var wire 5 4 reg_raddr_1 [4:0] $end
   $var wire 1 5 reg_ren_1 $end
   $var wire 32 - reg_rdata_1 [31:0] $end
   $scope module exu_load_inst $end
    $var wire 1 = hclk $end
    $var wire 1 # hrstn $end
    $var wire 4 > cycle_cnt [3:0] $end
    $var wire 1 . ifu_dec_stall $end
    $var wire 1 $ dec_load_en $end
    $var wire 1 % dec_lb $end
    $var wire 1 & dec_lh $end
    $var wire 1 ' dec_lw $end
    $var wire 1 ( dec_lbu $end
    $var wire 1 ) dec_lhu $end
    $var wire 12 * dec_imm_type_i [11:0] $end
    $var wire 5 + dec_rd [4:0] $end
    $var wire 5 , dec_rs1 [4:0] $end
    $var wire 5 / exu_load_rd [4:0] $end
    $var wire 32 0 exu_load_base_addr [31:0] $end
    $var wire 32 1 exu_load_offset [31:0] $end
    $var wire 1 2 exu_load_sext $end
    $var wire 2 3 exu_load_size [1:0] $end
    $var wire 1 . exu_load_en $end
    $var wire 5 4 reg_raddr_1 [4:0] $end
    $var wire 1 5 reg_ren_1 $end
    $var wire 32 - reg_rdata_1 [31:0] $end
    $var wire 5 6 mid_reg_raddr_1 [4:0] $end
    $var wire 1 5 mid_reg_ren_1 $end
    $var wire 5 7 exu_load_rd_buff [4:0] $end
    $var wire 32 8 exu_load_base_addr_buff [31:0] $end
    $var wire 32 9 exu_load_offset_buff [31:0] $end
    $var wire 1 : exu_load_sext_buff $end
    $var wire 2 ; exu_load_size_buff [1:0] $end
    $var wire 1 < exu_load_en_buff $end
    $var wire 32 ? LOAD_IDLE [31:0] $end
    $var wire 32 @ LOAD_BTYE [31:0] $end
    $var wire 32 A LOAD_HALFWORD [31:0] $end
    $var wire 32 B LOAD_WORD [31:0] $end
   $upscope $end
  $upscope $end
 $upscope $end
$enddefinitions $end


#0
0#
1$
1%
0&
0'
0(
0)
b000000001010 *
b00101 +
b00010 ,
b00000000000000000000000000000010 -
0.
b00000 /
b00000000000000000000000000000000 0
b00000000000000000000000000000000 1
02
b00 3
b00000 4
05
b00000 6
b00000 7
b00000000000000000000000000000000 8
b00000000000000000000000000000000 9
0:
b00 ;
0<
0=
b0000 >
b00000000000000000000000000000000 ?
b00000000000000000000000000000001 @
b00000000000000000000000000000010 A
b00000000000000000000000000000011 B
#5
1=
#10
0=
#15
1=
#20
1#
0=
#25
1=
b0001 >
#30
0=
#35
b00010 4
15
b00010 6
1=
b0010 >
#40
0=
#45
b00000 4
05
b00000 6
1=
b0011 >
#50
0=
#55
b00101 7
b00000000000000000000000000000010 8
b00000000000000000000000000001010 9
1:
b01 ;
1<
1=
b0100 >
#60
0=
#65
1.
b00101 /
b00000000000000000000000000000010 0
b00000000000000000000000000001010 1
12
b01 3
1=
b0001 >
#70
0=
#75
b00010 4
15
b00010 6
b00000 7
b00000000000000000000000000000000 8
b00000000000000000000000000000000 9
0:
b00 ;
0<
1=
b0010 >
#80
0=
#85
b00000 4
05
b00000 6
1=
b0011 >
#90
0=
#95
b00101 7
b00000000000000000000000000000010 8
b00000000000000000000000000001010 9
1:
b01 ;
1<
1=
b0100 >
#100
0=
#105
1=
b0001 >
#110
0=
#115
b00010 4
15
b00010 6
b00000 7
b00000000000000000000000000000000 8
b00000000000000000000000000000000 9
0:
b00 ;
0<
1=
b0010 >
#120
0%
1)
0=
#125
b00000 4
05
b00000 6
1=
b0011 >
#130
0=
#135
b00101 7
b00000000000000000000000000000010 8
b00000000000000000000000000001010 9
b10 ;
1<
1=
b0100 >
#140
0=
#145
02
b10 3
1=
b0001 >
#150
0=
#155
b00010 4
15
b00010 6
b00000 7
b00000000000000000000000000000000 8
b00000000000000000000000000000000 9
b00 ;
0<
1=
b0010 >
#160
0=
#165
b00000 4
05
b00000 6
1=
b0011 >
#170
0=
#175
b00101 7
b00000000000000000000000000000010 8
b00000000000000000000000000001010 9
b10 ;
1<
1=
b0100 >
#180
0=
#185
1=
b0001 >
#190
0=
#195
b00010 4
15
b00010 6
b00000 7
b00000000000000000000000000000000 8
b00000000000000000000000000000000 9
b00 ;
0<
1=
b0010 >
#200
0=
#205
b00000 4
05
b00000 6
1=
b0011 >
#210
0=
#215
b00101 7
b00000000000000000000000000000010 8
b00000000000000000000000000001010 9
b10 ;
1<
1=
b0100 >
#220
0=
#225
1=
b0001 >
#230
0=
#235
b00010 4
15
b00010 6
b00000 7
b00000000000000000000000000000000 8
b00000000000000000000000000000000 9
b00 ;
0<
1=
b0010 >
#240
0=
#245
b00000 4
05
b00000 6
1=
b0011 >
#250
0=
#255
b00101 7
b00000000000000000000000000000010 8
b00000000000000000000000000001010 9
b10 ;
1<
1=
b0100 >
#260
0=
#265
1=
b0001 >
#270
0=
#275
b00010 4
15
b00010 6
b00000 7
b00000000000000000000000000000000 8
b00000000000000000000000000000000 9
b00 ;
0<
1=
b0010 >
#280
0=
#285
b00000 4
05
b00000 6
1=
b0011 >
#290
0=
#295
b00101 7
b00000000000000000000000000000010 8
b00000000000000000000000000001010 9
b10 ;
1<
1=
b0100 >
#300
0=
#305
1=
b0001 >
#310
0=
#315
b00010 4
15
b00010 6
b00000 7
b00000000000000000000000000000000 8
b00000000000000000000000000000000 9
b00 ;
0<
1=
b0010 >
#320
0=
#325
b00000 4
05
b00000 6
1=
b0011 >
#330
0=
#335
b00101 7
b00000000000000000000000000000010 8
b00000000000000000000000000001010 9
b10 ;
1<
1=
b0100 >
#340
0=
#345
1=
b0001 >
#350
0=
#355
b00010 4
15
b00010 6
b00000 7
b00000000000000000000000000000000 8
b00000000000000000000000000000000 9
b00 ;
0<
1=
b0010 >
#360
0=
#365
b00000 4
05
b00000 6
1=
b0011 >
#370
0=
#375
b00101 7
b00000000000000000000000000000010 8
b00000000000000000000000000001010 9
b10 ;
1<
1=
b0100 >
#380
0=
#385
1=
b0001 >
#390
0=
#395
b00010 4
15
b00010 6
b00000 7
b00000000000000000000000000000000 8
b00000000000000000000000000000000 9
b00 ;
0<
1=
b0010 >
#400
0=
#405
b00000 4
05
b00000 6
1=
b0011 >
#410
0=
#415
b00101 7
b00000000000000000000000000000010 8
b00000000000000000000000000001010 9
b10 ;
1<
1=
b0100 >
#420
0=
#425
1=
b0001 >
#430
0=
#435
b00010 4
15
b00010 6
b00000 7
b00000000000000000000000000000000 8
b00000000000000000000000000000000 9
b00 ;
0<
1=
b0010 >
#440
0=
#445
b00000 4
05
b00000 6
1=
b0011 >
#450
0=
#455
b00101 7
b00000000000000000000000000000010 8
b00000000000000000000000000001010 9
b10 ;
1<
1=
b0100 >
#460
0=
#465
1=
b0001 >
#470
0=
#475
b00010 4
15
b00010 6
b00000 7
b00000000000000000000000000000000 8
b00000000000000000000000000000000 9
b00 ;
0<
1=
b0010 >
#480
0=
#485
b00000 4
05
b00000 6
1=
b0011 >
#490
0=
#495
b00101 7
b00000000000000000000000000000010 8
b00000000000000000000000000001010 9
b10 ;
1<
1=
b0100 >
#500
0=
#505
1=
b0001 >
#510
0=
#515
b00010 4
15
b00010 6
b00000 7
b00000000000000000000000000000000 8
b00000000000000000000000000000000 9
b00 ;
0<
1=
b0010 >
#520
0=
#525
b00000 4
05
b00000 6
1=
b0011 >
#530
0=
#535
b00101 7
b00000000000000000000000000000010 8
b00000000000000000000000000001010 9
b10 ;
1<
1=
b0100 >
#540
0=
#545
1=
b0001 >
#550
0=
#555
b00010 4
15
b00010 6
b00000 7
b00000000000000000000000000000000 8
b00000000000000000000000000000000 9
b00 ;
0<
1=
b0010 >
#560
0=
#565
b00000 4
05
b00000 6
1=
b0011 >
#570
0=
#575
b00101 7
b00000000000000000000000000000010 8
b00000000000000000000000000001010 9
b10 ;
1<
1=
b0100 >
#580
0=
#585
1=
b0001 >
#590
0=
#595
b00010 4
15
b00010 6
b00000 7
b00000000000000000000000000000000 8
b00000000000000000000000000000000 9
b00 ;
0<
1=
b0010 >
#600
0=
#605
b00000 4
05
b00000 6
1=
b0011 >
#610
0=
#615
b00101 7
b00000000000000000000000000000010 8
b00000000000000000000000000001010 9
b10 ;
1<
1=
b0100 >
#620
0=
#625
1=
b0001 >
#630
0=
#635
b00010 4
15
b00010 6
b00000 7
b00000000000000000000000000000000 8
b00000000000000000000000000000000 9
b00 ;
0<
1=
b0010 >
#640
0=
#645
b00000 4
05
b00000 6
1=
b0011 >
#650
0=
#655
b00101 7
b00000000000000000000000000000010 8
b00000000000000000000000000001010 9
b10 ;
1<
1=
b0100 >
#660
0=
#665
1=
b0001 >
#670
0=
#675
b00010 4
15
b00010 6
b00000 7
b00000000000000000000000000000000 8
b00000000000000000000000000000000 9
b00 ;
0<
1=
b0010 >
#680
0=
#685
b00000 4
05
b00000 6
1=
b0011 >
#690
0=
#695
b00101 7
b00000000000000000000000000000010 8
b00000000000000000000000000001010 9
b10 ;
1<
1=
b0100 >
#700
0=
#705
1=
b0001 >
#710
0=
#715
b00010 4
15
b00010 6
b00000 7
b00000000000000000000000000000000 8
b00000000000000000000000000000000 9
b00 ;
0<
1=
b0010 >
#720
0=
#725
b00000 4
05
b00000 6
1=
b0011 >
#730
0=
#735
b00101 7
b00000000000000000000000000000010 8
b00000000000000000000000000001010 9
b10 ;
1<
1=
b0100 >
#740
0=
#745
1=
b0001 >
#750
0=
#755
b00010 4
15
b00010 6
b00000 7
b00000000000000000000000000000000 8
b00000000000000000000000000000000 9
b00 ;
0<
1=
b0010 >
#760
0=
#765
b00000 4
05
b00000 6
1=
b0011 >
#770
0=
#775
b00101 7
b00000000000000000000000000000010 8
b00000000000000000000000000001010 9
b10 ;
1<
1=
b0100 >
#780
0=
#785
1=
b0001 >
#790
0=
#795
b00010 4
15
b00010 6
b00000 7
b00000000000000000000000000000000 8
b00000000000000000000000000000000 9
b00 ;
0<
1=
b0010 >
#800
0=
#805
b00000 4
05
b00000 6
1=
b0011 >
#810
0=
#815
b00101 7
b00000000000000000000000000000010 8
b00000000000000000000000000001010 9
b10 ;
1<
1=
b0100 >
#820
0=
#825
1=
b0001 >
#830
0=
#835
b00010 4
15
b00010 6
b00000 7
b00000000000000000000000000000000 8
b00000000000000000000000000000000 9
b00 ;
0<
1=
b0010 >
#840
0=
#845
b00000 4
05
b00000 6
1=
b0011 >
#850
0=
#855
b00101 7
b00000000000000000000000000000010 8
b00000000000000000000000000001010 9
b10 ;
1<
1=
b0100 >
#860
0=
#865
1=
b0001 >
#870
0=
#875
b00010 4
15
b00010 6
b00000 7
b00000000000000000000000000000000 8
b00000000000000000000000000000000 9
b00 ;
0<
1=
b0010 >
#880
0=
#885
b00000 4
05
b00000 6
1=
b0011 >
#890
0=
#895
b00101 7
b00000000000000000000000000000010 8
b00000000000000000000000000001010 9
b10 ;
1<
1=
b0100 >
#900
0=
#905
1=
b0001 >
#910
0=
#915
b00010 4
15
b00010 6
b00000 7
b00000000000000000000000000000000 8
b00000000000000000000000000000000 9
b00 ;
0<
1=
b0010 >
#920
0=
#925
b00000 4
05
b00000 6
1=
b0011 >
#930
0=
#935
b00101 7
b00000000000000000000000000000010 8
b00000000000000000000000000001010 9
b10 ;
1<
1=
b0100 >
#940
0=
#945
1=
b0001 >
#950
0=
#955
b00010 4
15
b00010 6
b00000 7
b00000000000000000000000000000000 8
b00000000000000000000000000000000 9
b00 ;
0<
1=
b0010 >
#960
0=
#965
b00000 4
05
b00000 6
1=
b0011 >
#970
0=
#975
b00101 7
b00000000000000000000000000000010 8
b00000000000000000000000000001010 9
b10 ;
1<
1=
b0100 >
#980
0=
#985
1=
b0001 >
#990
0=
#995
b00010 4
15
b00010 6
b00000 7
b00000000000000000000000000000000 8
b00000000000000000000000000000000 9
b00 ;
0<
1=
b0010 >
#1000
0=
#1005
b00000 4
05
b00000 6
1=
b0011 >
#1010
0=
#1015
b00101 7
b00000000000000000000000000000010 8
b00000000000000000000000000001010 9
b10 ;
1<
1=
b0100 >
#1020
0=
#1025
1=
b0001 >
#1030
0=
#1035
b00010 4
15
b00010 6
b00000 7
b00000000000000000000000000000000 8
b00000000000000000000000000000000 9
b00 ;
0<
1=
b0010 >
#1040
0=
#1045
b00000 4
05
b00000 6
1=
b0011 >
#1050
0=
#1055
b00101 7
b00000000000000000000000000000010 8
b00000000000000000000000000001010 9
b10 ;
1<
1=
b0100 >
#1060
0=
#1065
1=
b0001 >
#1070
0=
#1075
b00010 4
15
b00010 6
b00000 7
b00000000000000000000000000000000 8
b00000000000000000000000000000000 9
b00 ;
0<
1=
b0010 >
#1080
0=
#1085
b00000 4
05
b00000 6
1=
b0011 >
#1090
0=
#1095
b00101 7
b00000000000000000000000000000010 8
b00000000000000000000000000001010 9
b10 ;
1<
1=
b0100 >
#1100
0=
#1105
1=
b0001 >
#1110
0=
#1115
b00010 4
15
b00010 6
b00000 7
b00000000000000000000000000000000 8
b00000000000000000000000000000000 9
b00 ;
0<
1=
b0010 >
#1120
0=
#1125
b00000 4
05
b00000 6
1=
b0011 >
#1130
0=
#1135
b00101 7
b00000000000000000000000000000010 8
b00000000000000000000000000001010 9
b10 ;
1<
1=
b0100 >
#1140
0=
#1145
1=
b0001 >
#1150
0=
#1155
b00010 4
15
b00010 6
b00000 7
b00000000000000000000000000000000 8
b00000000000000000000000000000000 9
b00 ;
0<
1=
b0010 >
#1160
0=
#1165
b00000 4
05
b00000 6
1=
b0011 >
#1170
0=
#1175
b00101 7
b00000000000000000000000000000010 8
b00000000000000000000000000001010 9
b10 ;
1<
1=
b0100 >
#1180
0=
#1185
1=
b0001 >
#1190
0=
#1195
b00010 4
15
b00010 6
b00000 7
b00000000000000000000000000000000 8
b00000000000000000000000000000000 9
b00 ;
0<
1=
b0010 >
#1200
0=
#1205
b00000 4
05
b00000 6
1=
b0011 >
#1210
0=
#1215
b00101 7
b00000000000000000000000000000010 8
b00000000000000000000000000001010 9
b10 ;
1<
1=
b0100 >
#1220
0=
#1225
1=
b0001 >
#1230
0=
#1235
b00010 4
15
b00010 6
b00000 7
b00000000000000000000000000000000 8
b00000000000000000000000000000000 9
b00 ;
0<
1=
b0010 >
#1240
0=
#1245
b00000 4
05
b00000 6
1=
b0011 >
#1250
0=
#1255
b00101 7
b00000000000000000000000000000010 8
b00000000000000000000000000001010 9
b10 ;
1<
1=
b0100 >
#1260
0=
#1265
1=
b0001 >
#1270
0=
#1275
b00010 4
15
b00010 6
b00000 7
b00000000000000000000000000000000 8
b00000000000000000000000000000000 9
b00 ;
0<
1=
b0010 >
#1280
0=
#1285
b00000 4
05
b00000 6
1=
b0011 >
#1290
0=
#1295
b00101 7
b00000000000000000000000000000010 8
b00000000000000000000000000001010 9
b10 ;
1<
1=
b0100 >
#1300
0=
#1305
1=
b0001 >
#1310
0=
#1315
b00010 4
15
b00010 6
b00000 7
b00000000000000000000000000000000 8
b00000000000000000000000000000000 9
b00 ;
0<
1=
b0010 >
#1320
0=
#1325
b00000 4
05
b00000 6
1=
b0011 >
#1330
0=
#1335
b00101 7
b00000000000000000000000000000010 8
b00000000000000000000000000001010 9
b10 ;
1<
1=
b0100 >
#1340
0=
#1345
1=
b0001 >
#1350
0=
#1355
b00010 4
15
b00010 6
b00000 7
b00000000000000000000000000000000 8
b00000000000000000000000000000000 9
b00 ;
0<
1=
b0010 >
#1360
0=
#1365
b00000 4
05
b00000 6
1=
b0011 >
#1370
0=
#1375
b00101 7
b00000000000000000000000000000010 8
b00000000000000000000000000001010 9
b10 ;
1<
1=
b0100 >
#1380
0=
#1385
1=
b0001 >
#1390
0=
#1395
b00010 4
15
b00010 6
b00000 7
b00000000000000000000000000000000 8
b00000000000000000000000000000000 9
b00 ;
0<
1=
b0010 >
#1400
0=
#1405
b00000 4
05
b00000 6
1=
b0011 >
#1410
0=
#1415
b00101 7
b00000000000000000000000000000010 8
b00000000000000000000000000001010 9
b10 ;
1<
1=
b0100 >
#1420
0=
#1425
1=
b0001 >
#1430
0=
#1435
b00010 4
15
b00010 6
b00000 7
b00000000000000000000000000000000 8
b00000000000000000000000000000000 9
b00 ;
0<
1=
b0010 >
#1440
0=
#1445
b00000 4
05
b00000 6
1=
b0011 >
#1450
0=
#1455
b00101 7
b00000000000000000000000000000010 8
b00000000000000000000000000001010 9
b10 ;
1<
1=
b0100 >
#1460
0=
#1465
1=
b0001 >
#1470
0=
#1475
b00010 4
15
b00010 6
b00000 7
b00000000000000000000000000000000 8
b00000000000000000000000000000000 9
b00 ;
0<
1=
b0010 >
#1480
0=
#1485
b00000 4
05
b00000 6
1=
b0011 >
#1490
0=
#1495
b00101 7
b00000000000000000000000000000010 8
b00000000000000000000000000001010 9
b10 ;
1<
1=
b0100 >
#1500
0=
#1505
1=
b0001 >
#1510
0=
#1515
b00010 4
15
b00010 6
b00000 7
b00000000000000000000000000000000 8
b00000000000000000000000000000000 9
b00 ;
0<
1=
b0010 >
#1520
0=
#1525
b00000 4
05
b00000 6
1=
b0011 >
#1530
0=
#1535
b00101 7
b00000000000000000000000000000010 8
b00000000000000000000000000001010 9
b10 ;
1<
1=
b0100 >
#1540
0=
#1545
1=
b0001 >
#1550
0=
#1555
b00010 4
15
b00010 6
b00000 7
b00000000000000000000000000000000 8
b00000000000000000000000000000000 9
b00 ;
0<
1=
b0010 >
#1560
0=
#1565
b00000 4
05
b00000 6
1=
b0011 >
#1570
0=
#1575
b00101 7
b00000000000000000000000000000010 8
b00000000000000000000000000001010 9
b10 ;
1<
1=
b0100 >
#1580
0=
#1585
1=
b0001 >
#1590
0=
#1595
b00010 4
15
b00010 6
b00000 7
b00000000000000000000000000000000 8
b00000000000000000000000000000000 9
b00 ;
0<
1=
b0010 >
#1600
0=
#1605
b00000 4
05
b00000 6
1=
b0011 >
#1610
0=
#1615
b00101 7
b00000000000000000000000000000010 8
b00000000000000000000000000001010 9
b10 ;
1<
1=
b0100 >
#1620
0=
#1625
1=
b0001 >
#1630
0=
#1635
b00010 4
15
b00010 6
b00000 7
b00000000000000000000000000000000 8
b00000000000000000000000000000000 9
b00 ;
0<
1=
b0010 >
#1640
0=
#1645
b00000 4
05
b00000 6
1=
b0011 >
#1650
0=
#1655
b00101 7
b00000000000000000000000000000010 8
b00000000000000000000000000001010 9
b10 ;
1<
1=
b0100 >
#1660
0=
#1665
1=
b0001 >
#1670
0=
#1675
b00010 4
15
b00010 6
b00000 7
b00000000000000000000000000000000 8
b00000000000000000000000000000000 9
b00 ;
0<
1=
b0010 >
#1680
0=
#1685
b00000 4
05
b00000 6
1=
b0011 >
#1690
0=
#1695
b00101 7
b00000000000000000000000000000010 8
b00000000000000000000000000001010 9
b10 ;
1<
1=
b0100 >
#1700
0=
#1705
1=
b0001 >
#1710
0=
#1715
b00010 4
15
b00010 6
b00000 7
b00000000000000000000000000000000 8
b00000000000000000000000000000000 9
b00 ;
0<
1=
b0010 >
#1720
0=
#1725
b00000 4
05
b00000 6
1=
b0011 >
#1730
0=
#1735
b00101 7
b00000000000000000000000000000010 8
b00000000000000000000000000001010 9
b10 ;
1<
1=
b0100 >
#1740
0=
#1745
1=
b0001 >
#1750
0=
#1755
b00010 4
15
b00010 6
b00000 7
b00000000000000000000000000000000 8
b00000000000000000000000000000000 9
b00 ;
0<
1=
b0010 >
#1760
0=
#1765
b00000 4
05
b00000 6
1=
b0011 >
#1770
0=
#1775
b00101 7
b00000000000000000000000000000010 8
b00000000000000000000000000001010 9
b10 ;
1<
1=
b0100 >
#1780
0=
#1785
1=
b0001 >
#1790
0=
#1795
b00010 4
15
b00010 6
b00000 7
b00000000000000000000000000000000 8
b00000000000000000000000000000000 9
b00 ;
0<
1=
b0010 >
#1800
0=
#1805
b00000 4
05
b00000 6
1=
b0011 >
#1810
0=
#1815
b00101 7
b00000000000000000000000000000010 8
b00000000000000000000000000001010 9
b10 ;
1<
1=
b0100 >
#1820
0=
#1825
1=
b0001 >
#1830
0=
#1835
b00010 4
15
b00010 6
b00000 7
b00000000000000000000000000000000 8
b00000000000000000000000000000000 9
b00 ;
0<
1=
b0010 >
#1840
0=
#1845
b00000 4
05
b00000 6
1=
b0011 >
#1850
0=
#1855
b00101 7
b00000000000000000000000000000010 8
b00000000000000000000000000001010 9
b10 ;
1<
1=
b0100 >
#1860
0=
#1865
1=
b0001 >
#1870
0=
#1875
b00010 4
15
b00010 6
b00000 7
b00000000000000000000000000000000 8
b00000000000000000000000000000000 9
b00 ;
0<
1=
b0010 >
#1880
0=
#1885
b00000 4
05
b00000 6
1=
b0011 >
#1890
0=
#1895
b00101 7
b00000000000000000000000000000010 8
b00000000000000000000000000001010 9
b10 ;
1<
1=
b0100 >
#1900
0=
#1905
1=
b0001 >
#1910
0=
#1915
b00010 4
15
b00010 6
b00000 7
b00000000000000000000000000000000 8
b00000000000000000000000000000000 9
b00 ;
0<
1=
b0010 >
#1920
0=
#1925
b00000 4
05
b00000 6
1=
b0011 >
#1930
0=
#1935
b00101 7
b00000000000000000000000000000010 8
b00000000000000000000000000001010 9
b10 ;
1<
1=
b0100 >
#1940
0=
#1945
1=
b0001 >
#1950
0=
#1955
b00010 4
15
b00010 6
b00000 7
b00000000000000000000000000000000 8
b00000000000000000000000000000000 9
b00 ;
0<
1=
b0010 >
#1960
0=
#1965
b00000 4
05
b00000 6
1=
b0011 >
#1970
0=
