rtl/chip/lib/syncfifo_swc/syncfifo_swc.v
module syncfifo_swc(
    rstn    ,
    clk     ,
    wen     ,
    wdata   ,
    full    ,
    ren     ,
    rdata   ,
    empty   
);

// parameters
parameter data_width = 32                               ;
parameter ram_size   = 16                               ; // must be a power of 2
parameter addr_width = $clog2(ram_size)                 ;

// general signals
input                           rstn                    ;
input                           clk                     ;

// write  
input                           wen                     ;
input   [data_width-1:0]        wdata                   ;
output                          full                    ;

// read     
input                           ren                     ;
output  reg [data_width-1:0]    rdata                   ;
output                          empty                   ;

// address
wire    [addr_width-1:0]        waddr                   ;
wire    [addr_width-1:0]        raddr                   ;

// address pointers
reg     [addr_width:0]          waddr_ptr               ;
reg     [addr_width:0]          raddr_ptr               ;

// FIFO ram
reg [data_width-1:0] fifo_ram [ram_size-1:0];
    
// waddr raddr
assign waddr = waddr_ptr[addr_width-1:0];
assign raddr = raddr_ptr[addr_width-1:0];

// write ram
generate
    genvar i;
    for (i = 0; i < ram_size; i = i + 1) begin
        always @(posedge clk) begin
            if (!rstn)
                fifo_ram[i] <= 0;
            else if (wen && !full && (i == waddr))
                fifo_ram[i] <= wdata;
            else
                fifo_ram[i] <= fifo_ram[i];
        end
    end
endgenerate

// read ram
always @(posedge clk) begin
    if(!rstn)
        rdata <= 0;
    else if(ren && !empty)
        rdata <= fifo_ram[raddr];
    else
        rdata <= 0;
end

// waddr_ptr
always @(posedge clk) begin
    if(!rstn)
        waddr_ptr <= 0;
    else if(wen && !full)
        waddr_ptr <= waddr_ptr + 1;
    else
        waddr_ptr <= waddr_ptr;
end

// raddr_ptr
always @(posedge clk) begin
    if(!rstn)
        raddr_ptr <= 0;
    else if(ren && (~empty))
        raddr_ptr <= raddr_ptr + 1;
    else
        raddr_ptr <= raddr_ptr;
end

// signs
assign empty = (raddr_ptr == waddr_ptr);
assign full  = (waddr_ptr[addr_width - 1:0] == raddr_ptr[addr_width - 1:0]) && (waddr_ptr[addr_width] != raddr_ptr[addr_width]);

endmodule

rtl/chip/lib/syncfifo_swc/syncfifo_swc_tb.v
module syncfifo_swc_tb;
    
    reg 						      rstn  ;
	reg 						      clk   ;

	reg 						      wen   ;
	reg 	      [31:0]	          wdata ;
	wire						      full  ;
				
	reg 						      ren   ;
	wire	      [31:0]	          rdata ;
	wire	 					      empty ;

    syncfifo_swc syncfifo_swc_inst
	(
		  .rstn         (rstn)  ,
		  .clk          (clk)  ,
		  .wen          (wen)   ,
		  .wdata        (wdata) ,
		  .full         (full)  ,
		  .ren          (ren)   ,
		  .rdata        (rdata) ,
		  .empty        (empty)
);
    
    initial clk = 0;
    always#10 clk = ~clk;
    
    always@(posedge clk or negedge rstn)begin
        if(!rstn)
            wdata <= 0;
        else if(wen && !full)
            wdata <= wdata + 1;
        else
            wdata <= wdata;
    end
    
    initial begin
        rstn = 0;
        wen = 0;
        ren = 0;
        #200;
        rstn = 1;
        wen = 1;
        #20000;
        wen = 0;
        ren = 1;
        #20000;
        ren = 0;
        $finish; 
    end

    initial begin
        $dumpfile("syncfifo_swc_tb.vcd");
        $dumpvars(0, syncfifo_swc_tb);
        #50000 $finish;
    end
    
endmodule

rtl/chip/lib/syncfifo_swc/syncfifo_swc_tb.vcd
$version Generated by VerilatedVcd $end
$timescale 1ps $end
 $scope module TOP $end
  $scope module syncfifo_swc_tb $end
   $var wire 1 9 rstn $end
   $var wire 1 : clk $end
   $var wire 1 ; wen $end
   $var wire 32 < wdata [31:0] $end
   $var wire 1 = full $end
   $var wire 1 > ren $end
   $var wire 32 # rdata [31:0] $end
   $var wire 1 $ empty $end
   $scope module syncfifo_swc_inst $end
    $var wire 32 ? data_width [31:0] $end
    $var wire 32 @ ram_size [31:0] $end
    $var wire 32 A addr_width [31:0] $end
    $var wire 1 9 rstn $end
    $var wire 1 : clk $end
    $var wire 1 ; wen $end
    $var wire 32 < wdata [31:0] $end
    $var wire 1 = full $end
    $var wire 1 > ren $end
    $var wire 32 # rdata [31:0] $end
    $var wire 1 $ empty $end
    $var wire 4 % waddr [3:0] $end
    $var wire 4 & raddr [3:0] $end
    $var wire 5 ' waddr_ptr [4:0] $end
    $var wire 5 ( raddr_ptr [4:0] $end
    $var wire 32 ) fifo_ram[0] [31:0] $end
    $var wire 32 * fifo_ram[1] [31:0] $end
    $var wire 32 + fifo_ram[2] [31:0] $end
    $var wire 32 , fifo_ram[3] [31:0] $end
    $var wire 32 - fifo_ram[4] [31:0] $end
    $var wire 32 . fifo_ram[5] [31:0] $end
    $var wire 32 / fifo_ram[6] [31:0] $end
    $var wire 32 0 fifo_ram[7] [31:0] $end
    $var wire 32 1 fifo_ram[8] [31:0] $end
    $var wire 32 2 fifo_ram[9] [31:0] $end
    $var wire 32 3 fifo_ram[10] [31:0] $end
    $var wire 32 4 fifo_ram[11] [31:0] $end
    $var wire 32 5 fifo_ram[12] [31:0] $end
    $var wire 32 6 fifo_ram[13] [31:0] $end
    $var wire 32 7 fifo_ram[14] [31:0] $end
    $var wire 32 8 fifo_ram[15] [31:0] $end
   $upscope $end
  $upscope $end
 $upscope $end
$enddefinitions $end


#0
b00000000000000000000000000000000 #
1$
b0000 %
b0000 &
b00000 '
b00000 (
b00000000000000000000000000000000 )
b00000000000000000000000000000000 *
b00000000000000000000000000000000 +
b00000000000000000000000000000000 ,
b00000000000000000000000000000000 -
b00000000000000000000000000000000 .
b00000000000000000000000000000000 /
b00000000000000000000000000000000 0
b00000000000000000000000000000000 1
b00000000000000000000000000000000 2
b00000000000000000000000000000000 3
b00000000000000000000000000000000 4
b00000000000000000000000000000000 5
b00000000000000000000000000000000 6
b00000000000000000000000000000000 7
b00000000000000000000000000000000 8
09
0:
0;
b00000000000000000000000000000000 <
0=
0>
b00000000000000000000000000100000 ?
b00000000000000000000000000010000 @
b00000000000000000000000000000100 A
#10
1:
#20
0:
#30
1:
#40
0:
#50
1:
#60
0:
#70
1:
#80
0:
#90
1:
#100
0:
#110
1:
#120
0:
#130
1:
#140
0:
#150
1:
#160
0:
#170
1:
#180
0:
#190
1:
#200
19
0:
1;
#210
0$
b0001 %
b00001 '
1:
b00000000000000000000000000000001 <
#220
0:
#230
b0010 %
b00010 '
b00000000000000000000000000000001 *
1:
b00000000000000000000000000000010 <
#240
0:
#250
b0011 %
b00011 '
b00000000000000000000000000000010 +
1:
b00000000000000000000000000000011 <
#260
0:
#270
b0100 %
b00100 '
b00000000000000000000000000000011 ,
1:
b00000000000000000000000000000100 <
#280
0:
#290
b0101 %
b00101 '
b00000000000000000000000000000100 -
1:
b00000000000000000000000000000101 <
#300
0:
#310
b0110 %
b00110 '
b00000000000000000000000000000101 .
1:
b00000000000000000000000000000110 <
#320
0:
#330
b0111 %
b00111 '
b00000000000000000000000000000110 /
1:
b00000000000000000000000000000111 <
#340
0:
#350
b1000 %
b01000 '
b00000000000000000000000000000111 0
1:
b00000000000000000000000000001000 <
#360
0:
#370
b1001 %
b01001 '
b00000000000000000000000000001000 1
1:
b00000000000000000000000000001001 <
#380
0:
#390
b1010 %
b01010 '
b00000000000000000000000000001001 2
1:
b00000000000000000000000000001010 <
#400
0:
#410
b1011 %
b01011 '
b00000000000000000000000000001010 3
1:
b00000000000000000000000000001011 <
#420
0:
#430
b1100 %
b01100 '
b00000000000000000000000000001011 4
1:
b00000000000000000000000000001100 <
#440
0:
#450
b1101 %
b01101 '
b00000000000000000000000000001100 5
1:
b00000000000000000000000000001101 <
#460
0:
#470
b1110 %
b01110 '
b00000000000000000000000000001101 6
1:
b00000000000000000000000000001110 <
#480
0:
#490
b1111 %
b01111 '
b00000000000000000000000000001110 7
1:
b00000000000000000000000000001111 <
#500
0:
#510
b0000 %
b10000 '
b00000000000000000000000000001111 8
1:
b00000000000000000000000000010000 <
1=
