rtl/component/apb_swc/apbs_swc/apbs_swc.v
module apbs_swc (
    pclk        ,
    prstn       ,
    paddr       ,
    psel        ,
    penable     ,
    pwrite      ,
    pwdata      ,
    pready      ,
    prdata      ,
    pslverr     
);
// APB Bus Signals
parameter PD_NUM = 3;   // Peripherals devices number
input                           pclk        ;
input                           prstn       ;
input           [31:0]          paddr       ;
input                           psel        ;
input                           penable     ;
input                           pwrite      ;
input           [31:0]          pwdata      ;
output reg                      pready      ;
output reg      [31:0]          prdata      ;
output                          pslverr     ;

reg             [31:0]          SPI_CR      ;

// pslverr
assign pslverr = 0;

// pready
always @(posedge pclk) begin
    if(psel) begin
        pready <= 1;
    end else begin
        pready <= 0;
    end
end

// SPI_CR
always @(posedge pclk) begin
    if(psel && penable && pwrite && paddr == 'h00) begin
        SPI_CR <= pwdata;
    end else begin
        SPI_CR <= SPI_CR;
    end
end

// prdata
always @(posedge pclk) begin
    if(psel && penable && !pwrite && paddr == 'h00) begin
        prdata <= SPI_CR;
    end
end
    
endmodule

rtl/component/apb_swc/apbm_swc/apbm_swc.v
module apbm_swc (
    pclk        ,
    prstn       ,
    paddr       ,
    pselx       ,
    penable     ,
    pwrite      ,
    pwdata      ,
    pready      ,
    prdata      ,
    pslverr     ,
    wbuffread   ,
    wreq        ,
    wbuffdata   ,
    wbuffaddr   ,
    rbuffwrite  ,
    rreq        ,
    rbuffdata   ,
    rbuffaddr   
);
// APB Bus Signals
parameter PD_NUM = 3;   // Peripherals devices number
input                           pclk        ;
input                           prstn       ;
output  reg     [31:0]          paddr       ;
output  reg     [PD_NUM-1:0]    pselx       ;
output  reg                     penable     ;
output  reg                     pwrite      ;
output  reg     [31:0]          pwdata      ;
input                           pready      ;
input           [31:0]          prdata      ;
input                           pslverr     ;
// Read buff signals
output  reg                     wbuffread   ;
input                           wreq        ;
input           [31:0]          wbuffdata   ;
input           [31:0]          wbuffaddr   ;
output                          rbuffwrite  ;
input                           rreq        ;
output          [31:0]          rbuffdata   ;
input           [31:0]          rbuffaddr   ;
// State machine signals
localparam  IDLE     = 0                    ,
            STEUP    = 1                    ,
            ACCESS   = 2                    ;
reg     [1:0]           state               ;
reg     [1:0]           nextstate           ;

// State machine
always @(posedge pclk) begin
    if(!prstn) begin
        state <= IDLE;
    end else begin
        state <= nextstate;
    end
end

always @(*) begin
    case (state)
        IDLE: begin
            if(wreq || rreq) begin
                nextstate = STEUP;
            end else begin
                nextstate = IDLE;
            end
        end
        STEUP: begin
            nextstate = ACCESS;
        end
        ACCESS: begin
            if(!pready) begin
                nextstate = ACCESS;
            end else if(pready && (wreq || rreq)) begin
                nextstate = STEUP;
            end else begin
                nextstate = IDLE;
            end
        end
        default: nextstate = IDLE;
    endcase
end

// pselx
always @(posedge pclk) begin
    if(!prstn) begin
        pselx <= 0;
    end else if(nextstate == IDLE) begin
        pselx <= 0;
    end else if(nextstate == STEUP) begin
        pselx <= 1;
    end else if(nextstate == ACCESS) begin
        pselx <= 1;
    end else begin
        pselx <= 0;
    end
end

// penable
always @(posedge pclk) begin
    if(!prstn) begin
        penable <= 0;
    end else if(nextstate == IDLE) begin
        penable <= 0;
    end else if(nextstate == STEUP) begin
        penable <= 0;
    end else if(nextstate == ACCESS) begin
        penable <= 1;
    end else begin
        penable <= 0;
    end
end

// pwdata
always @(posedge pclk) begin
    if(!prstn) begin
        pwdata <= 0;
    end else if(nextstate == IDLE) begin
        pwdata <= 0;
    end else if(nextstate == STEUP) begin
        if(wreq) begin
            pwdata <= wbuffdata;
        end else begin
            pwdata <= 0;
        end
    end else if(nextstate == ACCESS) begin
        pwdata <= pwdata;
    end else begin
        pwdata <= 0;
    end
end

// paddr
always @(posedge pclk) begin
    if(!prstn) begin
        paddr <= 0;
    end else if(nextstate == IDLE) begin
        paddr <= 0;
    end else if(nextstate == STEUP) begin
        if(wreq) begin
            paddr <= wbuffaddr;
        end else if(rreq) begin
            paddr <= rbuffaddr;
        end else begin
            paddr <= 0;
        end
    end else if(nextstate == ACCESS) begin
        paddr <= paddr;
    end else begin
        paddr <= 0;
    end
end

// wbuffread
always @(posedge pclk) begin
    if(!prstn) begin
        wbuffread <= 0;
    end else if(nextstate == IDLE) begin
        wbuffread <= 0;
    end else if(nextstate == STEUP) begin
        wbuffread <= 1;
    end else if(nextstate == ACCESS) begin
        wbuffread <= 0;
    end else begin
        wbuffread <= 0;
    end
end

//pwrite
always @(posedge pclk) begin
    if(!prstn) begin
        pwrite <= 0;
    end else if(nextstate == IDLE) begin
        pwrite <= 0;
    end else if(nextstate == STEUP) begin
        if(wreq) begin
            pwrite <= 1;
        end else if(rreq) begin
            pwrite <= 0;
        end else begin
            pwrite <= 0;
        end
    end else if(nextstate == ACCESS) begin
        pwrite <= pwrite;
    end else begin
        pwrite <= 0;
    end
end
    
endmodule

rtl/component/apb_swc/apb_swc_tb.v
module apb_swc_tb;
// Parameters
parameter PD_NUM = 3;
// Ports
reg                     pclk = 1        ;
reg                     prstn = 0       ;
wire    [31:0]          paddr           ;
wire    [PD_NUM-1:0]    pselx           ;
wire                    penable         ;
wire                    pwrite          ;
wire    [31:0]          pwdata          ;
wire                    pready          ;
reg     [31:0]          prdata          ;
wire                    pslverr         ;
wire                    wbuffread       ;
reg                     wreq            ;
reg     [31:0]          wbuffdata       ;
reg     [31:0]          wbuffaddr       ;
reg                     rbuffwrite      ;
reg                     rreq            ;
wire    [31:0]          rbuffdata       ;
reg     [31:0]          rbuffaddr       ;

apbm_swc apbm_swc_inst(
    .pclk       (pclk       ),
    .prstn      (prstn      ),
    .paddr      (paddr      ),
    .pselx      (pselx      ),
    .penable    (penable    ),
    .pwrite     (pwrite     ),
    .pwdata     (pwdata     ),
    .pready     (pready     ),
    .prdata     (prdata     ),
    .pslverr    (pslverr    ),
    .wbuffread  (wbuffread  ),
    .wreq       (wreq       ),
    .wbuffdata  (wbuffdata  ),
    .wbuffaddr  (wbuffaddr  ),
    .rbuffwrite (rbuffwrite ),
    .rreq       (rreq       ),
    .rbuffdata  (rbuffdata  ),
    .rbuffaddr  (rbuffaddr  )
);

apbs_swc  apbs_swc_inst (
    .pclk       (pclk       ),
    .prstn      (prstn      ),
    .paddr      (paddr      ),
    .psel       (pselx[0]   ),
    .penable    (penable    ),
    .pwrite     (pwrite     ),
    .pwdata     (pwdata     ),
    .pready     (pready     ),
    .prdata     (prdata     ),
    .pslverr    (pslverr    )
  );

always #5  pclk = ! pclk ;

reg [7:0] cnt;

initial begin
    $dumpfile("apb_swc_tb.vcd");
    $dumpvars(0, apb_swc_tb);
    #500 $finish;
end

initial begin
    #1;
    #10;
    prstn = 1;
    #10;
    // write
    wreq = 1;
    wbuffdata = 'h10;
    wbuffaddr = 'h00;
    #20;
    wreq = 0;
    wbuffdata = 0;
    wbuffaddr = 'h00;
    //read
    rreq = 1;
    rbuffaddr = 'h00;
    #20;
    rreq = 0;
    rbuffaddr = 'h00;
end

endmodule

rtl/component/apb_swc/apb_swc_tb.vcd
$version Generated by VerilatedVcd $end
$timescale 1ps $end

 $scope module TOP $end
  $scope module apb_swc_tb $end
   $var wire 32 6 PD_NUM [31:0] $end
   $var wire  8 : cnt [7:0] $end
   $var wire 32 ) paddr [31:0] $end
   $var wire  1 4 pclk $end
   $var wire  1 + penable $end
   $var wire 32 / prdata [31:0] $end
   $var wire  1 . pready $end
   $var wire  1 # prstn $end
   $var wire  3 * pselx [2:0] $end
   $var wire  1 7 pslverr $end
   $var wire 32 - pwdata [31:0] $end
   $var wire  1 , pwrite $end
   $var wire 32 ( rbuffaddr [31:0] $end
   $var wire 32 9 rbuffdata [31:0] $end
   $var wire  1 8 rbuffwrite $end
   $var wire  1 ' rreq $end
   $var wire 32 & wbuffaddr [31:0] $end
   $var wire 32 % wbuffdata [31:0] $end
   $var wire  1 0 wbuffread $end
   $var wire  1 $ wreq $end
   $scope module apbm_swc_inst $end
    $var wire 32 = ACCESS [31:0] $end
    $var wire 32 ; IDLE [31:0] $end
    $var wire 32 6 PD_NUM [31:0] $end
    $var wire 32 < STEUP [31:0] $end
    $var wire  2 5 nextstate [1:0] $end
    $var wire 32 ) paddr [31:0] $end
    $var wire  1 4 pclk $end
    $var wire  1 + penable $end
    $var wire 32 / prdata [31:0] $end
    $var wire  1 . pready $end
    $var wire  1 # prstn $end
    $var wire  3 * pselx [2:0] $end
    $var wire  1 7 pslverr $end
    $var wire 32 - pwdata [31:0] $end
    $var wire  1 , pwrite $end
    $var wire 32 ( rbuffaddr [31:0] $end
    $var wire 32 9 rbuffdata [31:0] $end
    $var wire  1 8 rbuffwrite $end
    $var wire  1 ' rreq $end
    $var wire  2 1 state [1:0] $end
    $var wire 32 & wbuffaddr [31:0] $end
    $var wire 32 % wbuffdata [31:0] $end
    $var wire  1 0 wbuffread $end
    $var wire  1 $ wreq $end
   $upscope $end
   $scope module apbs_swc_inst $end
    $var wire 32 6 PD_NUM [31:0] $end
    $var wire 32 3 SPI_CR [31:0] $end
    $var wire 32 ) paddr [31:0] $end
    $var wire  1 4 pclk $end
    $var wire  1 + penable $end
    $var wire 32 / prdata [31:0] $end
    $var wire  1 . pready $end
    $var wire  1 # prstn $end
    $var wire  1 2 psel $end
    $var wire  1 7 pslverr $end
    $var wire 32 - pwdata [31:0] $end
    $var wire  1 , pwrite $end
   $upscope $end
  $upscope $end
 $upscope $end
$enddefinitions $end


#0
0#
0$
b00000000000000000000000000000000 %
b00000000000000000000000000000000 &
0'
b00000000000000000000000000000000 (
b00000000000000000000000000000000 )
b000 *
0+
0,
b00000000000000000000000000000000 -
0.
b00000000000000000000000000000000 /
00
b00 1
02
b00000000000000000000000000000000 3
14
b00 5
b00000000000000000000000000000011 6
07
08
b00000000000000000000000000000000 9
b00000000 :
b00000000000000000000000000000000 ;
b00000000000000000000000000000001 <
b00000000000000000000000000000010 =
#1
#5
04
#10
14
#11
1#
#15
04
#20
14
#21
1$
b00000000000000000000000000010000 %
b01 5
#25
04
#30
b001 *
1,
b00000000000000000000000000010000 -
10
b01 1
12
14
b10 5
#35
04
#40
1+
1.
00
b10 1
14
b01 5
#41
0$
b00000000000000000000000000000000 %
1'
#45
04
#50
0+
0,
b00000000000000000000000000000000 -
10
b01 1
b00000000000000000000000000010000 3
14
b10 5
#55
04
#60
1+
00
b10 1
14
b01 5
#61
0'
b00 5
#65
04
#70
b000 *
0+
b00000000000000000000000000010000 /
b00 1
02
14
#75
04
#80
0.
14
